Workbook

Sheet Overview
A1: instasure.ca: SEO keyword, page and content plan
A2: Built from the October 2026 competitor research (Ratehub, Rates.ca, PolicyAdvisor, Sun Life, Manulife, Sonnet) and the live site at https://instasure.ca. Generated October 3, 2026.
A4: At a glance
A5: Pages on the site | B5: =COUNTA(Pages!$B$2:$B$829) | C5: All URLs the site serves (Pages tab).
A6: Indexable pages | B6: =COUNTIF(Pages!$I$2:$I$829,"Yes") | C6: In the XML sitemap and open to search engines.
A7: Noindex pages to enrich | B7: =COUNTIF(Pages!$I$2:$I$829,"No") | C7: Thin programmatic pages kept out of search until an editor adds local content.
A8: Keywords in the map | B8: =COUNTA('Nationwide KWs'!$A$2:$A$168)+COUNTA('Provincial KWs'!$A$2:$A$137)+COUNTA('City KWs'!$A$2:$A$419) | C8: Nationwide + Provincial + City tabs.
A9: Nationwide keywords | B9: =COUNTA('Nationwide KWs'!$A$2:$A$168) | C9: Canada-wide head terms and topics.
A10: Provincial keywords | B10: =COUNTA('Provincial KWs'!$A$2:$A$137) | C10: Product + province, regulation and French (Quebec, planned).
A11: City keywords | B11: =COUNTA('City KWs'!$A$2:$A$419) | C11: Product + city, GTA sub-areas and French cities (planned).
A12: Modelled search volume / mo | B12: =SUM('Nationwide KWs'!$D$2:$D$168)+SUM('Provincial KWs'!$E$2:$E$137)+SUM('City KWs'!$F$2:$F$419) | C12: Sum of modelled monthly searches. Use to order work, not to forecast traffic.
A13: Keywords mapped to a live page | B13: =COUNTA('Page-Keyword Map'!$D$2:$D$675) | C13: Rows on the Page-Keyword Map tab.
A14: Keywords in the backlog | B14: =COUNTA('Backlog (Unmapped)'!$A$2:$A$48) | C14: No page yet: planned URLs and blocked items (e.g. French Quebec).
A15: Blog topics planned | B15: =COUNTIF('Blog Content Plan'!$B$2:$B$541,"<>Published") | C15: Blog Content Plan tab (last tab).
A16: Priority 1 topics | B16: =COUNTIFS('Blog Content Plan'!$C$2:$C$541,1,'Blog Content Plan'!$B$2:$B$541,"<>Published") | C16: Write these first.
A17: Blog posts published | B17: =COUNTIF('Blog Content Plan'!$B$2:$B$541,"Published") | C17: The 18 launch guides, plus any you mark Published.
A19: Tabs
A20: Segment Summary | B20: Pages, keywords (by level), volume, backlog and blog topics for each insurance segment.
A21: Pages | B21: Every URL: type, segment, place, indexable, title tag, meta description, H1, primary keyword, keyword counts by level.
A22: Page-Keyword Map | B22: One row per keyword per target page. Primary keyword goes in the title, H1 and first paragraph; secondary keywords in H2s, FAQ and body.
A23: Nationwide KWs | B23: Canada-wide keywords, highest volume first.
A24: Provincial KWs | B24: Province-level keywords, highest volume first.
A25: City KWs | B25: City-level keywords, highest volume first.
A26: Backlog (Unmapped) | B26: Keywords with no page yet, with the planned URL where one is set.
A27: Blog Content Plan | B27: Exhaustive blog topic list per insurance segment from the competitor research: title, URL, focus and secondary keywords, meta title and description, H2 outline, FAQ, value asset, internal links, CTA, schema, competitor gap, optimization and compliance instructions.
A29: How to use
A30: Yellow cells | B30: Fill these in: status, owner, dates, measured volume, current rank. Everything else is data or a formula.
A31: Formulas | B31: Counts, lengths, lookups and "keyword in title?" checks recalculate when you edit the sheet.
A32: Volumes | B32: Modelled estimates (October 2026), not measured. Import Keyword Planner, Ahrefs or Semrush data into the yellow "Measured volume" columns, and into Admin → SEO → Keyword map on the site.
A33: Levels | B33: Nationwide = Canada-wide query. Provincial = names a province or a provincial system (ICBC, FSRA, Care-First). City = names a city or GTA sub-area.
A34: Priority | B34: 1 = do first. Weighs lead value, volume, competitor gap and serviceability. Quebec stays at 3 or lower until AMF registration and French pages exist.
A35: Publishing a blog | B35: Admin → Content on instasure.ca: paste the meta title, meta description and focus keyword from the Blog Content Plan, add the FAQ, sources and a licensed reviewer, then mark the row Published.
A36: Compliance | B36: No "best", "cheapest" or "lowest" claims without a published methodology; estimates are labelled as estimates; verify every fact flagged in the Compliance column against the primary source (see docs/CONTENT_REVIEW.md in the repo).
A37: Source files | B37: Repo NanoQode/Calculators → instasure.ca/docs: STRATEGY.md, SITE_REVIEW.md, KEYWORDS.md, keywords.csv, CONTENT_REVIEW.md, research/*.md.

Sheet Segment Summary
A1: Insurance segment | B1: Pages (all) | C1: Indexable pages | D1: Nationwide keywords | E1: Nationwide volume / mo | F1: Provincial keywords | G1: Provincial volume / mo | H1: City keywords | I1: City volume / mo | J1: Total keyword volume / mo | K1: Unmapped keywords (backlog) | L1: Blog topics planned | M1: Priority 1 topics | N1: Blog posts published
A2: Life insurance | B2: =COUNTIF(Pages!$D$2:$D$829,$A2) | C2: =COUNTIFS(Pages!$D$2:$D$829,$A2,Pages!$I$2:$I$829,"Yes") | D2: =COUNTIF('Nationwide KWs'!$B$2:$B$168,$A2) | E2: =SUMIF('Nationwide KWs'!$B$2:$B$168,$A2,'Nationwide KWs'!$D$2:$D$168) | F2: =COUNTIF('Provincial KWs'!$B$2:$B$137,$A2) | G2: =SUMIF('Provincial KWs'!$B$2:$B$137,$A2,'Provincial KWs'!$E$2:$E$137) | H2: =COUNTIF('City KWs'!$B$2:$B$419,$A2) | I2: =SUMIF('City KWs'!$B$2:$B$419,$A2,'City KWs'!$F$2:$F$419) | J2: =E2+G2+I2 | K2: =COUNTIF('Backlog (Unmapped)'!$C$2:$C$48,$A2) | L2: =COUNTIFS('Blog Content Plan'!$D$2:$D$541,$A2,'Blog Content Plan'!$B$2:$B$541,"<>Published") | M2: =COUNTIFS('Blog Content Plan'!$D$2:$D$541,$A2,'Blog Content Plan'!$C$2:$C$541,1,'Blog Content Plan'!$B$2:$B$541,"<>Published") | N2: =COUNTIFS('Blog Content Plan'!$D$2:$D$541,$A2,'Blog Content Plan'!$B$2:$B$541,"Published")
A3: Mortgage protection | B3: =COUNTIF(Pages!$D$2:$D$829,$A3) | C3: =COUNTIFS(Pages!$D$2:$D$829,$A3,Pages!$I$2:$I$829,"Yes") | D3: =COUNTIF('Nationwide KWs'!$B$2:$B$168,$A3) | E3: =SUMIF('Nationwide KWs'!$B$2:$B$168,$A3,'Nationwide KWs'!$D$2:$D$168) | F3: =COUNTIF('Provincial KWs'!$B$2:$B$137,$A3) | G3: =SUMIF('Provincial KWs'!$B$2:$B$137,$A3,'Provincial KWs'!$E$2:$E$137) | H3: =COUNTIF('City KWs'!$B$2:$B$419,$A3) | I3: =SUMIF('City KWs'!$B$2:$B$419,$A3,'City KWs'!$F$2:$F$419) | J3: =E3+G3+I3 | K3: =COUNTIF('Backlog (Unmapped)'!$C$2:$C$48,$A3) | L3: =COUNTIFS('Blog Content Plan'!$D$2:$D$541,$A3,'Blog Content Plan'!$B$2:$B$541,"<>Published") | M3: =COUNTIFS('Blog Content Plan'!$D$2:$D$541,$A3,'Blog Content Plan'!$C$2:$C$541,1,'Blog Content Plan'!$B$2:$B$541,"<>Published") | N3: =COUNTIFS('Blog Content Plan'!$D$2:$D$541,$A3,'Blog Content Plan'!$B$2:$B$541,"Published")
A4: Critical illness insurance | B4: =COUNTIF(Pages!$D$2:$D$829,$A4) | C4: =COUNTIFS(Pages!$D$2:$D$829,$A4,Pages!$I$2:$I$829,"Yes") | D4: =COUNTIF('Nationwide KWs'!$B$2:$B$168,$A4) | E4: =SUMIF('Nationwide KWs'!$B$2:$B$168,$A4,'Nationwide KWs'!$D$2:$D$168) | F4: =COUNTIF('Provincial KWs'!$B$2:$B$137,$A4) | G4: =SUMIF('Provincial KWs'!$B$2:$B$137,$A4,'Provincial KWs'!$E$2:$E$137) | H4: =COUNTIF('City KWs'!$B$2:$B$419,$A4) | I4: =SUMIF('City KWs'!$B$2:$B$419,$A4,'City KWs'!$F$2:$F$419) | J4: =E4+G4+I4 | K4: =COUNTIF('Backlog (Unmapped)'!$C$2:$C$48,$A4) | L4: =COUNTIFS('Blog Content Plan'!$D$2:$D$541,$A4,'Blog Content Plan'!$B$2:$B$541,"<>Published") | M4: =COUNTIFS('Blog Content Plan'!$D$2:$D$541,$A4,'Blog Content Plan'!$C$2:$C$541,1,'Blog Content Plan'!$B$2:$B$541,"<>Published") | N4: =COUNTIFS('Blog Content Plan'!$D$2:$D$541,$A4,'Blog Content Plan'!$B$2:$B$541,"Published")
A5: Disability insurance | B5: =COUNTIF(Pages!$D$2:$D$829,$A5) | C5: =COUNTIFS(Pages!$D$2:$D$829,$A5,Pages!$I$2:$I$829,"Yes") | D5: =COUNTIF('Nationwide KWs'!$B$2:$B$168,$A5) | E5: =SUMIF('Nationwide KWs'!$B$2:$B$168,$A5,'Nationwide KWs'!$D$2:$D$168) | F5: =COUNTIF('Provincial KWs'!$B$2:$B$137,$A5) | G5: =SUMIF('Provincial KWs'!$B$2:$B$137,$A5,'Provincial KWs'!$E$2:$E$137) | H5: =COUNTIF('City KWs'!$B$2:$B$419,$A5) | I5: =SUMIF('City KWs'!$B$2:$B$419,$A5,'City KWs'!$F$2:$F$419) | J5: =E5+G5+I5 | K5: =COUNTIF('Backlog (Unmapped)'!$C$2:$C$48,$A5) | L5: =COUNTIFS('Blog Content Plan'!$D$2:$D$541,$A5,'Blog Content Plan'!$B$2:$B$541,"<>Published") | M5: =COUNTIFS('Blog Content Plan'!$D$2:$D$541,$A5,'Blog Content Plan'!$C$2:$C$541,1,'Blog Content Plan'!$B$2:$B$541,"<>Published") | N5: =COUNTIFS('Blog Content Plan'!$D$2:$D$541,$A5,'Blog Content Plan'!$B$2:$B$541,"Published")
A6: Health & dental insurance | B6: =COUNTIF(Pages!$D$2:$D$829,$A6) | C6: =COUNTIFS(Pages!$D$2:$D$829,$A6,Pages!$I$2:$I$829,"Yes") | D6: =COUNTIF('Nationwide KWs'!$B$2:$B$168,$A6) | E6: =SUMIF('Nationwide KWs'!$B$2:$B$168,$A6,'Nationwide KWs'!$D$2:$D$168) | F6: =COUNTIF('Provincial KWs'!$B$2:$B$137,$A6) | G6: =SUMIF('Provincial KWs'!$B$2:$B$137,$A6,'Provincial KWs'!$E$2:$E$137) | H6: =COUNTIF('City KWs'!$B$2:$B$419,$A6) | I6: =SUMIF('City KWs'!$B$2:$B$419,$A6,'City KWs'!$F$2:$F$419) | J6: =E6+G6+I6 | K6: =COUNTIF('Backlog (Unmapped)'!$C$2:$C$48,$A6) | L6: =COUNTIFS('Blog Content Plan'!$D$2:$D$541,$A6,'Blog Content Plan'!$B$2:$B$541,"<>Published") | M6: =COUNTIFS('Blog Content Plan'!$D$2:$D$541,$A6,'Blog Content Plan'!$C$2:$C$541,1,'Blog Content Plan'!$B$2:$B$541,"<>Published") | N6: =COUNTIFS('Blog Content Plan'!$D$2:$D$541,$A6,'Blog Content Plan'!$B$2:$B$541,"Published")
A7: Group benefits | B7: =COUNTIF(Pages!$D$2:$D$829,$A7) | C7: =COUNTIFS(Pages!$D$2:$D$829,$A7,Pages!$I$2:$I$829,"Yes") | D7: =COUNTIF('Nationwide KWs'!$B$2:$B$168,$A7) | E7: =SUMIF('Nationwide KWs'!$B$2:$B$168,$A7,'Nationwide KWs'!$D$2:$D$168) | F7: =COUNTIF('Provincial KWs'!$B$2:$B$137,$A7) | G7: =SUMIF('Provincial KWs'!$B$2:$B$137,$A7,'Provincial KWs'!$E$2:$E$137) | H7: =COUNTIF('City KWs'!$B$2:$B$419,$A7) | I7: =SUMIF('City KWs'!$B$2:$B$419,$A7,'City KWs'!$F$2:$F$419) | J7: =E7+G7+I7 | K7: =COUNTIF('Backlog (Unmapped)'!$C$2:$C$48,$A7) | L7: =COUNTIFS('Blog Content Plan'!$D$2:$D$541,$A7,'Blog Content Plan'!$B$2:$B$541,"<>Published") | M7: =COUNTIFS('Blog Content Plan'!$D$2:$D$541,$A7,'Blog Content Plan'!$C$2:$C$541,1,'Blog Content Plan'!$B$2:$B$541,"<>Published") | N7: =COUNTIFS('Blog Content Plan'!$D$2:$D$541,$A7,'Blog Content Plan'!$B$2:$B$541,"Published")
A8: Travel insurance | B8: =COUNTIF(Pages!$D$2:$D$829,$A8) | C8: =COUNTIFS(Pages!$D$2:$D$829,$A8,Pages!$I$2:$I$829,"Yes") | D8: =COUNTIF('Nationwide KWs'!$B$2:$B$168,$A8) | E8: =SUMIF('Nationwide KWs'!$B$2:$B$168,$A8,'Nationwide KWs'!$D$2:$D$168) | F8: =COUNTIF('Provincial KWs'!$B$2:$B$137,$A8) | G8: =SUMIF('Provincial KWs'!$B$2:$B$137,$A8,'Provincial KWs'!$E$2:$E$137) | H8: =COUNTIF('City KWs'!$B$2:$B$419,$A8) | I8: =SUMIF('City KWs'!$B$2:$B$419,$A8,'City KWs'!$F$2:$F$419) | J8: =E8+G8+I8 | K8: =COUNTIF('Backlog (Unmapped)'!$C$2:$C$48,$A8) | L8: =COUNTIFS('Blog Content Plan'!$D$2:$D$541,$A8,'Blog Content Plan'!$B$2:$B$541,"<>Published") | M8: =COUNTIFS('Blog Content Plan'!$D$2:$D$541,$A8,'Blog Content Plan'!$C$2:$C$541,1,'Blog Content Plan'!$B$2:$B$541,"<>Published") | N8: =COUNTIFS('Blog Content Plan'!$D$2:$D$541,$A8,'Blog Content Plan'!$B$2:$B$541,"Published")
A9: Super Visa & visitors insurance | B9: =COUNTIF(Pages!$D$2:$D$829,$A9) | C9: =COUNTIFS(Pages!$D$2:$D$829,$A9,Pages!$I$2:$I$829,"Yes") | D9: =COUNTIF('Nationwide KWs'!$B$2:$B$168,$A9) | E9: =SUMIF('Nationwide KWs'!$B$2:$B$168,$A9,'Nationwide KWs'!$D$2:$D$168) | F9: =COUNTIF('Provincial KWs'!$B$2:$B$137,$A9) | G9: =SUMIF('Provincial KWs'!$B$2:$B$137,$A9,'Provincial KWs'!$E$2:$E$137) | H9: =COUNTIF('City KWs'!$B$2:$B$419,$A9) | I9: =SUMIF('City KWs'!$B$2:$B$419,$A9,'City KWs'!$F$2:$F$419) | J9: =E9+G9+I9 | K9: =COUNTIF('Backlog (Unmapped)'!$C$2:$C$48,$A9) | L9: =COUNTIFS('Blog Content Plan'!$D$2:$D$541,$A9,'Blog Content Plan'!$B$2:$B$541,"<>Published") | M9: =COUNTIFS('Blog Content Plan'!$D$2:$D$541,$A9,'Blog Content Plan'!$C$2:$C$541,1,'Blog Content Plan'!$B$2:$B$541,"<>Published") | N9: =COUNTIFS('Blog Content Plan'!$D$2:$D$541,$A9,'Blog Content Plan'!$B$2:$B$541,"Published")
A10: Car insurance | B10: =COUNTIF(Pages!$D$2:$D$829,$A10) | C10: =COUNTIFS(Pages!$D$2:$D$829,$A10,Pages!$I$2:$I$829,"Yes") | D10: =COUNTIF('Nationwide KWs'!$B$2:$B$168,$A10) | E10: =SUMIF('Nationwide KWs'!$B$2:$B$168,$A10,'Nationwide KWs'!$D$2:$D$168) | F10: =COUNTIF('Provincial KWs'!$B$2:$B$137,$A10) | G10: =SUMIF('Provincial KWs'!$B$2:$B$137,$A10,'Provincial KWs'!$E$2:$E$137) | H10: =COUNTIF('City KWs'!$B$2:$B$419,$A10) | I10: =SUMIF('City KWs'!$B$2:$B$419,$A10,'City KWs'!$F$2:$F$419) | J10: =E10+G10+I10 | K10: =COUNTIF('Backlog (Unmapped)'!$C$2:$C$48,$A10) | L10: =COUNTIFS('Blog Content Plan'!$D$2:$D$541,$A10,'Blog Content Plan'!$B$2:$B$541,"<>Published") | M10: =COUNTIFS('Blog Content Plan'!$D$2:$D$541,$A10,'Blog Content Plan'!$C$2:$C$541,1,'Blog Content Plan'!$B$2:$B$541,"<>Published") | N10: =COUNTIFS('Blog Content Plan'!$D$2:$D$541,$A10,'Blog Content Plan'!$B$2:$B$541,"Published")
A11: Recreational vehicles | B11: =COUNTIF(Pages!$D$2:$D$829,$A11) | C11: =COUNTIFS(Pages!$D$2:$D$829,$A11,Pages!$I$2:$I$829,"Yes") | D11: =COUNTIF('Nationwide KWs'!$B$2:$B$168,$A11) | E11: =SUMIF('Nationwide KWs'!$B$2:$B$168,$A11,'Nationwide KWs'!$D$2:$D$168) | F11: =COUNTIF('Provincial KWs'!$B$2:$B$137,$A11) | G11: =SUMIF('Provincial KWs'!$B$2:$B$137,$A11,'Provincial KWs'!$E$2:$E$137) | H11: =COUNTIF('City KWs'!$B$2:$B$419,$A11) | I11: =SUMIF('City KWs'!$B$2:$B$419,$A11,'City KWs'!$F$2:$F$419) | J11: =E11+G11+I11 | K11: =COUNTIF('Backlog (Unmapped)'!$C$2:$C$48,$A11) | L11: =COUNTIFS('Blog Content Plan'!$D$2:$D$541,$A11,'Blog Content Plan'!$B$2:$B$541,"<>Published") | M11: =COUNTIFS('Blog Content Plan'!$D$2:$D$541,$A11,'Blog Content Plan'!$C$2:$C$541,1,'Blog Content Plan'!$B$2:$B$541,"<>Published") | N11: =COUNTIFS('Blog Content Plan'!$D$2:$D$541,$A11,'Blog Content Plan'!$B$2:$B$541,"Published")
A12: Home insurance | B12: =COUNTIF(Pages!$D$2:$D$829,$A12) | C12: =COUNTIFS(Pages!$D$2:$D$829,$A12,Pages!$I$2:$I$829,"Yes") | D12: =COUNTIF('Nationwide KWs'!$B$2:$B$168,$A12) | E12: =SUMIF('Nationwide KWs'!$B$2:$B$168,$A12,'Nationwide KWs'!$D$2:$D$168) | F12: =COUNTIF('Provincial KWs'!$B$2:$B$137,$A12) | G12: =SUMIF('Provincial KWs'!$B$2:$B$137,$A12,'Provincial KWs'!$E$2:$E$137) | H12: =COUNTIF('City KWs'!$B$2:$B$419,$A12) | I12: =SUMIF('City KWs'!$B$2:$B$419,$A12,'City KWs'!$F$2:$F$419) | J12: =E12+G12+I12 | K12: =COUNTIF('Backlog (Unmapped)'!$C$2:$C$48,$A12) | L12: =COUNTIFS('Blog Content Plan'!$D$2:$D$541,$A12,'Blog Content Plan'!$B$2:$B$541,"<>Published") | M12: =COUNTIFS('Blog Content Plan'!$D$2:$D$541,$A12,'Blog Content Plan'!$C$2:$C$541,1,'Blog Content Plan'!$B$2:$B$541,"<>Published") | N12: =COUNTIFS('Blog Content Plan'!$D$2:$D$541,$A12,'Blog Content Plan'!$B$2:$B$541,"Published")
A13: Condo insurance | B13: =COUNTIF(Pages!$D$2:$D$829,$A13) | C13: =COUNTIFS(Pages!$D$2:$D$829,$A13,Pages!$I$2:$I$829,"Yes") | D13: =COUNTIF('Nationwide KWs'!$B$2:$B$168,$A13) | E13: =SUMIF('Nationwide KWs'!$B$2:$B$168,$A13,'Nationwide KWs'!$D$2:$D$168) | F13: =COUNTIF('Provincial KWs'!$B$2:$B$137,$A13) | G13: =SUMIF('Provincial KWs'!$B$2:$B$137,$A13,'Provincial KWs'!$E$2:$E$137) | H13: =COUNTIF('City KWs'!$B$2:$B$419,$A13) | I13: =SUMIF('City KWs'!$B$2:$B$419,$A13,'City KWs'!$F$2:$F$419) | J13: =E13+G13+I13 | K13: =COUNTIF('Backlog (Unmapped)'!$C$2:$C$48,$A13) | L13: =COUNTIFS('Blog Content Plan'!$D$2:$D$541,$A13,'Blog Content Plan'!$B$2:$B$541,"<>Published") | M13: =COUNTIFS('Blog Content Plan'!$D$2:$D$541,$A13,'Blog Content Plan'!$C$2:$C$541,1,'Blog Content Plan'!$B$2:$B$541,"<>Published") | N13: =COUNTIFS('Blog Content Plan'!$D$2:$D$541,$A13,'Blog Content Plan'!$B$2:$B$541,"Published")
... A23: Site, tools & trust | B23: =COUNTIF(Pages!$D$2:$D$829,$A23) | C23: =COUNTIFS(Pages!$D$2:$D$829,$A23,Pages!$I$2:$I$829,"Yes") | D23: =COUNTIF('Nationwide KWs'!$B$2:$B$168,$A23) | E23: =SUMIF('Nationwide KWs'!$B$2:$B$168,$A23,'Nationwide KWs'!$D$2:$D$168) | F23: =COUNTIF('Provincial KWs'!$B$2:$B$137,$A23) | G23: =SUMIF('Provincial KWs'!$B$2:$B$137,$A23,'Provincial KWs'!$E$2:$E$137) | H23: =COUNTIF('City KWs'!$B$2:$B$419,$A23) | I23: =SUMIF('City KWs'!$B$2:$B$419,$A23,'City KWs'!$F$2:$F$419) | J23: =E23+G23+I23 | K23: =COUNTIF('Backlog (Unmapped)'!$C$2:$C$48,$A23) | L23: =COUNTIFS('Blog Content Plan'!$D$2:$D$541,$A23,'Blog Content Plan'!$B$2:$B$541,"<>Published") | M23: =COUNTIFS('Blog Content Plan'!$D$2:$D$541,$A23,'Blog Content Plan'!$C$2:$C$541,1,'Blog Content Plan'!$B$2:$B$541,"<>Published") | N23: =COUNTIFS('Blog Content Plan'!$D$2:$D$541,$A23,'Blog Content Plan'!$B$2:$B$541,"Published")
A24: Total | B24: =SUM(B2:B23) | C24: =SUM(C2:C23) | D24: =SUM(D2:D23) | E24: =SUM(E2:E23) | F24: =SUM(F2:F23) | G24: =SUM(G2:G23) | H24: =SUM(H2:H23) | I24: =SUM(I2:I23) | ... N24: =SUM(N2:N23)
A26: Every number on this tab is a formula over the other tabs. Volumes are modelled monthly Google searches in Canada (October 2026), not measured data.

Sheet Pages
A1: Page ID | B1: URL | C1: Page type | D1: Insurance segment | E1: Product line | F1: Service | G1: Province | H1: City | I1: Indexable | J1: Title tag | K1: Title length | L1: Meta description | M1: Description length | N1: H1 | O1: Primary keyword | P1: Primary keyword volume | Q1: Primary keyword level | R1: Suggested keyword (not yet in keyword map) | S1: Keywords mapped | T1: Mapped volume / mo | U1: Nationwide keywords | V1: Provincial keywords | W1: City keywords | X1: Primary keyword in title? | Y1: Sitemap priority | Z1: Sitemap file | AA1: Status | AB1: Owner | AC1: Notes
A2: P0001 | B2: https://instasure.ca/ | C2: Static / tool | D2: Site, tools & trust | I2: Yes | J2: Instasure.ca — Compare Insurance Quotes in Canada | Instant Estimates | K2: =LEN(J2) | L2: Instant insurance estimates for life, critical illness, home, tenant, car, travel and business coverage in every province — then a licensed advisor compares… | M2: =LEN(L2) | N2: Compare Canadian insurance quotes. Instant estimates in 60 seconds. | S2: =COUNTIF('Page-Keyword Map'!$A$2:$A$675,B2) | T2: =SUMIF('Page-Keyword Map'!$A$2:$A$675,B2,'Page-Keyword Map'!$H$2:$H$675) | U2: =COUNTIFS('Page-Keyword Map'!$A$2:$A$675,B2,'Page-Keyword Map'!$E$2:$E$675,"Nationwide") | V2: =COUNTIFS('Page-Keyword Map'!$A$2:$A$675,B2,'Page-Keyword Map'!$E$2:$E$675,"Provincial") | W2: =COUNTIFS('Page-Keyword Map'!$A$2:$A$675,B2,'Page-Keyword Map'!$E$2:$E$675,"City") | X2: =IF(O2="","",IF(ISNUMBER(SEARCH(O2,J2)),"Yes","No")) | Y2: 1 | Z2: sitemap-core.xml | AA2: Live – indexable
A3: P0002 | B3: https://instasure.ca/about/ | C3: Static / tool | D3: Site, tools & trust | I3: Yes | J3: About Instasure.ca | K3: =LEN(J3) | L3: Instasure.ca helps Canadians understand insurance and price it instantly, then connects them with advisors licensed in their province. | M3: =LEN(L3) | N3: About Instasure.ca | S3: =COUNTIF('Page-Keyword Map'!$A$2:$A$675,B3) | T3: =SUMIF('Page-Keyword Map'!$A$2:$A$675,B3,'Page-Keyword Map'!$H$2:$H$675) | U3: =COUNTIFS('Page-Keyword Map'!$A$2:$A$675,B3,'Page-Keyword Map'!$E$2:$E$675,"Nationwide") | V3: =COUNTIFS('Page-Keyword Map'!$A$2:$A$675,B3,'Page-Keyword Map'!$E$2:$E$675,"Provincial") | W3: =COUNTIFS('Page-Keyword Map'!$A$2:$A$675,B3,'Page-Keyword Map'!$E$2:$E$675,"City") | X3: =IF(O3="","",IF(ISNUMBER(SEARCH(O3,J3)),"Yes","No")) | Y3: 0.4 | Z3: sitemap-core.xml | AA3: Live – indexable
A4: P0003 | B4: https://instasure.ca/accessibility/ | C4: Static / tool | D4: Site, tools & trust | I4: Yes | J4: Accessibility | Instasure.ca | K4: =LEN(J4) | L4: Instasure.ca’s commitment to an accessible website for all Canadians, including AODA and WCAG 2.1 AA alignment. | M4: =LEN(L4) | N4: Accessibility | S4: =COUNTIF('Page-Keyword Map'!$A$2:$A$675,B4) | T4: =SUMIF('Page-Keyword Map'!$A$2:$A$675,B4,'Page-Keyword Map'!$H$2:$H$675) | U4: =COUNTIFS('Page-Keyword Map'!$A$2:$A$675,B4,'Page-Keyword Map'!$E$2:$E$675,"Nationwide") | V4: =COUNTIFS('Page-Keyword Map'!$A$2:$A$675,B4,'Page-Keyword Map'!$E$2:$E$675,"Provincial") | W4: =COUNTIFS('Page-Keyword Map'!$A$2:$A$675,B4,'Page-Keyword Map'!$E$2:$E$675,"City") | X4: =IF(O4="","",IF(ISNUMBER(SEARCH(O4,J4)),"Yes","No")) | Y4: 0.2 | Z4: sitemap-core.xml | AA4: Live – indexable
A5: P0004 | B5: https://instasure.ca/advisors/ | C5: Static / tool | D5: Site, tools & trust | I5: Yes | J5: Licensed Insurance Advisors Across Canada | Instasure.ca | K5: =LEN(J5) | L5: Meet Instasure’s licensed insurance advisors. Every advisor is licensed in the provinces they serve and matched to you by province, product and language. | M5: =LEN(L5) | N5: Licensed insurance advisors across Canada | O5: insurance broker near me | P5: 6600 | Q5: Nationwide | S5: =COUNTIF('Page-Keyword Map'!$A$2:$A$675,B5) | T5: =SUMIF('Page-Keyword Map'!$A$2:$A$675,B5,'Page-Keyword Map'!$H$2:$H$675) | U5: =COUNTIFS('Page-Keyword Map'!$A$2:$A$675,B5,'Page-Keyword Map'!$E$2:$E$675,"Nationwide") | V5: =COUNTIFS('Page-Keyword Map'!$A$2:$A$675,B5,'Page-Keyword Map'!$E$2:$E$675,"Provincial") | W5: =COUNTIFS('Page-Keyword Map'!$A$2:$A$675,B5,'Page-Keyword Map'!$E$2:$E$675,"City") | X5: =IF(O5="","",IF(ISNUMBER(SEARCH(O5,J5)),"Yes","No")) | Y5: 0.7 | Z5: sitemap-core.xml | AA5: Live – indexable
A6: P0005 | B6: https://instasure.ca/calculators/ | C6: Static / tool | D6: Site, tools & trust | I6: Yes | J6: Free Insurance Calculators for Canadians | Instasure.ca | K6: =LEN(J6) | L6: Free Canadian insurance calculators: life insurance needs, mortgage protection vs term life, tenant & condo coverage and small-business coverage — instant results,… | M6: =LEN(L6) | N6: Insurance calculators for Canadians | S6: =COUNTIF('Page-Keyword Map'!$A$2:$A$675,B6) | T6: =SUMIF('Page-Keyword Map'!$A$2:$A$675,B6,'Page-Keyword Map'!$H$2:$H$675) | U6: =COUNTIFS('Page-Keyword Map'!$A$2:$A$675,B6,'Page-Keyword Map'!$E$2:$E$675,"Nationwide") | V6: =COUNTIFS('Page-Keyword Map'!$A$2:$A$675,B6,'Page-Keyword Map'!$E$2:$E$675,"Provincial") | W6: =COUNTIFS('Page-Keyword Map'!$A$2:$A$675,B6,'Page-Keyword Map'!$E$2:$E$675,"City") | X6: =IF(O6="","",IF(ISNUMBER(SEARCH(O6,J6)),"Yes","No")) | Y6: 0.8 | Z6: sitemap-core.xml | AA6: Live – indexable
A7: P0006 | B7: https://instasure.ca/calculators/business-coverage/ | C7: Static / tool | D7: Site, tools & trust | I7: Yes | J7: Small Business Insurance Coverage Checker | Instasure.ca | K7: =LEN(J7) | L7: Answer a few questions about your business to see recommended CGL, E&O, property and cyber coverage plus an instant cost estimate. | M7: =LEN(L7) | N7: What business insurance do I need? | O7: business insurance calculator | P7: 140 | Q7: Nationwide | S7: =COUNTIF('Page-Keyword Map'!$A$2:$A$675,B7) | T7: =SUMIF('Page-Keyword Map'!$A$2:$A$675,B7,'Page-Keyword Map'!$H$2:$H$675) | U7: =COUNTIFS('Page-Keyword Map'!$A$2:$A$675,B7,'Page-Keyword Map'!$E$2:$E$675,"Nationwide") | V7: =COUNTIFS('Page-Keyword Map'!$A$2:$A$675,B7,'Page-Keyword Map'!$E$2:$E$675,"Provincial") | W7: =COUNTIFS('Page-Keyword Map'!$A$2:$A$675,B7,'Page-Keyword Map'!$E$2:$E$675,"City") | X7: =IF(O7="","",IF(ISNUMBER(SEARCH(O7,J7)),"Yes","No")) | Y7: 0.6 | Z7: sitemap-core.xml | AA7: Live – indexable
A8: P0007 | B8: https://instasure.ca/calculators/life-insurance-needs/ | C8: Static / tool | D8: Site, tools & trust | I8: Yes | J8: Life Insurance Needs Calculator (Canada) | Instasure.ca | K8: =LEN(J8) | L8: Calculate how much life insurance your family needs using your income, mortgage, debts, childcare and education costs — built for Canadian households. | M8: =LEN(L8) | N8: How much life insurance do I need? | O8: life insurance calculator | P8: 2400 | Q8: Nationwide | S8: =COUNTIF('Page-Keyword Map'!$A$2:$A$675,B8) | T8: =SUMIF('Page-Keyword Map'!$A$2:$A$675,B8,'Page-Keyword Map'!$H$2:$H$675) | U8: =COUNTIFS('Page-Keyword Map'!$A$2:$A$675,B8,'Page-Keyword Map'!$E$2:$E$675,"Nationwide") | V8: =COUNTIFS('Page-Keyword Map'!$A$2:$A$675,B8,'Page-Keyword Map'!$E$2:$E$675,"Provincial") | W8: =COUNTIFS('Page-Keyword Map'!$A$2:$A$675,B8,'Page-Keyword Map'!$E$2:$E$675,"City") | X8: =IF(O8="","",IF(ISNUMBER(SEARCH(O8,J8)),"Yes","No")) | Y8: 0.8 | Z8: sitemap-core.xml | AA8: Live – indexable
A9: P0008 | B9: https://instasure.ca/calculators/mortgage-protection/ | C9: Static / tool | D9: Site, tools & trust | I9: Yes | J9: Mortgage Life Insurance vs Term Life Calculator | Instasure.ca | K9: =LEN(J9) | L9: Compare the cost and payout of bank mortgage creditor insurance against a personal term life policy for your mortgage balance and age. | M9: =LEN(L9) | N9: Mortgage protection calculator: bank insurance vs term life | O9: mortgage life insurance calculator | P9: 260 | Q9: Nationwide | S9: =COUNTIF('Page-Keyword Map'!$A$2:$A$675,B9) | T9: =SUMIF('Page-Keyword Map'!$A$2:$A$675,B9,'Page-Keyword Map'!$H$2:$H$675) | U9: =COUNTIFS('Page-Keyword Map'!$A$2:$A$675,B9,'Page-Keyword Map'!$E$2:$E$675,"Nationwide") | V9: =COUNTIFS('Page-Keyword Map'!$A$2:$A$675,B9,'Page-Keyword Map'!$E$2:$E$675,"Provincial") | W9: =COUNTIFS('Page-Keyword Map'!$A$2:$A$675,B9,'Page-Keyword Map'!$E$2:$E$675,"City") | X9: =IF(O9="","",IF(ISNUMBER(SEARCH(O9,J9)),"Yes","No")) | Y9: 0.6 | Z9: sitemap-core.xml | AA9: Live – indexable
A10: P0009 | B10: https://instasure.ca/calculators/tenant-condo-coverage/ | C10: Static / tool | D10: Site, tools & trust | I10: Yes | J10: Tenant & Condo Insurance Coverage Calculator | Instasure.ca | K10: =LEN(J10) | L10: Estimate the replacement value of your belongings, condo improvements and the deductible-assessment coverage your building requires. | M10: =LEN(L10) | N10: How much tenant or condo insurance do I need? | O10: how much contents insurance do i need | P10: 260 | Q10: Nationwide | S10: =COUNTIF('Page-Keyword Map'!$A$2:$A$675,B10) | T10: =SUMIF('Page-Keyword Map'!$A$2:$A$675,B10,'Page-Keyword Map'!$H$2:$H$675) | U10: =COUNTIFS('Page-Keyword Map'!$A$2:$A$675,B10,'Page-Keyword Map'!$E$2:$E$675,"Nationwide") | V10: =COUNTIFS('Page-Keyword Map'!$A$2:$A$675,B10,'Page-Keyword Map'!$E$2:$E$675,"Provincial") | W10: =COUNTIFS('Page-Keyword Map'!$A$2:$A$675,B10,'Page-Keyword Map'!$E$2:$E$675,"City") | X10: =IF(O10="","",IF(ISNUMBER(SEARCH(O10,J10)),"Yes","No")) | Y10: 0.6 | Z10: sitemap-core.xml | AA10: Live – indexable
A11: P0010 | B11: https://instasure.ca/compare/ | C11: Static / tool | D11: Site, tools & trust | I11: Yes | J11: Compare life insurance options in Canada (2026) | Instasure.ca | K11: =LEN(J11) | L11: Side-by-side comparison of life insurance options in Canada — price, underwriting speed, medical requirements and features — with instant estimates and licensed… | M11: =LEN(L11) | N11: Compare life insurance options | O11: compare insurance quotes canada | P11: 1000 | Q11: Nationwide | S11: =COUNTIF('Page-Keyword Map'!$A$2:$A$675,B11) | T11: =SUMIF('Page-Keyword Map'!$A$2:$A$675,B11,'Page-Keyword Map'!$H$2:$H$675) | U11: =COUNTIFS('Page-Keyword Map'!$A$2:$A$675,B11,'Page-Keyword Map'!$E$2:$E$675,"Nationwide") | V11: =COUNTIFS('Page-Keyword Map'!$A$2:$A$675,B11,'Page-Keyword Map'!$E$2:$E$675,"Provincial") | W11: =COUNTIFS('Page-Keyword Map'!$A$2:$A$675,B11,'Page-Keyword Map'!$E$2:$E$675,"City") | X11: =IF(O11="","",IF(ISNUMBER(SEARCH(O11,J11)),"Yes","No")) | Y11: 0.7 | Z11: sitemap-core.xml | AA11: Live – indexable
A12: P0011 | B12: https://instasure.ca/contact/ | C12: Static / tool | D12: Site, tools & trust | I12: Yes | J12: Contact Instasure — Book a Free Licensed Advisor Review | K12: =LEN(J12) | L12: Book a free, no-obligation insurance review with an advisor licensed in your province, or send us a question. | M12: =LEN(L12) | N12: Talk to a licensed advisor | S12: =COUNTIF('Page-Keyword Map'!$A$2:$A$675,B12) | T12: =SUMIF('Page-Keyword Map'!$A$2:$A$675,B12,'Page-Keyword Map'!$H$2:$H$675) | U12: =COUNTIFS('Page-Keyword Map'!$A$2:$A$675,B12,'Page-Keyword Map'!$E$2:$E$675,"Nationwide") | V12: =COUNTIFS('Page-Keyword Map'!$A$2:$A$675,B12,'Page-Keyword Map'!$E$2:$E$675,"Provincial") | W12: =COUNTIFS('Page-Keyword Map'!$A$2:$A$675,B12,'Page-Keyword Map'!$E$2:$E$675,"City") | X12: =IF(O12="","",IF(ISNUMBER(SEARCH(O12,J12)),"Yes","No")) | Y12: 0.4 | Z12: sitemap-core.xml | AA12: Live – indexable
A13: P0012 | B13: https://instasure.ca/editorial-guidelines/ | C13: Static / tool | D13: Site, tools & trust | I13: Yes | J13: Editorial guidelines | Instasure.ca | K13: =LEN(J13) | L13: How Instasure.ca researches, writes, reviews and updates its insurance guides — sources, expert review, corrections and independence. | M13: =LEN(L13) | N13: Editorial guidelines | S13: =COUNTIF('Page-Keyword Map'!$A$2:$A$675,B13) | T13: =SUMIF('Page-Keyword Map'!$A$2:$A$675,B13,'Page-Keyword Map'!$H$2:$H$675) | U13: =COUNTIFS('Page-Keyword Map'!$A$2:$A$675,B13,'Page-Keyword Map'!$E$2:$E$675,"Nationwide") | V13: =COUNTIFS('Page-Keyword Map'!$A$2:$A$675,B13,'Page-Keyword Map'!$E$2:$E$675,"Provincial") | W13: =COUNTIFS('Page-Keyword Map'!$A$2:$A$675,B13,'Page-Keyword Map'!$E$2:$E$675,"City") | X13: =IF(O13="","",IF(ISNUMBER(SEARCH(O13,J13)),"Yes","No")) | Y13: 0.4 | Z13: sitemap-core.xml | AA13: Live – indexable
A14: P0013 | B14: https://instasure.ca/glossary/ | C14: Static / tool | D14: Site, tools & trust | I14: Yes | J14: Canadian Insurance Glossary: Plain-Language Definitions | K14: =LEN(J14) | L14: Plain-language definitions of Canadian insurance terms — from accident benefits and DCPD to riders, simplified issue and deductible assessments. | M14: =LEN(L14) | N14: Canadian insurance glossary | O14: car insurance deductible | P14: 880 | Q14: Nationwide | S14: =COUNTIF('Page-Keyword Map'!$A$2:$A$675,B14) | T14: =SUMIF('Page-Keyword Map'!$A$2:$A$675,B14,'Page-Keyword Map'!$H$2:$H$675) | U14: =COUNTIFS('Page-Keyword Map'!$A$2:$A$675,B14,'Page-Keyword Map'!$E$2:$E$675,"Nationwide") | V14: =COUNTIFS('Page-Keyword Map'!$A$2:$A$675,B14,'Page-Keyword Map'!$E$2:$E$675,"Provincial") | W14: =COUNTIFS('Page-Keyword Map'!$A$2:$A$675,B14,'Page-Keyword Map'!$E$2:$E$675,"City") | X14: =IF(O14="","",IF(ISNUMBER(SEARCH(O14,J14)),"Yes","No")) | Y14: 0.5 | Z14: sitemap-core.xml | AA14: Live – indexable
A15: P0014 | B15: https://instasure.ca/guides/ | C15: Static / tool | D15: Site, tools & trust | I15: Yes | J15: Insurance Guides for Canadians — Knowledge & Risk Center | K15: =LEN(J15) | L15: Plain-language Canadian insurance guides: life, critical illness, home, tenant, car, travel and business coverage — with calculators, province rules and… | M15: =LEN(L15) | N15: Insurance Knowledge & Risk Center | S15: =COUNTIF('Page-Keyword Map'!$A$2:$A$675,B15) | T15: =SUMIF('Page-Keyword Map'!$A$2:$A$675,B15,'Page-Keyword Map'!$H$2:$H$675) | U15: =COUNTIFS('Page-Keyword Map'!$A$2:$A$675,B15,'Page-Keyword Map'!$E$2:$E$675,"Nationwide") | V15: =COUNTIFS('Page-Keyword Map'!$A$2:$A$675,B15,'Page-Keyword Map'!$E$2:$E$675,"Provincial") | W15: =COUNTIFS('Page-Keyword Map'!$A$2:$A$675,B15,'Page-Keyword Map'!$E$2:$E$675,"City") | X15: =IF(O15="","",IF(ISNUMBER(SEARCH(O15,J15)),"Yes","No")) | Y15: 0.8 | Z15: sitemap-core.xml | AA15: Live – indexable
A16: P0015 | B16: https://instasure.ca/how-we-make-money/ | C16: Static / tool | D16: Site, tools & trust | I16: Yes | J16: How Instasure makes money | Instasure.ca | K16: =LEN(J16) | L16: Transparency about how Instasure.ca is paid, how advisors are compensated, and how that affects (and doesn’t affect) what you pay. | M16: =LEN(L16) | N16: How Instasure makes money | S16: =COUNTIF('Page-Keyword Map'!$A$2:$A$675,B16) | T16: =SUMIF('Page-Keyword Map'!$A$2:$A$675,B16,'Page-Keyword Map'!$H$2:$H$675) | U16: =COUNTIFS('Page-Keyword Map'!$A$2:$A$675,B16,'Page-Keyword Map'!$E$2:$E$675,"Nationwide") | V16: =COUNTIFS('Page-Keyword Map'!$A$2:$A$675,B16,'Page-Keyword Map'!$E$2:$E$675,"Provincial") | W16: =COUNTIFS('Page-Keyword Map'!$A$2:$A$675,B16,'Page-Keyword Map'!$E$2:$E$675,"City") | X16: =IF(O16="","",IF(ISNUMBER(SEARCH(O16,J16)),"Yes","No")) | Y16: 0.4 | Z16: sitemap-core.xml | AA16: Live – indexable
A17: P0016 | B17: https://instasure.ca/insights/rate-index/ | C17: Static / tool | D17: Site, tools & trust | I17: No | J17: Instasure Rate Index — Canadian Insurance Estimates (October 2026) | K17: =LEN(J17) | L17: Quarterly index of Canadian insurance estimate ranges by product and province, built from anonymised Instasure quote requests. | M17: =LEN(L17) | N17: Instasure Rate Index | O17: average car insurance cost canada | P17: 2900 | Q17: Nationwide | S17: =COUNTIF('Page-Keyword Map'!$A$2:$A$675,B17) | T17: =SUMIF('Page-Keyword Map'!$A$2:$A$675,B17,'Page-Keyword Map'!$H$2:$H$675) | U17: =COUNTIFS('Page-Keyword Map'!$A$2:$A$675,B17,'Page-Keyword Map'!$E$2:$E$675,"Nationwide") | V17: =COUNTIFS('Page-Keyword Map'!$A$2:$A$675,B17,'Page-Keyword Map'!$E$2:$E$675,"Provincial") | W17: =COUNTIFS('Page-Keyword Map'!$A$2:$A$675,B17,'Page-Keyword Map'!$E$2:$E$675,"City") | X17: =IF(O17="","",IF(ISNUMBER(SEARCH(O17,J17)),"Yes","No")) | Y17: 0.7 | Z17: (not listed: noindex) | AA17: Live – noindex (enrich before indexing)
A18: P0017 | B18: https://instasure.ca/insurance-services/ | C18: Static / tool | D18: Cross-product & brand | I18: Yes | J18: All Insurance Services & Specialist Desks in Canada | K18: =LEN(J18) | L18: Every type of insurance Instasure covers, from car, home and life to pet, boat, landlord and commercial auto, plus specialist desks for hard-to-place needs. | M18: =LEN(L18) | N18: Every kind of insurance, one licensed advisor | O18: types of insurance in canada | P18: 1000 | Q18: Nationwide | S18: =COUNTIF('Page-Keyword Map'!$A$2:$A$675,B18) | T18: =SUMIF('Page-Keyword Map'!$A$2:$A$675,B18,'Page-Keyword Map'!$H$2:$H$675) | U18: =COUNTIFS('Page-Keyword Map'!$A$2:$A$675,B18,'Page-Keyword Map'!$E$2:$E$675,"Nationwide") | V18: =COUNTIFS('Page-Keyword Map'!$A$2:$A$675,B18,'Page-Keyword Map'!$E$2:$E$675,"Provincial") | W18: =COUNTIFS('Page-Keyword Map'!$A$2:$A$675,B18,'Page-Keyword Map'!$E$2:$E$675,"City") | X18: =IF(O18="","",IF(ISNUMBER(SEARCH(O18,J18)),"Yes","No")) | Y18: 0.8 | Z18: sitemap-core.xml | AA18: Live – indexable
A19: P0018 | B19: https://instasure.ca/insurance/ | C19: Static / tool | D19: Multi-line (place hubs) | I19: Yes | J19: Insurance in Canada by Province & Territory | Instasure.ca | K19: =LEN(J19) | L19: How insurance works in each Canadian province and territory — regulators, public vs private auto insurance, local risks and licensed advisors. | M19: =LEN(L19) | N19: Insurance in Canada, province by province | S19: =COUNTIF('Page-Keyword Map'!$A$2:$A$675,B19) | T19: =SUMIF('Page-Keyword Map'!$A$2:$A$675,B19,'Page-Keyword Map'!$H$2:$H$675) | U19: =COUNTIFS('Page-Keyword Map'!$A$2:$A$675,B19,'Page-Keyword Map'!$E$2:$E$675,"Nationwide") | V19: =COUNTIFS('Page-Keyword Map'!$A$2:$A$675,B19,'Page-Keyword Map'!$E$2:$E$675,"Provincial") | W19: =COUNTIFS('Page-Keyword Map'!$A$2:$A$675,B19,'Page-Keyword Map'!$E$2:$E$675,"City") | X19: =IF(O19="","",IF(ISNUMBER(SEARCH(O19,J19)),"Yes","No")) | Y19: 0.7 | Z19: sitemap-core.xml | AA19: Live – indexable
A20: P0019 | B20: https://instasure.ca/licensing/ | C20: Static / tool | D20: Site, tools & trust | I20: Yes | J20: Licensing & disclosures | Instasure.ca | K20: =LEN(J20) | L20: Licensing, regulatory and complaint information for Instasure.ca and the licensed advisors who serve its users. | M20: =LEN(L20) | N20: Licensing & disclosures | S20: =COUNTIF('Page-Keyword Map'!$A$2:$A$675,B20) | T20: =SUMIF('Page-Keyword Map'!$A$2:$A$675,B20,'Page-Keyword Map'!$H$2:$H$675) | U20: =COUNTIFS('Page-Keyword Map'!$A$2:$A$675,B20,'Page-Keyword Map'!$E$2:$E$675,"Nationwide") | V20: =COUNTIFS('Page-Keyword Map'!$A$2:$A$675,B20,'Page-Keyword Map'!$E$2:$E$675,"Provincial") | W20: =COUNTIFS('Page-Keyword Map'!$A$2:$A$675,B20,'Page-Keyword Map'!$E$2:$E$675,"City") | X20: =IF(O20="","",IF(ISNUMBER(SEARCH(O20,J20)),"Yes","No")) | Y20: 0.4 | Z20: sitemap-core.xml | AA20: Live – indexable
A21: P0020 | B21: https://instasure.ca/privacy/ | C21: Static / tool | D21: Site, tools & trust | I21: Yes | J21: Privacy policy | Instasure.ca | K21: =LEN(J21) | L21: How Instasure.ca collects, uses, shares and protects personal information under PIPEDA and applicable provincial privacy laws, including Quebec’s Law 25. | M21: =LEN(L21) | N21: Privacy policy | S21: =COUNTIF('Page-Keyword Map'!$A$2:$A$675,B21) | T21: =SUMIF('Page-Keyword Map'!$A$2:$A$675,B21,'Page-Keyword Map'!$H$2:$H$675) | U21: =COUNTIFS('Page-Keyword Map'!$A$2:$A$675,B21,'Page-Keyword Map'!$E$2:$E$675,"Nationwide") | V21: =COUNTIFS('Page-Keyword Map'!$A$2:$A$675,B21,'Page-Keyword Map'!$E$2:$E$675,"Provincial") | W21: =COUNTIFS('Page-Keyword Map'!$A$2:$A$675,B21,'Page-Keyword Map'!$E$2:$E$675,"City") | X21: =IF(O21="","",IF(ISNUMBER(SEARCH(O21,J21)),"Yes","No")) | Y21: 0.2 | Z21: sitemap-core.xml | AA21: Live – indexable
A22: P0021 | B22: https://instasure.ca/quote/ | C22: Static / tool | D22: Site, tools & trust | I22: Yes | J22: Get an Instant Insurance Quote in Canada | Instasure.ca | K22: =LEN(J22) | L22: Choose your coverage and get an instant premium estimate in about 60 seconds — life, critical illness, disability, home, tenant, condo, car, travel, Super Visa and… | M22: =LEN(L22) | N22: What would you like to insure? | O22: insurance quotes | P22: 6600 | Q22: Nationwide | S22: =COUNTIF('Page-Keyword Map'!$A$2:$A$675,B22) | T22: =SUMIF('Page-Keyword Map'!$A$2:$A$675,B22,'Page-Keyword Map'!$H$2:$H$675) | U22: =COUNTIFS('Page-Keyword Map'!$A$2:$A$675,B22,'Page-Keyword Map'!$E$2:$E$675,"Nationwide") | V22: =COUNTIFS('Page-Keyword Map'!$A$2:$A$675,B22,'Page-Keyword Map'!$E$2:$E$675,"Provincial") | W22: =COUNTIFS('Page-Keyword Map'!$A$2:$A$675,B22,'Page-Keyword Map'!$E$2:$E$675,"City") | X22: =IF(O22="","",IF(ISNUMBER(SEARCH(O22,J22)),"Yes","No")) | Y22: 0.9 | Z22: sitemap-core.xml | AA22: Live – indexable
A23: P0022 | B23: https://instasure.ca/site-map/ | C23: Static / tool | D23: Site, tools & trust | I23: Yes | J23: Site map | Instasure.ca | K23: =LEN(J23) | L23: Every guide, product, province and city page on Instasure.ca. | M23: =LEN(L23) | N23: Site map | S23: =COUNTIF('Page-Keyword Map'!$A$2:$A$675,B23) | T23: =SUMIF('Page-Keyword Map'!$A$2:$A$675,B23,'Page-Keyword Map'!$H$2:$H$675) | U23: =COUNTIFS('Page-Keyword Map'!$A$2:$A$675,B23,'Page-Keyword Map'!$E$2:$E$675,"Nationwide") | V23: =COUNTIFS('Page-Keyword Map'!$A$2:$A$675,B23,'Page-Keyword Map'!$E$2:$E$675,"Provincial") | W23: =COUNTIFS('Page-Keyword Map'!$A$2:$A$675,B23,'Page-Keyword Map'!$E$2:$E$675,"City") | X23: =IF(O23="","",IF(ISNUMBER(SEARCH(O23,J23)),"Yes","No")) | Y23: 0.3 | Z23: sitemap-core.xml | AA23: Live – indexable
A24: P0023 | B24: https://instasure.ca/terms/ | C24: Static / tool | D24: Site, tools & trust | I24: Yes | J24: Terms of use | Instasure.ca | K24: =LEN(J24) | L24: Terms governing your use of Instasure.ca, its guides, calculators and instant estimates. | M24: =LEN(L24) | N24: Terms of use | S24: =COUNTIF('Page-Keyword Map'!$A$2:$A$675,B24) | T24: =SUMIF('Page-Keyword Map'!$A$2:$A$675,B24,'Page-Keyword Map'!$H$2:$H$675) | U24: =COUNTIFS('Page-Keyword Map'!$A$2:$A$675,B24,'Page-Keyword Map'!$E$2:$E$675,"Nationwide") | V24: =COUNTIFS('Page-Keyword Map'!$A$2:$A$675,B24,'Page-Keyword Map'!$E$2:$E$675,"Provincial") | W24: =COUNTIFS('Page-Keyword Map'!$A$2:$A$675,B24,'Page-Keyword Map'!$E$2:$E$675,"City") | X24: =IF(O24="","",IF(ISNUMBER(SEARCH(O24,J24)),"Yes","No")) | Y24: 0.2 | Z24: sitemap-core.xml | AA24: Live – indexable
A25: P0024 | B25: https://instasure.ca/business-insurance/ | C25: Product pillar | D25: Business insurance | E25: Business Insurance | I25: Yes | J25: Small Business Insurance (2026) | Instasure.ca | K25: =LEN(J25) | L25: From sole proprietors to growing teams — the coverage clients, landlords and contracts require. Instant business insurance estimates for every province,… | M25: =LEN(L25) | N25: Small Business Insurance: Liability, Property & Professional Coverage | O25: business insurance | P25: 8100 | Q25: Nationwide | S25: =COUNTIF('Page-Keyword Map'!$A$2:$A$675,B25) | T25: =SUMIF('Page-Keyword Map'!$A$2:$A$675,B25,'Page-Keyword Map'!$H$2:$H$675) | U25: =COUNTIFS('Page-Keyword Map'!$A$2:$A$675,B25,'Page-Keyword Map'!$E$2:$E$675,"Nationwide") | V25: =COUNTIFS('Page-Keyword Map'!$A$2:$A$675,B25,'Page-Keyword Map'!$E$2:$E$675,"Provincial") | W25: =COUNTIFS('Page-Keyword Map'!$A$2:$A$675,B25,'Page-Keyword Map'!$E$2:$E$675,"City") | X25: =IF(O25="","",IF(ISNUMBER(SEARCH(O25,J25)),"Yes","No")) | Y25: 0.9 | Z25: sitemap-core.xml | AA25: Live – indexable
A26: P0025 | B26: https://instasure.ca/car-insurance/ | C26: Product pillar | D26: Car insurance | E26: Car Insurance | I26: Yes | J26: Car Insurance Quotes (2026) | Instasure.ca | K26: =LEN(J26) | L26: See what drivers like you pay, then let a licensed advisor compare insurers for you. Instant car insurance estimates for every province, plain-language guidance… | M26: =LEN(L26) | N26: Car Insurance Quotes: Compare Rates in Minutes | O26: car insurance | P26: 74000 | Q26: Nationwide | S26: =COUNTIF('Page-Keyword Map'!$A$2:$A$675,B26) | T26: =SUMIF('Page-Keyword Map'!$A$2:$A$675,B26,'Page-Keyword Map'!$H$2:$H$675) | U26: =COUNTIFS('Page-Keyword Map'!$A$2:$A$675,B26,'Page-Keyword Map'!$E$2:$E$675,"Nationwide") | V26: =COUNTIFS('Page-Keyword Map'!$A$2:$A$675,B26,'Page-Keyword Map'!$E$2:$E$675,"Provincial") | W26: =COUNTIFS('Page-Keyword Map'!$A$2:$A$675,B26,'Page-Keyword Map'!$E$2:$E$675,"City") | X26: =IF(O26="","",IF(ISNUMBER(SEARCH(O26,J26)),"Yes","No")) | Y26: 0.9 | Z26: sitemap-core.xml | AA26: Live – indexable
A27: P0026 | B27: https://instasure.ca/condo-insurance/ | C27: Product pillar | D27: Condo insurance | E27: Condo Insurance | I27: Yes | J27: Condo Insurance (2026) | Instasure.ca | K27: =LEN(J27) | L27: Your corporation’s policy covers the building — not your belongings, upgrades or your share of a large deductible. Instant condo insurance estimates for every… | M27: =LEN(L27) | N27: Condo Insurance: Unit, Improvements & Deductible Assessment Coverage | O27: condo insurance | P27: 6600 | Q27: Nationwide | S27: =COUNTIF('Page-Keyword Map'!$A$2:$A$675,B27) | T27: =SUMIF('Page-Keyword Map'!$A$2:$A$675,B27,'Page-Keyword Map'!$H$2:$H$675) | U27: =COUNTIFS('Page-Keyword Map'!$A$2:$A$675,B27,'Page-Keyword Map'!$E$2:$E$675,"Nationwide") | V27: =COUNTIFS('Page-Keyword Map'!$A$2:$A$675,B27,'Page-Keyword Map'!$E$2:$E$675,"Provincial") | W27: =COUNTIFS('Page-Keyword Map'!$A$2:$A$675,B27,'Page-Keyword Map'!$E$2:$E$675,"City") | X27: =IF(O27="","",IF(ISNUMBER(SEARCH(O27,J27)),"Yes","No")) | Y27: 0.9 | Z27: sitemap-core.xml | AA27: Live – indexable
A28: P0027 | B28: https://instasure.ca/contractor-insurance/ | C28: Product pillar | D28: Contractor & trades insurance | E28: Contractor Insurance | I28: Yes | J28: Contractor Insurance for Trades (2026) | Instasure.ca | K28: =LEN(J28) | L28: Get the certificate the general contractor or homeowner needs — fast. Instant contractor insurance estimates for every province, plain-language guidance and… | M28: =LEN(L28) | N28: Contractor Insurance for Trades: Liability, Tools & Equipment | O28: contractor insurance | P28: 1300 | Q28: Nationwide | S28: =COUNTIF('Page-Keyword Map'!$A$2:$A$675,B28) | T28: =SUMIF('Page-Keyword Map'!$A$2:$A$675,B28,'Page-Keyword Map'!$H$2:$H$675) | U28: =COUNTIFS('Page-Keyword Map'!$A$2:$A$675,B28,'Page-Keyword Map'!$E$2:$E$675,"Nationwide") | V28: =COUNTIFS('Page-Keyword Map'!$A$2:$A$675,B28,'Page-Keyword Map'!$E$2:$E$675,"Provincial") | W28: =COUNTIFS('Page-Keyword Map'!$A$2:$A$675,B28,'Page-Keyword Map'!$E$2:$E$675,"City") | X28: =IF(O28="","",IF(ISNUMBER(SEARCH(O28,J28)),"Yes","No")) | Y28: 0.9 | Z28: sitemap-core.xml | AA28: Live – indexable
A29: P0028 | B29: https://instasure.ca/critical-illness-insurance/ | C29: Product pillar | D29: Critical illness insurance | E29: Critical Illness Insurance | I29: Yes | J29: Critical Illness Insurance in Canada (2026) | Instasure.ca | K29: =LEN(J29) | L29: A lump-sum payment after a covered diagnosis like cancer, heart attack or stroke — spend it however recovery requires. Instant critical illness insurance estimates… | M29: =LEN(L29) | N29: Critical Illness Insurance in Canada: Tax-Free Cash If You Get Sick | O29: critical illness insurance | P29: 6600 | Q29: Nationwide | S29: =COUNTIF('Page-Keyword Map'!$A$2:$A$675,B29) | T29: =SUMIF('Page-Keyword Map'!$A$2:$A$675,B29,'Page-Keyword Map'!$H$2:$H$675) | U29: =COUNTIFS('Page-Keyword Map'!$A$2:$A$675,B29,'Page-Keyword Map'!$E$2:$E$675,"Nationwide") | V29: =COUNTIFS('Page-Keyword Map'!$A$2:$A$675,B29,'Page-Keyword Map'!$E$2:$E$675,"Provincial") | W29: =COUNTIFS('Page-Keyword Map'!$A$2:$A$675,B29,'Page-Keyword Map'!$E$2:$E$675,"City") | X29: =IF(O29="","",IF(ISNUMBER(SEARCH(O29,J29)),"Yes","No")) | Y29: 0.9 | Z29: sitemap-core.xml | AA29: Live – indexable
A30: P0029 | B30: https://instasure.ca/disability-insurance/ | C30: Product pillar | D30: Disability insurance | E30: Disability Insurance | I30: Yes | J30: Disability Insurance in Canada (2026) | Instasure.ca | K30: =LEN(J30) | L30: Monthly income if illness or injury stops you from working — essential for the self-employed. Instant disability insurance estimates for every province,… | M30: =LEN(L30) | N30: Disability Insurance in Canada: Protect Your Income | O30: disability insurance | P30: 4400 | Q30: Nationwide | S30: =COUNTIF('Page-Keyword Map'!$A$2:$A$675,B30) | T30: =SUMIF('Page-Keyword Map'!$A$2:$A$675,B30,'Page-Keyword Map'!$H$2:$H$675) | U30: =COUNTIFS('Page-Keyword Map'!$A$2:$A$675,B30,'Page-Keyword Map'!$E$2:$E$675,"Nationwide") | V30: =COUNTIFS('Page-Keyword Map'!$A$2:$A$675,B30,'Page-Keyword Map'!$E$2:$E$675,"Provincial") | W30: =COUNTIFS('Page-Keyword Map'!$A$2:$A$675,B30,'Page-Keyword Map'!$E$2:$E$675,"City") | X30: =IF(O30="","",IF(ISNUMBER(SEARCH(O30,J30)),"Yes","No")) | Y30: 0.9 | Z30: sitemap-core.xml | AA30: Live – indexable
A31: P0030 | B31: https://instasure.ca/group-benefits/ | C31: Product pillar | D31: Group benefits | E31: Group Benefits | I31: Yes | J31: Group Benefits for Small Businesses (2026) | Instasure.ca | K31: =LEN(J31) | L31: Attract and keep great people with a benefits plan sized for teams of 2 to 200. Instant group benefits estimates for every province, plain-language guidance and… | M31: =LEN(L31) | N31: Group Benefits for Small Businesses: Health, Dental & More | O31: group benefits for small business | P31: 1300 | Q31: Nationwide | S31: =COUNTIF('Page-Keyword Map'!$A$2:$A$675,B31) | T31: =SUMIF('Page-Keyword Map'!$A$2:$A$675,B31,'Page-Keyword Map'!$H$2:$H$675) | U31: =COUNTIFS('Page-Keyword Map'!$A$2:$A$675,B31,'Page-Keyword Map'!$E$2:$E$675,"Nationwide") | V31: =COUNTIFS('Page-Keyword Map'!$A$2:$A$675,B31,'Page-Keyword Map'!$E$2:$E$675,"Provincial") | W31: =COUNTIFS('Page-Keyword Map'!$A$2:$A$675,B31,'Page-Keyword Map'!$E$2:$E$675,"City") | X31: =IF(O31="","",IF(ISNUMBER(SEARCH(O31,J31)),"Yes","No")) | Y31: 0.9 | Z31: sitemap-core.xml | AA31: Live – indexable
A32: P0031 | B32: https://instasure.ca/health-dental-insurance/ | C32: Product pillar | D32: Health & dental insurance | E32: Health & Dental Insurance | I32: Yes | J32: Health & Dental Insurance for Individuals and Families (2026) | K32: =LEN(J32) | L32: Prescription drugs, dental, vision and paramedical care that provincial plans don’t fully cover. Instant health & dental insurance estimates for every province,… | M32: =LEN(L32) | N32: Health & Dental Insurance for Individuals and Families | O32: dental insurance | P32: 8100 | Q32: Nationwide | S32: =COUNTIF('Page-Keyword Map'!$A$2:$A$675,B32) | T32: =SUMIF('Page-Keyword Map'!$A$2:$A$675,B32,'Page-Keyword Map'!$H$2:$H$675) | U32: =COUNTIFS('Page-Keyword Map'!$A$2:$A$675,B32,'Page-Keyword Map'!$E$2:$E$675,"Nationwide") | V32: =COUNTIFS('Page-Keyword Map'!$A$2:$A$675,B32,'Page-Keyword Map'!$E$2:$E$675,"Provincial") | W32: =COUNTIFS('Page-Keyword Map'!$A$2:$A$675,B32,'Page-Keyword Map'!$E$2:$E$675,"City") | X32: =IF(O32="","",IF(ISNUMBER(SEARCH(O32,J32)),"Yes","No")) | Y32: 0.9 | Z32: sitemap-core.xml | AA32: Live – indexable
A33: P0032 | B33: https://instasure.ca/home-insurance/ | C33: Product pillar | D33: Home insurance | E33: Home Insurance | I33: Yes | J33: Home Insurance Quotes (2026) | Instasure.ca | K33: =LEN(J33) | L33: Coverage built for Canadian risks — water, wind, hail, wildfire and theft. Instant home insurance estimates for every province, plain-language guidance and… | M33: =LEN(L33) | N33: Home Insurance Quotes: Protect Your House, Belongings & Liability | O33: home insurance | P33: 27000 | Q33: Nationwide | S33: =COUNTIF('Page-Keyword Map'!$A$2:$A$675,B33) | T33: =SUMIF('Page-Keyword Map'!$A$2:$A$675,B33,'Page-Keyword Map'!$H$2:$H$675) | U33: =COUNTIFS('Page-Keyword Map'!$A$2:$A$675,B33,'Page-Keyword Map'!$E$2:$E$675,"Nationwide") | V33: =COUNTIFS('Page-Keyword Map'!$A$2:$A$675,B33,'Page-Keyword Map'!$E$2:$E$675,"Provincial") | W33: =COUNTIFS('Page-Keyword Map'!$A$2:$A$675,B33,'Page-Keyword Map'!$E$2:$E$675,"City") | X33: =IF(O33="","",IF(ISNUMBER(SEARCH(O33,J33)),"Yes","No")) | Y33: 0.9 | Z33: sitemap-core.xml | AA33: Live – indexable
A34: P0033 | B34: https://instasure.ca/life-insurance/ | C34: Product pillar | D34: Life insurance | E34: Life Insurance | I34: Yes | J34: Life Insurance in Canada (2026) | Instasure.ca | K34: =LEN(J34) | L34: Protect your family’s income, mortgage and future with term or permanent coverage from leading Canadian insurers. Instant life insurance estimates for every… | M34: =LEN(L34) | N34: Life Insurance in Canada: Compare Quotes in 60 Seconds | O34: life insurance | P34: 33000 | Q34: Nationwide | S34: =COUNTIF('Page-Keyword Map'!$A$2:$A$675,B34) | T34: =SUMIF('Page-Keyword Map'!$A$2:$A$675,B34,'Page-Keyword Map'!$H$2:$H$675) | U34: =COUNTIFS('Page-Keyword Map'!$A$2:$A$675,B34,'Page-Keyword Map'!$E$2:$E$675,"Nationwide") | V34: =COUNTIFS('Page-Keyword Map'!$A$2:$A$675,B34,'Page-Keyword Map'!$E$2:$E$675,"Provincial") | W34: =COUNTIFS('Page-Keyword Map'!$A$2:$A$675,B34,'Page-Keyword Map'!$E$2:$E$675,"City") | X34: =IF(O34="","",IF(ISNUMBER(SEARCH(O34,J34)),"Yes","No")) | Y34: 0.9 | Z34: sitemap-core.xml | AA34: Live – indexable
A35: P0034 | B35: https://instasure.ca/mortgage-life-insurance/ | C35: Product pillar | D35: Mortgage protection | E35: Mortgage Life Insurance | I35: Yes | J35: Mortgage Life Insurance vs Term Life (2026) | Instasure.ca | K35: =LEN(J35) | L35: Make sure your family keeps the house — without overpaying for bank creditor insurance. Instant mortgage life insurance estimates for every province,… | M35: =LEN(L35) | N35: Mortgage Life Insurance vs Term Life: Protect Your Home for Less | O35: mortgage life insurance | P35: 2400 | Q35: Nationwide | S35: =COUNTIF('Page-Keyword Map'!$A$2:$A$675,B35) | T35: =SUMIF('Page-Keyword Map'!$A$2:$A$675,B35,'Page-Keyword Map'!$H$2:$H$675) | U35: =COUNTIFS('Page-Keyword Map'!$A$2:$A$675,B35,'Page-Keyword Map'!$E$2:$E$675,"Nationwide") | V35: =COUNTIFS('Page-Keyword Map'!$A$2:$A$675,B35,'Page-Keyword Map'!$E$2:$E$675,"Provincial") | W35: =COUNTIFS('Page-Keyword Map'!$A$2:$A$675,B35,'Page-Keyword Map'!$E$2:$E$675,"City") | X35: =IF(O35="","",IF(ISNUMBER(SEARCH(O35,J35)),"Yes","No")) | Y35: 0.9 | Z35: sitemap-core.xml | AA35: Live – indexable
A36: P0035 | B36: https://instasure.ca/no-medical-life-insurance/ | C36: Product pillar | D36: Life insurance | E36: No-Medical Life Insurance | I36: Yes | J36: No-Medical Life Insurance in Canada (2026) | Instasure.ca | K36: =LEN(J36) | L36: Fast approval with health questions instead of needles — including options if you have a medical condition. Instant no-medical life insurance estimates for every… | M36: =LEN(L36) | N36: No-Medical Life Insurance in Canada: Get Covered Without an Exam | O36: no medical life insurance | P36: 1300 | Q36: Nationwide | S36: =COUNTIF('Page-Keyword Map'!$A$2:$A$675,B36) | T36: =SUMIF('Page-Keyword Map'!$A$2:$A$675,B36,'Page-Keyword Map'!$H$2:$H$675) | U36: =COUNTIFS('Page-Keyword Map'!$A$2:$A$675,B36,'Page-Keyword Map'!$E$2:$E$675,"Nationwide") | V36: =COUNTIFS('Page-Keyword Map'!$A$2:$A$675,B36,'Page-Keyword Map'!$E$2:$E$675,"Provincial") | W36: =COUNTIFS('Page-Keyword Map'!$A$2:$A$675,B36,'Page-Keyword Map'!$E$2:$E$675,"City") | X36: =IF(O36="","",IF(ISNUMBER(SEARCH(O36,J36)),"Yes","No")) | Y36: 0.9 | Z36: sitemap-core.xml | AA36: Live – indexable
... A42: P0041 | B42: https://instasure.ca/whole-life-insurance/ | C42: Product pillar | D42: Life insurance | E42: Whole Life Insurance | I42: Yes | J42: Whole Life Insurance in Canada (2026) | Instasure.ca | K42: =LEN(J42) | L42: Lifetime coverage with guaranteed premiums and cash value — for estate, legacy and business planning. Instant whole life insurance estimates for every province,… | M42: =LEN(L42) | N42: Whole Life Insurance in Canada: Costs, Cash Value & When It Makes Sense | O42: whole life insurance | P42: 5400 | Q42: Nationwide | S42: =COUNTIF('Page-Keyword Map'!$A$2:$A$675,B42) | T42: =SUMIF('Page-Keyword Map'!$A$2:$A$675,B42,'Page-Keyword Map'!$H$2:$H$675) | U42: =COUNTIFS('Page-Keyword Map'!$A$2:$A$675,B42,'Page-Keyword Map'!$E$2:$E$675,"Nationwide") | V42: =COUNTIFS('Page-Keyword Map'!$A$2:$A$675,B42,'Page-Keyword Map'!$E$2:$E$675,"Provincial") | W42: =COUNTIFS('Page-Keyword Map'!$A$2:$A$675,B42,'Page-Keyword Map'!$E$2:$E$675,"City") | X42: =IF(O42="","",IF(ISNUMBER(SEARCH(O42,J42)),"Yes","No")) | Y42: 0.9 | Z42: sitemap-core.xml | AA42: Live – indexable
A43: P0042 | B43: https://instasure.ca/atv-snowmobile-insurance/ | C43: Service page | D43: Recreational vehicles | E43: Car Insurance | F43: ATV & Snowmobile Insurance | I43: Yes | J43: ATV & Snowmobile Insurance in Canada | Instasure.ca | K43: =LEN(J43) | L43: Insurance for ATVs, side-by-sides and snowmobiles: when it is required, trail permits, liability and damage coverage, and seasonal pricing. | M43: =LEN(L43) | N43: ATV & Snowmobile Insurance | O43: snowmobile insurance | P43: 1000 | Q43: Nationwide | S43: =COUNTIF('Page-Keyword Map'!$A$2:$A$675,B43) | T43: =SUMIF('Page-Keyword Map'!$A$2:$A$675,B43,'Page-Keyword Map'!$H$2:$H$675) | U43: =COUNTIFS('Page-Keyword Map'!$A$2:$A$675,B43,'Page-Keyword Map'!$E$2:$E$675,"Nationwide") | V43: =COUNTIFS('Page-Keyword Map'!$A$2:$A$675,B43,'Page-Keyword Map'!$E$2:$E$675,"Provincial") | W43: =COUNTIFS('Page-Keyword Map'!$A$2:$A$675,B43,'Page-Keyword Map'!$E$2:$E$675,"City") | X43: =IF(O43="","",IF(ISNUMBER(SEARCH(O43,J43)),"Yes","No")) | Y43: 0.7 | Z43: sitemap-services.xml | AA43: Live – indexable
A44: P0043 | B44: https://instasure.ca/boat-insurance/ | C44: Service page | D44: Recreational vehicles | E44: Home Insurance | F44: Boat Insurance | I44: Yes | J44: Boat Insurance in Canada: Pleasure Craft and Watercraft | K44: =LEN(J44) | L44: Boat and personal watercraft insurance in Canada: liability, hull and equipment coverage, what a home policy covers and marina requirements. | M44: =LEN(L44) | N44: Boat Insurance | O44: boat insurance | P44: 2900 | Q44: Nationwide | S44: =COUNTIF('Page-Keyword Map'!$A$2:$A$675,B44) | T44: =SUMIF('Page-Keyword Map'!$A$2:$A$675,B44,'Page-Keyword Map'!$H$2:$H$675) | U44: =COUNTIFS('Page-Keyword Map'!$A$2:$A$675,B44,'Page-Keyword Map'!$E$2:$E$675,"Nationwide") | V44: =COUNTIFS('Page-Keyword Map'!$A$2:$A$675,B44,'Page-Keyword Map'!$E$2:$E$675,"Provincial") | W44: =COUNTIFS('Page-Keyword Map'!$A$2:$A$675,B44,'Page-Keyword Map'!$E$2:$E$675,"City") | X44: =IF(O44="","",IF(ISNUMBER(SEARCH(O44,J44)),"Yes","No")) | Y44: 0.7 | Z44: sitemap-services.xml | AA44: Live – indexable
A45: P0044 | B45: https://instasure.ca/business-insurance/commercial-auto/ | C45: Service page | D45: Business insurance | E45: Business Insurance | F45: Commercial Auto & Fleet Insurance | I45: Yes | J45: Commercial Auto Insurance: Vans, Trucks and Small Fleets | K45: =LEN(J45) | L45: Commercial vehicle insurance for Canadian businesses: work vans, pickups, small fleets, trucking and cargo, employee drivers and what personal policies exclude. | M45: =LEN(L45) | N45: Commercial Auto & Fleet Insurance | O45: commercial auto insurance | P45: 1300 | Q45: Nationwide | S45: =COUNTIF('Page-Keyword Map'!$A$2:$A$675,B45) | T45: =SUMIF('Page-Keyword Map'!$A$2:$A$675,B45,'Page-Keyword Map'!$H$2:$H$675) | U45: =COUNTIFS('Page-Keyword Map'!$A$2:$A$675,B45,'Page-Keyword Map'!$E$2:$E$675,"Nationwide") | V45: =COUNTIFS('Page-Keyword Map'!$A$2:$A$675,B45,'Page-Keyword Map'!$E$2:$E$675,"Provincial") | W45: =COUNTIFS('Page-Keyword Map'!$A$2:$A$675,B45,'Page-Keyword Map'!$E$2:$E$675,"City") | X45: =IF(O45="","",IF(ISNUMBER(SEARCH(O45,J45)),"Yes","No")) | Y45: 0.8 | Z45: sitemap-services.xml | AA45: Live – indexable
A46: P0045 | B46: https://instasure.ca/business-insurance/cyber/ | C46: Service page | D46: Business insurance | E46: Business Insurance | F46: Cyber Insurance | I46: Yes | J46: Cyber Insurance for Canadian Small Businesses | Instasure.ca | K46: =LEN(J46) | L46: Cyber insurance for Canadian small businesses: data breaches, ransomware, downtime, privacy breach reporting and the security insurers expect. | M46: =LEN(L46) | N46: Cyber Insurance | O46: cyber insurance canada | P46: 590 | Q46: Nationwide | S46: =COUNTIF('Page-Keyword Map'!$A$2:$A$675,B46) | T46: =SUMIF('Page-Keyword Map'!$A$2:$A$675,B46,'Page-Keyword Map'!$H$2:$H$675) | U46: =COUNTIFS('Page-Keyword Map'!$A$2:$A$675,B46,'Page-Keyword Map'!$E$2:$E$675,"Nationwide") | V46: =COUNTIFS('Page-Keyword Map'!$A$2:$A$675,B46,'Page-Keyword Map'!$E$2:$E$675,"Provincial") | W46: =COUNTIFS('Page-Keyword Map'!$A$2:$A$675,B46,'Page-Keyword Map'!$E$2:$E$675,"City") | X46: =IF(O46="","",IF(ISNUMBER(SEARCH(O46,J46)),"Yes","No")) | Y46: 0.7 | Z46: sitemap-services.xml | AA46: Live – indexable
A47: P0046 | B47: https://instasure.ca/business-insurance/directors-and-officers/ | C47: Service page | D47: Business insurance | E47: Business Insurance | F47: Directors & Officers Insurance | I47: Yes | J47: Directors & Officers (D&O) Insurance in Canada | Instasure.ca | K47: =LEN(J47) | L47: D&O insurance for Canadian companies and non-profits: personal liability of directors and officers, what it covers, who needs it and typical exclusions. | M47: =LEN(L47) | N47: Directors & Officers Insurance | O47: directors and officers insurance | P47: 880 | Q47: Nationwide | S47: =COUNTIF('Page-Keyword Map'!$A$2:$A$675,B47) | T47: =SUMIF('Page-Keyword Map'!$A$2:$A$675,B47,'Page-Keyword Map'!$H$2:$H$675) | U47: =COUNTIFS('Page-Keyword Map'!$A$2:$A$675,B47,'Page-Keyword Map'!$E$2:$E$675,"Nationwide") | V47: =COUNTIFS('Page-Keyword Map'!$A$2:$A$675,B47,'Page-Keyword Map'!$E$2:$E$675,"Provincial") | W47: =COUNTIFS('Page-Keyword Map'!$A$2:$A$675,B47,'Page-Keyword Map'!$E$2:$E$675,"City") | X47: =IF(O47="","",IF(ISNUMBER(SEARCH(O47,J47)),"Yes","No")) | Y47: 0.7 | Z47: sitemap-services.xml | AA47: Live – indexable
A48: P0047 | B48: https://instasure.ca/business-insurance/home-based/ | C48: Service page | D48: Business insurance | E48: Business Insurance | F48: Home-Based Business Insurance | I48: Yes | J48: Home-Based Business Insurance in Canada | Instasure.ca | K48: =LEN(J48) | L48: Insurance for businesses run from home: what your home policy excludes, home business endorsements vs commercial policies, clients and equipment. | M48: =LEN(L48) | N48: Home-Based Business Insurance | O48: home based business insurance | P48: 480 | Q48: Nationwide | S48: =COUNTIF('Page-Keyword Map'!$A$2:$A$675,B48) | T48: =SUMIF('Page-Keyword Map'!$A$2:$A$675,B48,'Page-Keyword Map'!$H$2:$H$675) | U48: =COUNTIFS('Page-Keyword Map'!$A$2:$A$675,B48,'Page-Keyword Map'!$E$2:$E$675,"Nationwide") | V48: =COUNTIFS('Page-Keyword Map'!$A$2:$A$675,B48,'Page-Keyword Map'!$E$2:$E$675,"Provincial") | W48: =COUNTIFS('Page-Keyword Map'!$A$2:$A$675,B48,'Page-Keyword Map'!$E$2:$E$675,"City") | X48: =IF(O48="","",IF(ISNUMBER(SEARCH(O48,J48)),"Yes","No")) | Y48: 0.7 | Z48: sitemap-services.xml | AA48: Live – indexable
A49: P0048 | B49: https://instasure.ca/business-insurance/key-person/ | C49: Service page | D49: Business insurance | E49: Life Insurance | F49: Key Person & Buy-Sell Insurance | I49: Yes | J49: Key Person & Buy-Sell Insurance for Canadian Businesses | K49: =LEN(J49) | L49: Key person and buy-sell insurance for Canadian businesses: protect the company if an owner or key employee dies or falls ill, and fund shareholder agreements. | M49: =LEN(L49) | N49: Key Person & Buy-Sell Insurance | O49: key person insurance | P49: 480 | Q49: Nationwide | S49: =COUNTIF('Page-Keyword Map'!$A$2:$A$675,B49) | T49: =SUMIF('Page-Keyword Map'!$A$2:$A$675,B49,'Page-Keyword Map'!$H$2:$H$675) | U49: =COUNTIFS('Page-Keyword Map'!$A$2:$A$675,B49,'Page-Keyword Map'!$E$2:$E$675,"Nationwide") | V49: =COUNTIFS('Page-Keyword Map'!$A$2:$A$675,B49,'Page-Keyword Map'!$E$2:$E$675,"Provincial") | W49: =COUNTIFS('Page-Keyword Map'!$A$2:$A$675,B49,'Page-Keyword Map'!$E$2:$E$675,"City") | X49: =IF(O49="","",IF(ISNUMBER(SEARCH(O49,J49)),"Yes","No")) | Y49: 0.7 | Z49: sitemap-services.xml | AA49: Live – indexable
A50: P0049 | B50: https://instasure.ca/business-insurance/restaurants/ | C50: Service page | D50: Business insurance | E50: Business Insurance | F50: Restaurant & Food Service Insurance | I50: Yes | J50: Restaurant & Food Service Insurance in Canada | Instasure.ca | K50: =LEN(J50) | L50: Insurance for restaurants, cafés, bars and food trucks: general liability, liquor liability, property, equipment breakdown, spoilage and business interruption. | M50: =LEN(L50) | N50: Restaurant & Food Service Insurance | O50: restaurant insurance | P50: 590 | Q50: Nationwide | S50: =COUNTIF('Page-Keyword Map'!$A$2:$A$675,B50) | T50: =SUMIF('Page-Keyword Map'!$A$2:$A$675,B50,'Page-Keyword Map'!$H$2:$H$675) | U50: =COUNTIFS('Page-Keyword Map'!$A$2:$A$675,B50,'Page-Keyword Map'!$E$2:$E$675,"Nationwide") | V50: =COUNTIFS('Page-Keyword Map'!$A$2:$A$675,B50,'Page-Keyword Map'!$E$2:$E$675,"Provincial") | W50: =COUNTIFS('Page-Keyword Map'!$A$2:$A$675,B50,'Page-Keyword Map'!$E$2:$E$675,"City") | X50: =IF(O50="","",IF(ISNUMBER(SEARCH(O50,J50)),"Yes","No")) | Y50: 0.7 | Z50: sitemap-services.xml | AA50: Live – indexable
A51: P0050 | B51: https://instasure.ca/car-insurance/accident-benefits-review/ | C51: Service page | D51: Car insurance | E51: Car Insurance | F51: Ontario Accident Benefits Review | I51: Yes | J51: Ontario Accident Benefits Review: What to Keep After July 2026 | K51: =LEN(J51) | L51: A free review of Ontario’s optional accident benefits (income replacement, caregiver, death and funeral and more): what to keep at renewal and what it costs. | M51: =LEN(L51) | N51: Ontario Accident Benefits Review | O51: should i buy optional accident benefits | P51: 210 | Q51: Nationwide | S51: =COUNTIF('Page-Keyword Map'!$A$2:$A$675,B51) | T51: =SUMIF('Page-Keyword Map'!$A$2:$A$675,B51,'Page-Keyword Map'!$H$2:$H$675) | U51: =COUNTIFS('Page-Keyword Map'!$A$2:$A$675,B51,'Page-Keyword Map'!$E$2:$E$675,"Nationwide") | V51: =COUNTIFS('Page-Keyword Map'!$A$2:$A$675,B51,'Page-Keyword Map'!$E$2:$E$675,"Provincial") | W51: =COUNTIFS('Page-Keyword Map'!$A$2:$A$675,B51,'Page-Keyword Map'!$E$2:$E$675,"City") | X51: =IF(O51="","",IF(ISNUMBER(SEARCH(O51,J51)),"Yes","No")) | Y51: 0.8 | Z51: sitemap-services.xml | AA51: Live – indexable
A52: P0051 | B52: https://instasure.ca/car-insurance/classic-cars/ | C52: Service page | D52: Car insurance | E52: Car Insurance | F52: Classic & Collector Car Insurance | I52: Yes | J52: Classic & Collector Car Insurance in Canada | Instasure.ca | K52: =LEN(J52) | L52: Insurance for classic, antique and collector cars: agreed-value coverage, limited-use rules, storage requirements and who qualifies. | M52: =LEN(L52) | N52: Classic & Collector Car Insurance | O52: classic car insurance | P52: 1300 | Q52: Nationwide | S52: =COUNTIF('Page-Keyword Map'!$A$2:$A$675,B52) | T52: =SUMIF('Page-Keyword Map'!$A$2:$A$675,B52,'Page-Keyword Map'!$H$2:$H$675) | U52: =COUNTIFS('Page-Keyword Map'!$A$2:$A$675,B52,'Page-Keyword Map'!$E$2:$E$675,"Nationwide") | V52: =COUNTIFS('Page-Keyword Map'!$A$2:$A$675,B52,'Page-Keyword Map'!$E$2:$E$675,"Provincial") | W52: =COUNTIFS('Page-Keyword Map'!$A$2:$A$675,B52,'Page-Keyword Map'!$E$2:$E$675,"City") | X52: =IF(O52="","",IF(ISNUMBER(SEARCH(O52,J52)),"Yes","No")) | Y52: 0.7 | Z52: sitemap-services.xml | AA52: Live – indexable
A53: P0052 | B53: https://instasure.ca/car-insurance/electric-and-hybrid/ | C53: Service page | D53: Car insurance | E53: Car Insurance | F53: Electric & Hybrid Car Insurance | I53: Yes | J53: Electric & Hybrid Car Insurance in Canada | Instasure.ca | K53: =LEN(J53) | L53: How insurers price electric and hybrid cars in Canada: repair and battery costs, EV discounts, charging equipment and what to ask before you buy. | M53: =LEN(L53) | N53: Electric & Hybrid Car Insurance | O53: electric car insurance | P53: 880 | Q53: Nationwide | S53: =COUNTIF('Page-Keyword Map'!$A$2:$A$675,B53) | T53: =SUMIF('Page-Keyword Map'!$A$2:$A$675,B53,'Page-Keyword Map'!$H$2:$H$675) | U53: =COUNTIFS('Page-Keyword Map'!$A$2:$A$675,B53,'Page-Keyword Map'!$E$2:$E$675,"Nationwide") | V53: =COUNTIFS('Page-Keyword Map'!$A$2:$A$675,B53,'Page-Keyword Map'!$E$2:$E$675,"Provincial") | W53: =COUNTIFS('Page-Keyword Map'!$A$2:$A$675,B53,'Page-Keyword Map'!$E$2:$E$675,"City") | X53: =IF(O53="","",IF(ISNUMBER(SEARCH(O53,J53)),"Yes","No")) | Y53: 0.7 | Z53: sitemap-services.xml | AA53: Live – indexable
A54: P0053 | B54: https://instasure.ca/car-insurance/high-risk-drivers/ | C54: Service page | D54: Car insurance | E54: Car Insurance | F54: High-Risk Car Insurance | I54: Yes | J54: High-Risk Car Insurance: After Tickets, Claims or a Lapse | K54: =LEN(J54) | L54: Car insurance after at-fault claims, convictions, a lapse or a cancellation: who still insures you, what it costs and how to get back to standard rates. | M54: =LEN(L54) | N54: High-Risk Car Insurance | O54: high risk car insurance | P54: 1600 | Q54: Nationwide | S54: =COUNTIF('Page-Keyword Map'!$A$2:$A$675,B54) | T54: =SUMIF('Page-Keyword Map'!$A$2:$A$675,B54,'Page-Keyword Map'!$H$2:$H$675) | U54: =COUNTIFS('Page-Keyword Map'!$A$2:$A$675,B54,'Page-Keyword Map'!$E$2:$E$675,"Nationwide") | V54: =COUNTIFS('Page-Keyword Map'!$A$2:$A$675,B54,'Page-Keyword Map'!$E$2:$E$675,"Provincial") | W54: =COUNTIFS('Page-Keyword Map'!$A$2:$A$675,B54,'Page-Keyword Map'!$E$2:$E$675,"City") | X54: =IF(O54="","",IF(ISNUMBER(SEARCH(O54,J54)),"Yes","No")) | Y54: 0.8 | Z54: sitemap-services.xml | AA54: Live – indexable
... A71: P0070 | B71: https://instasure.ca/landlord-insurance/ | C71: Service page | D71: Landlord & rental property | E71: Home Insurance | F71: Landlord & Rental Property Insurance | I71: Yes | J71: Landlord Insurance in Canada: Rental Houses, Condos and Units | K71: =LEN(J71) | L71: Insurance for rental properties in Canada: rental dwelling policies, lost rental income, landlord liability, condo rentals and what tenant insurance excludes. | M71: =LEN(L71) | N71: Landlord & Rental Property Insurance | O71: landlord insurance | P71: 2400 | Q71: Nationwide | S71: =COUNTIF('Page-Keyword Map'!$A$2:$A$675,B71) | T71: =SUMIF('Page-Keyword Map'!$A$2:$A$675,B71,'Page-Keyword Map'!$H$2:$H$675) | U71: =COUNTIFS('Page-Keyword Map'!$A$2:$A$675,B71,'Page-Keyword Map'!$E$2:$E$675,"Nationwide") | V71: =COUNTIFS('Page-Keyword Map'!$A$2:$A$675,B71,'Page-Keyword Map'!$E$2:$E$675,"Provincial") | W71: =COUNTIFS('Page-Keyword Map'!$A$2:$A$675,B71,'Page-Keyword Map'!$E$2:$E$675,"City") | X71: =IF(O71="","",IF(ISNUMBER(SEARCH(O71,J71)),"Yes","No")) | Y71: 0.7 | Z71: sitemap-services.xml | AA71: Live – indexable
A72: P0071 | B72: https://instasure.ca/life-insurance/children/ | C72: Service page | D72: Life insurance | E72: Whole Life Insurance | F72: Children’s Life Insurance | I72: Yes | J72: Children’s Life Insurance in Canada: Pros and Cons | Instasure.ca | K72: =LEN(J72) | L72: Life insurance for children in Canada: guaranteed future insurability, low permanent premiums, child riders and when it makes sense. | M72: =LEN(L72) | N72: Children’s Life Insurance | R72: children's life insurance | S72: =COUNTIF('Page-Keyword Map'!$A$2:$A$675,B72) | T72: =SUMIF('Page-Keyword Map'!$A$2:$A$675,B72,'Page-Keyword Map'!$H$2:$H$675) | U72: =COUNTIFS('Page-Keyword Map'!$A$2:$A$675,B72,'Page-Keyword Map'!$E$2:$E$675,"Nationwide") | V72: =COUNTIFS('Page-Keyword Map'!$A$2:$A$675,B72,'Page-Keyword Map'!$E$2:$E$675,"Provincial") | W72: =COUNTIFS('Page-Keyword Map'!$A$2:$A$675,B72,'Page-Keyword Map'!$E$2:$E$675,"City") | X72: =IF(O72="","",IF(ISNUMBER(SEARCH(O72,J72)),"Yes","No")) | Y72: 0.7 | Z72: sitemap-services.xml | AA72: Live – indexable
A73: P0072 | B73: https://instasure.ca/life-insurance/final-expense/ | C73: Service page | D73: Life insurance | E73: Whole Life Insurance | F73: Final Expense Insurance | I73: Yes | J73: Final Expense Insurance Canada: Costs and Options | Instasure.ca | K73: =LEN(J73) | L73: Final expense insurance in Canada: small permanent policies for final bills, debts and funeral costs, simplified or guaranteed issue, and what they cost. | M73: =LEN(L73) | N73: Final Expense Insurance | O73: final expense insurance canada | P73: 1000 | Q73: Nationwide | S73: =COUNTIF('Page-Keyword Map'!$A$2:$A$675,B73) | T73: =SUMIF('Page-Keyword Map'!$A$2:$A$675,B73,'Page-Keyword Map'!$H$2:$H$675) | U73: =COUNTIFS('Page-Keyword Map'!$A$2:$A$675,B73,'Page-Keyword Map'!$E$2:$E$675,"Nationwide") | V73: =COUNTIFS('Page-Keyword Map'!$A$2:$A$675,B73,'Page-Keyword Map'!$E$2:$E$675,"Provincial") | W73: =COUNTIFS('Page-Keyword Map'!$A$2:$A$675,B73,'Page-Keyword Map'!$E$2:$E$675,"City") | X73: =IF(O73="","",IF(ISNUMBER(SEARCH(O73,J73)),"Yes","No")) | Y73: 0.7 | Z73: sitemap-services.xml | AA73: Live – indexable
A74: P0073 | B74: https://instasure.ca/life-insurance/funeral-expense/ | C74: Service page | D74: Life insurance | E74: Whole Life Insurance | F74: Funeral Expense Insurance | I74: Yes | J74: Funeral Expense Insurance in Canada from $1 a Day | Instasure.ca | K74: =LEN(J74) | L74: Funeral expense insurance from about $1 a day: $5,000 to $50,000 of lifelong cover, no medical exam and a tax-free payout your family can use right away. | M74: =LEN(L74) | N74: Funeral Expense Insurance from $1 a Day | O74: funeral insurance | P74: 1900 | Q74: Nationwide | S74: =COUNTIF('Page-Keyword Map'!$A$2:$A$675,B74) | T74: =SUMIF('Page-Keyword Map'!$A$2:$A$675,B74,'Page-Keyword Map'!$H$2:$H$675) | U74: =COUNTIFS('Page-Keyword Map'!$A$2:$A$675,B74,'Page-Keyword Map'!$E$2:$E$675,"Nationwide") | V74: =COUNTIFS('Page-Keyword Map'!$A$2:$A$675,B74,'Page-Keyword Map'!$E$2:$E$675,"Provincial") | W74: =COUNTIFS('Page-Keyword Map'!$A$2:$A$675,B74,'Page-Keyword Map'!$E$2:$E$675,"City") | X74: =IF(O74="","",IF(ISNUMBER(SEARCH(O74,J74)),"Yes","No")) | Y74: 0.7 | Z74: sitemap-services.xml | AA74: Live – indexable
A75: P0074 | B75: https://instasure.ca/life-insurance/joint/ | C75: Service page | D75: Life insurance | E75: Life Insurance | F75: Joint Life Insurance | I75: Yes | J75: Joint Life Insurance: First-to-Die vs Last-to-Die | Instasure.ca | K75: =LEN(J75) | L75: Joint life insurance in Canada: first-to-die and last-to-die policies, when a joint policy suits couples and estates, and when two policies are better. | M75: =LEN(L75) | N75: Joint Life Insurance | O75: joint life insurance | P75: 590 | Q75: Nationwide | S75: =COUNTIF('Page-Keyword Map'!$A$2:$A$675,B75) | T75: =SUMIF('Page-Keyword Map'!$A$2:$A$675,B75,'Page-Keyword Map'!$H$2:$H$675) | U75: =COUNTIFS('Page-Keyword Map'!$A$2:$A$675,B75,'Page-Keyword Map'!$E$2:$E$675,"Nationwide") | V75: =COUNTIFS('Page-Keyword Map'!$A$2:$A$675,B75,'Page-Keyword Map'!$E$2:$E$675,"Provincial") | W75: =COUNTIFS('Page-Keyword Map'!$A$2:$A$675,B75,'Page-Keyword Map'!$E$2:$E$675,"City") | X75: =IF(O75="","",IF(ISNUMBER(SEARCH(O75,J75)),"Yes","No")) | Y75: 0.7 | Z75: sitemap-services.xml | AA75: Live – indexable
A76: P0075 | B76: https://instasure.ca/life-insurance/medical-conditions/ | C76: Service page | D76: Life insurance | E76: Life Insurance | F76: Life Insurance with Medical Conditions | I76: Yes | J76: Life Insurance with Medical Conditions: Diabetes, Heart | K76: =LEN(J76) | L76: Life insurance with diabetes, heart disease, high blood pressure, cancer history or mental health conditions: rated policies, exclusions and no-medical options. | M76: =LEN(L76) | N76: Life Insurance with Medical Conditions | O76: life insurance for smokers | P76: 390 | Q76: Nationwide | S76: =COUNTIF('Page-Keyword Map'!$A$2:$A$675,B76) | T76: =SUMIF('Page-Keyword Map'!$A$2:$A$675,B76,'Page-Keyword Map'!$H$2:$H$675) | U76: =COUNTIFS('Page-Keyword Map'!$A$2:$A$675,B76,'Page-Keyword Map'!$E$2:$E$675,"Nationwide") | V76: =COUNTIFS('Page-Keyword Map'!$A$2:$A$675,B76,'Page-Keyword Map'!$E$2:$E$675,"Provincial") | W76: =COUNTIFS('Page-Keyword Map'!$A$2:$A$675,B76,'Page-Keyword Map'!$E$2:$E$675,"City") | X76: =IF(O76="","",IF(ISNUMBER(SEARCH(O76,J76)),"Yes","No")) | Y76: 0.8 | Z76: sitemap-services.xml | AA76: Live – indexable
A77: P0076 | B77: https://instasure.ca/life-insurance/newcomers/ | C77: Service page | D77: Life insurance | E77: Life Insurance | F77: Life Insurance for Newcomers | I77: Yes | J77: Life Insurance for Newcomers: PR, Work Permits and Students | K77: =LEN(J77) | L77: Life insurance for newcomers to Canada: eligibility for permanent residents, work-permit holders and students, coverage limits and advice in your language. | M77: =LEN(L77) | N77: Life Insurance for Newcomers | R77: life insurance for newcomers to canada | S77: =COUNTIF('Page-Keyword Map'!$A$2:$A$675,B77) | T77: =SUMIF('Page-Keyword Map'!$A$2:$A$675,B77,'Page-Keyword Map'!$H$2:$H$675) | U77: =COUNTIFS('Page-Keyword Map'!$A$2:$A$675,B77,'Page-Keyword Map'!$E$2:$E$675,"Nationwide") | V77: =COUNTIFS('Page-Keyword Map'!$A$2:$A$675,B77,'Page-Keyword Map'!$E$2:$E$675,"Provincial") | W77: =COUNTIFS('Page-Keyword Map'!$A$2:$A$675,B77,'Page-Keyword Map'!$E$2:$E$675,"City") | X77: =IF(O77="","",IF(ISNUMBER(SEARCH(O77,J77)),"Yes","No")) | Y77: 0.8 | Z77: sitemap-services.xml | AA77: Live – indexable
A78: P0077 | B78: https://instasure.ca/life-insurance/seniors/ | C78: Service page | D78: Life insurance | E78: Term Life Insurance | F78: Life Insurance for Seniors | I78: Yes | J78: Life Insurance for Seniors: Term, Permanent and No-Medical | K78: =LEN(J78) | L78: Life insurance for Canadians over 60: term to age 80 or 85, permanent coverage, no-medical options, estate taxes and what it costs. | M78: =LEN(L78) | N78: Life Insurance for Seniors | O78: life insurance for seniors | P78: 1600 | Q78: Nationwide | S78: =COUNTIF('Page-Keyword Map'!$A$2:$A$675,B78) | T78: =SUMIF('Page-Keyword Map'!$A$2:$A$675,B78,'Page-Keyword Map'!$H$2:$H$675) | U78: =COUNTIFS('Page-Keyword Map'!$A$2:$A$675,B78,'Page-Keyword Map'!$E$2:$E$675,"Nationwide") | V78: =COUNTIFS('Page-Keyword Map'!$A$2:$A$675,B78,'Page-Keyword Map'!$E$2:$E$675,"Provincial") | W78: =COUNTIFS('Page-Keyword Map'!$A$2:$A$675,B78,'Page-Keyword Map'!$E$2:$E$675,"City") | X78: =IF(O78="","",IF(ISNUMBER(SEARCH(O78,J78)),"Yes","No")) | Y78: 0.7 | Z78: sitemap-services.xml | AA78: Live – indexable
A79: P0078 | B79: https://instasure.ca/life-insurance/universal-life/ | C79: Service page | D79: Life insurance | E79: Whole Life Insurance | F79: Universal Life Insurance | I79: Yes | J79: Universal Life Insurance in Canada: How It Works | Instasure.ca | K79: =LEN(J79) | L79: Universal life insurance in Canada: permanent coverage with a tax-advantaged investment account, cost-of-insurance options and how it compares with whole life. | M79: =LEN(L79) | N79: Universal Life Insurance | O79: universal life insurance | P79: 1300 | Q79: Nationwide | S79: =COUNTIF('Page-Keyword Map'!$A$2:$A$675,B79) | T79: =SUMIF('Page-Keyword Map'!$A$2:$A$675,B79,'Page-Keyword Map'!$H$2:$H$675) | U79: =COUNTIFS('Page-Keyword Map'!$A$2:$A$675,B79,'Page-Keyword Map'!$E$2:$E$675,"Nationwide") | V79: =COUNTIFS('Page-Keyword Map'!$A$2:$A$675,B79,'Page-Keyword Map'!$E$2:$E$675,"Provincial") | W79: =COUNTIFS('Page-Keyword Map'!$A$2:$A$675,B79,'Page-Keyword Map'!$E$2:$E$675,"City") | X79: =IF(O79="","",IF(ISNUMBER(SEARCH(O79,J79)),"Yes","No")) | Y79: 0.7 | Z79: sitemap-services.xml | AA79: Live – indexable
A80: P0079 | B80: https://instasure.ca/long-term-care-insurance/ | C80: Service page | D80: Health & dental insurance | E80: Health & Dental Insurance | F80: Long-Term Care Insurance | I80: Yes | J80: Long-Term Care Insurance in Canada | Instasure.ca | K80: =LEN(J80) | L80: Long-term care insurance in Canada: what triggers benefits, home care vs facility care, how it differs from critical illness and disability, and alternatives. | M80: =LEN(L80) | N80: Long-Term Care Insurance | O80: long term care insurance canada | P80: 1300 | Q80: Nationwide | S80: =COUNTIF('Page-Keyword Map'!$A$2:$A$675,B80) | T80: =SUMIF('Page-Keyword Map'!$A$2:$A$675,B80,'Page-Keyword Map'!$H$2:$H$675) | U80: =COUNTIFS('Page-Keyword Map'!$A$2:$A$675,B80,'Page-Keyword Map'!$E$2:$E$675,"Nationwide") | V80: =COUNTIFS('Page-Keyword Map'!$A$2:$A$675,B80,'Page-Keyword Map'!$E$2:$E$675,"Provincial") | W80: =COUNTIFS('Page-Keyword Map'!$A$2:$A$675,B80,'Page-Keyword Map'!$E$2:$E$675,"City") | X80: =IF(O80="","",IF(ISNUMBER(SEARCH(O80,J80)),"Yes","No")) | Y80: 0.7 | Z80: sitemap-services.xml | AA80: Live – indexable
A81: P0080 | B81: https://instasure.ca/motorcycle-insurance/ | C81: Service page | D81: Recreational vehicles | E81: Car Insurance | F81: Motorcycle Insurance | I81: Yes | J81: Motorcycle Insurance in Canada: M1, M2 and Seasonal Coverage | K81: =LEN(J81) | L81: Motorcycle insurance in Canada: mandatory coverage, graduated motorcycle licences, seasonal riding, gear coverage and what drives the price. | M81: =LEN(L81) | N81: Motorcycle Insurance | O81: motorcycle insurance | P81: 5400 | Q81: Nationwide | S81: =COUNTIF('Page-Keyword Map'!$A$2:$A$675,B81) | T81: =SUMIF('Page-Keyword Map'!$A$2:$A$675,B81,'Page-Keyword Map'!$H$2:$H$675) | U81: =COUNTIFS('Page-Keyword Map'!$A$2:$A$675,B81,'Page-Keyword Map'!$E$2:$E$675,"Nationwide") | V81: =COUNTIFS('Page-Keyword Map'!$A$2:$A$675,B81,'Page-Keyword Map'!$E$2:$E$675,"Provincial") | W81: =COUNTIFS('Page-Keyword Map'!$A$2:$A$675,B81,'Page-Keyword Map'!$E$2:$E$675,"City") | X81: =IF(O81="","",IF(ISNUMBER(SEARCH(O81,J81)),"Yes","No")) | Y81: 0.7 | Z81: sitemap-services.xml | AA81: Live – indexable
A82: P0081 | B82: https://instasure.ca/pet-insurance/ | C82: Service page | D82: Pet insurance | E82: Home Insurance | F82: Pet Insurance | I82: Yes | J82: Pet Insurance in Canada: Accident, Illness and Wellness Plans | K82: =LEN(J82) | L82: Pet insurance for dogs and cats in Canada: accident-only, accident and illness, and wellness plans, waiting periods, pre-existing conditions and claims. | M82: =LEN(L82) | N82: Pet Insurance | O82: pet insurance | P82: 14000 | Q82: Nationwide | S82: =COUNTIF('Page-Keyword Map'!$A$2:$A$675,B82) | T82: =SUMIF('Page-Keyword Map'!$A$2:$A$675,B82,'Page-Keyword Map'!$H$2:$H$675) | U82: =COUNTIFS('Page-Keyword Map'!$A$2:$A$675,B82,'Page-Keyword Map'!$E$2:$E$675,"Nationwide") | V82: =COUNTIFS('Page-Keyword Map'!$A$2:$A$675,B82,'Page-Keyword Map'!$E$2:$E$675,"Provincial") | W82: =COUNTIFS('Page-Keyword Map'!$A$2:$A$675,B82,'Page-Keyword Map'!$E$2:$E$675,"City") | X82: =IF(O82="","",IF(ISNUMBER(SEARCH(O82,J82)),"Yes","No")) | Y82: 0.7 | Z82: sitemap-services.xml | AA82: Live – indexable
A83: P0082 | B83: https://instasure.ca/rv-insurance/ | C83: Service page | D83: Recreational vehicles | E83: Car Insurance | F83: RV & Trailer Insurance | I83: Yes | J83: RV & Trailer Insurance in Canada: Motorhomes and Campers | K83: =LEN(J83) | L83: Insurance for motorhomes, travel trailers, fifth wheels and campers: what the tow vehicle covers, contents and seasonal-site coverage. | M83: =LEN(L83) | N83: RV & Trailer Insurance | O83: rv insurance | P83: 1900 | Q83: Nationwide | S83: =COUNTIF('Page-Keyword Map'!$A$2:$A$675,B83) | T83: =SUMIF('Page-Keyword Map'!$A$2:$A$675,B83,'Page-Keyword Map'!$H$2:$H$675) | U83: =COUNTIFS('Page-Keyword Map'!$A$2:$A$675,B83,'Page-Keyword Map'!$E$2:$E$675,"Nationwide") | V83: =COUNTIFS('Page-Keyword Map'!$A$2:$A$675,B83,'Page-Keyword Map'!$E$2:$E$675,"Provincial") | W83: =COUNTIFS('Page-Keyword Map'!$A$2:$A$675,B83,'Page-Keyword Map'!$E$2:$E$675,"City") | X83: =IF(O83="","",IF(ISNUMBER(SEARCH(O83,J83)),"Yes","No")) | Y83: 0.7 | Z83: sitemap-services.xml | AA83: Live – indexable
A84: P0083 | B84: https://instasure.ca/tenant-insurance/students/ | C84: Service page | D84: Tenant insurance | E84: Tenant Insurance | F84: Tenant Insurance for Students | I84: Yes | J84: Tenant Insurance for Students: Residence and Shared Houses | K84: =LEN(J84) | L84: Insurance for students renting in residence, shared houses or apartments: what a parent's policy covers, roommates, laptops, bikes and landlord rules. | M84: =LEN(L84) | N84: Tenant Insurance for Students | O84: tenant insurance for students | P84: 390 | Q84: Nationwide | S84: =COUNTIF('Page-Keyword Map'!$A$2:$A$675,B84) | T84: =SUMIF('Page-Keyword Map'!$A$2:$A$675,B84,'Page-Keyword Map'!$H$2:$H$675) | U84: =COUNTIFS('Page-Keyword Map'!$A$2:$A$675,B84,'Page-Keyword Map'!$E$2:$E$675,"Nationwide") | V84: =COUNTIFS('Page-Keyword Map'!$A$2:$A$675,B84,'Page-Keyword Map'!$E$2:$E$675,"Provincial") | W84: =COUNTIFS('Page-Keyword Map'!$A$2:$A$675,B84,'Page-Keyword Map'!$E$2:$E$675,"City") | X84: =IF(O84="","",IF(ISNUMBER(SEARCH(O84,J84)),"Yes","No")) | Y84: 0.7 | Z84: sitemap-services.xml | AA84: Live – indexable
A85: P0084 | B85: https://instasure.ca/travel-insurance/international-students/ | C85: Service page | D85: Travel insurance | E85: Travel Insurance | F85: International Student Health Insurance | I85: Yes | J85: Health Insurance for International Students in Canada | K85: =LEN(J85) | L85: Health insurance for international students in Canada: provincial coverage rules, school plans such as UHIP, gaps before coverage starts and renters insurance. | M85: =LEN(L85) | N85: International Student Health Insurance | O85: international student health insurance canada | P85: 720 | Q85: Nationwide | S85: =COUNTIF('Page-Keyword Map'!$A$2:$A$675,B85) | T85: =SUMIF('Page-Keyword Map'!$A$2:$A$675,B85,'Page-Keyword Map'!$H$2:$H$675) | U85: =COUNTIFS('Page-Keyword Map'!$A$2:$A$675,B85,'Page-Keyword Map'!$E$2:$E$675,"Nationwide") | V85: =COUNTIFS('Page-Keyword Map'!$A$2:$A$675,B85,'Page-Keyword Map'!$E$2:$E$675,"Provincial") | W85: =COUNTIFS('Page-Keyword Map'!$A$2:$A$675,B85,'Page-Keyword Map'!$E$2:$E$675,"City") | X85: =IF(O85="","",IF(ISNUMBER(SEARCH(O85,J85)),"Yes","No")) | Y85: 0.7 | Z85: sitemap-services.xml | AA85: Live – indexable
A86: P0085 | B86: https://instasure.ca/travel-insurance/snowbirds/ | C86: Service page | D86: Travel insurance | E86: Travel Insurance | F86: Snowbird Travel Insurance | I86: Yes | J86: Snowbird Travel Insurance: Long Stays and Stability Periods | K86: =LEN(J86) | L86: Travel medical insurance for Canadian snowbirds: long-stay coverage, medical questionnaires, stability periods, provincial time-away rules and top-ups. | M86: =LEN(L86) | N86: Snowbird Travel Insurance | O86: snowbird travel insurance | P86: 1300 | Q86: Nationwide | S86: =COUNTIF('Page-Keyword Map'!$A$2:$A$675,B86) | T86: =SUMIF('Page-Keyword Map'!$A$2:$A$675,B86,'Page-Keyword Map'!$H$2:$H$675) | U86: =COUNTIFS('Page-Keyword Map'!$A$2:$A$675,B86,'Page-Keyword Map'!$E$2:$E$675,"Nationwide") | V86: =COUNTIFS('Page-Keyword Map'!$A$2:$A$675,B86,'Page-Keyword Map'!$E$2:$E$675,"Provincial") | W86: =COUNTIFS('Page-Keyword Map'!$A$2:$A$675,B86,'Page-Keyword Map'!$E$2:$E$675,"City") | X86: =IF(O86="","",IF(ISNUMBER(SEARCH(O86,J86)),"Yes","No")) | Y86: 0.8 | Z86: sitemap-services.xml | AA86: Live – indexable
A87: P0086 | B87: https://instasure.ca/travel-insurance/visitors-to-canada/ | C87: Service page | D87: Super Visa & visitors insurance | E87: Super Visa Insurance | F87: Visitors to Canada Insurance | I87: Yes | J87: Visitors to Canada Insurance: Emergency Medical for Guests | K87: =LEN(J87) | L87: Emergency medical insurance for visitors to Canada: who needs it, how it differs from Super Visa insurance, pre-existing conditions and deductibles. | M87: =LEN(L87) | N87: Visitors to Canada Insurance | O87: visitors insurance canada | P87: 4400 | Q87: Nationwide | S87: =COUNTIF('Page-Keyword Map'!$A$2:$A$675,B87) | T87: =SUMIF('Page-Keyword Map'!$A$2:$A$675,B87,'Page-Keyword Map'!$H$2:$H$675) | U87: =COUNTIFS('Page-Keyword Map'!$A$2:$A$675,B87,'Page-Keyword Map'!$E$2:$E$675,"Nationwide") | V87: =COUNTIFS('Page-Keyword Map'!$A$2:$A$675,B87,'Page-Keyword Map'!$E$2:$E$675,"Provincial") | W87: =COUNTIFS('Page-Keyword Map'!$A$2:$A$675,B87,'Page-Keyword Map'!$E$2:$E$675,"City") | X87: =IF(O87="","",IF(ISNUMBER(SEARCH(O87,J87)),"Yes","No")) | Y87: 0.7 | Z87: sitemap-services.xml | AA87: Live – indexable
A88: P0087 | B88: https://instasure.ca/umbrella-insurance/ | C88: Service page | D88: Home insurance | E88: Home Insurance | F88: Umbrella Liability Insurance | I88: Yes | J88: Umbrella Liability Insurance in Canada | Instasure.ca | K88: =LEN(J88) | L88: Personal umbrella insurance in Canada: extra liability above your home, auto and boat policies, who needs it, required underlying limits and amounts. | M88: =LEN(L88) | N88: Umbrella Liability Insurance | O88: umbrella insurance | P88: 1300 | Q88: Nationwide | S88: =COUNTIF('Page-Keyword Map'!$A$2:$A$675,B88) | T88: =SUMIF('Page-Keyword Map'!$A$2:$A$675,B88,'Page-Keyword Map'!$H$2:$H$675) | U88: =COUNTIFS('Page-Keyword Map'!$A$2:$A$675,B88,'Page-Keyword Map'!$E$2:$E$675,"Nationwide") | V88: =COUNTIFS('Page-Keyword Map'!$A$2:$A$675,B88,'Page-Keyword Map'!$E$2:$E$675,"Provincial") | W88: =COUNTIFS('Page-Keyword Map'!$A$2:$A$675,B88,'Page-Keyword Map'!$E$2:$E$675,"City") | X88: =IF(O88="","",IF(ISNUMBER(SEARCH(O88,J88)),"Yes","No")) | Y88: 0.7 | Z88: sitemap-services.xml | AA88: Live – indexable
A89: P0088 | B89: https://instasure.ca/business-insurance/alberta/ | C89: Product × province | D89: Business insurance | E89: Business Insurance | G89: Alberta | I89: Yes | J89: Business Insurance in Alberta: Costs, Rules & Quotes (2026) | K89: =LEN(J89) | L89: Business Insurance in Alberta: how it works under the Superintendent of Insurance, what drives price, instant estimates and advisors licensed in Alberta. | M89: =LEN(L89) | N89: Business Insurance in Alberta | O89: business insurance alberta | P89: 370 | Q89: Provincial | S89: =COUNTIF('Page-Keyword Map'!$A$2:$A$675,B89) | T89: =SUMIF('Page-Keyword Map'!$A$2:$A$675,B89,'Page-Keyword Map'!$H$2:$H$675) | U89: =COUNTIFS('Page-Keyword Map'!$A$2:$A$675,B89,'Page-Keyword Map'!$E$2:$E$675,"Nationwide") | V89: =COUNTIFS('Page-Keyword Map'!$A$2:$A$675,B89,'Page-Keyword Map'!$E$2:$E$675,"Provincial") | W89: =COUNTIFS('Page-Keyword Map'!$A$2:$A$675,B89,'Page-Keyword Map'!$E$2:$E$675,"City") | X89: =IF(O89="","",IF(ISNUMBER(SEARCH(O89,J89)),"Yes","No")) | Y89: 0.7 | Z89: sitemap-provinces.xml | AA89: Live – indexable
A90: P0089 | B90: https://instasure.ca/business-insurance/british-columbia/ | C90: Product × province | D90: Business insurance | E90: Business Insurance | G90: British Columbia | I90: Yes | J90: Business Insurance in British Columbia: Costs, Rules & Quotes (2026) | K90: =LEN(J90) | L90: Business Insurance in British Columbia: how it works under BCFSA, what drives price, instant estimates and advisors licensed in British Columbia. | M90: =LEN(L90) | N90: Business Insurance in British Columbia | O90: business insurance bc | P90: 430 | Q90: Provincial | S90: =COUNTIF('Page-Keyword Map'!$A$2:$A$675,B90) | T90: =SUMIF('Page-Keyword Map'!$A$2:$A$675,B90,'Page-Keyword Map'!$H$2:$H$675) | U90: =COUNTIFS('Page-Keyword Map'!$A$2:$A$675,B90,'Page-Keyword Map'!$E$2:$E$675,"Nationwide") | V90: =COUNTIFS('Page-Keyword Map'!$A$2:$A$675,B90,'Page-Keyword Map'!$E$2:$E$675,"Provincial") | W90: =COUNTIFS('Page-Keyword Map'!$A$2:$A$675,B90,'Page-Keyword Map'!$E$2:$E$675,"City") | X90: =IF(O90="","",IF(ISNUMBER(SEARCH(O90,J90)),"Yes","No")) | Y90: 0.7 | Z90: sitemap-provinces.xml | AA90: Live – indexable
A91: P0090 | B91: https://instasure.ca/business-insurance/manitoba/ | C91: Product × province | D91: Business insurance | E91: Business Insurance | G91: Manitoba | I91: Yes | J91: Business Insurance in Manitoba: Costs, Rules & Quotes (2026) | K91: =LEN(J91) | L91: Business Insurance in Manitoba: how it works under FIRB, what drives price, instant estimates and advisors licensed in Manitoba. | M91: =LEN(L91) | N91: Business Insurance in Manitoba | O91: business insurance manitoba | P91: 130 | Q91: Provincial | S91: =COUNTIF('Page-Keyword Map'!$A$2:$A$675,B91) | T91: =SUMIF('Page-Keyword Map'!$A$2:$A$675,B91,'Page-Keyword Map'!$H$2:$H$675) | U91: =COUNTIFS('Page-Keyword Map'!$A$2:$A$675,B91,'Page-Keyword Map'!$E$2:$E$675,"Nationwide") | V91: =COUNTIFS('Page-Keyword Map'!$A$2:$A$675,B91,'Page-Keyword Map'!$E$2:$E$675,"Provincial") | W91: =COUNTIFS('Page-Keyword Map'!$A$2:$A$675,B91,'Page-Keyword Map'!$E$2:$E$675,"City") | X91: =IF(O91="","",IF(ISNUMBER(SEARCH(O91,J91)),"Yes","No")) | Y91: 0.7 | Z91: sitemap-provinces.xml | AA91: Live – indexable
A92: P0091 | B92: https://instasure.ca/business-insurance/new-brunswick/ | C92: Product × province | D92: Business insurance | E92: Business Insurance | G92: New Brunswick | I92: Yes | J92: Business Insurance in New Brunswick: Costs, Rules & Quotes (2026) | K92: =LEN(J92) | L92: Business Insurance in New Brunswick: how it works under FCNB, what drives price, instant estimates and advisors licensed in New Brunswick. | M92: =LEN(L92) | N92: Business Insurance in New Brunswick | O92: business insurance new brunswick | P92: 80 | Q92: Provincial | S92: =COUNTIF('Page-Keyword Map'!$A$2:$A$675,B92) | T92: =SUMIF('Page-Keyword Map'!$A$2:$A$675,B92,'Page-Keyword Map'!$H$2:$H$675) | U92: =COUNTIFS('Page-Keyword Map'!$A$2:$A$675,B92,'Page-Keyword Map'!$E$2:$E$675,"Nationwide") | V92: =COUNTIFS('Page-Keyword Map'!$A$2:$A$675,B92,'Page-Keyword Map'!$E$2:$E$675,"Provincial") | W92: =COUNTIFS('Page-Keyword Map'!$A$2:$A$675,B92,'Page-Keyword Map'!$E$2:$E$675,"City") | X92: =IF(O92="","",IF(ISNUMBER(SEARCH(O92,J92)),"Yes","No")) | Y92: 0.7 | Z92: sitemap-provinces.xml | AA92: Live – indexable
A93: P0092 | B93: https://instasure.ca/business-insurance/newfoundland-and-labrador/ | C93: Product × province | D93: Business insurance | E93: Business Insurance | G93: Newfoundland and Labrador | I93: Yes | J93: Business Insurance in Newfoundland and Labrador: Costs, Rules & Quotes (2026) | K93: =LEN(J93) | L93: Business Insurance in Newfoundland and Labrador: how it works under Service NL, what drives price, instant estimates and advisors licensed in Newfoundland and… | M93: =LEN(L93) | N93: Business Insurance in Newfoundland and Labrador | O93: business insurance newfoundland | P93: 55 | Q93: Provincial | S93: =COUNTIF('Page-Keyword Map'!$A$2:$A$675,B93) | T93: =SUMIF('Page-Keyword Map'!$A$2:$A$675,B93,'Page-Keyword Map'!$H$2:$H$675) | U93: =COUNTIFS('Page-Keyword Map'!$A$2:$A$675,B93,'Page-Keyword Map'!$E$2:$E$675,"Nationwide") | V93: =COUNTIFS('Page-Keyword Map'!$A$2:$A$675,B93,'Page-Keyword Map'!$E$2:$E$675,"Provincial") | W93: =COUNTIFS('Page-Keyword Map'!$A$2:$A$675,B93,'Page-Keyword Map'!$E$2:$E$675,"City") | X93: =IF(O93="","",IF(ISNUMBER(SEARCH(O93,J93)),"Yes","No")) | Y93: 0.7 | Z93: sitemap-provinces.xml | AA93: Live – indexable
A94: P0093 | B94: https://instasure.ca/business-insurance/northwest-territories/ | C94: Product × province | D94: Business insurance | E94: Business Insurance | G94: Northwest Territories | I94: Yes | J94: Business Insurance in Northwest Territories: Costs, Rules & Quotes (2026) | K94: =LEN(J94) | L94: Business Insurance in Northwest Territories: how it works under the NWT Superintendent, what drives price, instant estimates and a waitlist for licensed advice in… | M94: =LEN(L94) | N94: Business Insurance in Northwest Territories | R94: business insurance northwest territories | S94: =COUNTIF('Page-Keyword Map'!$A$2:$A$675,B94) | T94: =SUMIF('Page-Keyword Map'!$A$2:$A$675,B94,'Page-Keyword Map'!$H$2:$H$675) | U94: =COUNTIFS('Page-Keyword Map'!$A$2:$A$675,B94,'Page-Keyword Map'!$E$2:$E$675,"Nationwide") | V94: =COUNTIFS('Page-Keyword Map'!$A$2:$A$675,B94,'Page-Keyword Map'!$E$2:$E$675,"Provincial") | W94: =COUNTIFS('Page-Keyword Map'!$A$2:$A$675,B94,'Page-Keyword Map'!$E$2:$E$675,"City") | X94: =IF(O94="","",IF(ISNUMBER(SEARCH(O94,J94)),"Yes","No")) | Y94: 0.7 | Z94: sitemap-provinces.xml | AA94: Live – indexable
A95: P0094 | B95: https://instasure.ca/business-insurance/nova-scotia/ | C95: Product × province | D95: Business insurance | E95: Business Insurance | G95: Nova Scotia | I95: Yes | J95: Business Insurance in Nova Scotia: Costs, Rules & Quotes (2026) | K95: =LEN(J95) | L95: Business Insurance in Nova Scotia: how it works under the NS Superintendent of Insurance, what drives price, instant estimates and advisors licensed in Nova Scotia. | M95: =LEN(L95) | N95: Business Insurance in Nova Scotia | O95: business insurance nova scotia | P95: 97 | Q95: Provincial | S95: =COUNTIF('Page-Keyword Map'!$A$2:$A$675,B95) | T95: =SUMIF('Page-Keyword Map'!$A$2:$A$675,B95,'Page-Keyword Map'!$H$2:$H$675) | U95: =COUNTIFS('Page-Keyword Map'!$A$2:$A$675,B95,'Page-Keyword Map'!$E$2:$E$675,"Nationwide") | V95: =COUNTIFS('Page-Keyword Map'!$A$2:$A$675,B95,'Page-Keyword Map'!$E$2:$E$675,"Provincial") | W95: =COUNTIFS('Page-Keyword Map'!$A$2:$A$675,B95,'Page-Keyword Map'!$E$2:$E$675,"City") | X95: =IF(O95="","",IF(ISNUMBER(SEARCH(O95,J95)),"Yes","No")) | Y95: 0.7 | Z95: sitemap-provinces.xml | AA95: Live – indexable
A96: P0095 | B96: https://instasure.ca/business-insurance/nunavut/ | C96: Product × province | D96: Business insurance | E96: Business Insurance | G96: Nunavut | I96: Yes | J96: Business Insurance in Nunavut: Costs, Rules & Quotes (2026) | K96: =LEN(J96) | L96: Business Insurance in Nunavut: how it works under the Nunavut Superintendent, what drives price, instant estimates and a waitlist for licensed advice in Nunavut. | M96: =LEN(L96) | N96: Business Insurance in Nunavut | R96: business insurance nunavut | S96: =COUNTIF('Page-Keyword Map'!$A$2:$A$675,B96) | T96: =SUMIF('Page-Keyword Map'!$A$2:$A$675,B96,'Page-Keyword Map'!$H$2:$H$675) | U96: =COUNTIFS('Page-Keyword Map'!$A$2:$A$675,B96,'Page-Keyword Map'!$E$2:$E$675,"Nationwide") | V96: =COUNTIFS('Page-Keyword Map'!$A$2:$A$675,B96,'Page-Keyword Map'!$E$2:$E$675,"Provincial") | W96: =COUNTIFS('Page-Keyword Map'!$A$2:$A$675,B96,'Page-Keyword Map'!$E$2:$E$675,"City") | X96: =IF(O96="","",IF(ISNUMBER(SEARCH(O96,J96)),"Yes","No")) | Y96: 0.7 | Z96: sitemap-provinces.xml | AA96: Live – indexable
A97: P0096 | B97: https://instasure.ca/business-insurance/ontario/ | C97: Product × province | D97: Business insurance | E97: Business Insurance | G97: Ontario | I97: Yes | J97: Business Insurance in Ontario: Costs, Rules & Quotes (2026) | K97: =LEN(J97) | L97: Business Insurance in Ontario: how it works under FSRA, what drives price, instant estimates and advisors licensed in Ontario. | M97: =LEN(L97) | N97: Business Insurance in Ontario | O97: business insurance ontario | P97: 1200 | Q97: Provincial | S97: =COUNTIF('Page-Keyword Map'!$A$2:$A$675,B97) | T97: =SUMIF('Page-Keyword Map'!$A$2:$A$675,B97,'Page-Keyword Map'!$H$2:$H$675) | U97: =COUNTIFS('Page-Keyword Map'!$A$2:$A$675,B97,'Page-Keyword Map'!$E$2:$E$675,"Nationwide") | V97: =COUNTIFS('Page-Keyword Map'!$A$2:$A$675,B97,'Page-Keyword Map'!$E$2:$E$675,"Provincial") | W97: =COUNTIFS('Page-Keyword Map'!$A$2:$A$675,B97,'Page-Keyword Map'!$E$2:$E$675,"City") | X97: =IF(O97="","",IF(ISNUMBER(SEARCH(O97,J97)),"Yes","No")) | Y97: 0.7 | Z97: sitemap-provinces.xml | AA97: Live – indexable
A98: P0097 | B98: https://instasure.ca/business-insurance/prince-edward-island/ | C98: Product × province | D98: Business insurance | E98: Business Insurance | G98: Prince Edward Island | I98: Yes | J98: Business Insurance in Prince Edward Island: Costs, Rules & Quotes (2026) | K98: =LEN(J98) | L98: Business Insurance in Prince Edward Island: how it works under the PEI Superintendent, what drives price, instant estimates and advisors licensed in Prince Edward… | M98: =LEN(L98) | N98: Business Insurance in Prince Edward Island | R98: business insurance prince edward island | S98: =COUNTIF('Page-Keyword Map'!$A$2:$A$675,B98) | T98: =SUMIF('Page-Keyword Map'!$A$2:$A$675,B98,'Page-Keyword Map'!$H$2:$H$675) | U98: =COUNTIFS('Page-Keyword Map'!$A$2:$A$675,B98,'Page-Keyword Map'!$E$2:$E$675,"Nationwide") | V98: =COUNTIFS('Page-Keyword Map'!$A$2:$A$675,B98,'Page-Keyword Map'!$E$2:$E$675,"Provincial") | W98: =COUNTIFS('Page-Keyword Map'!$A$2:$A$675,B98,'Page-Keyword Map'!$E$2:$E$675,"City") | X98: =IF(O98="","",IF(ISNUMBER(SEARCH(O98,J98)),"Yes","No")) | Y98: 0.7 | Z98: sitemap-provinces.xml | AA98: Live – indexable
A99: P0098 | B99: https://instasure.ca/business-insurance/quebec/ | C99: Product × province | D99: Business insurance | E99: Business Insurance | G99: Quebec | I99: Yes | J99: Business Insurance in Quebec: Costs, Rules & Quotes (2026) | K99: =LEN(J99) | L99: Business Insurance in Quebec: how it works under AMF, what drives price, instant estimates and a waitlist for licensed advice in Quebec. | M99: =LEN(L99) | N99: Business Insurance in Quebec | O99: business insurance quebec | P99: 210 | Q99: Provincial | S99: =COUNTIF('Page-Keyword Map'!$A$2:$A$675,B99) | T99: =SUMIF('Page-Keyword Map'!$A$2:$A$675,B99,'Page-Keyword Map'!$H$2:$H$675) | U99: =COUNTIFS('Page-Keyword Map'!$A$2:$A$675,B99,'Page-Keyword Map'!$E$2:$E$675,"Nationwide") | V99: =COUNTIFS('Page-Keyword Map'!$A$2:$A$675,B99,'Page-Keyword Map'!$E$2:$E$675,"Provincial") | W99: =COUNTIFS('Page-Keyword Map'!$A$2:$A$675,B99,'Page-Keyword Map'!$E$2:$E$675,"City") | X99: =IF(O99="","",IF(ISNUMBER(SEARCH(O99,J99)),"Yes","No")) | Y99: 0.7 | Z99: sitemap-provinces.xml | AA99: Live – indexable
A100: P0099 | B100: https://instasure.ca/business-insurance/saskatchewan/ | C100: Product × province | D100: Business insurance | E100: Business Insurance | G100: Saskatchewan | I100: Yes | J100: Business Insurance in Saskatchewan: Costs, Rules & Quotes (2026) | K100: =LEN(J100) | L100: Business Insurance in Saskatchewan: how it works under FCAA, what drives price, instant estimates and advisors licensed in Saskatchewan. | M100: =LEN(L100) | N100: Business Insurance in Saskatchewan | O100: business insurance saskatchewan | P100: 110 | Q100: Provincial | S100: =COUNTIF('Page-Keyword Map'!$A$2:$A$675,B100) | T100: =SUMIF('Page-Keyword Map'!$A$2:$A$675,B100,'Page-Keyword Map'!$H$2:$H$675) | U100: =COUNTIFS('Page-Keyword Map'!$A$2:$A$675,B100,'Page-Keyword Map'!$E$2:$E$675,"Nationwide") | V100: =COUNTIFS('Page-Keyword Map'!$A$2:$A$675,B100,'Page-Keyword Map'!$E$2:$E$675,"Provincial") | W100: =COUNTIFS('Page-Keyword Map'!$A$2:$A$675,B100,'Page-Keyword Map'!$E$2:$E$675,"City") | X100: =IF(O100="","",IF(ISNUMBER(SEARCH(O100,J100)),"Yes","No")) | Y100: 0.7 | Z100: sitemap-provinces.xml | AA100: Live – indexable
A101: P0100 | B101: https://instasure.ca/business-insurance/yukon/ | C101: Product × province | D101: Business insurance | E101: Business Insurance | G101: Yukon | I101: Yes | J101: Business Insurance in Yukon: Costs, Rules & Quotes (2026) | K101: =LEN(J101) | L101: Business Insurance in Yukon: how it works under the Yukon Superintendent, what drives price, instant estimates and a waitlist for licensed advice in Yukon. | M101: =LEN(L101) | N101: Business Insurance in Yukon | R101: business insurance yukon | S101: =COUNTIF('Page-Keyword Map'!$A$2:$A$675,B101) | T101: =SUMIF('Page-Keyword Map'!$A$2:$A$675,B101,'Page-Keyword Map'!$H$2:$H$675) | U101: =COUNTIFS('Page-Keyword Map'!$A$2:$A$675,B101,'Page-Keyword Map'!$E$2:$E$675,"Nationwide") | V101: =COUNTIFS('Page-Keyword Map'!$A$2:$A$675,B101,'Page-Keyword Map'!$E$2:$E$675,"Provincial") | W101: =COUNTIFS('Page-Keyword Map'!$A$2:$A$675,B101,'Page-Keyword Map'!$E$2:$E$675,"City") | X101: =IF(O101="","",IF(ISNUMBER(SEARCH(O101,J101)),"Yes","No")) | Y101: 0.7 | Z101: sitemap-provinces.xml | AA101: Live – indexable
A102: P0101 | B102: https://instasure.ca/car-insurance/alberta/ | C102: Product × province | D102: Car insurance | E102: Car Insurance | G102: Alberta | I102: Yes | J102: Car Insurance in Alberta: Costs, Rules & Quotes (2026) | K102: =LEN(J102) | L102: Car Insurance in Alberta: how it works under the Superintendent of Insurance, what drives price, instant estimates and advisors licensed in Alberta. | M102: =LEN(L102) | N102: Car Insurance in Alberta | O102: car insurance alberta | P102: 4500 | Q102: Provincial | S102: =COUNTIF('Page-Keyword Map'!$A$2:$A$675,B102) | T102: =SUMIF('Page-Keyword Map'!$A$2:$A$675,B102,'Page-Keyword Map'!$H$2:$H$675) | U102: =COUNTIFS('Page-Keyword Map'!$A$2:$A$675,B102,'Page-Keyword Map'!$E$2:$E$675,"Nationwide") | V102: =COUNTIFS('Page-Keyword Map'!$A$2:$A$675,B102,'Page-Keyword Map'!$E$2:$E$675,"Provincial") | W102: =COUNTIFS('Page-Keyword Map'!$A$2:$A$675,B102,'Page-Keyword Map'!$E$2:$E$675,"City") | X102: =IF(O102="","",IF(ISNUMBER(SEARCH(O102,J102)),"Yes","No")) | Y102: 0.7 | Z102: sitemap-provinces.xml | AA102: Live – indexable
A103: P0102 | B103: https://instasure.ca/car-insurance/british-columbia/ | C103: Product × province | D103: Car insurance | E103: Car Insurance | G103: British Columbia | I103: Yes | J103: Car Insurance in British Columbia: Costs, Rules & Quotes (2026) | K103: =LEN(J103) | L103: Car Insurance in British Columbia: how it works under BCFSA, what drives price, instant estimates and advisors licensed in British Columbia. | M103: =LEN(L103) | N103: Car Insurance in British Columbia | O103: car insurance bc | P103: 2200 | Q103: Provincial | S103: =COUNTIF('Page-Keyword Map'!$A$2:$A$675,B103) | T103: =SUMIF('Page-Keyword Map'!$A$2:$A$675,B103,'Page-Keyword Map'!$H$2:$H$675) | U103: =COUNTIFS('Page-Keyword Map'!$A$2:$A$675,B103,'Page-Keyword Map'!$E$2:$E$675,"Nationwide") | V103: =COUNTIFS('Page-Keyword Map'!$A$2:$A$675,B103,'Page-Keyword Map'!$E$2:$E$675,"Provincial") | W103: =COUNTIFS('Page-Keyword Map'!$A$2:$A$675,B103,'Page-Keyword Map'!$E$2:$E$675,"City") | X103: =IF(O103="","",IF(ISNUMBER(SEARCH(O103,J103)),"Yes","No")) | Y103: 0.7 | Z103: sitemap-provinces.xml | AA103: Live – indexable
A104: P0103 | B104: https://instasure.ca/car-insurance/manitoba/ | C104: Product × province | D104: Car insurance | E104: Car Insurance | G104: Manitoba | I104: Yes | J104: Car Insurance in Manitoba: Costs, Rules & Quotes (2026) | K104: =LEN(J104) | L104: Car Insurance in Manitoba: how it works under FIRB, what drives price, instant estimates and advisors licensed in Manitoba. | M104: =LEN(L104) | N104: Car Insurance in Manitoba | O104: car insurance manitoba | P104: 660 | Q104: Provincial | S104: =COUNTIF('Page-Keyword Map'!$A$2:$A$675,B104) | T104: =SUMIF('Page-Keyword Map'!$A$2:$A$675,B104,'Page-Keyword Map'!$H$2:$H$675) | U104: =COUNTIFS('Page-Keyword Map'!$A$2:$A$675,B104,'Page-Keyword Map'!$E$2:$E$675,"Nationwide") | V104: =COUNTIFS('Page-Keyword Map'!$A$2:$A$675,B104,'Page-Keyword Map'!$E$2:$E$675,"Provincial") | W104: =COUNTIFS('Page-Keyword Map'!$A$2:$A$675,B104,'Page-Keyword Map'!$E$2:$E$675,"City") | X104: =IF(O104="","",IF(ISNUMBER(SEARCH(O104,J104)),"Yes","No")) | Y104: 0.7 | Z104: sitemap-provinces.xml | AA104: Live – indexable
A105: P0104 | B105: https://instasure.ca/car-insurance/new-brunswick/ | C105: Product × province | D105: Car insurance | E105: Car Insurance | G105: New Brunswick | I105: Yes | J105: Car Insurance in New Brunswick: Costs, Rules & Quotes (2026) | K105: =LEN(J105) | L105: Car Insurance in New Brunswick: how it works under FCNB, what drives price, instant estimates and advisors licensed in New Brunswick. | M105: =LEN(L105) | N105: Car Insurance in New Brunswick | O105: car insurance new brunswick | P105: 810 | Q105: Provincial | S105: =COUNTIF('Page-Keyword Map'!$A$2:$A$675,B105) | T105: =SUMIF('Page-Keyword Map'!$A$2:$A$675,B105,'Page-Keyword Map'!$H$2:$H$675) | U105: =COUNTIFS('Page-Keyword Map'!$A$2:$A$675,B105,'Page-Keyword Map'!$E$2:$E$675,"Nationwide") | V105: =COUNTIFS('Page-Keyword Map'!$A$2:$A$675,B105,'Page-Keyword Map'!$E$2:$E$675,"Provincial") | W105: =COUNTIFS('Page-Keyword Map'!$A$2:$A$675,B105,'Page-Keyword Map'!$E$2:$E$675,"City") | X105: =IF(O105="","",IF(ISNUMBER(SEARCH(O105,J105)),"Yes","No")) | Y105: 0.7 | Z105: sitemap-provinces.xml | AA105: Live – indexable
A106: P0105 | B106: https://instasure.ca/car-insurance/newfoundland-and-labrador/ | C106: Product × province | D106: Car insurance | E106: Car Insurance | G106: Newfoundland and Labrador | I106: Yes | J106: Car Insurance in Newfoundland and Labrador: Costs, Rules & Quotes (2026) | K106: =LEN(J106) | L106: Car Insurance in Newfoundland and Labrador: how it works under Service NL, what drives price, instant estimates and advisors licensed in Newfoundland and Labrador. | M106: =LEN(L106) | N106: Car Insurance in Newfoundland and Labrador | O106: car insurance newfoundland | P106: 560 | Q106: Provincial | S106: =COUNTIF('Page-Keyword Map'!$A$2:$A$675,B106) | T106: =SUMIF('Page-Keyword Map'!$A$2:$A$675,B106,'Page-Keyword Map'!$H$2:$H$675) | U106: =COUNTIFS('Page-Keyword Map'!$A$2:$A$675,B106,'Page-Keyword Map'!$E$2:$E$675,"Nationwide") | V106: =COUNTIFS('Page-Keyword Map'!$A$2:$A$675,B106,'Page-Keyword Map'!$E$2:$E$675,"Provincial") | W106: =COUNTIFS('Page-Keyword Map'!$A$2:$A$675,B106,'Page-Keyword Map'!$E$2:$E$675,"City") | X106: =IF(O106="","",IF(ISNUMBER(SEARCH(O106,J106)),"Yes","No")) | Y106: 0.7 | Z106: sitemap-provinces.xml | AA106: Live – indexable
A107: P0106 | B107: https://instasure.ca/car-insurance/northwest-territories/ | C107: Product × province | D107: Car insurance | E107: Car Insurance | G107: Northwest Territories | I107: No | J107: Car Insurance in Northwest Territories: Costs, Rules & Quotes (2026) | K107: =LEN(J107) | L107: Car Insurance in Northwest Territories: how it works under the NWT Superintendent, what drives price, instant estimates and a waitlist for licensed advice in… | M107: =LEN(L107) | N107: Car Insurance in Northwest Territories | R107: car insurance northwest territories | S107: =COUNTIF('Page-Keyword Map'!$A$2:$A$675,B107) | T107: =SUMIF('Page-Keyword Map'!$A$2:$A$675,B107,'Page-Keyword Map'!$H$2:$H$675) | U107: =COUNTIFS('Page-Keyword Map'!$A$2:$A$675,B107,'Page-Keyword Map'!$E$2:$E$675,"Nationwide") | V107: =COUNTIFS('Page-Keyword Map'!$A$2:$A$675,B107,'Page-Keyword Map'!$E$2:$E$675,"Provincial") | W107: =COUNTIFS('Page-Keyword Map'!$A$2:$A$675,B107,'Page-Keyword Map'!$E$2:$E$675,"City") | X107: =IF(O107="","",IF(ISNUMBER(SEARCH(O107,J107)),"Yes","No")) | Y107: 0.7 | Z107: (not listed: noindex) | AA107: Live – noindex (enrich before indexing)
A108: P0107 | B108: https://instasure.ca/car-insurance/nova-scotia/ | C108: Product × province | D108: Car insurance | E108: Car Insurance | G108: Nova Scotia | I108: Yes | J108: Car Insurance in Nova Scotia: Costs, Rules & Quotes (2026) | K108: =LEN(J108) | L108: Car Insurance in Nova Scotia: how it works under the NS Superintendent of Insurance, what drives price, instant estimates and advisors licensed in Nova Scotia. | M108: =LEN(L108) | N108: Car Insurance in Nova Scotia | O108: car insurance nova scotia | P108: 990 | Q108: Provincial | S108: =COUNTIF('Page-Keyword Map'!$A$2:$A$675,B108) | T108: =SUMIF('Page-Keyword Map'!$A$2:$A$675,B108,'Page-Keyword Map'!$H$2:$H$675) | U108: =COUNTIFS('Page-Keyword Map'!$A$2:$A$675,B108,'Page-Keyword Map'!$E$2:$E$675,"Nationwide") | V108: =COUNTIFS('Page-Keyword Map'!$A$2:$A$675,B108,'Page-Keyword Map'!$E$2:$E$675,"Provincial") | W108: =COUNTIFS('Page-Keyword Map'!$A$2:$A$675,B108,'Page-Keyword Map'!$E$2:$E$675,"City") | X108: =IF(O108="","",IF(ISNUMBER(SEARCH(O108,J108)),"Yes","No")) | Y108: 0.7 | Z108: sitemap-provinces.xml | AA108: Live – indexable
A109: P0108 | B109: https://instasure.ca/car-insurance/nunavut/ | C109: Product × province | D109: Car insurance | E109: Car Insurance | G109: Nunavut | I109: No | J109: Car Insurance in Nunavut: Costs, Rules & Quotes (2026) | K109: =LEN(J109) | L109: Car Insurance in Nunavut: how it works under the Nunavut Superintendent, what drives price, instant estimates and a waitlist for licensed advice in Nunavut. | M109: =LEN(L109) | N109: Car Insurance in Nunavut | R109: car insurance nunavut | S109: =COUNTIF('Page-Keyword Map'!$A$2:$A$675,B109) | T109: =SUMIF('Page-Keyword Map'!$A$2:$A$675,B109,'Page-Keyword Map'!$H$2:$H$675) | U109: =COUNTIFS('Page-Keyword Map'!$A$2:$A$675,B109,'Page-Keyword Map'!$E$2:$E$675,"Nationwide") | V109: =COUNTIFS('Page-Keyword Map'!$A$2:$A$675,B109,'Page-Keyword Map'!$E$2:$E$675,"Provincial") | W109: =COUNTIFS('Page-Keyword Map'!$A$2:$A$675,B109,'Page-Keyword Map'!$E$2:$E$675,"City") | X109: =IF(O109="","",IF(ISNUMBER(SEARCH(O109,J109)),"Yes","No")) | Y109: 0.7 | Z109: (not listed: noindex) | AA109: Live – noindex (enrich before indexing)
A110: P0109 | B110: https://instasure.ca/car-insurance/ontario/ | C110: Product × province | D110: Car insurance | E110: Car Insurance | G110: Ontario | I110: Yes | J110: Car Insurance in Ontario: Costs, Rules & Quotes (2026) | K110: =LEN(J110) | L110: Car Insurance in Ontario: how it works under FSRA, what drives price, instant estimates and advisors licensed in Ontario. | M110: =LEN(L110) | N110: Car Insurance in Ontario | O110: car insurance ontario | P110: 12000 | Q110: Provincial | S110: =COUNTIF('Page-Keyword Map'!$A$2:$A$675,B110) | T110: =SUMIF('Page-Keyword Map'!$A$2:$A$675,B110,'Page-Keyword Map'!$H$2:$H$675) | U110: =COUNTIFS('Page-Keyword Map'!$A$2:$A$675,B110,'Page-Keyword Map'!$E$2:$E$675,"Nationwide") | V110: =COUNTIFS('Page-Keyword Map'!$A$2:$A$675,B110,'Page-Keyword Map'!$E$2:$E$675,"Provincial") | W110: =COUNTIFS('Page-Keyword Map'!$A$2:$A$675,B110,'Page-Keyword Map'!$E$2:$E$675,"City") | X110: =IF(O110="","",IF(ISNUMBER(SEARCH(O110,J110)),"Yes","No")) | Y110: 0.7 | Z110: sitemap-provinces.xml | AA110: Live – indexable
A111: P0110 | B111: https://instasure.ca/car-insurance/prince-edward-island/ | C111: Product × province | D111: Car insurance | E111: Car Insurance | G111: Prince Edward Island | I111: Yes | J111: Car Insurance in Prince Edward Island: Costs, Rules & Quotes (2026) | K111: =LEN(J111) | L111: Car Insurance in Prince Edward Island: how it works under the PEI Superintendent, what drives price, instant estimates and advisors licensed in Prince Edward Island. | M111: =LEN(L111) | N111: Car Insurance in Prince Edward Island | O111: car insurance pei | P111: 190 | Q111: Provincial | S111: =COUNTIF('Page-Keyword Map'!$A$2:$A$675,B111) | T111: =SUMIF('Page-Keyword Map'!$A$2:$A$675,B111,'Page-Keyword Map'!$H$2:$H$675) | U111: =COUNTIFS('Page-Keyword Map'!$A$2:$A$675,B111,'Page-Keyword Map'!$E$2:$E$675,"Nationwide") | V111: =COUNTIFS('Page-Keyword Map'!$A$2:$A$675,B111,'Page-Keyword Map'!$E$2:$E$675,"Provincial") | W111: =COUNTIFS('Page-Keyword Map'!$A$2:$A$675,B111,'Page-Keyword Map'!$E$2:$E$675,"City") | X111: =IF(O111="","",IF(ISNUMBER(SEARCH(O111,J111)),"Yes","No")) | Y111: 0.7 | Z111: sitemap-provinces.xml | AA111: Live – indexable
A112: P0111 | B112: https://instasure.ca/car-insurance/quebec/ | C112: Product × province | D112: Car insurance | E112: Car Insurance | G112: Quebec | I112: Yes | J112: Car Insurance in Quebec: Costs, Rules & Quotes (2026) | K112: =LEN(J112) | L112: Car Insurance in Quebec: how it works under AMF, what drives price, instant estimates and a waitlist for licensed advice in Quebec. | M112: =LEN(L112) | N112: Car Insurance in Quebec | O112: car insurance quebec | P112: 2200 | Q112: Provincial | S112: =COUNTIF('Page-Keyword Map'!$A$2:$A$675,B112) | T112: =SUMIF('Page-Keyword Map'!$A$2:$A$675,B112,'Page-Keyword Map'!$H$2:$H$675) | U112: =COUNTIFS('Page-Keyword Map'!$A$2:$A$675,B112,'Page-Keyword Map'!$E$2:$E$675,"Nationwide") | V112: =COUNTIFS('Page-Keyword Map'!$A$2:$A$675,B112,'Page-Keyword Map'!$E$2:$E$675,"Provincial") | W112: =COUNTIFS('Page-Keyword Map'!$A$2:$A$675,B112,'Page-Keyword Map'!$E$2:$E$675,"City") | X112: =IF(O112="","",IF(ISNUMBER(SEARCH(O112,J112)),"Yes","No")) | Y112: 0.7 | Z112: sitemap-provinces.xml | AA112: Live – indexable
A113: P0112 | B113: https://instasure.ca/car-insurance/saskatchewan/ | C113: Product × province | D113: Car insurance | E113: Car Insurance | G113: Saskatchewan | I113: Yes | J113: Car Insurance in Saskatchewan: Costs, Rules & Quotes (2026) | K113: =LEN(J113) | L113: Car Insurance in Saskatchewan: how it works under FCAA, what drives price, instant estimates and advisors licensed in Saskatchewan. | M113: =LEN(L113) | N113: Car Insurance in Saskatchewan | O113: car insurance saskatchewan | P113: 570 | Q113: Provincial | S113: =COUNTIF('Page-Keyword Map'!$A$2:$A$675,B113) | T113: =SUMIF('Page-Keyword Map'!$A$2:$A$675,B113,'Page-Keyword Map'!$H$2:$H$675) | U113: =COUNTIFS('Page-Keyword Map'!$A$2:$A$675,B113,'Page-Keyword Map'!$E$2:$E$675,"Nationwide") | V113: =COUNTIFS('Page-Keyword Map'!$A$2:$A$675,B113,'Page-Keyword Map'!$E$2:$E$675,"Provincial") | W113: =COUNTIFS('Page-Keyword Map'!$A$2:$A$675,B113,'Page-Keyword Map'!$E$2:$E$675,"City") | X113: =IF(O113="","",IF(ISNUMBER(SEARCH(O113,J113)),"Yes","No")) | Y113: 0.7 | Z113: sitemap-provinces.xml | AA113: Live – indexable
A114: P0113 | B114: https://instasure.ca/car-insurance/yukon/ | C114: Product × province | D114: Car insurance | E114: Car Insurance | G114: Yukon | I114: No | J114: Car Insurance in Yukon: Costs, Rules & Quotes (2026) | K114: =LEN(J114) | L114: Car Insurance in Yukon: how it works under the Yukon Superintendent, what drives price, instant estimates and a waitlist for licensed advice in Yukon. | M114: =LEN(L114) | N114: Car Insurance in Yukon | R114: car insurance yukon | S114: =COUNTIF('Page-Keyword Map'!$A$2:$A$675,B114) | T114: =SUMIF('Page-Keyword Map'!$A$2:$A$675,B114,'Page-Keyword Map'!$H$2:$H$675) | U114: =COUNTIFS('Page-Keyword Map'!$A$2:$A$675,B114,'Page-Keyword Map'!$E$2:$E$675,"Nationwide") | V114: =COUNTIFS('Page-Keyword Map'!$A$2:$A$675,B114,'Page-Keyword Map'!$E$2:$E$675,"Provincial") | W114: =COUNTIFS('Page-Keyword Map'!$A$2:$A$675,B114,'Page-Keyword Map'!$E$2:$E$675,"City") | X114: =IF(O114="","",IF(ISNUMBER(SEARCH(O114,J114)),"Yes","No")) | Y114: 0.7 | Z114: (not listed: noindex) | AA114: Live – noindex (enrich before indexing)
A115: P0114 | B115: https://instasure.ca/condo-insurance/alberta/ | C115: Product × province | D115: Condo insurance | E115: Condo Insurance | G115: Alberta | I115: Yes | J115: Condo Insurance in Alberta: Costs, Rules & Quotes (2026) | K115: =LEN(J115) | L115: Condo Insurance in Alberta: how it works under the Superintendent of Insurance, what drives price, instant estimates and advisors licensed in Alberta. | M115: =LEN(L115) | N115: Condo Insurance in Alberta | O115: condo insurance alberta | P115: 220 | Q115: Provincial | S115: =COUNTIF('Page-Keyword Map'!$A$2:$A$675,B115) | T115: =SUMIF('Page-Keyword Map'!$A$2:$A$675,B115,'Page-Keyword Map'!$H$2:$H$675) | U115: =COUNTIFS('Page-Keyword Map'!$A$2:$A$675,B115,'Page-Keyword Map'!$E$2:$E$675,"Nationwide") | V115: =COUNTIFS('Page-Keyword Map'!$A$2:$A$675,B115,'Page-Keyword Map'!$E$2:$E$675,"Provincial") | W115: =COUNTIFS('Page-Keyword Map'!$A$2:$A$675,B115,'Page-Keyword Map'!$E$2:$E$675,"City") | X115: =IF(O115="","",IF(ISNUMBER(SEARCH(O115,J115)),"Yes","No")) | Y115: 0.7 | Z115: sitemap-provinces.xml | AA115: Live – indexable
A116: P0115 | B116: https://instasure.ca/condo-insurance/british-columbia/ | C116: Product × province | D116: Condo insurance | E116: Condo Insurance | G116: British Columbia | I116: Yes | J116: Condo Insurance in British Columbia: Costs, Rules & Quotes (2026) | K116: =LEN(J116) | L116: Condo Insurance in British Columbia: how it works under BCFSA, what drives price, instant estimates and advisors licensed in British Columbia. | M116: =LEN(L116) | N116: Condo Insurance in British Columbia | O116: condo insurance bc | P116: 260 | Q116: Provincial | S116: =COUNTIF('Page-Keyword Map'!$A$2:$A$675,B116) | T116: =SUMIF('Page-Keyword Map'!$A$2:$A$675,B116,'Page-Keyword Map'!$H$2:$H$675) | U116: =COUNTIFS('Page-Keyword Map'!$A$2:$A$675,B116,'Page-Keyword Map'!$E$2:$E$675,"Nationwide") | V116: =COUNTIFS('Page-Keyword Map'!$A$2:$A$675,B116,'Page-Keyword Map'!$E$2:$E$675,"Provincial") | W116: =COUNTIFS('Page-Keyword Map'!$A$2:$A$675,B116,'Page-Keyword Map'!$E$2:$E$675,"City") | X116: =IF(O116="","",IF(ISNUMBER(SEARCH(O116,J116)),"Yes","No")) | Y116: 0.7 | Z116: sitemap-provinces.xml | AA116: Live – indexable
A117: P0116 | B117: https://instasure.ca/condo-insurance/manitoba/ | C117: Product × province | D117: Condo insurance | E117: Condo Insurance | G117: Manitoba | I117: Yes | J117: Condo Insurance in Manitoba: Costs, Rules & Quotes (2026) | K117: =LEN(J117) | L117: Condo Insurance in Manitoba: how it works under FIRB, what drives price, instant estimates and advisors licensed in Manitoba. | M117: =LEN(L117) | N117: Condo Insurance in Manitoba | O117: condo insurance manitoba | P117: 78 | Q117: Provincial | S117: =COUNTIF('Page-Keyword Map'!$A$2:$A$675,B117) | T117: =SUMIF('Page-Keyword Map'!$A$2:$A$675,B117,'Page-Keyword Map'!$H$2:$H$675) | U117: =COUNTIFS('Page-Keyword Map'!$A$2:$A$675,B117,'Page-Keyword Map'!$E$2:$E$675,"Nationwide") | V117: =COUNTIFS('Page-Keyword Map'!$A$2:$A$675,B117,'Page-Keyword Map'!$E$2:$E$675,"Provincial") | W117: =COUNTIFS('Page-Keyword Map'!$A$2:$A$675,B117,'Page-Keyword Map'!$E$2:$E$675,"City") | X117: =IF(O117="","",IF(ISNUMBER(SEARCH(O117,J117)),"Yes","No")) | Y117: 0.7 | Z117: sitemap-provinces.xml | AA117: Live – indexable
A118: P0117 | B118: https://instasure.ca/condo-insurance/new-brunswick/ | C118: Product × province | D118: Condo insurance | E118: Condo Insurance | G118: New Brunswick | I118: Yes | J118: Condo Insurance in New Brunswick: Costs, Rules & Quotes (2026) | K118: =LEN(J118) | L118: Condo Insurance in New Brunswick: how it works under FCNB, what drives price, instant estimates and advisors licensed in New Brunswick. | M118: =LEN(L118) | N118: Condo Insurance in New Brunswick | O118: condo insurance new brunswick | P118: 48 | Q118: Provincial | S118: =COUNTIF('Page-Keyword Map'!$A$2:$A$675,B118) | T118: =SUMIF('Page-Keyword Map'!$A$2:$A$675,B118,'Page-Keyword Map'!$H$2:$H$675) | U118: =COUNTIFS('Page-Keyword Map'!$A$2:$A$675,B118,'Page-Keyword Map'!$E$2:$E$675,"Nationwide") | V118: =COUNTIFS('Page-Keyword Map'!$A$2:$A$675,B118,'Page-Keyword Map'!$E$2:$E$675,"Provincial") | W118: =COUNTIFS('Page-Keyword Map'!$A$2:$A$675,B118,'Page-Keyword Map'!$E$2:$E$675,"City") | X118: =IF(O118="","",IF(ISNUMBER(SEARCH(O118,J118)),"Yes","No")) | Y118: 0.7 | Z118: sitemap-provinces.xml | AA118: Live – indexable
A119: P0118 | B119: https://instasure.ca/condo-insurance/newfoundland-and-labrador/ | C119: Product × province | D119: Condo insurance | E119: Condo Insurance | G119: Newfoundland and Labrador | I119: Yes | J119: Condo Insurance in Newfoundland and Labrador: Costs, Rules & Quotes (2026) | K119: =LEN(J119) | L119: Condo Insurance in Newfoundland and Labrador: how it works under Service NL, what drives price, instant estimates and advisors licensed in Newfoundland and Labrador. | M119: =LEN(L119) | N119: Condo Insurance in Newfoundland and Labrador | O119: condo insurance newfoundland | P119: 33 | Q119: Provincial | S119: =COUNTIF('Page-Keyword Map'!$A$2:$A$675,B119) | T119: =SUMIF('Page-Keyword Map'!$A$2:$A$675,B119,'Page-Keyword Map'!$H$2:$H$675) | U119: =COUNTIFS('Page-Keyword Map'!$A$2:$A$675,B119,'Page-Keyword Map'!$E$2:$E$675,"Nationwide") | V119: =COUNTIFS('Page-Keyword Map'!$A$2:$A$675,B119,'Page-Keyword Map'!$E$2:$E$675,"Provincial") | W119: =COUNTIFS('Page-Keyword Map'!$A$2:$A$675,B119,'Page-Keyword Map'!$E$2:$E$675,"City") | X119: =IF(O119="","",IF(ISNUMBER(SEARCH(O119,J119)),"Yes","No")) | Y119: 0.7 | Z119: sitemap-provinces.xml | AA119: Live – indexable
A120: P0119 | B120: https://instasure.ca/condo-insurance/northwest-territories/ | C120: Product × province | D120: Condo insurance | E120: Condo Insurance | G120: Northwest Territories | I120: Yes | J120: Condo Insurance in Northwest Territories: Costs, Rules & Quotes (2026) | K120: =LEN(J120) | L120: Condo Insurance in Northwest Territories: how it works under the NWT Superintendent, what drives price, instant estimates and a waitlist for licensed advice in… | M120: =LEN(L120) | N120: Condo Insurance in Northwest Territories | R120: condo insurance northwest territories | S120: =COUNTIF('Page-Keyword Map'!$A$2:$A$675,B120) | T120: =SUMIF('Page-Keyword Map'!$A$2:$A$675,B120,'Page-Keyword Map'!$H$2:$H$675) | U120: =COUNTIFS('Page-Keyword Map'!$A$2:$A$675,B120,'Page-Keyword Map'!$E$2:$E$675,"Nationwide") | V120: =COUNTIFS('Page-Keyword Map'!$A$2:$A$675,B120,'Page-Keyword Map'!$E$2:$E$675,"Provincial") | W120: =COUNTIFS('Page-Keyword Map'!$A$2:$A$675,B120,'Page-Keyword Map'!$E$2:$E$675,"City") | X120: =IF(O120="","",IF(ISNUMBER(SEARCH(O120,J120)),"Yes","No")) | Y120: 0.7 | Z120: sitemap-provinces.xml | AA120: Live – indexable
A121: P0120 | B121: https://instasure.ca/condo-insurance/nova-scotia/ | C121: Product × province | D121: Condo insurance | E121: Condo Insurance | G121: Nova Scotia | I121: Yes | J121: Condo Insurance in Nova Scotia: Costs, Rules & Quotes (2026) | K121: =LEN(J121) | L121: Condo Insurance in Nova Scotia: how it works under the NS Superintendent of Insurance, what drives price, instant estimates and advisors licensed in Nova Scotia. | M121: =LEN(L121) | N121: Condo Insurance in Nova Scotia | O121: condo insurance nova scotia | P121: 58 | Q121: Provincial | S121: =COUNTIF('Page-Keyword Map'!$A$2:$A$675,B121) | T121: =SUMIF('Page-Keyword Map'!$A$2:$A$675,B121,'Page-Keyword Map'!$H$2:$H$675) | U121: =COUNTIFS('Page-Keyword Map'!$A$2:$A$675,B121,'Page-Keyword Map'!$E$2:$E$675,"Nationwide") | V121: =COUNTIFS('Page-Keyword Map'!$A$2:$A$675,B121,'Page-Keyword Map'!$E$2:$E$675,"Provincial") | W121: =COUNTIFS('Page-Keyword Map'!$A$2:$A$675,B121,'Page-Keyword Map'!$E$2:$E$675,"City") | X121: =IF(O121="","",IF(ISNUMBER(SEARCH(O121,J121)),"Yes","No")) | Y121: 0.7 | Z121: sitemap-provinces.xml | AA121: Live – indexable
...

Sheet Page-Keyword Map
A1: URL | B1: Page type | C1: Insurance segment | D1: Keyword | E1: Level | F1: Province | G1: City | H1: Volume / mo (modelled) | I1: Difficulty (0–100) | J1: Intent | K1: Cluster | L1: Priority (1 = first) | M1: Role on page | N1: Keyword in page title? | O1: Competitors seen | P1: Notes
A2: https://instasure.ca/car-insurance/ | B2: Product pillar | C2: Car insurance | D2: car insurance | E2: Nationwide | H2: 74000 | I2: 85 | J2: commercial | K2: auto-core | L2: 2 | M2: Primary | N2: =IFERROR(IF(ISNUMBER(SEARCH(D2,INDEX(Pages!$J$2:$J$829,MATCH(A2,Pages!$B$2:$B$829,0)))),"Yes","No"),"Page not found") | O2: ratehub, rates.ca, kanetix, mychoice, insurer brands | P2: Head term. Win through province and city depth rather than head-on.
A3: https://instasure.ca/car-insurance/ | B3: Product pillar | C3: Car insurance | D3: auto insurance | E3: Nationwide | H3: 33000 | I3: 82 | J3: commercial | K3: auto-core | L3: 3 | M3: Secondary | N3: =IFERROR(IF(ISNUMBER(SEARCH(D3,INDEX(Pages!$J$2:$J$829,MATCH(A3,Pages!$B$2:$B$829,0)))),"Yes","No"),"Page not found") | O3: ratehub, rates.ca, insurer brands | P3: Synonym. Use in H2s and meta descriptions, not a separate page.
A4: https://instasure.ca/car-insurance/ | B4: Product pillar | C4: Car insurance | D4: cheap car insurance | E4: Nationwide | H4: 9900 | I4: 75 | J4: transactional | K4: auto-cost | L4: 2 | M4: Secondary | N4: =IFERROR(IF(ISNUMBER(SEARCH(D4,INDEX(Pages!$J$2:$J$829,MATCH(A4,Pages!$B$2:$B$829,0)))),"Yes","No"),"Page not found") | O4: ratehub (15 ways), rates.ca, mychoice | P4: Answer with savings factors and compare. No "cheapest" claim without a published methodology.
A5: https://instasure.ca/travel-insurance/ | B5: Product pillar | C5: Travel insurance | D5: travel insurance | E5: Nationwide | H5: 40000 | I5: 80 | J5: commercial | K5: travel | L5: 3 | M5: Primary | N5: =IFERROR(IF(ISNUMBER(SEARCH(D5,INDEX(Pages!$J$2:$J$829,MATCH(A5,Pages!$B$2:$B$829,0)))),"Yes","No"),"Page not found") | O5: sun life, manulife, credit cards, ratehub | P5: Huge but low lead value. Capture through super visa, snowbird and visitors.
A6: https://instasure.ca/travel-insurance/ | B6: Product pillar | C6: Travel insurance | D6: out of province travel insurance | E6: Nationwide | H6: 480 | I6: 35 | J6: informational | K6: travel | L6: 3 | M6: Secondary | N6: =IFERROR(IF(ISNUMBER(SEARCH(D6,INDEX(Pages!$J$2:$J$829,MATCH(A6,Pages!$B$2:$B$829,0)))),"Yes","No"),"Page not found") | O6: sun life
A7: https://instasure.ca/home-insurance/ | B7: Product pillar | C7: Home insurance | D7: home insurance | E7: Nationwide | H7: 27000 | I7: 82 | J7: commercial | K7: property-core | L7: 1 | M7: Primary | N7: =IFERROR(IF(ISNUMBER(SEARCH(D7,INDEX(Pages!$J$2:$J$829,MATCH(A7,Pages!$B$2:$B$829,0)))),"Yes","No"),"Page not found") | O7: ratehub, rates.ca, sonnet, insurer brands
A8: https://instasure.ca/home-insurance/ | B8: Product pillar | C8: Home insurance | D8: house insurance | E8: Nationwide | H8: 8100 | I8: 75 | J8: commercial | K8: property-core | L8: 2 | M8: Secondary | N8: =IFERROR(IF(ISNUMBER(SEARCH(D8,INDEX(Pages!$J$2:$J$829,MATCH(A8,Pages!$B$2:$B$829,0)))),"Yes","No"),"Page not found") | O8: ratehub, rates.ca
A9: https://instasure.ca/life-insurance/ | B9: Product pillar | C9: Life insurance | D9: life insurance | E9: Nationwide | H9: 33000 | I9: 85 | J9: commercial | K9: life-core | L9: 1 | M9: Primary | N9: =IFERROR(IF(ISNUMBER(SEARCH(D9,INDEX(Pages!$J$2:$J$829,MATCH(A9,Pages!$B$2:$B$829,0)))),"Yes","No"),"Page not found") | O9: policyadvisor, sun life, manulife, policyme, ratehub, canada life | P9: Highest-value head term. Province, city and cost pages feed it.
A10: https://instasure.ca/tenant-insurance/ | B10: Product pillar | C10: Tenant insurance | D10: tenant insurance | E10: Nationwide | H10: 15000 | I10: 70 | J10: commercial | K10: property-core | L10: 1 | M10: Primary | N10: =IFERROR(IF(ISNUMBER(SEARCH(D10,INDEX(Pages!$J$2:$J$829,MATCH(A10,Pages!$B$2:$B$829,0)))),"Yes","No"),"Page not found") | O10: sonnet, ratehub, rates.ca, squareone
A11: https://instasure.ca/tenant-insurance/ | B11: Product pillar | C11: Tenant insurance | D11: renters insurance | E11: Nationwide | H11: 9900 | I11: 65 | J11: commercial | K11: property-core | L11: 2 | M11: Secondary | N11: =IFERROR(IF(ISNUMBER(SEARCH(D11,INDEX(Pages!$J$2:$J$829,MATCH(A11,Pages!$B$2:$B$829,0)))),"Yes","No"),"Page not found") | O11: sonnet, ratehub | P11: Synonym used in titles ("Tenant (Renters) Insurance").
A12: https://instasure.ca/tenant-insurance/ | B12: Product pillar | C12: Tenant insurance | D12: tenant insurance cost | E12: Nationwide | H12: 1300 | I12: 40 | J12: informational | K12: property-cost | L12: 1 | M12: Secondary | N12: =IFERROR(IF(ISNUMBER(SEARCH(D12,INDEX(Pages!$J$2:$J$829,MATCH(A12,Pages!$B$2:$B$829,0)))),"Yes","No"),"Page not found") | O12: ratehub, sonnet
A13: https://instasure.ca/business-insurance/ | B13: Product pillar | C13: Business insurance | D13: business insurance | E13: Nationwide | H13: 8100 | I13: 70 | J13: commercial | K13: business | L13: 1 | M13: Primary | N13: =IFERROR(IF(ISNUMBER(SEARCH(D13,INDEX(Pages!$J$2:$J$829,MATCH(A13,Pages!$B$2:$B$829,0)))),"Yes","No"),"Page not found") | O13: ratehub, rates.ca, zensurance, apollo
A14: https://instasure.ca/business-insurance/ | B14: Product pillar | C14: Business insurance | D14: liability insurance | E14: Nationwide | H14: 5400 | I14: 65 | J14: commercial | K14: business | L14: 3 | M14: Secondary | N14: =IFERROR(IF(ISNUMBER(SEARCH(D14,INDEX(Pages!$J$2:$J$829,MATCH(A14,Pages!$B$2:$B$829,0)))),"Yes","No"),"Page not found") | O14: ratehub, rates.ca
A15: https://instasure.ca/business-insurance/ | B15: Product pillar | C15: Business insurance | D15: small business insurance | E15: Nationwide | H15: 2900 | I15: 60 | J15: commercial | K15: business | L15: 1 | M15: Secondary | N15: =IFERROR(IF(ISNUMBER(SEARCH(D15,INDEX(Pages!$J$2:$J$829,MATCH(A15,Pages!$B$2:$B$829,0)))),"Yes","No"),"Page not found") | O15: rates.ca, ratehub
A16: https://instasure.ca/business-insurance/ | B16: Product pillar | C16: Business insurance | D16: general liability insurance | E16: Nationwide | H16: 2400 | I16: 55 | J16: commercial | K16: business | L16: 2 | M16: Secondary | N16: =IFERROR(IF(ISNUMBER(SEARCH(D16,INDEX(Pages!$J$2:$J$829,MATCH(A16,Pages!$B$2:$B$829,0)))),"Yes","No"),"Page not found") | O16: ratehub (CGL), rates.ca
A17: https://instasure.ca/quote/car-insurance/ | B17: (not a live page) | C17: Car insurance | D17: car insurance quotes | E17: Nationwide | H17: 14000 | I17: 78 | J17: transactional | K17: auto-core | L17: 1 | M17: Primary | N17: =IFERROR(IF(ISNUMBER(SEARCH(D17,INDEX(Pages!$J$2:$J$829,MATCH(A17,Pages!$B$2:$B$829,0)))),"Yes","No"),"Page not found") | O17: ratehub, rates.ca, kanetix, lowestrates | P17: Money term: send to the instant estimate flow.
A18: https://instasure.ca/quote/car-insurance/ | B18: (not a live page) | C18: Car insurance | D18: car insurance calculator | E18: Nationwide | H18: 2400 | I18: 55 | J18: transactional | K18: auto-tools | L18: 2 | M18: Secondary | N18: =IFERROR(IF(ISNUMBER(SEARCH(D18,INDEX(Pages!$J$2:$J$829,MATCH(A18,Pages!$B$2:$B$829,0)))),"Yes","No"),"Page not found") | O18: rates.ca (ON, AB), lowestrates (ON) | P18: Instant estimate covers the intent. Planned: /calculators/car-insurance-cost/ with province selector.
A19: https://instasure.ca/quote/car-insurance/ | B19: (not a live page) | C19: Car insurance | D19: ontario car insurance calculator | E19: Provincial | F19: Ontario | H19: 880 | I19: 45 | J19: transactional | K19: auto-tools | L19: 2 | M19: Secondary | N19: =IFERROR(IF(ISNUMBER(SEARCH(D19,INDEX(Pages!$J$2:$J$829,MATCH(A19,Pages!$B$2:$B$829,0)))),"Yes","No"),"Page not found") | O19: rates.ca, lowestrates
A20: https://instasure.ca/quote/car-insurance/ | B20: (not a live page) | C20: Car insurance | D20: alberta car insurance calculator | E20: Provincial | F20: Alberta | H20: 390 | I20: 35 | J20: transactional | K20: auto-tools | L20: 2 | M20: Secondary | N20: =IFERROR(IF(ISNUMBER(SEARCH(D20,INDEX(Pages!$J$2:$J$829,MATCH(A20,Pages!$B$2:$B$829,0)))),"Yes","No"),"Page not found") | O20: rates.ca
A21: https://instasure.ca/pet-insurance/ | B21: Service page | C21: Pet insurance | D21: pet insurance | E21: Nationwide | H21: 14000 | I21: 70 | J21: commercial | K21: specialty-personal | L21: 4 | M21: Primary | N21: =IFERROR(IF(ISNUMBER(SEARCH(D21,INDEX(Pages!$J$2:$J$829,MATCH(A21,Pages!$B$2:$B$829,0)))),"Yes","No"),"Page not found") | O21: sonnet (pet product), trupanion, petsecure, pets plus us | P21: Big but low advisor fit: most pet insurers sell direct. A completeness page that keeps visitors on site.
A22: https://instasure.ca/health-dental-insurance/ | B22: Product pillar | C22: Health & dental insurance | D22: dental insurance | E22: Nationwide | H22: 8100 | I22: 65 | J22: commercial | K22: health-dental | L22: 2 | M22: Primary | N22: =IFERROR(IF(ISNUMBER(SEARCH(D22,INDEX(Pages!$J$2:$J$829,MATCH(A22,Pages!$B$2:$B$829,0)))),"Yes","No"),"Page not found") | O22: sun life, manulife, blue cross, policyadvisor | P22: Much of the volume is CDCP navigation; target the self-employed and CDCP-ineligible.
A23: https://instasure.ca/health-dental-insurance/ | B23: Product pillar | C23: Health & dental insurance | D23: private health insurance canada | E23: Nationwide | H23: 2900 | I23: 60 | J23: commercial | K23: health-dental | L23: 2 | M23: Secondary | N23: =IFERROR(IF(ISNUMBER(SEARCH(D23,INDEX(Pages!$J$2:$J$829,MATCH(A23,Pages!$B$2:$B$829,0)))),"Yes","No"),"Page not found") | O23: policyadvisor, sun life, manulife, blue cross
A24: https://instasure.ca/health-dental-insurance/ | B24: Product pillar | C24: Health & dental insurance | D24: health and dental insurance | E24: Nationwide | H24: 2400 | I24: 55 | J24: commercial | K24: health-dental | L24: 1 | M24: Secondary | N24: =IFERROR(IF(ISNUMBER(SEARCH(D24,INDEX(Pages!$J$2:$J$829,MATCH(A24,Pages!$B$2:$B$829,0)))),"Yes","No"),"Page not found") | O24: policyadvisor, sun life, blue cross
A25: https://instasure.ca/health-dental-insurance/ | B25: Product pillar | C25: Health & dental insurance | D25: health insurance for self employed | E25: Nationwide | H25: 590 | I25: 35 | J25: commercial | K25: health-dental | L25: 2 | M25: Secondary | N25: =IFERROR(IF(ISNUMBER(SEARCH(D25,INDEX(Pages!$J$2:$J$829,MATCH(A25,Pages!$B$2:$B$829,0)))),"Yes","No"),"Page not found") | O25: policyadvisor
A26: https://instasure.ca/car-insurance/ontario/ | B26: Product × province | C26: Car insurance | D26: car insurance ontario | E26: Provincial | F26: Ontario | H26: 12000 | I26: 79 | J26: commercial | K26: auto-province | L26: 1 | M26: Primary | N26: =IFERROR(IF(ISNUMBER(SEARCH(D26,INDEX(Pages!$J$2:$J$829,MATCH(A26,Pages!$B$2:$B$829,0)))),"Yes","No"),"Page not found") | O26: ratehub, rates.ca, sonnet
A27: https://instasure.ca/car-insurance/ontario/toronto/ | B27: Product × city | C27: Car insurance | D27: car insurance toronto | E27: City | F27: Ontario | G27: Toronto | H27: 6600 | I27: 84 | J27: local | K27: auto-local | L27: 1 | M27: Primary | N27: =IFERROR(IF(ISNUMBER(SEARCH(D27,INDEX(Pages!$J$2:$J$829,MATCH(A27,Pages!$B$2:$B$829,0)))),"Yes","No"),"Page not found") | O27: ratehub, rates.ca, sonnet, mychoice/squareone/thinkinsure | P27: Competitor city pages here are thin or carry stale dates (October 2026 review): freshness opening.
A28: https://instasure.ca/car-insurance/ontario/toronto/ | B28: Product × city | C28: Car insurance | D28: cheap car insurance toronto | E28: City | F28: Ontario | G28: Toronto | H28: 2300 | I28: 79 | J28: transactional | K28: auto-local | L28: 1 | M28: Secondary | N28: =IFERROR(IF(ISNUMBER(SEARCH(D28,INDEX(Pages!$J$2:$J$829,MATCH(A28,Pages!$B$2:$B$829,0)))),"Yes","No"),"Page not found") | O28: ratehub, rates.ca, sonnet, mychoice/squareone/thinkinsure | P28: Rates.ca titles lead with "Cheap"; answer with factors and FSA data, not a price promise.
A29: https://instasure.ca/car-insurance/ontario/toronto/ | B29: Product × city | C29: Car insurance | D29: how much is car insurance in toronto | E29: City | F29: Ontario | G29: Toronto | H29: 1300 | I29: 79 | J29: informational | K29: auto-local | L29: 2 | M29: Secondary | N29: =IFERROR(IF(ISNUMBER(SEARCH(D29,INDEX(Pages!$J$2:$J$829,MATCH(A29,Pages!$B$2:$B$829,0)))),"Yes","No"),"Page not found") | O29: ratehub, rates.ca, sonnet, mychoice/squareone/thinkinsure | P29: Ratehub ranks a blog post for this. The city page answers it in the first two sentences with a dated average.
A30: https://instasure.ca/super-visa-insurance/ | B30: Product pillar | C30: Super Visa & visitors insurance | D30: super visa insurance | E30: Nationwide | H30: 9900 | I30: 55 | J30: transactional | K30: travel-visitors | L30: 1 | M30: Primary | N30: =IFERROR(IF(ISNUMBER(SEARCH(D30,INDEX(Pages!$J$2:$J$829,MATCH(A30,Pages!$B$2:$B$829,0)))),"Yes","No"),"Page not found") | O30: policyadvisor (38 visitor pages incl. insurer reviews), ratehub, hellosafe, bestquote, coverme | P30: Mandatory purchase with high intent and a strong newcomer-community fit.
A31: https://instasure.ca/term-life-insurance/ | B31: Product pillar | C31: Life insurance | D31: term life insurance | E31: Nationwide | H31: 6600 | I31: 70 | J31: commercial | K31: life-core | L31: 1 | M31: Primary | N31: =IFERROR(IF(ISNUMBER(SEARCH(D31,INDEX(Pages!$J$2:$J$829,MATCH(A31,Pages!$B$2:$B$829,0)))),"Yes","No"),"Page not found") | O31: policyadvisor, sun life, ratehub, policyme
A32: https://instasure.ca/term-life-insurance/ | B32: Product pillar | C32: Life insurance | D32: term life insurance rates | E32: Nationwide | H32: 880 | I32: 55 | J32: commercial | K32: life-cost | L32: 2 | M32: Secondary | N32: =IFERROR(IF(ISNUMBER(SEARCH(D32,INDEX(Pages!$J$2:$J$829,MATCH(A32,Pages!$B$2:$B$829,0)))),"Yes","No"),"Page not found") | O32: sun life (rates page), policyadvisor
A33: https://instasure.ca/term-life-insurance/ | B33: Product pillar | C33: Life insurance | D33: 20 year term life insurance | E33: Nationwide | H33: 480 | I33: 40 | J33: commercial | K33: life-core | L33: 3 | M33: Secondary | N33: =IFERROR(IF(ISNUMBER(SEARCH(D33,INDEX(Pages!$J$2:$J$829,MATCH(A33,Pages!$B$2:$B$829,0)))),"Yes","No"),"Page not found") | O33: sun life
A34: https://instasure.ca/advisors/ | B34: Static / tool | C34: Cross-product & brand | D34: insurance broker near me | E34: Nationwide | H34: 6600 | I34: 60 | J34: local | K34: advisors | L34: 2 | M34: Primary | N34: =IFERROR(IF(ISNUMBER(SEARCH(D34,INDEX(Pages!$J$2:$J$829,MATCH(A34,Pages!$B$2:$B$829,0)))),"Yes","No"),"Page not found") | O34: local brokers, thinkinsure | P34: Needs Google Business Profiles. Say "licensed advisor" unless the entity is a registered brokerage.
A35: https://instasure.ca/advisors/ | B35: Static / tool | C35: Cross-product & brand | D35: insurance advisor near me | E35: Nationwide | H35: 1300 | I35: 40 | J35: local | K35: advisors | L35: 1 | M35: Secondary | N35: =IFERROR(IF(ISNUMBER(SEARCH(D35,INDEX(Pages!$J$2:$J$829,MATCH(A35,Pages!$B$2:$B$829,0)))),"Yes","No"),"Page not found") | O35: policyadvisor (advisor pages), sun life advisor microsites
A36: https://instasure.ca/quote/home-insurance/ | B36: (not a live page) | C36: Home insurance | D36: home insurance quotes | E36: Nationwide | H36: 6600 | I36: 75 | J36: transactional | K36: property-core | L36: 1 | M36: Primary | N36: =IFERROR(IF(ISNUMBER(SEARCH(D36,INDEX(Pages!$J$2:$J$829,MATCH(A36,Pages!$B$2:$B$829,0)))),"Yes","No"),"Page not found") | O36: ratehub, rates.ca, sonnet, squareone
A37: https://instasure.ca/quote/home-insurance/ | B37: (not a live page) | C37: Home insurance | D37: home insurance calculator | E37: Nationwide | H37: 1000 | I37: 45 | J37: transactional | K37: property-tools | L37: 2 | M37: Secondary | N37: =IFERROR(IF(ISNUMBER(SEARCH(D37,INDEX(Pages!$J$2:$J$829,MATCH(A37,Pages!$B$2:$B$829,0)))),"Yes","No"),"Page not found") | O37: rates.ca (AB)
A38: https://instasure.ca/critical-illness-insurance/ | B38: Product pillar | C38: Critical illness insurance | D38: critical illness insurance | E38: Nationwide | H38: 6600 | I38: 65 | J38: commercial | K38: living-benefits | L38: 1 | M38: Primary | N38: =IFERROR(IF(ISNUMBER(SEARCH(D38,INDEX(Pages!$J$2:$J$829,MATCH(A38,Pages!$B$2:$B$829,0)))),"Yes","No"),"Page not found") | O38: policyadvisor, sun life, policyme, ratehub
A39: https://instasure.ca/critical-illness-insurance/ | B39: Product pillar | C39: Critical illness insurance | D39: critical illness insurance cost | E39: Nationwide | H39: 880 | I39: 45 | J39: informational | K39: living-benefits | L39: 1 | M39: Secondary | N39: =IFERROR(IF(ISNUMBER(SEARCH(D39,INDEX(Pages!$J$2:$J$829,MATCH(A39,Pages!$B$2:$B$829,0)))),"Yes","No"),"Page not found") | O39: policyadvisor (cost page + calculator), ratehub (age table), policyme
A40: https://instasure.ca/condo-insurance/ | B40: Product pillar | C40: Condo insurance | D40: condo insurance | E40: Nationwide | H40: 6600 | I40: 65 | J40: commercial | K40: property-core | L40: 1 | M40: Primary | N40: =IFERROR(IF(ISNUMBER(SEARCH(D40,INDEX(Pages!$J$2:$J$829,MATCH(A40,Pages!$B$2:$B$829,0)))),"Yes","No"),"Page not found") | O40: sonnet, ratehub, rates.ca
A41: https://instasure.ca/condo-insurance/ | B41: Product pillar | C41: Condo insurance | D41: condo insurance cost | E41: Nationwide | H41: 720 | I41: 40 | J41: informational | K41: property-cost | L41: 2 | M41: Secondary | N41: =IFERROR(IF(ISNUMBER(SEARCH(D41,INDEX(Pages!$J$2:$J$829,MATCH(A41,Pages!$B$2:$B$829,0)))),"Yes","No"),"Page not found") | O41: ratehub, rates.ca
A42: https://instasure.ca/disability-insurance/ | B42: Product pillar | C42: Disability insurance | D42: disability insurance | E42: Nationwide | H42: 4400 | I42: 60 | J42: commercial | K42: living-benefits | L42: 1 | M42: Primary | N42: =IFERROR(IF(ISNUMBER(SEARCH(D42,INDEX(Pages!$J$2:$J$829,MATCH(A42,Pages!$B$2:$B$829,0)))),"Yes","No"),"Page not found") | O42: policyadvisor, sun life
A43: https://instasure.ca/disability-insurance/ | B43: Product pillar | C43: Disability insurance | D43: long term disability insurance | E43: Nationwide | H43: 2900 | I43: 55 | J43: informational | K43: living-benefits | L43: 3 | M43: Secondary | N43: =IFERROR(IF(ISNUMBER(SEARCH(D43,INDEX(Pages!$J$2:$J$829,MATCH(A43,Pages!$B$2:$B$829,0)))),"Yes","No"),"Page not found") | O43: policyadvisor | P43: Much of the volume is about group or claims; qualify carefully.
A44: https://instasure.ca/quote/ | B44: Static / tool | C44: Cross-product & brand | D44: insurance quotes | E44: Nationwide | H44: 6600 | I44: 75 | J44: transactional | K44: brand-instant | L44: 1 | M44: Primary | N44: =IFERROR(IF(ISNUMBER(SEARCH(D44,INDEX(Pages!$J$2:$J$829,MATCH(A44,Pages!$B$2:$B$829,0)))),"Yes","No"),"Page not found") | O44: ratehub, rates.ca, kanetix
A45: https://instasure.ca/quote/ | B45: Static / tool | C45: Cross-product & brand | D45: instant insurance quote | E45: Nationwide | H45: 320 | I45: 30 | J45: transactional | K45: brand-instant | L45: 1 | M45: Secondary | N45: =IFERROR(IF(ISNUMBER(SEARCH(D45,INDEX(Pages!$J$2:$J$829,MATCH(A45,Pages!$B$2:$B$829,0)))),"Yes","No"),"Page not found") | O45: (fragmented) | P45: Brand-defining term for instasure.ca.
A46: https://instasure.ca/guides/ontario-auto-insurance-changes-july-2026/ | B46: Guide (blog) | C46: Car insurance | D46: ontario auto insurance changes 2026 | E46: Provincial | F46: Ontario | H46: 4400 | I46: 45 | J46: informational | K46: auto-regulation | L46: 1 | M46: Primary | N46: =IFERROR(IF(ISNUMBER(SEARCH(D46,INDEX(Pages!$J$2:$J$829,MATCH(A46,Pages!$B$2:$B$829,0)))),"Yes","No"),"Page not found") | O46: rates.ca, ratelab, thinkinsure, intact, IBC, RIBO, CP24 | P46: Every Ontario renewal from July 2026 to June 2027 forces the opt-out decision.
A47: https://instasure.ca/guides/ontario-auto-insurance-changes-july-2026/ | B47: Guide (blog) | C47: Car insurance | D47: optional accident benefits ontario | E47: Provincial | F47: Ontario | H47: 1300 | I47: 35 | J47: informational | K47: auto-regulation | L47: 1 | M47: Secondary | N47: =IFERROR(IF(ISNUMBER(SEARCH(D47,INDEX(Pages!$J$2:$J$829,MATCH(A47,Pages!$B$2:$B$829,0)))),"Yes","No"),"Page not found") | O47: intact, northbridge, thebig.ca
A48: https://instasure.ca/guides/ontario-auto-insurance-changes-july-2026/ | B48: Guide (blog) | C48: Car insurance | D48: income replacement benefit ontario opt out | E48: Provincial | F48: Ontario | H48: 480 | I48: 25 | J48: informational | K48: auto-regulation | L48: 1 | M48: Secondary | N48: =IFERROR(IF(ISNUMBER(SEARCH(D48,INDEX(Pages!$J$2:$J$829,MATCH(A48,Pages!$B$2:$B$829,0)))),"Yes","No"),"Page not found") | O48: thebig.ca, thinkinsure | P48: Pair with the disability insurance page for self-employed drivers.
A49: https://instasure.ca/motorcycle-insurance/ | B49: Service page | C49: Recreational vehicles | D49: motorcycle insurance | E49: Nationwide | H49: 5400 | I49: 60 | J49: commercial | K49: auto-recreational | L49: 3 | M49: Primary | N49: =IFERROR(IF(ISNUMBER(SEARCH(D49,INDEX(Pages!$J$2:$J$829,MATCH(A49,Pages!$B$2:$B$829,0)))),"Yes","No"),"Page not found") | O49: ratehub (ON, AB), rates.ca, insurer brands | P49: Seasonal: searches peak March to May. Province pages are the next step if quote volume justifies them.
A50: https://instasure.ca/whole-life-insurance/ | B50: Product pillar | C50: Life insurance | D50: whole life insurance | E50: Nationwide | H50: 5400 | I50: 70 | J50: commercial | K50: life-core | L50: 1 | M50: Primary | N50: =IFERROR(IF(ISNUMBER(SEARCH(D50,INDEX(Pages!$J$2:$J$829,MATCH(A50,Pages!$B$2:$B$829,0)))),"Yes","No"),"Page not found") | O50: policyadvisor, sun life, ratehub
A51: https://instasure.ca/insights/rate-index/ | B51: Static / tool | C51: Car insurance | D51: average car insurance cost canada | E51: Nationwide | H51: 2900 | I51: 55 | J51: informational | K51: auto-cost | L51: 1 | M51: Primary | N51: =IFERROR(IF(ISNUMBER(SEARCH(D51,INDEX(Pages!$J$2:$J$829,MATCH(A51,Pages!$B$2:$B$829,0)))),"Yes","No"),"Page not found") | O51: ratehub, rates.ca, sonnet, hellosafe barometer | P51: Rate Index page. It stays noindex until a product × province cell has 25 quote requests; the province pages carry the published averages meanwhile.
A52: https://instasure.ca/insights/rate-index/ | B52: Static / tool | C52: Home insurance | D52: average home insurance cost canada | E52: Nationwide | H52: 1300 | I52: 50 | J52: informational | K52: property-cost | L52: 1 | M52: Secondary | N52: =IFERROR(IF(ISNUMBER(SEARCH(D52,INDEX(Pages!$J$2:$J$829,MATCH(A52,Pages!$B$2:$B$829,0)))),"Yes","No"),"Page not found") | O52: ratehub, rates.ca
A53: https://instasure.ca/insights/rate-index/ | B53: Static / tool | C53: Car insurance | D53: car insurance rates by province | E53: Nationwide | H53: 1000 | I53: 45 | J53: informational | K53: auto-cost | L53: 2 | M53: Secondary | N53: =IFERROR(IF(ISNUMBER(SEARCH(D53,INDEX(Pages!$J$2:$J$829,MATCH(A53,Pages!$B$2:$B$829,0)))),"Yes","No"),"Page not found") | O53: sonnet, rates.ca
A54: https://instasure.ca/guides/does-home-insurance-cover-water-damage-canada/ | B54: Guide (blog) | C54: Home insurance | D54: does home insurance cover water damage | E54: Nationwide | H54: 1600 | I54: 40 | J54: informational | K54: property-coverage | L54: 1 | M54: Primary | N54: =IFERROR(IF(ISNUMBER(SEARCH(D54,INDEX(Pages!$J$2:$J$829,MATCH(A54,Pages!$B$2:$B$829,0)))),"Yes","No"),"Page not found") | O54: ratehub, CAA, RBC, westland | P54: Peaks after storms. A strong AI-citation format.
A55: https://instasure.ca/guides/does-home-insurance-cover-water-damage-canada/ | B55: Guide (blog) | C55: Home insurance | D55: flood insurance canada | E55: Nationwide | H55: 1300 | I55: 45 | J55: informational | K55: property-coverage | L55: 2 | M55: Secondary | N55: =IFERROR(IF(ISNUMBER(SEARCH(D55,INDEX(Pages!$J$2:$J$829,MATCH(A55,Pages!$B$2:$B$829,0)))),"Yes","No"),"Page not found") | O55: money.ca, mychoice, IBC | P55: The national flood program is delayed. Planned: a tracker page.
A56: https://instasure.ca/guides/does-home-insurance-cover-water-damage-canada/ | B56: Guide (blog) | C56: Home insurance | D56: overland flood insurance | E56: Nationwide | H56: 880 | I56: 40 | J56: informational | K56: property-coverage | L56: 1 | M56: Secondary | N56: =IFERROR(IF(ISNUMBER(SEARCH(D56,INDEX(Pages!$J$2:$J$829,MATCH(A56,Pages!$B$2:$B$829,0)))),"Yes","No"),"Page not found") | O56: ratehub, CAA
A57: https://instasure.ca/guides/does-home-insurance-cover-water-damage-canada/ | B57: Guide (blog) | C57: Home insurance | D57: sewer backup insurance | E57: Nationwide | H57: 590 | I57: 35 | J57: informational | K57: property-coverage | L57: 2 | M57: Secondary | N57: =IFERROR(IF(ISNUMBER(SEARCH(D57,INDEX(Pages!$J$2:$J$829,MATCH(A57,Pages!$B$2:$B$829,0)))),"Yes","No"),"Page not found") | O57: (brokers)
A58: https://instasure.ca/guides/does-home-insurance-cover-water-damage-canada/ | B58: Guide (blog) | C58: Home insurance | D58: basement flood insurance toronto | E58: City | F58: Ontario | G58: Toronto | H58: 210 | I58: 25 | J58: local | K58: property-coverage | L58: 2 | M58: Secondary | N58: =IFERROR(IF(ISNUMBER(SEARCH(D58,INDEX(Pages!$J$2:$J$829,MATCH(A58,Pages!$B$2:$B$829,0)))),"Yes","No"),"Page not found") | O58: mcdougall, brokers
A59: https://instasure.ca/life-insurance/funeral-expense/ | B59: Service page | C59: Life insurance | D59: funeral insurance | E59: Nationwide | H59: 1900 | I59: 35 | J59: commercial | K59: life-audience | L59: 1 | M59: Primary | N59: =IFERROR(IF(ISNUMBER(SEARCH(D59,INDEX(Pages!$J$2:$J$829,MATCH(A59,Pages!$B$2:$B$829,0)))),"Yes","No"),"Page not found") | O59: policyadvisor (final expense), sun life (funeral page), carrier direct plans | P59: Funeral expense desk. H1 "from $1 a day" is backed by a labelled example estimate (50-year-old female non-smoker, $10,000) and hides itself if the model rises above $1 a day.
A60: https://instasure.ca/life-insurance/funeral-expense/ | B60: Service page | C60: Life insurance | D60: funeral insurance canada | E60: Nationwide | H60: 880 | I60: 35 | J60: commercial | K60: life-audience | L60: 1 | M60: Secondary | N60: =IFERROR(IF(ISNUMBER(SEARCH(D60,INDEX(Pages!$J$2:$J$829,MATCH(A60,Pages!$B$2:$B$829,0)))),"Yes","No"),"Page not found") | O60: policyadvisor, sun life
A61: https://instasure.ca/life-insurance/funeral-expense/ | B61: Service page | C61: Life insurance | D61: burial insurance canada | E61: Nationwide | H61: 480 | I61: 30 | J61: commercial | K61: life-audience | L61: 2 | M61: Secondary | N61: =IFERROR(IF(ISNUMBER(SEARCH(D61,INDEX(Pages!$J$2:$J$829,MATCH(A61,Pages!$B$2:$B$829,0)))),"Yes","No"),"Page not found") | O61: US-style phrasing, carrier direct plans | P61: Same page; use "burial" in an H2 and FAQ.
A62: https://instasure.ca/life-insurance/funeral-expense/ | B62: Service page | C62: Life insurance | D62: funeral expense insurance | E62: Nationwide | H62: 390 | I62: 30 | J62: commercial | K62: life-audience | L62: 1 | M62: Secondary | N62: =IFERROR(IF(ISNUMBER(SEARCH(D62,INDEX(Pages!$J$2:$J$829,MATCH(A62,Pages!$B$2:$B$829,0)))),"Yes","No"),"Page not found") | O62: policyadvisor (final expense), ratehub (final expense) | P62: Page primary keyword (title, H1, slug). Final expense insurance keeps its own page; the two cross-link.
A63: https://instasure.ca/life-insurance/funeral-expense/ | B63: Service page | C63: Life insurance | D63: funeral insurance for seniors | E63: Nationwide | H63: 390 | I63: 30 | J63: commercial | K63: life-audience | L63: 2 | M63: Secondary | N63: =IFERROR(IF(ISNUMBER(SEARCH(D63,INDEX(Pages!$J$2:$J$829,MATCH(A63,Pages!$B$2:$B$829,0)))),"Yes","No"),"Page not found") | O63: policyadvisor, sun life
A64: https://instasure.ca/life-insurance/funeral-expense/ | B64: Service page | C64: Life insurance | D64: funeral insurance cost | E64: Nationwide | H64: 260 | I64: 25 | J64: commercial | K64: life-audience | L64: 2 | M64: Secondary | N64: =IFERROR(IF(ISNUMBER(SEARCH(D64,INDEX(Pages!$J$2:$J$829,MATCH(A64,Pages!$B$2:$B$829,0)))),"Yes","No"),"Page not found") | O64: policyadvisor | P64: Answered by the example estimate and the quote flow (small-policy mode, $5,000 to $50,000).
A65: https://instasure.ca/life-insurance/funeral-expense/ | B65: Service page | C65: Life insurance | D65: funeral insurance no medical | E65: Nationwide | H65: 210 | I65: 25 | J65: commercial | K65: life-instant | L65: 2 | M65: Secondary | N65: =IFERROR(IF(ISNUMBER(SEARCH(D65,INDEX(Pages!$J$2:$J$829,MATCH(A65,Pages!$B$2:$B$829,0)))),"Yes","No"),"Page not found") | O65: policyadvisor, sun life go guaranteed
A66: https://instasure.ca/car-insurance/alberta/ | B66: Product × province | C66: Car insurance | D66: car insurance alberta | E66: Provincial | F66: Alberta | H66: 4500 | I66: 67 | J66: commercial | K66: auto-province | L66: 1 | M66: Primary | N66: =IFERROR(IF(ISNUMBER(SEARCH(D66,INDEX(Pages!$J$2:$J$829,MATCH(A66,Pages!$B$2:$B$829,0)))),"Yes","No"),"Page not found") | O66: ratehub, rates.ca
A67: https://instasure.ca/car-insurance/ontario/brampton/ | B67: Product × city | C67: Car insurance | D67: car insurance brampton | E67: City | F67: Ontario | G67: Brampton | H67: 2900 | I67: 76 | J67: local | K67: auto-local | L67: 1 | M67: Primary | N67: =IFERROR(IF(ISNUMBER(SEARCH(D67,INDEX(Pages!$J$2:$J$829,MATCH(A67,Pages!$B$2:$B$829,0)))),"Yes","No"),"Page not found") | O67: ratehub, rates.ca, mychoice/squareone/thinkinsure | P67: Competitor city pages here are thin or carry stale dates (October 2026 review): freshness opening.
A68: https://instasure.ca/car-insurance/ontario/brampton/ | B68: Product × city | C68: Car insurance | D68: cheap car insurance brampton | E68: City | F68: Ontario | G68: Brampton | H68: 1000 | I68: 71 | J68: transactional | K68: auto-local | L68: 2 | M68: Secondary | N68: =IFERROR(IF(ISNUMBER(SEARCH(D68,INDEX(Pages!$J$2:$J$829,MATCH(A68,Pages!$B$2:$B$829,0)))),"Yes","No"),"Page not found") | O68: ratehub, rates.ca, mychoice/squareone/thinkinsure | P68: Rates.ca titles lead with "Cheap"; answer with factors and FSA data, not a price promise.
A69: https://instasure.ca/car-insurance/ontario/brampton/ | B69: Product × city | C69: Car insurance | D69: how much is car insurance in brampton | E69: City | F69: Ontario | G69: Brampton | H69: 570 | I69: 71 | J69: informational | K69: auto-local | L69: 2 | M69: Secondary | N69: =IFERROR(IF(ISNUMBER(SEARCH(D69,INDEX(Pages!$J$2:$J$829,MATCH(A69,Pages!$B$2:$B$829,0)))),"Yes","No"),"Page not found") | O69: ratehub, rates.ca, mychoice/squareone/thinkinsure | P69: Ratehub ranks a blog post for this. The city page answers it in the first two sentences with a dated average.
A70: https://instasure.ca/quote/life-insurance/ | B70: (not a live page) | C70: Life insurance | D70: life insurance quotes | E70: Nationwide | H70: 4400 | I70: 70 | J70: transactional | K70: life-core | L70: 1 | M70: Primary | N70: =IFERROR(IF(ISNUMBER(SEARCH(D70,INDEX(Pages!$J$2:$J$829,MATCH(A70,Pages!$B$2:$B$829,0)))),"Yes","No"),"Page not found") | O70: policyadvisor ("instantly"), policyme, ratehub, sun life | P70: Money term: instant estimate, then a licensed advisor.
A71: https://instasure.ca/travel-insurance/visitors-to-canada/ | B71: Service page | C71: Super Visa & visitors insurance | D71: visitors insurance canada | E71: Nationwide | H71: 4400 | I71: 55 | J71: transactional | K71: travel-visitors | L71: 2 | M71: Primary | N71: =IFERROR(IF(ISNUMBER(SEARCH(D71,INDEX(Pages!$J$2:$J$829,MATCH(A71,Pages!$B$2:$B$829,0)))),"Yes","No"),"Page not found") | O71: ratehub, rates.ca, policyadvisor, sun life | P71: Built: dedicated visitors page. The super visa page covers the mandatory case.
A72: https://instasure.ca/car-insurance/alberta/calgary/ | B72: Product × city | C72: Car insurance | D72: car insurance calgary | E72: City | F72: Alberta | G72: Calgary | H72: 2800 | I72: 76 | J72: local | K72: auto-local | L72: 1 | M72: Primary | N72: =IFERROR(IF(ISNUMBER(SEARCH(D72,INDEX(Pages!$J$2:$J$829,MATCH(A72,Pages!$B$2:$B$829,0)))),"Yes","No"),"Page not found") | O72: ratehub, rates.ca
A73: https://instasure.ca/car-insurance/alberta/calgary/ | B73: Product × city | C73: Car insurance | D73: cheap car insurance calgary | E73: City | F73: Alberta | G73: Calgary | H73: 970 | I73: 71 | J73: transactional | K73: auto-local | L73: 2 | M73: Secondary | N73: =IFERROR(IF(ISNUMBER(SEARCH(D73,INDEX(Pages!$J$2:$J$829,MATCH(A73,Pages!$B$2:$B$829,0)))),"Yes","No"),"Page not found") | O73: ratehub, rates.ca | P73: Rates.ca titles lead with "Cheap"; answer with factors and FSA data, not a price promise.
A74: https://instasure.ca/car-insurance/alberta/calgary/ | B74: Product × city | C74: Car insurance | D74: how much is car insurance in calgary | E74: City | F74: Alberta | G74: Calgary | H74: 550 | I74: 71 | J74: informational | K74: auto-local | L74: 3 | M74: Secondary | N74: =IFERROR(IF(ISNUMBER(SEARCH(D74,INDEX(Pages!$J$2:$J$829,MATCH(A74,Pages!$B$2:$B$829,0)))),"Yes","No"),"Page not found") | O74: ratehub, rates.ca | P74: Ratehub ranks a blog post for this. The city page answers it in the first two sentences with a dated average.
A75: https://instasure.ca/calculators/life-insurance-needs/ | B75: Static / tool | C75: Life insurance | D75: life insurance calculator | E75: Nationwide | H75: 2400 | I75: 60 | J75: transactional | K75: life-tools | L75: 1 | M75: Primary | N75: =IFERROR(IF(ISNUMBER(SEARCH(D75,INDEX(Pages!$J$2:$J$829,MATCH(A75,Pages!$B$2:$B$829,0)))),"Yes","No"),"Page not found") | O75: sun life, policyadvisor (standalone), policyme, hardbacon
A76: https://instasure.ca/calculators/life-insurance-needs/ | B76: Static / tool | C76: Life insurance | D76: how much life insurance do i need | E76: Nationwide | H76: 1900 | I76: 55 | J76: informational | K76: life-tools | L76: 1 | M76: Secondary | N76: =IFERROR(IF(ISNUMBER(SEARCH(D76,INDEX(Pages!$J$2:$J$829,MATCH(A76,Pages!$B$2:$B$829,0)))),"Yes","No"),"Page not found") | O76: policyme, ratehub, policyadvisor | P76: Guide twin: /guides/how-much-life-insurance-do-i-need-canada/.
A77: https://instasure.ca/guides/alberta-car-insurance-2026-care-first/ | B77: Guide (blog) | C77: Car insurance | D77: alberta car insurance increase 2026 | E77: Provincial | F77: Alberta | H77: 1900 | I77: 35 | J77: informational | K77: auto-regulation | L77: 1 | M77: Primary | N77: =IFERROR(IF(ISNUMBER(SEARCH(D77,INDEX(Pages!$J$2:$J$829,MATCH(A77,Pages!$B$2:$B$829,0)))),"Yes","No"),"Page not found") | O77: globalnews, daily hive, brokers | P77: Alberta auto premiums rose 22.6% year over year in Q2 2026 (Applied, verify). Few aggregator pages.
A78: https://instasure.ca/guides/alberta-car-insurance-2026-care-first/ | B78: Guide (blog) | C78: Car insurance | D78: care first auto insurance alberta | E78: Provincial | F78: Alberta | H78: 1600 | I78: 30 | J78: informational | K78: auto-regulation | L78: 1 | M78: Secondary | N78: =IFERROR(IF(ISNUMBER(SEARCH(D78,INDEX(Pages!$J$2:$J$829,MATCH(A78,Pages!$B$2:$B$829,0)))),"Yes","No"),"Page not found") | O78: alberta.ca, western financial | P78: Starts January 1, 2027.
A79: https://instasure.ca/guides/alberta-car-insurance-2026-care-first/ | B79: Guide (blog) | C79: Car insurance | D79: alberta good driver rate cap | E79: Provincial | F79: Alberta | H79: 720 | I79: 30 | J79: informational | K79: auto-regulation | L79: 1 | M79: Secondary | N79: =IFERROR(IF(ISNUMBER(SEARCH(D79,INDEX(Pages!$J$2:$J$829,MATCH(A79,Pages!$B$2:$B$829,0)))),"Yes","No"),"Page not found") | O79: globalnews, alberta.ca
A80: https://instasure.ca/car-insurance/ontario/mississauga/ | B80: Product × city | C80: Car insurance | D80: car insurance mississauga | E80: City | F80: Ontario | G80: Mississauga | H80: 2400 | I80: 84 | J80: local | K80: auto-local | L80: 1 | M80: Primary | N80: =IFERROR(IF(ISNUMBER(SEARCH(D80,INDEX(Pages!$J$2:$J$829,MATCH(A80,Pages!$B$2:$B$829,0)))),"Yes","No"),"Page not found") | O80: ratehub, rates.ca, sonnet, mychoice/squareone/thinkinsure | P80: Competitor city pages here are thin or carry stale dates (October 2026 review): freshness opening.
A81: https://instasure.ca/car-insurance/ontario/mississauga/ | B81: Product × city | C81: Car insurance | D81: cheap car insurance mississauga | E81: City | F81: Ontario | G81: Mississauga | H81: 840 | I81: 79 | J81: transactional | K81: auto-local | L81: 2 | M81: Secondary | N81: =IFERROR(IF(ISNUMBER(SEARCH(D81,INDEX(Pages!$J$2:$J$829,MATCH(A81,Pages!$B$2:$B$829,0)))),"Yes","No"),"Page not found") | O81: ratehub, rates.ca, sonnet, mychoice/squareone/thinkinsure | P81: Rates.ca titles lead with "Cheap"; answer with factors and FSA data, not a price promise.
A82: https://instasure.ca/car-insurance/ontario/mississauga/ | B82: Product × city | C82: Car insurance | D82: how much is car insurance in mississauga | E82: City | F82: Ontario | G82: Mississauga | H82: 480 | I82: 79 | J82: informational | K82: auto-local | L82: 3 | M82: Secondary | N82: =IFERROR(IF(ISNUMBER(SEARCH(D82,INDEX(Pages!$J$2:$J$829,MATCH(A82,Pages!$B$2:$B$829,0)))),"Yes","No"),"Page not found") | O82: ratehub, rates.ca, sonnet, mychoice/squareone/thinkinsure | P82: Ratehub ranks a blog post for this. The city page answers it in the first two sentences with a dated average.
A83: https://instasure.ca/home-insurance/ontario/ | B83: Product × province | C83: Home insurance | D83: home insurance ontario | E83: Provincial | F83: Ontario | H83: 3000 | I83: 69 | J83: commercial | K83: property-province | L83: 1 | M83: Primary | N83: =IFERROR(IF(ISNUMBER(SEARCH(D83,INDEX(Pages!$J$2:$J$829,MATCH(A83,Pages!$B$2:$B$829,0)))),"Yes","No"),"Page not found") | O83: ratehub, rates.ca, sonnet
A84: https://instasure.ca/home-insurance/ontario/ | B84: Product × province | C84: Home insurance | D84: is home insurance mandatory in ontario | E84: Provincial | F84: Ontario | H84: 590 | I84: 30 | J84: informational | K84: property-coverage | L84: 2 | M84: Secondary | N84: =IFERROR(IF(ISNUMBER(SEARCH(D84,INDEX(Pages!$J$2:$J$829,MATCH(A84,Pages!$B$2:$B$829,0)))),"Yes","No"),"Page not found") | O84: sonnet faq
A85: https://instasure.ca/mortgage-life-insurance/ | B85: Product pillar | C85: Mortgage protection | D85: mortgage life insurance | E85: Nationwide | H85: 2400 | I85: 55 | J85: commercial | K85: life-mortgage | L85: 1 | M85: Primary | N85: =IFERROR(IF(ISNUMBER(SEARCH(D85,INDEX(Pages!$J$2:$J$829,MATCH(A85,Pages!$B$2:$B$829,0)))),"Yes","No"),"Page not found") | O85: policyadvisor (9 pages), ratehub, policyme, banks | P85: About 1.15M mortgage renewals in 2026 (CMHC via MPA, verify).
A86: https://instasure.ca/mortgage-life-insurance/ | B86: Product pillar | C86: Mortgage protection | D86: mortgage protection insurance | E86: Nationwide | H86: 1000 | I86: 45 | J86: commercial | K86: life-mortgage | L86: 1 | M86: Secondary | N86: =IFERROR(IF(ISNUMBER(SEARCH(D86,INDEX(Pages!$J$2:$J$829,MATCH(A86,Pages!$B$2:$B$829,0)))),"Yes","No"),"Page not found") | O86: policyadvisor, manulife mortgage protection plan
A87: https://instasure.ca/car-insurance/alberta/edmonton/ | B87: Product × city | C87: Car insurance | D87: car insurance edmonton | E87: City | F87: Alberta | G87: Edmonton | H87: 2100 | I87: 76 | J87: local | K87: auto-local | L87: 1 | M87: Primary | N87: =IFERROR(IF(ISNUMBER(SEARCH(D87,INDEX(Pages!$J$2:$J$829,MATCH(A87,Pages!$B$2:$B$829,0)))),"Yes","No"),"Page not found") | O87: ratehub, rates.ca
A88: https://instasure.ca/car-insurance/alberta/edmonton/ | B88: Product × city | C88: Car insurance | D88: cheap car insurance edmonton | E88: City | F88: Alberta | G88: Edmonton | H88: 730 | I88: 71 | J88: transactional | K88: auto-local | L88: 2 | M88: Secondary | N88: =IFERROR(IF(ISNUMBER(SEARCH(D88,INDEX(Pages!$J$2:$J$829,MATCH(A88,Pages!$B$2:$B$829,0)))),"Yes","No"),"Page not found") | O88: ratehub, rates.ca | P88: Rates.ca titles lead with "Cheap"; answer with factors and FSA data, not a price promise.
A89: https://instasure.ca/car-insurance/alberta/edmonton/ | B89: Product × city | C89: Car insurance | D89: how much is car insurance in edmonton | E89: City | F89: Alberta | G89: Edmonton | H89: 420 | I89: 71 | J89: informational | K89: auto-local | L89: 3 | M89: Secondary | N89: =IFERROR(IF(ISNUMBER(SEARCH(D89,INDEX(Pages!$J$2:$J$829,MATCH(A89,Pages!$B$2:$B$829,0)))),"Yes","No"),"Page not found") | O89: ratehub, rates.ca | P89: Ratehub ranks a blog post for this. The city page answers it in the first two sentences with a dated average.
A90: https://instasure.ca/guides/how-much-does-life-insurance-cost-canada/ | B90: Guide (blog) | C90: Life insurance | D90: how much does life insurance cost | E90: Nationwide | H90: 1600 | I90: 55 | J90: informational | K90: life-cost | L90: 1 | M90: Primary | N90: =IFERROR(IF(ISNUMBER(SEARCH(D90,INDEX(Pages!$J$2:$J$829,MATCH(A90,Pages!$B$2:$B$829,0)))),"Yes","No"),"Page not found") | O90: policyadvisor, policyme, sun life (rates pages)
A91: https://instasure.ca/guides/how-much-does-life-insurance-cost-canada/ | B91: Guide (blog) | C91: Life insurance | D91: life insurance cost by age | E91: Nationwide | H91: 880 | I91: 45 | J91: informational | K91: life-cost | L91: 1 | M91: Secondary | N91: =IFERROR(IF(ISNUMBER(SEARCH(D91,INDEX(Pages!$J$2:$J$829,MATCH(A91,Pages!$B$2:$B$829,0)))),"Yes","No"),"Page not found") | O91: policyadvisor (20/40/50 pages) | P91: Planned: one page per age band (/life-insurance/cost/age-35/) once the Rate Index has quote data.
A92: https://instasure.ca/guides/how-much-does-life-insurance-cost-canada/ | B92: Guide (blog) | C92: Life insurance | D92: 500000 life insurance cost | E92: Nationwide | H92: 390 | I92: 35 | J92: informational | K92: life-cost | L92: 2 | M92: Secondary | N92: =IFERROR(IF(ISNUMBER(SEARCH(D92,INDEX(Pages!$J$2:$J$829,MATCH(A92,Pages!$B$2:$B$829,0)))),"Yes","No"),"Page not found") | O92: policyadvisor
A93: https://instasure.ca/guides/how-much-does-life-insurance-cost-canada/ | B93: Guide (blog) | C93: Life insurance | D93: 1 million life insurance cost | E93: Nationwide | H93: 320 | I93: 35 | J93: informational | K93: life-cost | L93: 2 | M93: Secondary | N93: =IFERROR(IF(ISNUMBER(SEARCH(D93,INDEX(Pages!$J$2:$J$829,MATCH(A93,Pages!$B$2:$B$829,0)))),"Yes","No"),"Page not found") | O93: policyadvisor
A94: https://instasure.ca/boat-insurance/ | B94: Service page | C94: Recreational vehicles | D94: boat insurance | E94: Nationwide | H94: 2900 | I94: 50 | J94: commercial | K94: auto-recreational | L94: 4 | M94: Primary | N94: =IFERROR(IF(ISNUMBER(SEARCH(D94,INDEX(Pages!$J$2:$J$829,MATCH(A94,Pages!$B$2:$B$829,0)))),"Yes","No"),"Page not found") | O94: ratehub (boat, marine) | P94: Often an endorsement on the home policy; the page explains when a separate policy is needed.
A95: https://instasure.ca/car-insurance/high-risk-drivers/ | B95: Service page | C95: Car insurance | D95: high risk car insurance | E95: Nationwide | H95: 1600 | I95: 45 | J95: commercial | K95: auto-persona | L95: 1 | M95: Primary | N95: =IFERROR(IF(ISNUMBER(SEARCH(D95,INDEX(Pages!$J$2:$J$829,MATCH(A95,Pages!$B$2:$B$829,0)))),"Yes","No"),"Page not found") | O95: ratehub, rates.ca guide, facility association | P95: Built with the High-risk auto desk (niche gap: competitors run one generic page). Next: sub-guides after an accident, tickets, lapsed or cancelled.
A96: https://instasure.ca/car-insurance/high-risk-drivers/ | B96: Service page | C96: Car insurance | D96: car insurance after accident | E96: Nationwide | H96: 1300 | I96: 35 | J96: informational | K96: auto-persona | L96: 3 | M96: Secondary | N96: =IFERROR(IF(ISNUMBER(SEARCH(D96,INDEX(Pages!$J$2:$J$829,MATCH(A96,Pages!$B$2:$B$829,0)))),"Yes","No"),"Page not found") | O96: rates.ca | P96: Answered on the high-risk page; a dedicated guide is still planned.
A97: https://instasure.ca/car-insurance/new-drivers/ | B97: Service page | C97: Car insurance | D97: car insurance for new drivers | E97: Nationwide | H97: 1900 | I97: 50 | J97: commercial | K97: auto-persona | L97: 2 | M97: Primary | N97: =IFERROR(IF(ISNUMBER(SEARCH(D97,INDEX(Pages!$J$2:$J$829,MATCH(A97,Pages!$B$2:$B$829,0)))),"Yes","No"),"Page not found") | O97: rates.ca guide, ratehub blog | P97: Built: service page with a new-driver example estimate. Next: per-province sections (G1/G2/G, Class 7, L/N).
A98: https://instasure.ca/car-insurance/new-drivers/ | B98: Service page | C98: Car insurance | D98: g2 car insurance ontario | E98: Provincial | F98: Ontario | H98: 880 | I98: 40 | J98: commercial | K98: auto-persona | L98: 2 | M98: Secondary | N98: =IFERROR(IF(ISNUMBER(SEARCH(D98,INDEX(Pages!$J$2:$J$829,MATCH(A98,Pages!$B$2:$B$829,0)))),"Yes","No"),"Page not found") | O98: rates.ca (money page), ratehub blog | P98: Answered on the new-drivers page. Planned: an Ontario G1/G2/G section or /car-insurance/ontario/g2-drivers/.
A99: https://instasure.ca/business-insurance/commercial-auto/ | B99: Service page | C99: Business insurance | D99: commercial auto insurance | E99: Nationwide | H99: 1300 | I99: 50 | J99: commercial | K99: business | L99: 2 | M99: Primary | N99: =IFERROR(IF(ISNUMBER(SEARCH(D99,INDEX(Pages!$J$2:$J$829,MATCH(A99,Pages!$B$2:$B$829,0)))),"Yes","No"),"Page not found") | O99: rates.ca | P99: Built with the Commercial auto & trucking desk.
A100: https://instasure.ca/business-insurance/commercial-auto/ | B100: Service page | C100: Business insurance | D100: trucking insurance | E100: Nationwide | H100: 1300 | I100: 50 | J100: commercial | K100: business-trades | L100: 3 | M100: Secondary | N100: =IFERROR(IF(ISNUMBER(SEARCH(D100,INDEX(Pages!$J$2:$J$829,MATCH(A100,Pages!$B$2:$B$829,0)))),"Yes","No"),"Page not found") | O100: brokers, specialty MGAs | P100: Answered on the commercial auto page (Commercial auto & trucking desk). A trucking-only page waits for real for-hire volume.
...

Sheet Nationwide KWs
A1: Keyword | B1: Insurance segment | C1: Product line | D1: Volume / mo (modelled) | E1: Difficulty (0–100) | F1: Intent | G1: Cluster | H1: Priority (1 = first) | I1: Target page | J1: Mapped? | K1: Keyword in target title? | L1: Competitors seen | M1: Notes / planned URL | N1: Measured volume (Keyword Planner) | O1: Current Google rank | P1: Last checked
A2: car insurance | B2: Car insurance | C2: Car Insurance | D2: 74000 | E2: 85 | F2: commercial | G2: auto-core | H2: 2 | I2: https://instasure.ca/car-insurance/ | J2: =IF(I2="","No","Yes") | K2: =IF(I2="","",IFERROR(IF(ISNUMBER(SEARCH(A2,INDEX(Pages!$J$2:$J$829,MATCH(I2,Pages!$B$2:$B$829,0)))),"Yes","No"),"Page not found")) | L2: ratehub, rates.ca, kanetix, mychoice, insurer brands | M2: Head term. Win through province and city depth rather than head-on.
A3: travel insurance | B3: Travel insurance | C3: Travel Insurance | D3: 40000 | E3: 80 | F3: commercial | G3: travel | H3: 3 | I3: https://instasure.ca/travel-insurance/ | J3: =IF(I3="","No","Yes") | K3: =IF(I3="","",IFERROR(IF(ISNUMBER(SEARCH(A3,INDEX(Pages!$J$2:$J$829,MATCH(I3,Pages!$B$2:$B$829,0)))),"Yes","No"),"Page not found")) | L3: sun life, manulife, credit cards, ratehub | M3: Huge but low lead value. Capture through super visa, snowbird and visitors.
A4: auto insurance | B4: Car insurance | C4: Car Insurance | D4: 33000 | E4: 82 | F4: commercial | G4: auto-core | H4: 3 | I4: https://instasure.ca/car-insurance/ | J4: =IF(I4="","No","Yes") | K4: =IF(I4="","",IFERROR(IF(ISNUMBER(SEARCH(A4,INDEX(Pages!$J$2:$J$829,MATCH(I4,Pages!$B$2:$B$829,0)))),"Yes","No"),"Page not found")) | L4: ratehub, rates.ca, insurer brands | M4: Synonym. Use in H2s and meta descriptions, not a separate page.
A5: life insurance | B5: Life insurance | C5: Life Insurance | D5: 33000 | E5: 85 | F5: commercial | G5: life-core | H5: 1 | I5: https://instasure.ca/life-insurance/ | J5: =IF(I5="","No","Yes") | K5: =IF(I5="","",IFERROR(IF(ISNUMBER(SEARCH(A5,INDEX(Pages!$J$2:$J$829,MATCH(I5,Pages!$B$2:$B$829,0)))),"Yes","No"),"Page not found")) | L5: policyadvisor, sun life, manulife, policyme, ratehub, canada life | M5: Highest-value head term. Province, city and cost pages feed it.
A6: home insurance | B6: Home insurance | C6: Home Insurance | D6: 27000 | E6: 82 | F6: commercial | G6: property-core | H6: 1 | I6: https://instasure.ca/home-insurance/ | J6: =IF(I6="","No","Yes") | K6: =IF(I6="","",IFERROR(IF(ISNUMBER(SEARCH(A6,INDEX(Pages!$J$2:$J$829,MATCH(I6,Pages!$B$2:$B$829,0)))),"Yes","No"),"Page not found")) | L6: ratehub, rates.ca, sonnet, insurer brands
A7: tenant insurance | B7: Tenant insurance | C7: Tenant Insurance | D7: 15000 | E7: 70 | F7: commercial | G7: property-core | H7: 1 | I7: https://instasure.ca/tenant-insurance/ | J7: =IF(I7="","No","Yes") | K7: =IF(I7="","",IFERROR(IF(ISNUMBER(SEARCH(A7,INDEX(Pages!$J$2:$J$829,MATCH(I7,Pages!$B$2:$B$829,0)))),"Yes","No"),"Page not found")) | L7: sonnet, ratehub, rates.ca, squareone
A8: car insurance quotes | B8: Car insurance | C8: Car Insurance | D8: 14000 | E8: 78 | F8: transactional | G8: auto-core | H8: 1 | I8: https://instasure.ca/quote/car-insurance/ | J8: =IF(I8="","No","Yes") | K8: =IF(I8="","",IFERROR(IF(ISNUMBER(SEARCH(A8,INDEX(Pages!$J$2:$J$829,MATCH(I8,Pages!$B$2:$B$829,0)))),"Yes","No"),"Page not found")) | L8: ratehub, rates.ca, kanetix, lowestrates | M8: Money term: send to the instant estimate flow.
A9: pet insurance | B9: Pet insurance | C9: Home Insurance | D9: 14000 | E9: 70 | F9: commercial | G9: specialty-personal | H9: 4 | I9: https://instasure.ca/pet-insurance/ | J9: =IF(I9="","No","Yes") | K9: =IF(I9="","",IFERROR(IF(ISNUMBER(SEARCH(A9,INDEX(Pages!$J$2:$J$829,MATCH(I9,Pages!$B$2:$B$829,0)))),"Yes","No"),"Page not found")) | L9: sonnet (pet product), trupanion, petsecure, pets plus us | M9: Big but low advisor fit: most pet insurers sell direct. A completeness page that keeps visitors on site.
A10: cheap car insurance | B10: Car insurance | C10: Car Insurance | D10: 9900 | E10: 75 | F10: transactional | G10: auto-cost | H10: 2 | I10: https://instasure.ca/car-insurance/ | J10: =IF(I10="","No","Yes") | K10: =IF(I10="","",IFERROR(IF(ISNUMBER(SEARCH(A10,INDEX(Pages!$J$2:$J$829,MATCH(I10,Pages!$B$2:$B$829,0)))),"Yes","No"),"Page not found")) | L10: ratehub (15 ways), rates.ca, mychoice | M10: Answer with savings factors and compare. No "cheapest" claim without a published methodology.
A11: renters insurance | B11: Tenant insurance | C11: Tenant Insurance | D11: 9900 | E11: 65 | F11: commercial | G11: property-core | H11: 2 | I11: https://instasure.ca/tenant-insurance/ | J11: =IF(I11="","No","Yes") | K11: =IF(I11="","",IFERROR(IF(ISNUMBER(SEARCH(A11,INDEX(Pages!$J$2:$J$829,MATCH(I11,Pages!$B$2:$B$829,0)))),"Yes","No"),"Page not found")) | L11: sonnet, ratehub | M11: Synonym used in titles ("Tenant (Renters) Insurance").
A12: super visa insurance | B12: Super Visa & visitors insurance | C12: Super Visa Insurance | D12: 9900 | E12: 55 | F12: transactional | G12: travel-visitors | H12: 1 | I12: https://instasure.ca/super-visa-insurance/ | J12: =IF(I12="","No","Yes") | K12: =IF(I12="","",IFERROR(IF(ISNUMBER(SEARCH(A12,INDEX(Pages!$J$2:$J$829,MATCH(I12,Pages!$B$2:$B$829,0)))),"Yes","No"),"Page not found")) | L12: policyadvisor (38 visitor pages incl. insurer reviews), ratehub, hellosafe, bestquote, coverme | M12: Mandatory purchase with high intent and a strong newcomer-community fit.
A13: business insurance | B13: Business insurance | C13: Business Insurance | D13: 8100 | E13: 70 | F13: commercial | G13: business | H13: 1 | I13: https://instasure.ca/business-insurance/ | J13: =IF(I13="","No","Yes") | K13: =IF(I13="","",IFERROR(IF(ISNUMBER(SEARCH(A13,INDEX(Pages!$J$2:$J$829,MATCH(I13,Pages!$B$2:$B$829,0)))),"Yes","No"),"Page not found")) | L13: ratehub, rates.ca, zensurance, apollo
A14: dental insurance | B14: Health & dental insurance | C14: Health & Dental Insurance | D14: 8100 | E14: 65 | F14: commercial | G14: health-dental | H14: 2 | I14: https://instasure.ca/health-dental-insurance/ | J14: =IF(I14="","No","Yes") | K14: =IF(I14="","",IFERROR(IF(ISNUMBER(SEARCH(A14,INDEX(Pages!$J$2:$J$829,MATCH(I14,Pages!$B$2:$B$829,0)))),"Yes","No"),"Page not found")) | L14: sun life, manulife, blue cross, policyadvisor | M14: Much of the volume is CDCP navigation; target the self-employed and CDCP-ineligible.
A15: house insurance | B15: Home insurance | C15: Home Insurance | D15: 8100 | E15: 75 | F15: commercial | G15: property-core | H15: 2 | I15: https://instasure.ca/home-insurance/ | J15: =IF(I15="","No","Yes") | K15: =IF(I15="","",IFERROR(IF(ISNUMBER(SEARCH(A15,INDEX(Pages!$J$2:$J$829,MATCH(I15,Pages!$B$2:$B$829,0)))),"Yes","No"),"Page not found")) | L15: ratehub, rates.ca
A16: condo insurance | B16: Condo insurance | C16: Condo Insurance | D16: 6600 | E16: 65 | F16: commercial | G16: property-core | H16: 1 | I16: https://instasure.ca/condo-insurance/ | J16: =IF(I16="","No","Yes") | K16: =IF(I16="","",IFERROR(IF(ISNUMBER(SEARCH(A16,INDEX(Pages!$J$2:$J$829,MATCH(I16,Pages!$B$2:$B$829,0)))),"Yes","No"),"Page not found")) | L16: sonnet, ratehub, rates.ca
A17: critical illness insurance | B17: Critical illness insurance | C17: Critical Illness Insurance | D17: 6600 | E17: 65 | F17: commercial | G17: living-benefits | H17: 1 | I17: https://instasure.ca/critical-illness-insurance/ | J17: =IF(I17="","No","Yes") | K17: =IF(I17="","",IFERROR(IF(ISNUMBER(SEARCH(A17,INDEX(Pages!$J$2:$J$829,MATCH(I17,Pages!$B$2:$B$829,0)))),"Yes","No"),"Page not found")) | L17: policyadvisor, sun life, policyme, ratehub
A18: home insurance quotes | B18: Home insurance | C18: Home Insurance | D18: 6600 | E18: 75 | F18: transactional | G18: property-core | H18: 1 | I18: https://instasure.ca/quote/home-insurance/ | J18: =IF(I18="","No","Yes") | K18: =IF(I18="","",IFERROR(IF(ISNUMBER(SEARCH(A18,INDEX(Pages!$J$2:$J$829,MATCH(I18,Pages!$B$2:$B$829,0)))),"Yes","No"),"Page not found")) | L18: ratehub, rates.ca, sonnet, squareone
A19: insurance broker near me | B19: Cross-product & brand | D19: 6600 | E19: 60 | F19: local | G19: advisors | H19: 2 | I19: https://instasure.ca/advisors/ | J19: =IF(I19="","No","Yes") | K19: =IF(I19="","",IFERROR(IF(ISNUMBER(SEARCH(A19,INDEX(Pages!$J$2:$J$829,MATCH(I19,Pages!$B$2:$B$829,0)))),"Yes","No"),"Page not found")) | L19: local brokers, thinkinsure | M19: Needs Google Business Profiles. Say "licensed advisor" unless the entity is a registered brokerage.
A20: insurance quotes | B20: Cross-product & brand | D20: 6600 | E20: 75 | F20: transactional | G20: brand-instant | H20: 1 | I20: https://instasure.ca/quote/ | J20: =IF(I20="","No","Yes") | K20: =IF(I20="","",IFERROR(IF(ISNUMBER(SEARCH(A20,INDEX(Pages!$J$2:$J$829,MATCH(I20,Pages!$B$2:$B$829,0)))),"Yes","No"),"Page not found")) | L20: ratehub, rates.ca, kanetix
A21: term life insurance | B21: Life insurance | C21: Term Life Insurance | D21: 6600 | E21: 70 | F21: commercial | G21: life-core | H21: 1 | I21: https://instasure.ca/term-life-insurance/ | J21: =IF(I21="","No","Yes") | K21: =IF(I21="","",IFERROR(IF(ISNUMBER(SEARCH(A21,INDEX(Pages!$J$2:$J$829,MATCH(I21,Pages!$B$2:$B$829,0)))),"Yes","No"),"Page not found")) | L21: policyadvisor, sun life, ratehub, policyme
A22: liability insurance | B22: Business insurance | C22: Business Insurance | D22: 5400 | E22: 65 | F22: commercial | G22: business | H22: 3 | I22: https://instasure.ca/business-insurance/ | J22: =IF(I22="","No","Yes") | K22: =IF(I22="","",IFERROR(IF(ISNUMBER(SEARCH(A22,INDEX(Pages!$J$2:$J$829,MATCH(I22,Pages!$B$2:$B$829,0)))),"Yes","No"),"Page not found")) | L22: ratehub, rates.ca
A23: motorcycle insurance | B23: Recreational vehicles | C23: Car Insurance | D23: 5400 | E23: 60 | F23: commercial | G23: auto-recreational | H23: 3 | I23: https://instasure.ca/motorcycle-insurance/ | J23: =IF(I23="","No","Yes") | K23: =IF(I23="","",IFERROR(IF(ISNUMBER(SEARCH(A23,INDEX(Pages!$J$2:$J$829,MATCH(I23,Pages!$B$2:$B$829,0)))),"Yes","No"),"Page not found")) | L23: ratehub (ON, AB), rates.ca, insurer brands | M23: Seasonal: searches peak March to May. Province pages are the next step if quote volume justifies them.
A24: whole life insurance | B24: Life insurance | C24: Whole Life Insurance | D24: 5400 | E24: 70 | F24: commercial | G24: life-core | H24: 1 | I24: https://instasure.ca/whole-life-insurance/ | J24: =IF(I24="","No","Yes") | K24: =IF(I24="","",IFERROR(IF(ISNUMBER(SEARCH(A24,INDEX(Pages!$J$2:$J$829,MATCH(I24,Pages!$B$2:$B$829,0)))),"Yes","No"),"Page not found")) | L24: policyadvisor, sun life, ratehub
A25: cpp death benefit | B25: Life insurance | C25: Life Insurance | D25: 4400 | E25: 40 | F25: informational | G25: life-audience | H25: 2 | J25: =IF(I25="","No","Yes") | K25: =IF(I25="","",IFERROR(IF(ISNUMBER(SEARCH(A25,INDEX(Pages!$J$2:$J$829,MATCH(I25,Pages!$B$2:$B$829,0)))),"Yes","No"),"Page not found")) | L25: canada.ca, media | M25: Planned guide: /guides/cpp-death-benefit-and-funeral-costs/. canada.ca: $2,500 basic plus a possible $2,500 top-up since January 1, 2025.
A26: disability insurance | B26: Disability insurance | C26: Disability Insurance | D26: 4400 | E26: 60 | F26: commercial | G26: living-benefits | H26: 1 | I26: https://instasure.ca/disability-insurance/ | J26: =IF(I26="","No","Yes") | K26: =IF(I26="","",IFERROR(IF(ISNUMBER(SEARCH(A26,INDEX(Pages!$J$2:$J$829,MATCH(I26,Pages!$B$2:$B$829,0)))),"Yes","No"),"Page not found")) | L26: policyadvisor, sun life
A27: life insurance quotes | B27: Life insurance | C27: Life Insurance | D27: 4400 | E27: 70 | F27: transactional | G27: life-core | H27: 1 | I27: https://instasure.ca/quote/life-insurance/ | J27: =IF(I27="","No","Yes") | K27: =IF(I27="","",IFERROR(IF(ISNUMBER(SEARCH(A27,INDEX(Pages!$J$2:$J$829,MATCH(I27,Pages!$B$2:$B$829,0)))),"Yes","No"),"Page not found")) | L27: policyadvisor ("instantly"), policyme, ratehub, sun life | M27: Money term: instant estimate, then a licensed advisor.
A28: visitors insurance canada | B28: Super Visa & visitors insurance | C28: Travel Insurance | D28: 4400 | E28: 55 | F28: transactional | G28: travel-visitors | H28: 2 | I28: https://instasure.ca/travel-insurance/visitors-to-canada/ | J28: =IF(I28="","No","Yes") | K28: =IF(I28="","",IFERROR(IF(ISNUMBER(SEARCH(A28,INDEX(Pages!$J$2:$J$829,MATCH(I28,Pages!$B$2:$B$829,0)))),"Yes","No"),"Page not found")) | L28: ratehub, rates.ca, policyadvisor, sun life | M28: Built: dedicated visitors page. The super visa page covers the mandatory case.
A29: average car insurance cost canada | B29: Car insurance | C29: Car Insurance | D29: 2900 | E29: 55 | F29: informational | G29: auto-cost | H29: 1 | I29: https://instasure.ca/insights/rate-index/ | J29: =IF(I29="","No","Yes") | K29: =IF(I29="","",IFERROR(IF(ISNUMBER(SEARCH(A29,INDEX(Pages!$J$2:$J$829,MATCH(I29,Pages!$B$2:$B$829,0)))),"Yes","No"),"Page not found")) | L29: ratehub, rates.ca, sonnet, hellosafe barometer | M29: Rate Index page. It stays noindex until a product × province cell has 25 quote requests; the province pages carry the published averages meanwhile.
A30: boat insurance | B30: Recreational vehicles | C30: Home Insurance | D30: 2900 | E30: 50 | F30: commercial | G30: auto-recreational | H30: 4 | I30: https://instasure.ca/boat-insurance/ | J30: =IF(I30="","No","Yes") | K30: =IF(I30="","",IFERROR(IF(ISNUMBER(SEARCH(A30,INDEX(Pages!$J$2:$J$829,MATCH(I30,Pages!$B$2:$B$829,0)))),"Yes","No"),"Page not found")) | L30: ratehub (boat, marine) | M30: Often an endorsement on the home policy; the page explains when a separate policy is needed.
A31: long term disability insurance | B31: Disability insurance | C31: Disability Insurance | D31: 2900 | E31: 55 | F31: informational | G31: living-benefits | H31: 3 | I31: https://instasure.ca/disability-insurance/ | J31: =IF(I31="","No","Yes") | K31: =IF(I31="","",IFERROR(IF(ISNUMBER(SEARCH(A31,INDEX(Pages!$J$2:$J$829,MATCH(I31,Pages!$B$2:$B$829,0)))),"Yes","No"),"Page not found")) | L31: policyadvisor | M31: Much of the volume is about group or claims; qualify carefully.
A32: private health insurance canada | B32: Health & dental insurance | C32: Health & Dental Insurance | D32: 2900 | E32: 60 | F32: commercial | G32: health-dental | H32: 2 | I32: https://instasure.ca/health-dental-insurance/ | J32: =IF(I32="","No","Yes") | K32: =IF(I32="","",IFERROR(IF(ISNUMBER(SEARCH(A32,INDEX(Pages!$J$2:$J$829,MATCH(I32,Pages!$B$2:$B$829,0)))),"Yes","No"),"Page not found")) | L32: policyadvisor, sun life, manulife, blue cross
A33: small business insurance | B33: Business insurance | C33: Business Insurance | D33: 2900 | E33: 60 | F33: commercial | G33: business | H33: 1 | I33: https://instasure.ca/business-insurance/ | J33: =IF(I33="","No","Yes") | K33: =IF(I33="","",IFERROR(IF(ISNUMBER(SEARCH(A33,INDEX(Pages!$J$2:$J$829,MATCH(I33,Pages!$B$2:$B$829,0)))),"Yes","No"),"Page not found")) | L33: rates.ca, ratehub
A34: best life insurance companies canada | B34: Life insurance | C34: Life Insurance | D34: 2400 | E34: 65 | F34: commercial | G34: life-reviews | H34: 2 | J34: =IF(I34="","No","Yes") | K34: =IF(I34="","",IFERROR(IF(ISNUMBER(SEARCH(A34,INDEX(Pages!$J$2:$J$829,MATCH(I34,Pages!$B$2:$B$829,0)))),"Yes","No"),"Page not found")) | L34: policyadvisor, wealthnorth, hellosafe | M34: Planned: /life-insurance/best-companies/. Publish the methodology first.
A35: car insurance calculator | B35: Car insurance | C35: Car Insurance | D35: 2400 | E35: 55 | F35: transactional | G35: auto-tools | H35: 2 | I35: https://instasure.ca/quote/car-insurance/ | J35: =IF(I35="","No","Yes") | K35: =IF(I35="","",IFERROR(IF(ISNUMBER(SEARCH(A35,INDEX(Pages!$J$2:$J$829,MATCH(I35,Pages!$B$2:$B$829,0)))),"Yes","No"),"Page not found")) | L35: rates.ca (ON, AB), lowestrates (ON) | M35: Instant estimate covers the intent. Planned: /calculators/car-insurance-cost/ with province selector.
A36: general liability insurance | B36: Business insurance | C36: Business Insurance | D36: 2400 | E36: 55 | F36: commercial | G36: business | H36: 2 | I36: https://instasure.ca/business-insurance/ | J36: =IF(I36="","No","Yes") | K36: =IF(I36="","",IFERROR(IF(ISNUMBER(SEARCH(A36,INDEX(Pages!$J$2:$J$829,MATCH(I36,Pages!$B$2:$B$829,0)))),"Yes","No"),"Page not found")) | L36: ratehub (CGL), rates.ca
A37: health and dental insurance | B37: Health & dental insurance | C37: Health & Dental Insurance | D37: 2400 | E37: 55 | F37: commercial | G37: health-dental | H37: 1 | I37: https://instasure.ca/health-dental-insurance/ | J37: =IF(I37="","No","Yes") | K37: =IF(I37="","",IFERROR(IF(ISNUMBER(SEARCH(A37,INDEX(Pages!$J$2:$J$829,MATCH(I37,Pages!$B$2:$B$829,0)))),"Yes","No"),"Page not found")) | L37: policyadvisor, sun life, blue cross
A38: landlord insurance | B38: Landlord & rental property | C38: Home Insurance | D38: 2400 | E38: 50 | F38: commercial | G38: property-niche | H38: 2 | I38: https://instasure.ca/landlord-insurance/ | J38: =IF(I38="","No","Yes") | K38: =IF(I38="","",IFERROR(IF(ISNUMBER(SEARCH(A38,INDEX(Pages!$J$2:$J$829,MATCH(I38,Pages!$B$2:$B$829,0)))),"Yes","No"),"Page not found")) | L38: ratehub, rates.ca | M38: Built (service page).
A39: life insurance calculator | B39: Life insurance | C39: Life Insurance | D39: 2400 | E39: 60 | F39: transactional | G39: life-tools | H39: 1 | I39: https://instasure.ca/calculators/life-insurance-needs/ | J39: =IF(I39="","No","Yes") | K39: =IF(I39="","",IFERROR(IF(ISNUMBER(SEARCH(A39,INDEX(Pages!$J$2:$J$829,MATCH(I39,Pages!$B$2:$B$829,0)))),"Yes","No"),"Page not found")) | L39: sun life, policyadvisor (standalone), policyme, hardbacon
A40: mortgage life insurance | B40: Mortgage protection | C40: Mortgage Life Insurance | D40: 2400 | E40: 55 | F40: commercial | G40: life-mortgage | H40: 1 | I40: https://instasure.ca/mortgage-life-insurance/ | J40: =IF(I40="","No","Yes") | K40: =IF(I40="","",IFERROR(IF(ISNUMBER(SEARCH(A40,INDEX(Pages!$J$2:$J$829,MATCH(I40,Pages!$B$2:$B$829,0)))),"Yes","No"),"Page not found")) | L40: policyadvisor (9 pages), ratehub, policyme, banks | M40: About 1.15M mortgage renewals in 2026 (CMHC via MPA, verify).
A41: most stolen cars canada | B41: Car insurance | C41: Car Insurance | D41: 2400 | E41: 40 | F41: informational | G41: auto-data | H41: 2 | J41: =IF(I41="","No","Yes") | K41: =IF(I41="","",IFERROR(IF(ISNUMBER(SEARCH(A41,INDEX(Pages!$J$2:$J$829,MATCH(I41,Pages!$B$2:$B$829,0)))),"Yes","No"),"Page not found")) | L41: sonnet, equite association, insurancehotline | M41: Planned: /guides/most-stolen-cars-canada/ refreshed with each Équité report.
A42: best car insurance companies canada | B42: Car insurance | C42: Car Insurance | D42: 1900 | E42: 60 | F42: commercial | G42: auto-reviews | H42: 3 | J42: =IF(I42="","No","Yes") | K42: =IF(I42="","",IFERROR(IF(ISNUMBER(SEARCH(A42,INDEX(Pages!$J$2:$J$829,MATCH(I42,Pages!$B$2:$B$829,0)))),"Yes","No"),"Page not found")) | L42: ratehub blog, mychoice, moneygeek | M42: Planned: /car-insurance/best-companies/. Needs a published ranking methodology first (Competition Act, RIBO).
A43: car insurance for new drivers | B43: Car insurance | C43: Car Insurance | D43: 1900 | E43: 50 | F43: commercial | G43: auto-persona | H43: 2 | I43: https://instasure.ca/car-insurance/new-drivers/ | J43: =IF(I43="","No","Yes") | K43: =IF(I43="","",IFERROR(IF(ISNUMBER(SEARCH(A43,INDEX(Pages!$J$2:$J$829,MATCH(I43,Pages!$B$2:$B$829,0)))),"Yes","No"),"Page not found")) | L43: rates.ca guide, ratehub blog | M43: Built: service page with a new-driver example estimate. Next: per-province sections (G1/G2/G, Class 7, L/N).
A44: funeral insurance | B44: Life insurance | C44: Life Insurance | D44: 1900 | E44: 35 | F44: commercial | G44: life-audience | H44: 1 | I44: https://instasure.ca/life-insurance/funeral-expense/ | J44: =IF(I44="","No","Yes") | K44: =IF(I44="","",IFERROR(IF(ISNUMBER(SEARCH(A44,INDEX(Pages!$J$2:$J$829,MATCH(I44,Pages!$B$2:$B$829,0)))),"Yes","No"),"Page not found")) | L44: policyadvisor (final expense), sun life (funeral page), carrier direct plans | M44: Funeral expense desk. H1 "from $1 a day" is backed by a labelled example estimate (50-year-old female non-smoker, $10,000) and hides itself if the model rises above $1 a day.
A45: how much life insurance do i need | B45: Life insurance | C45: Life Insurance | D45: 1900 | E45: 55 | F45: informational | G45: life-tools | H45: 1 | I45: https://instasure.ca/calculators/life-insurance-needs/ | J45: =IF(I45="","No","Yes") | K45: =IF(I45="","",IFERROR(IF(ISNUMBER(SEARCH(A45,INDEX(Pages!$J$2:$J$829,MATCH(I45,Pages!$B$2:$B$829,0)))),"Yes","No"),"Page not found")) | L45: policyme, ratehub, policyadvisor | M45: Guide twin: /guides/how-much-life-insurance-do-i-need-canada/.
A46: rv insurance | B46: Recreational vehicles | C46: Car Insurance | D46: 1900 | E46: 45 | F46: commercial | G46: auto-recreational | H46: 4 | I46: https://instasure.ca/rv-insurance/ | J46: =IF(I46="","No","Yes") | K46: =IF(I46="","",IFERROR(IF(ISNUMBER(SEARCH(A46,INDEX(Pages!$J$2:$J$829,MATCH(I46,Pages!$B$2:$B$829,0)))),"Yes","No"),"Page not found")) | L46: ratehub (rv, trailer)
A47: term vs whole life insurance | B47: Life insurance | C47: Term Life Insurance | D47: 1900 | E47: 50 | F47: informational | G47: life-compare | H47: 1 | I47: https://instasure.ca/guides/term-vs-whole-life-insurance-canada/ | J47: =IF(I47="","No","Yes") | K47: =IF(I47="","",IFERROR(IF(ISNUMBER(SEARCH(A47,INDEX(Pages!$J$2:$J$829,MATCH(I47,Pages!$B$2:$B$829,0)))),"Yes","No"),"Page not found")) | L47: policyadvisor, sun life, ratehub
A48: comprehensive vs collision insurance | B48: Car insurance | C48: Car Insurance | D48: 1600 | E48: 40 | F48: informational | G48: auto-coverage | H48: 3 | J48: =IF(I48="","No","Yes") | K48: =IF(I48="","",IFERROR(IF(ISNUMBER(SEARCH(A48,INDEX(Pages!$J$2:$J$829,MATCH(I48,Pages!$B$2:$B$829,0)))),"Yes","No"),"Page not found")) | L48: rates.ca coverage pages | M48: Planned guide. The glossary covers the terms meanwhile.
A49: cost of a funeral in canada | B49: Life insurance | C49: Life Insurance | D49: 1600 | E49: 30 | F49: informational | G49: life-audience | H49: 2 | J49: =IF(I49="","No","Yes") | K49: =IF(I49="","",IFERROR(IF(ISNUMBER(SEARCH(A49,INDEX(Pages!$J$2:$J$829,MATCH(I49,Pages!$B$2:$B$829,0)))),"Yes","No"),"Page not found")) | L49: funeral homes, media | M49: Planned guide: /guides/funeral-costs-canada-by-province/. Never invent an average; use provincial and funeral-home price lists.
A50: does home insurance cover water damage | B50: Home insurance | C50: Home Insurance | D50: 1600 | E50: 40 | F50: informational | G50: property-coverage | H50: 1 | I50: https://instasure.ca/guides/does-home-insurance-cover-water-damage-canada/ | J50: =IF(I50="","No","Yes") | K50: =IF(I50="","",IFERROR(IF(ISNUMBER(SEARCH(A50,INDEX(Pages!$J$2:$J$829,MATCH(I50,Pages!$B$2:$B$829,0)))),"Yes","No"),"Page not found")) | L50: ratehub, CAA, RBC, westland | M50: Peaks after storms. A strong AI-citation format.
A51: high risk car insurance | B51: Car insurance | C51: Car Insurance | D51: 1600 | E51: 45 | F51: commercial | G51: auto-persona | H51: 1 | I51: https://instasure.ca/car-insurance/high-risk-drivers/ | J51: =IF(I51="","No","Yes") | K51: =IF(I51="","",IFERROR(IF(ISNUMBER(SEARCH(A51,INDEX(Pages!$J$2:$J$829,MATCH(I51,Pages!$B$2:$B$829,0)))),"Yes","No"),"Page not found")) | L51: ratehub, rates.ca guide, facility association | M51: Built with the High-risk auto desk (niche gap: competitors run one generic page). Next: sub-guides after an accident, tickets, lapsed or cancelled.
A52: how much does life insurance cost | B52: Life insurance | C52: Life Insurance | D52: 1600 | E52: 55 | F52: informational | G52: life-cost | H52: 1 | I52: https://instasure.ca/guides/how-much-does-life-insurance-cost-canada/ | J52: =IF(I52="","No","Yes") | K52: =IF(I52="","",IFERROR(IF(ISNUMBER(SEARCH(A52,INDEX(Pages!$J$2:$J$829,MATCH(I52,Pages!$B$2:$B$829,0)))),"Yes","No"),"Page not found")) | L52: policyadvisor, policyme, sun life (rates pages)
A53: life insurance for seniors | B53: Life insurance | C53: Life Insurance | D53: 1600 | E53: 50 | F53: commercial | G53: life-audience | H53: 2 | I53: https://instasure.ca/life-insurance/seniors/ | J53: =IF(I53="","No","Yes") | K53: =IF(I53="","",IFERROR(IF(ISNUMBER(SEARCH(A53,INDEX(Pages!$J$2:$J$829,MATCH(I53,Pages!$B$2:$B$829,0)))),"Yes","No"),"Page not found")) | L53: policyadvisor, sun life | M53: Built with a seniors example estimate (no-medical, guaranteed issue and final expense covered on the page).
A54: professional liability insurance | B54: Professional liability (E&O) | C54: Professional Liability (E&O) Insurance | D54: 1600 | E54: 50 | F54: commercial | G54: business | H54: 1 | I54: https://instasure.ca/professional-liability-insurance/ | J54: =IF(I54="","No","Yes") | K54: =IF(I54="","",IFERROR(IF(ISNUMBER(SEARCH(A54,INDEX(Pages!$J$2:$J$829,MATCH(I54,Pages!$B$2:$B$829,0)))),"Yes","No"),"Page not found")) | L54: ratehub, rates.ca
A55: super visa insurance cost | B55: Super Visa & visitors insurance | C55: Super Visa Insurance | D55: 1600 | E55: 40 | F55: commercial | G55: travel-visitors | H55: 1 | I55: https://instasure.ca/guides/super-visa-insurance-requirements-cost/ | J55: =IF(I55="","No","Yes") | K55: =IF(I55="","",IFERROR(IF(ISNUMBER(SEARCH(A55,INDEX(Pages!$J$2:$J$829,MATCH(I55,Pages!$B$2:$B$829,0)))),"Yes","No"),"Page not found")) | L55: policyadvisor, hellosafe, bestquote
A56: why is my car insurance going up | B56: Car insurance | C56: Car Insurance | D56: 1600 | E56: 35 | F56: informational | G56: auto-regulation | H56: 1 | I56: https://instasure.ca/guides/why-is-my-car-insurance-going-up-2026/ | J56: =IF(I56="","No","Yes") | K56: =IF(I56="","",IFERROR(IF(ISNUMBER(SEARCH(A56,INDEX(Pages!$J$2:$J$829,MATCH(I56,Pages!$B$2:$B$829,0)))),"Yes","No"),"Page not found")) | L56: onlia, rates.ca | M56: Renewal-notice searches. Refresh each quarter with the Applied Rating Index.
A57: average home insurance cost canada | B57: Home insurance | C57: Home Insurance | D57: 1300 | E57: 50 | F57: informational | G57: property-cost | H57: 1 | I57: https://instasure.ca/insights/rate-index/ | J57: =IF(I57="","No","Yes") | K57: =IF(I57="","",IFERROR(IF(ISNUMBER(SEARCH(A57,INDEX(Pages!$J$2:$J$829,MATCH(I57,Pages!$B$2:$B$829,0)))),"Yes","No"),"Page not found")) | L57: ratehub, rates.ca
A58: car insurance after accident | B58: Car insurance | C58: Car Insurance | D58: 1300 | E58: 35 | F58: informational | G58: auto-persona | H58: 3 | I58: https://instasure.ca/car-insurance/high-risk-drivers/ | J58: =IF(I58="","No","Yes") | K58: =IF(I58="","",IFERROR(IF(ISNUMBER(SEARCH(A58,INDEX(Pages!$J$2:$J$829,MATCH(I58,Pages!$B$2:$B$829,0)))),"Yes","No"),"Page not found")) | L58: rates.ca | M58: Answered on the high-risk page; a dedicated guide is still planned.
A59: classic car insurance | B59: Car insurance | C59: Car Insurance | D59: 1300 | E59: 50 | F59: commercial | G59: auto-persona | H59: 4 | I59: https://instasure.ca/car-insurance/classic-cars/ | J59: =IF(I59="","No","Yes") | K59: =IF(I59="","",IFERROR(IF(ISNUMBER(SEARCH(A59,INDEX(Pages!$J$2:$J$829,MATCH(I59,Pages!$B$2:$B$829,0)))),"Yes","No"),"Page not found")) | L59: ratehub | M59: Built (advisor-quoted). Specialty market with low advisor fit.
A60: commercial auto insurance | B60: Business insurance | C60: Business Insurance | D60: 1300 | E60: 50 | F60: commercial | G60: business | H60: 2 | I60: https://instasure.ca/business-insurance/commercial-auto/ | J60: =IF(I60="","No","Yes") | K60: =IF(I60="","",IFERROR(IF(ISNUMBER(SEARCH(A60,INDEX(Pages!$J$2:$J$829,MATCH(I60,Pages!$B$2:$B$829,0)))),"Yes","No"),"Page not found")) | L60: rates.ca | M60: Built with the Commercial auto & trucking desk.
A61: contractor insurance | B61: Contractor & trades insurance | C61: Contractor Insurance | D61: 1300 | E61: 45 | F61: commercial | G61: business | H61: 1 | I61: https://instasure.ca/contractor-insurance/ | J61: =IF(I61="","No","Yes") | K61: =IF(I61="","",IFERROR(IF(ISNUMBER(SEARCH(A61,INDEX(Pages!$J$2:$J$829,MATCH(I61,Pages!$B$2:$B$829,0)))),"Yes","No"),"Page not found")) | L61: ratehub, rates.ca (15+ trades)
A62: flood insurance canada | B62: Home insurance | C62: Home Insurance | D62: 1300 | E62: 45 | F62: informational | G62: property-coverage | H62: 2 | I62: https://instasure.ca/guides/does-home-insurance-cover-water-damage-canada/ | J62: =IF(I62="","No","Yes") | K62: =IF(I62="","",IFERROR(IF(ISNUMBER(SEARCH(A62,INDEX(Pages!$J$2:$J$829,MATCH(I62,Pages!$B$2:$B$829,0)))),"Yes","No"),"Page not found")) | L62: money.ca, mychoice, IBC | M62: The national flood program is delayed. Planned: a tracker page.
A63: group benefits for small business | B63: Group benefits | C63: Group Benefits | D63: 1300 | E63: 50 | F63: commercial | G63: business-benefits | H63: 1 | I63: https://instasure.ca/group-benefits/ | J63: =IF(I63="","No","Yes") | K63: =IF(I63="","",IFERROR(IF(ISNUMBER(SEARCH(A63,INDEX(Pages!$J$2:$J$829,MATCH(I63,Pages!$B$2:$B$829,0)))),"Yes","No"),"Page not found")) | L63: policyadvisor, manulife, canada life | M63: Highest lead value on the site.
A64: insurance advisor near me | B64: Cross-product & brand | D64: 1300 | E64: 40 | F64: local | G64: advisors | H64: 1 | I64: https://instasure.ca/advisors/ | J64: =IF(I64="","No","Yes") | K64: =IF(I64="","",IFERROR(IF(ISNUMBER(SEARCH(A64,INDEX(Pages!$J$2:$J$829,MATCH(I64,Pages!$B$2:$B$829,0)))),"Yes","No"),"Page not found")) | L64: policyadvisor (advisor pages), sun life advisor microsites
A65: long term care insurance canada | B65: Health & dental insurance | C65: Health & Dental Insurance | D65: 1300 | E65: 45 | F65: commercial | G65: health-dental | H65: 3 | I65: https://instasure.ca/long-term-care-insurance/ | J65: =IF(I65="","No","Yes") | K65: =IF(I65="","",IFERROR(IF(ISNUMBER(SEARCH(A65,INDEX(Pages!$J$2:$J$829,MATCH(I65,Pages!$B$2:$B$829,0)))),"Yes","No"),"Page not found")) | L65: ratehub, policyadvisor | M65: Few Canadian insurers still sell individual LTC; the page says so and covers the alternatives.
A66: mortgage insurance vs life insurance | B66: Mortgage protection | C66: Mortgage Life Insurance | D66: 1300 | E66: 50 | F66: informational | G66: life-mortgage | H66: 1 | I66: https://instasure.ca/guides/mortgage-life-insurance-vs-term-life-insurance/ | J66: =IF(I66="","No","Yes") | K66: =IF(I66="","",IFERROR(IF(ISNUMBER(SEARCH(A66,INDEX(Pages!$J$2:$J$829,MATCH(I66,Pages!$B$2:$B$829,0)))),"Yes","No"),"Page not found")) | L66: policyadvisor, ratehub, policyme, money.ca
A67: no medical life insurance | B67: Life insurance | C67: No-Medical Life Insurance | D67: 1300 | E67: 45 | F67: commercial | G67: life-instant | H67: 1 | I67: https://instasure.ca/no-medical-life-insurance/ | J67: =IF(I67="","No","Yes") | K67: =IF(I67="","",IFERROR(IF(ISNUMBER(SEARCH(A67,INDEX(Pages!$J$2:$J$829,MATCH(I67,Pages!$B$2:$B$829,0)))),"Yes","No"),"Page not found")) | L67: policyadvisor, sun life go, coverme | M67: Core "instant" brand cluster.
A68: snowbird travel insurance | B68: Travel insurance | C68: Travel Insurance | D68: 1300 | E68: 45 | F68: commercial | G68: travel | H68: 2 | I68: https://instasure.ca/travel-insurance/snowbirds/ | J68: =IF(I68="","No","Yes") | K68: =IF(I68="","",IFERROR(IF(ISNUMBER(SEARCH(A68,INDEX(Pages!$J$2:$J$829,MATCH(I68,Pages!$B$2:$B$829,0)))),"Yes","No"),"Page not found")) | L68: (not seen) | M68: Built with the Snowbird travel desk and an example estimate.
A69: tenant insurance cost | B69: Tenant insurance | C69: Tenant Insurance | D69: 1300 | E69: 40 | F69: informational | G69: property-cost | H69: 1 | I69: https://instasure.ca/tenant-insurance/ | J69: =IF(I69="","No","Yes") | K69: =IF(I69="","",IFERROR(IF(ISNUMBER(SEARCH(A69,INDEX(Pages!$J$2:$J$829,MATCH(I69,Pages!$B$2:$B$829,0)))),"Yes","No"),"Page not found")) | L69: ratehub, sonnet
A70: travel insurance for seniors | B70: Travel insurance | C70: Travel Insurance | D70: 1300 | E70: 50 | F70: commercial | G70: travel | H70: 3 | I70: https://instasure.ca/travel-insurance/snowbirds/ | J70: =IF(I70="","No","Yes") | K70: =IF(I70="","",IFERROR(IF(ISNUMBER(SEARCH(A70,INDEX(Pages!$J$2:$J$829,MATCH(I70,Pages!$B$2:$B$829,0)))),"Yes","No"),"Page not found")) | L70: sun life | M70: Answered on the snowbird page; a separate seniors page is not planned.
