Workbook

Sheet Overview
A1: lmcmic.ca — SEO master sheet
A2: Lendmax Capital MIC investor site. Built from the live site on 2026-10-12. Source plan: content/data/seo-content-roadmap.xlsx (Tabs 1–3).
A4: Pages
A5: Indexable pages | B5: =COUNTA(Pages!B2:B98) -> 97 | C5: Every page in the Pages sheet
A6: Pages in the XML sitemap | B6: =COUNTIF(Pages!Z2:Z98,"Yes") -> 97 | C6: Should equal indexable pages
A7: Investor guides, tools, glossary and FAQ hub | B7: =COUNTIF(Pages!C2:C98,"<>Core page")-COUNTIF(Pages!C2:C98,"Hub")-COUNTIF(Pages!C2:C98,"Legal") -> 89
A8: Titles inside 30–65 characters | B8: =COUNTIF(Pages!H2:H98,"OK") -> 97 | C8: Pages sheet, column H
A9: Descriptions inside 120–160 characters | B9: =COUNTIF(Pages!K2:K98,"OK") -> 97 | C9: Pages sheet, column K
A10: Canonical tag matches the URL | B10: =COUNTIF(Pages!Q2:Q98,"Yes") -> 97 | C10: Pages sheet, column Q
A11: Pages with the GA4 tag | B11: =COUNTIF(Pages!AA2:AA98,"Yes") -> 97
A12: Total words on indexable pages | B12: =SUM(Pages!T2:T98) -> 273316 | C12: Main content only
A13: Content quality
A14: Articles passing every automated check | B14: =COUNTIF('Content QA'!H2:H91,"PASS") -> 90 | C14: of 90 planned articles
A15: Internal links (in-content) | B15: =COUNTA('Internal Links'!A2:A1310) -> 1309 | C15: Navigation and footer excluded
A16: Internal links pointing at a missing page | B16: =COUNTIF('Internal Links'!D2:D1310,"Check") -> 0 | C16: Should be 0
A17: External links resolving from the server | B17: =COUNTIF('External Links'!C2:C26,"Yes") -> 21 | C17: of 25; the rest block automated checks
A18: Keywords
A19: Workbook keywords | B19: =COUNTA(Keywords!A2:A383) -> 382 | C19: Tab 1 of the source workbook
A20: Mapped to a live page | B20: =COUNTIF(Keywords!M2:M383,"/*") -> 376
A21: Keyword terms present on their page | B21: =COUNTIF(Keywords!O2:O383,"Yes") -> 376
A22: Not built by design (workbook says do not build) | B22: =COUNTIF(Keywords!M2:M383,"") -> 6
A23: Tier 1 quick-win keywords | B23: =COUNTIF(Keywords!J2:J383,"1*") -> 98
A25: Action items
A26: BC Mortgage Services Act comes into force 13 October 2026 | C26: Update the BC pages from 'scheduled to come into force' to 'in force', confirm licence categories with BCFSA (Tab 3 L1).
A27: Search Console | C27: Confirm the sitemap shows Success with 97 discovered URLs; watch Page indexing for the first two weeks.
A28: Keyword volumes | C28: Fill the yellow columns on the Keywords sheet from Keyword Planner / Ahrefs (Canada) and Search Console.
A29: Second-person calculation check (K10) | C29: Have a second person recompute the worked examples and record it on Content QA.
A30: Four external links | C30: Click through the links marked 'Check by hand' on External Links (sites that block automated checks).
A31: Photography | C31: Supply more photos to give articles their own featured images (Tab 2 image specs are ready).
A32: Quarterly review | C32: Re-check return figures and regulatory statements each quarter (next: January 2027).
A34: Sheets
A35: Pages | C35: Every live page: title, description, H1, keywords, canonical, schema, words, links, images, QA.
A36: Keywords | C36: All 382 workbook keywords → the live page that targets them. Yellow columns are yours to fill.
A37: Content QA | C37: The Tab 3 pre-publication gate for all 90 articles, plus manual sign-offs.
A38: Internal Links | C38: Every in-content link with its anchor text.
A39: Redirects | C39: Canonical and legacy-URL redirect rules on the server.
A40: Images | C40: Photos and logos reused from lendmaxcapital.ca, every optimised size.
A41: External Links | C41: Outbound citations and whether each resolves.
A42: Technical SEO | C42: Domain, crawling, indexing, analytics, performance and security settings.
A43: SEO Checklist | C43: Tab 3 of the source workbook with how lmcmic.ca applies each rule.
A45: Legend
A46: Yellow cells | C46: Input cells for you to fill (e.g. Keywords: measured volume, Search Console position and clicks).
A47: Green / red / amber | C47: Pass / fail / needs review, set automatically by formulas and conditional formatting.

Sheet Pages
A1: # | B1: URL | C1: Page type | D1: Section / journey stage | E1: Priority | F1: Title tag | G1: Title length | H1: Title check | I1: Meta description | J1: Description length | K1: Description check | L1: H1 | M1: Primary keyword | N1: Secondary keywords | O1: Question keyword | P1: Canonical URL | Q1: Canonical matches | R1: Robots | S1: Structured data (schema.org) | T1: Words on page | U1: Internal links out | V1: Internal links in | W1: Share image (og:image) | X1: Photo | Y1: Partner logos | Z1: In sitemap | AA1: GA4 tag | AB1: Automated QA | AC1: Last modified | AD1: Live URL
A2: 1 | B2: / | C2: Core page | D2: Investing with Lendmax | E2: Core | F2: MIC Investment in Canada | Lendmax Capital MIC | G2: =LEN(F2) -> 46 | H2: =IF(AND(G2>=30,G2<=65),"OK","Review") -> OK | I2: Lendmax Capital MIC pools investor capital into residential first and second mortgages in Ontario, BC and Alberta. Quarterly distributions; RRSP/TFSA eligible. | J2: =LEN(I2) -> 159 | K2: =IF(AND(J2>=120,J2<=160),"OK","Review") -> OK | L2: Invest in Canadian Mortgages Through a MIC | M2: MIC investment | N2: mortgage investment corporation Canada; invest in mortgages Canada; MIC investments Canada; mortgage investment Canada | P2: https://lmcmic.ca/ | Q2: =IF(P2="https://lmcmic.ca"&B2,"Yes","No") -> Yes | R2: index, follow, max-image-preview:large, max-snippet:-1, max-video-preview:-1 | S2: Organization, FinancialService, WebSite, VideoObject, FAQPage | T2: 1474 | U2: 15 | V2: 0 | W2: https://lmcmic.ca/assets/og/home.png | X2: Yes | Y2: Yes | Z2: Yes | AA2: Yes | AB2: n/a (core page) | AC2: 2026-10-03 | AD2: =HYPERLINK("https://lmcmic.ca"&B2,"Open") -> Open
A3: 2 | B3: /contact/ | C3: Core page | D3: Investing with Lendmax | E3: Core | F3: Mortgage Investment Opportunities Canada | Lendmax Capital MIC | G3: =LEN(F3) -> 62 | H3: =IF(AND(G3>=30,G3<=65),"OK","Review") -> OK | I3: Ask about mortgage investment opportunities with Lendmax Capital MIC: request the offering memorandum, pick the best time to talk, then start your application. | J3: =LEN(I3) -> 159 | K3: =IF(AND(J3>=120,J3<=160),"OK","Review") -> OK | L3: Mortgage Investment Opportunities: Contact the Investor Desk | M3: mortgage investment opportunities | N3: mortgage investment opportunities Canada; mortgage investment opportunities Ontario | P3: https://lmcmic.ca/contact/ | Q3: =IF(P3="https://lmcmic.ca"&B3,"Yes","No") -> Yes | R3: index, follow, max-image-preview:large, max-snippet:-1, max-video-preview:-1 | S3: Organization, FinancialService, WebSite, FAQPage, ContactPage, BreadcrumbList | T3: 798 | U3: 5 | V3: 94 | W3: https://lmcmic.ca/assets/og/contact.png | X3: Yes | Z3: Yes | AA3: Yes | AB3: n/a (core page) | AC3: 2026-10-03 | AD3: =HYPERLINK("https://lmcmic.ca"&B3,"Open") -> Open
A4: 3 | B4: /how-to-invest/ | C4: Core page | D4: Investor profiles and process | E4: P1 | F4: How to Start Investing in Mortgages: Step by Step | G4: =LEN(F4) -> 49 | H4: =IF(AND(G4>=30,G4<=65),"OK","Review") -> OK | I4: How to start investing in mortgages through a MIC: the four steps from application to quarterly distributions, the documents you need, and what to check. | J4: =LEN(I4) -> 153 | K4: =IF(AND(J4>=120,J4<=160),"OK","Review") -> OK | L4: How to Start Investing in Mortgages: The Process Step by Step | M4: how to start investing in mortgages | N4: mortgage investment process steps; what documents do I need to invest in a MIC; how to invest in a MIC | O4: how do I invest in a MIC | P4: https://lmcmic.ca/how-to-invest/ | Q4: =IF(P4="https://lmcmic.ca"&B4,"Yes","No") -> Yes | R4: index, follow, max-image-preview:large, max-snippet:-1, max-video-preview:-1 | S4: Organization, FinancialService, WebSite, HowTo, FAQPage, BreadcrumbList | T4: 3232 | U4: 9 | V4: 14 | W4: https://lmcmic.ca/assets/og/how-to-invest.png | Y4: Yes | Z4: Yes | AA4: Yes | AB4: PASS | AC4: 2026-10-03 | AD4: =HYPERLINK("https://lmcmic.ca"&B4,"Open") -> Open
A5: 4 | B5: /performance-and-risk/ | C5: Core page | D5: Investing with Lendmax | E5: Core | F5: MIC Returns, Track Record & Risk Management | Lendmax Capital MIC | G5: =LEN(F5) -> 65 | H5: =IF(AND(G5>=30,G5<=65),"OK","Review") -> OK | I5: Lendmax Capital MIC's published net returns by fiscal year, how each mortgage is underwritten (asset, borrower, exit), portfolio controls and fund oversight. | J5: =LEN(I5) -> 157 | K5: =IF(AND(J5>=120,J5<=160),"OK","Review") -> OK | L5: Track Record, Governance and Risk Management | M5: mortgage investment returns | N5: how does a MIC decide which mortgages to fund; how are mortgages underwritten for investors; how do I know if a MIC is well run | P5: https://lmcmic.ca/performance-and-risk/ | Q5: =IF(P5="https://lmcmic.ca"&B5,"Yes","No") -> Yes | R5: index, follow, max-image-preview:large, max-snippet:-1, max-video-preview:-1 | S5: Organization, FinancialService, WebSite, FAQPage, BreadcrumbList | T5: 1175 | U5: 6 | V5: 3 | W5: https://lmcmic.ca/assets/og/performance-and-risk.png | X5: Yes | Y5: Yes | Z5: Yes | AA5: Yes | AB5: n/a (core page) | AC5: 2026-10-03 | AD5: =HYPERLINK("https://lmcmic.ca"&B5,"Open") -> Open
A6: 5 | B6: /why-invest-in-a-mic/ | C6: Core page | D6: Investing with Lendmax | E6: Core | F6: Why Invest in a MIC? How a Mortgage Investment Corporation Works | G6: =LEN(F6) -> 64 | H6: =IF(AND(G6>=30,G6<=65),"OK","Review") -> OK | I6: How a mortgage investment corporation works under section 130.1: tax flow-through, MIC vs direct mortgages vs REITs, RRSP/TFSA eligibility and fund custody. | J6: =LEN(I6) -> 156 | K6: =IF(AND(J6>=120,J6<=160),"OK","Review") -> OK | L6: Why Invest in a MIC? How Lendmax Capital MIC Works | M6: how does a MIC work | N6: how do MICs work; section 130.1 Income Tax Act; MIC vs REIT; MIC vs direct mortgage investing | P6: https://lmcmic.ca/why-invest-in-a-mic/ | Q6: =IF(P6="https://lmcmic.ca"&B6,"Yes","No") -> Yes | R6: index, follow, max-image-preview:large, max-snippet:-1, max-video-preview:-1 | S6: Organization, FinancialService, WebSite, FAQPage, BreadcrumbList | T6: 1227 | U6: 9 | V6: 1 | W6: https://lmcmic.ca/assets/og/why-invest-in-a-mic.png | Z6: Yes | AA6: Yes | AB6: n/a (core page) | AC6: 2026-10-03 | AD6: =HYPERLINK("https://lmcmic.ca"&B6,"Open") -> Open
A7: 6 | B7: /learn/ | C7: Hub | D7: Hub | E7: — | F7: Mortgage Investing in Canada: Guides | Lendmax Capital MIC | G7: =LEN(F7) -> 58 | H7: =IF(AND(G7>=30,G7<=65),"OK","Review") -> OK | I7: Plain-language guides to mortgage investing in Canada: what a MIC is, where returns come from, risk, tax, RRSP/TFSA rules, regulation and due diligence. | J7: =LEN(I7) -> 152 | K7: =IF(AND(J7>=120,J7<=160),"OK","Review") -> OK | L7: Mortgage Investing Guides for Canadian Investors | P7: https://lmcmic.ca/learn/ | Q7: =IF(P7="https://lmcmic.ca"&B7,"Yes","No") -> Yes | R7: index, follow, max-image-preview:large, max-snippet:-1, max-video-preview:-1 | S7: Organization, FinancialService, WebSite, CollectionPage, BreadcrumbList | T7: 4166 | U7: 88 | V7: 2 | W7: https://lmcmic.ca/assets/og/learn.png | Z7: Yes | AA7: Yes | AB7: n/a (core page) | AC7: 2026-10-03 | AD7: =HYPERLINK("https://lmcmic.ca"&B7,"Open") -> Open
A8: 7 | B8: /disclaimer/ | C8: Legal | D8: Legal | E8: — | F8: Risk Disclosure and Investor Notice | Lendmax Capital MIC | G8: =LEN(F8) -> 57 | H8: =IF(AND(G8>=30,G8<=65),"OK","Review") -> OK | I8: Risk disclosures for Lendmax Capital MIC: no guarantee, no deposit insurance, illiquidity, loss of principal, offering memorandum and exempt market rules. | J8: =LEN(I8) -> 154 | K8: =IF(AND(J8>=120,J8<=160),"OK","Review") -> OK | L8: Risk Disclosure and Investor Notice | P8: https://lmcmic.ca/disclaimer/ | Q8: =IF(P8="https://lmcmic.ca"&B8,"Yes","No") -> Yes | R8: index, follow, max-image-preview:large, max-snippet:-1, max-video-preview:-1 | S8: Organization, FinancialService, WebSite, BreadcrumbList | T8: 386 | U8: 0 | V8: 0 | W8: https://lmcmic.ca/assets/og/disclaimer.png | Z8: Yes | AA8: Yes | AB8: n/a (core page) | AC8: 2026-10-03 | AD8: =HYPERLINK("https://lmcmic.ca"&B8,"Open") -> Open
A9: 8 | B9: /faq/ | C9: FAQ hub | D9: Tools, data and reference | E9: P1 | F9: Mortgage Investment FAQ Canada: 60 Investor Questions | G9: =LEN(F9) -> 53 | H9: =IF(AND(G9>=30,G9<=65),"OK","Review") -> OK | I9: Mortgage investment FAQ for Canada: 60 plain answers on MICs, returns, tax, RRSPs and TFSAs, risk, redemptions, investor eligibility and regulation. | J9: =LEN(I9) -> 148 | K9: =IF(AND(J9>=120,J9<=160),"OK","Review") -> OK | L9: Mortgage Investing FAQ: 60 Questions Canadian Investors Ask | M9: mortgage investment FAQ Canada | N9: mortgage investing questions; what is a MIC; are MIC investments guaranteed | O9: what questions should I ask before investing in mortgages | P9: https://lmcmic.ca/faq/ | Q9: =IF(P9="https://lmcmic.ca"&B9,"Yes","No") -> Yes | R9: index, follow, max-image-preview:large, max-snippet:-1, max-video-preview:-1 | S9: Organization, FinancialService, WebSite, FAQPage, BreadcrumbList | T9: 4923 | U9: 9 | V9: 1 | W9: https://lmcmic.ca/assets/og/faq.png | Z9: Yes | AA9: Yes | AB9: PASS | AC9: 2026-10-03 | AD9: =HYPERLINK("https://lmcmic.ca"&B9,"Open") -> Open
A10: 9 | B10: /glossary/ | C10: Guide | D10: Understanding mortgage investing | E10: P1 | F10: Mortgage Investment Glossary for Canadian Investors | G10: =LEN(F10) -> 51 | H10: =IF(AND(G10>=30,G10<=65),"OK","Review") -> OK | I10: A mortgage investment glossary for Canada: 121 terms defined in plain English, from arrears and LTV to power of sale, retraction, hypothec and MIE. | J10: =LEN(I10) -> 147 | K10: =IF(AND(J10>=120,J10<=160),"OK","Review") -> OK | L10: Canadian Mortgage Investment Glossary: 121 Terms Defined | M10: mortgage investment glossary Canada | N10: mortgage investing terminology; LTV; power of sale; retraction; MIE | O10: what does arrears mean in an investing context | P10: https://lmcmic.ca/glossary/ | Q10: =IF(P10="https://lmcmic.ca"&B10,"Yes","No") -> Yes | R10: index, follow, max-image-preview:large, max-snippet:-1, max-video-preview:-1 | S10: Organization, FinancialService, WebSite, DefinedTermSet, FAQPage, BreadcrumbList | T10: 5022 | U10: 58 | V10: 76 | W10: https://lmcmic.ca/assets/og/glossary.png | Z10: Yes | AA10: Yes | AB10: PASS | AC10: 2026-10-03 | AD10: =HYPERLINK("https://lmcmic.ca"&B10,"Open") -> Open
A11: 10 | B11: /learn/accredited-investor-canada/ | C11: Guide | D11: Regulation, tax and eligibility | E11: P1 | F11: Accredited Investor in Canada: Who Qualifies | G11: =LEN(F11) -> 44 | H11: =IF(AND(G11>=30,G11<=65),"OK","Review") -> OK | I11: Accredited investor in Canada: the income, financial-asset and net-asset tests, the eligible investor definition, and buying MIC shares without accreditation. | J11: =LEN(I11) -> 158 | K11: =IF(AND(J11>=120,J11<=160),"OK","Review") -> OK | L11: Are You an Accredited Investor in Canada? Eligibility Explained | M11: accredited investor Canada | N11: am I an accredited investor Canada; eligible investor definition Canada; who can invest in a MIC | O11: can I invest in a MIC without being accredited | P11: https://lmcmic.ca/learn/accredited-investor-canada/ | Q11: =IF(P11="https://lmcmic.ca"&B11,"Yes","No") -> Yes | R11: index, follow, max-image-preview:large, max-snippet:-1, max-video-preview:-1 | S11: Organization, FinancialService, WebSite, Article, FAQPage, BreadcrumbList | T11: 2952 | U11: 9 | V11: 17 | W11: https://lmcmic.ca/assets/og/learn--accredited-investor-canada.png | Z11: Yes | AA11: Yes | AB11: PASS | AC11: 2026-10-03 | AD11: =HYPERLINK("https://lmcmic.ca"&B11,"Open") -> Open
A12: 11 | B12: /learn/alternative-fixed-income-canada/ | C12: Pillar page | D12: Comparisons with other investments | E12: P1 | F12: Alternative Fixed Income Investments in Canada | G12: =LEN(F12) -> 46 | H12: =IF(AND(G12>=30,G12<=65),"OK","Review") -> OK | I12: Alternative fixed income investments in Canada vs GICs and bonds: private debt, mortgages, preferred shares, and what the extra income costs in risk. | J12: =LEN(I12) -> 149 | K12: =IF(AND(J12>=120,J12<=160),"OK","Review") -> OK | L12: Alternative Fixed Income Investments in Canada: Where Mortgages Sit | M12: alternative fixed income investments Canada | N12: high yield investments Canada; income producing investments Canada | O12: what are the alternatives to GICs and bonds in Canada | P12: https://lmcmic.ca/learn/alternative-fixed-income-canada/ | Q12: =IF(P12="https://lmcmic.ca"&B12,"Yes","No") -> Yes | R12: index, follow, max-image-preview:large, max-snippet:-1, max-video-preview:-1 | S12: Organization, FinancialService, WebSite, Article, FAQPage, BreadcrumbList | T12: 2948 | U12: 8 | V12: 4 | W12: https://lmcmic.ca/assets/og/learn--alternative-fixed-income-canada.png | Z12: Yes | AA12: Yes | AB12: PASS | AC12: 2026-10-03 | AD12: =HYPERLINK("https://lmcmic.ca"&B12,"Open") -> Open
A13: 12 | B13: /learn/appraisals-for-mortgage-investors/ | C13: Explainer | D13: Risk, security and due diligence | E13: P1 | F13: Property Appraisals in a Mortgage Investment | G13: =LEN(F13) -> 44 | H13: =IF(AND(G13>=30,G13<=65),"OK","Review") -> OK | I13: How a property appraisal protects a mortgage investment, the difference between as-is and as-complete value, and what to check in the appraisal report. | J13: =LEN(I13) -> 151 | K13: =IF(AND(J13>=120,J13<=160),"OK","Review") -> OK | L13: Property Appraisals in a Mortgage Investment: As-Is vs As-Complete Value | M13: property appraisal mortgage investment | N13: as is value vs as complete value appraisal; how does an appraisal protect a mortgage investor | O13: how does an appraisal protect a mortgage investor | P13: https://lmcmic.ca/learn/appraisals-for-mortgage-investors/ | Q13: =IF(P13="https://lmcmic.ca"&B13,"Yes","No") -> Yes | R13: index, follow, max-image-preview:large, max-snippet:-1, max-video-preview:-1 | S13: Organization, FinancialService, WebSite, Article, FAQPage, BreadcrumbList | T13: 2754 | U13: 9 | V13: 12 | W13: https://lmcmic.ca/assets/og/learn--appraisals-for-mortgage-investors.png | Z13: Yes | AA13: Yes | AB13: PASS | AC13: 2026-10-03 | AD13: =HYPERLINK("https://lmcmic.ca"&B13,"Open") -> Open
A14: 13 | B14: /learn/are-mortgage-investments-guaranteed/ | C14: Explainer | D14: Risk, security and due diligence | E14: P1 | F14: Are MIC Investments Guaranteed? No. Here's Why | G14: =LEN(F14) -> 46 | H14: =IF(AND(G14>=30,G14<=65),"OK","Review") -> OK | I14: Are MIC investments guaranteed? No. MIC shares have no CDIC insurance and no principal guarantee. What that means, how losses happen and what protections do. | J14: =LEN(I14) -> 157 | K14: =IF(AND(J14>=120,J14<=160),"OK","Review") -> OK | L14: Are MIC Investments Guaranteed? No — Here Is What That Means | M14: are MIC investments guaranteed | N14: is my principal guaranteed mortgage investment; is a MIC CDIC insured | O14: is a MIC guaranteed | P14: https://lmcmic.ca/learn/are-mortgage-investments-guaranteed/ | Q14: =IF(P14="https://lmcmic.ca"&B14,"Yes","No") -> Yes | R14: index, follow, max-image-preview:large, max-snippet:-1, max-video-preview:-1 | S14: Organization, FinancialService, WebSite, Article, FAQPage, BreadcrumbList | T14: 2172 | U14: 6 | V14: 3 | W14: https://lmcmic.ca/assets/og/learn--are-mortgage-investments-guaranteed.png | Z14: Yes | AA14: Yes | AB14: PASS | AC14: 2026-10-03 | AD14: =HYPERLINK("https://lmcmic.ca"&B14,"Open") -> Open
A15: 14 | B15: /learn/borrower-default-mortgage-investment/ | C15: Pillar page | D15: Risk, security and due diligence | E15: P1 | F15: Borrower Default on a Mortgage Investment | Lendmax Capital MIC | G15: =LEN(F15) -> 63 | H15: =IF(AND(G15>=30,G15<=65),"OK","Review") -> OK | I15: Borrower default on a mortgage investment, step by step: demand, workout, enforcement by province, sale, shortfall, and how the losses reach each investor. | J15: =LEN(I15) -> 155 | K15: =IF(AND(J15>=120,J15<=160),"OK","Review") -> OK | L15: What Happens When a Borrower Defaults on Your Mortgage Investment | M15: borrower default mortgage investment | N15: mortgage default risk investor; what happens if a borrower stops paying; do foreclosures affect MIC returns | O15: what happens if the borrower defaults on my mortgage investment | P15: https://lmcmic.ca/learn/borrower-default-mortgage-investment/ | Q15: =IF(P15="https://lmcmic.ca"&B15,"Yes","No") -> Yes | R15: index, follow, max-image-preview:large, max-snippet:-1, max-video-preview:-1 | S15: Organization, FinancialService, WebSite, Article, FAQPage, BreadcrumbList | T15: 3265 | U15: 9 | V15: 13 | W15: https://lmcmic.ca/assets/og/learn--borrower-default-mortgage-investment.png | Z15: Yes | AA15: Yes | AB15: PASS | AC15: 2026-10-03 | AD15: =HYPERLINK("https://lmcmic.ca"&B15,"Open") -> Open
A16: 15 | B16: /learn/bridge-mortgage-investing/ | C16: Guide | D16: Types of mortgage investment | E16: P2 | F16: Bridge Mortgage Investing: How It Works | Lendmax Capital MIC | G16: =LEN(F16) -> 61 | H16: =IF(AND(G16>=30,G16<=65),"OK","Review") -> OK | I16: Bridge mortgage investing funds short gaps between a purchase and a sale or refinance. How it works, where the returns come from and what can go wrong. | J16: =LEN(I16) -> 151 | K16: =IF(AND(J16>=120,J16<=160),"OK","Review") -> OK | L16: Bridge Mortgage Investments: Short Terms, Fast Turnover | M16: bridge mortgage investing | N16: bridge financing investment returns; short term mortgage investment Canada | O16: how does a bridge mortgage investment work | P16: https://lmcmic.ca/learn/bridge-mortgage-investing/ | Q16: =IF(P16="https://lmcmic.ca"&B16,"Yes","No") -> Yes | R16: index, follow, max-image-preview:large, max-snippet:-1, max-video-preview:-1 | S16: Organization, FinancialService, WebSite, Article, FAQPage, BreadcrumbList | T16: 2433 | U16: 7 | V16: 5 | W16: https://lmcmic.ca/assets/og/learn--bridge-mortgage-investing.png | Z16: Yes | AA16: Yes | AB16: PASS | AC16: 2026-10-03 | AD16: =HYPERLINK("https://lmcmic.ca"&B16,"Open") -> Open
A17: 16 | B17: /learn/canadian-mic-market-data/ | C17: Data / research | D17: Tools, data and reference | E17: P1 | F17: MIC Market Size in Canada: Sources and How to Read Them | G17: =LEN(F17) -> 55 | H17: =IF(AND(G17>=30,G17<=65),"OK","Review") -> OK | I17: Where data on MIC market size in Canada is published, what market share, arrears, LTV and concentration figures mean, and how to read them with care. | J17: =LEN(I17) -> 149 | K17: =IF(AND(J17>=120,J17<=160),"OK","Review") -> OK | L17: MIC Market Size in Canada: Where the Numbers Come From and How to Read Them | M17: MIC market size Canada | N17: how many MICs are there in Canada; largest MICs in Canada; MIC delinquency rate Canada | O17: what is the size of the MIC market in Canada | P17: https://lmcmic.ca/learn/canadian-mic-market-data/ | Q17: =IF(P17="https://lmcmic.ca"&B17,"Yes","No") -> Yes | R17: index, follow, max-image-preview:large, max-snippet:-1, max-video-preview:-1 | S17: Organization, FinancialService, WebSite, Article, FAQPage, BreadcrumbList | T17: 2718 | U17: 8 | V17: 7 | W17: https://lmcmic.ca/assets/og/learn--canadian-mic-market-data.png | Z17: Yes | AA17: Yes | AB17: PASS | AC17: 2026-10-03 | AD17: =HYPERLINK("https://lmcmic.ca"&B17,"Open") -> Open
A18: 17 | B18: /learn/capital-preservation-and-loss-of-principal/ | C18: Explainer | D18: Returns, income and cash flow | E18: P1 | F18: Capital Preservation and Principal Loss in Mortgages | G18: =LEN(F18) -> 52 | H18: =IF(AND(G18>=30,G18<=65),"OK","Review") -> OK | I18: Capital preservation in a mortgage investment rests on LTV, position and enforcement, and principal can still be lost. Both sides, with a worked example. | J18: =LEN(I18) -> 153 | K18: =IF(AND(J18>=120,J18<=160),"OK","Review") -> OK | L18: Capital Preservation and Loss of Principal in a Mortgage Investment: Both Sides Stated Plainly | M18: capital preservation mortgage investment | N18: can you lose money investing in mortgages; mortgage investment risks | O18: can I lose my whole investment in a mortgage | P18: https://lmcmic.ca/learn/capital-preservation-and-loss-of-principal/ | Q18: =IF(P18="https://lmcmic.ca"&B18,"Yes","No") -> Yes | R18: index, follow, max-image-preview:large, max-snippet:-1, max-video-preview:-1 | S18: Organization, FinancialService, WebSite, Article, FAQPage, BreadcrumbList | T18: 2904 | U18: 7 | V18: 5 | W18: https://lmcmic.ca/assets/og/learn--capital-preservation-and-loss-of-principal.png | Z18: Yes | AA18: Yes | AB18: PASS | AC18: 2026-10-03 | AD18: =HYPERLINK("https://lmcmic.ca"&B18,"Open") -> Open
A19: 18 | B19: /learn/commercial-mortgage-investing/ | C19: Guide | D19: Types of mortgage investment | E19: P2 | F19: Commercial Mortgage Investing in Canada | Lendmax Capital MIC | G19: =LEN(F19) -> 61 | H19: =IF(AND(G19>=30,G19<=65),"OK","Review") -> OK | I19: Commercial mortgage investing in Canada lends against income property. How it is valued and underwritten, multi-residential and mixed-use loans, and risks. | J19: =LEN(I19) -> 155 | K19: =IF(AND(J19>=120,J19<=160),"OK","Review") -> OK | L19: Commercial Mortgage Investing in Canada | M19: commercial mortgage investing Canada | N19: multi-residential mortgage investing; mixed use property mortgage investment | O19: is commercial mortgage investing riskier than residential | P19: https://lmcmic.ca/learn/commercial-mortgage-investing/ | Q19: =IF(P19="https://lmcmic.ca"&B19,"Yes","No") -> Yes | R19: index, follow, max-image-preview:large, max-snippet:-1, max-video-preview:-1 | S19: Organization, FinancialService, WebSite, Article, FAQPage, BreadcrumbList | T19: 2540 | U19: 5 | V19: 3 | W19: https://lmcmic.ca/assets/og/learn--commercial-mortgage-investing.png | Z19: Yes | AA19: Yes | AB19: PASS | AC19: 2026-10-03 | AD19: =HYPERLINK("https://lmcmic.ca"&B19,"Open") -> Open
A20: 19 | B20: /learn/construction-mortgage-investments/ | C20: Pillar page | D20: Types of mortgage investment | E20: P1 | F20: Construction Mortgage Investments: Draws and Holdbacks | G20: =LEN(F20) -> 54 | H20: =IF(AND(G20>=30,G20<=65),"OK","Review") -> OK | I20: Construction mortgage investments fund a build in stages. How draws, holdbacks, cost to complete and liens work, what can go wrong, and what to check first. | J20: =LEN(I20) -> 156 | K20: =IF(AND(J20>=120,J20<=160),"OK","Review") -> OK | L20: Construction Mortgage Investments: Draws, Holdbacks and Cost to Complete | M20: construction mortgage investments | N20: construction loan investment risk; development financing investment Canada | O20: what are the risks of a construction mortgage investment | P20: https://lmcmic.ca/learn/construction-mortgage-investments/ | Q20: =IF(P20="https://lmcmic.ca"&B20,"Yes","No") -> Yes | R20: index, follow, max-image-preview:large, max-snippet:-1, max-video-preview:-1 | S20: Organization, FinancialService, WebSite, Article, FAQPage, BreadcrumbList | T20: 3385 | U20: 8 | V20: 5 | W20: https://lmcmic.ca/assets/og/learn--construction-mortgage-investments.png | Z20: Yes | AA20: Yes | AB20: PASS | AC20: 2026-10-03 | AD20: =HYPERLINK("https://lmcmic.ca"&B20,"Open") -> Open
... A95: 94 | B95: /learn/who-might-consider-mortgage-investing/ | C95: Guide | D95: Investor profiles and process | E95: P1 | F95: Who Should Invest in Mortgages? A Two-Sided Answer | G95: =LEN(F95) -> 50 | H95: =IF(AND(G95>=30,G95<=65),"OK","Review") -> OK | I95: Who should invest in mortgages is an individual question. The traits of investors who might consider it, where it fits poorly, and the risks on both sides. | J95: =LEN(I95) -> 155 | K95: =IF(AND(J95>=120,J95<=160),"OK","Review") -> OK | L95: Who Should Invest in Mortgages? Who Might Consider It — and Who Probably Should Not | M95: who should invest in mortgages | N95: mortgage investing for retirees Canada; diversify portfolio with mortgage investments | O95: who should consider a MIC | P95: https://lmcmic.ca/learn/who-might-consider-mortgage-investing/ | Q95: =IF(P95="https://lmcmic.ca"&B95,"Yes","No") -> Yes | R95: index, follow, max-image-preview:large, max-snippet:-1, max-video-preview:-1 | S95: Organization, FinancialService, WebSite, Article, FAQPage, BreadcrumbList | T95: 2727 | U95: 9 | V95: 3 | W95: https://lmcmic.ca/assets/og/learn--who-might-consider-mortgage-investing.png | Z95: Yes | AA95: Yes | AB95: PASS | AC95: 2026-10-03 | AD95: =HYPERLINK("https://lmcmic.ca"&B95,"Open") -> Open
A96: 95 | B96: /privacy/ | C96: Legal | D96: Legal | E96: — | F96: Privacy Notice | Lendmax Capital MIC | G96: =LEN(F96) -> 36 | H96: =IF(AND(G96>=30,G96<=65),"OK","Review") -> OK | I96: How Lendmax Capital MIC collects, uses and protects personal information submitted through lmcmic.ca, including investor enquiries and the intake form. | J96: =LEN(I96) -> 151 | K96: =IF(AND(J96>=120,J96<=160),"OK","Review") -> OK | L96: Privacy Notice | P96: https://lmcmic.ca/privacy/ | Q96: =IF(P96="https://lmcmic.ca"&B96,"Yes","No") -> Yes | R96: index, follow, max-image-preview:large, max-snippet:-1, max-video-preview:-1 | S96: Organization, FinancialService, WebSite, BreadcrumbList | T96: 438 | U96: 0 | V96: 2 | W96: https://lmcmic.ca/assets/og/privacy.png | Z96: Yes | AA96: Yes | AB96: n/a (core page) | AC96: 2026-10-03 | AD96: =HYPERLINK("https://lmcmic.ca"&B96,"Open") -> Open
A97: 96 | B97: /tools/after-tax-yield-calculator/ | C97: Tool | D97: Returns, income and cash flow | E97: P1 | F97: After-Tax Yield Calculator for Mortgage Investments | G97: =LEN(F97) -> 51 | H97: =IF(AND(G97>=30,G97<=65),"OK","Review") -> OK | I97: Estimate the after-tax return on a mortgage investment in Canada from amount, gross yield, fees, marginal tax rate and account type. Illustrative only. | J97: =LEN(I97) -> 151 | K97: =IF(AND(J97>=120,J97<=160),"OK","Review") -> OK | L97: After-Tax Yield Calculator for Mortgage Investments in Canada | M97: after tax return mortgage investment Canada | N97: MIC dividends taxed as interest income; mortgage investment tax treatment Canada | O97: how much tax will I pay on MIC dividends | P97: https://lmcmic.ca/tools/after-tax-yield-calculator/ | Q97: =IF(P97="https://lmcmic.ca"&B97,"Yes","No") -> Yes | R97: index, follow, max-image-preview:large, max-snippet:-1, max-video-preview:-1 | S97: Organization, FinancialService, WebSite, Article, FAQPage, WebApplication, BreadcrumbList | T97: 2133 | U97: 8 | V97: 12 | W97: https://lmcmic.ca/assets/og/tools--after-tax-yield-calculator.png | Z97: Yes | AA97: Yes | AB97: PASS | AC97: 2026-10-03 | AD97: =HYPERLINK("https://lmcmic.ca"&B97,"Open") -> Open
A98: 97 | B98: /tools/drip-compounding-calculator/ | C98: Tool | D98: Returns, income and cash flow | E98: P2 | F98: Mortgage Investment Compound Interest: DRIP Calculator | G98: =LEN(F98) -> 54 | H98: =IF(AND(G98>=30,G98<=65),"OK","Review") -> OK | I98: Model mortgage investment compound interest with a DRIP: reinvested quarterly distributions vs cash, with an optional comparison rate. Illustrative only. | J98: =LEN(I98) -> 153 | K98: =IF(AND(J98>=120,J98<=160),"OK","Review") -> OK | L98: Compound Interest on a Mortgage Investment: How a DRIP Changes the Math | M98: mortgage investment compound interest | N98: dividend reinvestment plan MIC; simple vs compound return mortgage investing | O98: how do I reinvest my mortgage investment distributions | P98: https://lmcmic.ca/tools/drip-compounding-calculator/ | Q98: =IF(P98="https://lmcmic.ca"&B98,"Yes","No") -> Yes | R98: index, follow, max-image-preview:large, max-snippet:-1, max-video-preview:-1 | S98: Organization, FinancialService, WebSite, Article, FAQPage, WebApplication, BreadcrumbList | T98: 2230 | U98: 6 | V98: 10 | W98: https://lmcmic.ca/assets/og/tools--drip-compounding-calculator.png | Z98: Yes | AA98: Yes | AB98: PASS | AC98: 2026-10-03 | AD98: =HYPERLINK("https://lmcmic.ca"&B98,"Open") -> Open

Sheet Keywords
A1: Keyword | B1: Keyword type | C1: Cluster | D1: Search intent | E1: Investor stage | F1: Geography | G1: Opportunity (1-5) | H1: Competition (1-5) | I1: Priority score | J1: Build tier | K1: AI / answer-engine relevance | L1: Workbook target page | M1: Live URL | N1: Live page title | O1: Terms on page | P1: Measured CA monthly volume | Q1: Volume source & date | R1: Google position (GSC) | S1: Clicks, last 28 days (GSC) | T1: Notes
A2: mortgage investing | B2: Short-tail | C2: 01 Core mortgage investing | D2: Informational | E2: Unaware | F2: Canada (national) | G2: 5 | H2: 4 | I2: =IF(AND(ISNUMBER(G2),ISNUMBER(H2)),G2*2-H2,"") -> 6 | J2: 2 - build early | K2: High | L2: Pillar: What is mortgage investing | M2: /learn/what-is-mortgage-investing/ | N2: =IF(M2="","Not built (workbook: do not build)",IFERROR(INDEX(Pages!$F$2:$F$98,MATCH(M2,Pages!$B$2:$B$98,0)),"Not found")) -> What Is Mortgage Investing in Canada? | Lendmax Capital MIC | O2: Yes
A3: invest in mortgages | B3: Short-tail | C3: 01 Core mortgage investing | D3: Informational | E3: Unaware | F3: Canada (national) | G3: 5 | H3: 4 | I3: =IF(AND(ISNUMBER(G3),ISNUMBER(H3)),G3*2-H3,"") -> 6 | J3: 2 - build early | K3: High | L3: Pillar: What is mortgage investing | M3: /learn/what-is-mortgage-investing/ | N3: =IF(M3="","Not built (workbook: do not build)",IFERROR(INDEX(Pages!$F$2:$F$98,MATCH(M3,Pages!$B$2:$B$98,0)),"Not found")) -> What Is Mortgage Investing in Canada? | Lendmax Capital MIC | O3: Yes
A4: invest in mortgages Canada | B4: Medium-tail | C4: 01 Core mortgage investing | D4: Educational | E4: Unaware | F4: Canada (national) | G4: 5 | H4: 3 | I4: =IF(AND(ISNUMBER(G4),ISNUMBER(H4)),G4*2-H4,"") -> 7 | J4: 2 - build early | K4: High | L4: Pillar: What is mortgage investing | M4: /learn/what-is-mortgage-investing/ | N4: =IF(M4="","Not built (workbook: do not build)",IFERROR(INDEX(Pages!$F$2:$F$98,MATCH(M4,Pages!$B$2:$B$98,0)),"Not found")) -> What Is Mortgage Investing in Canada? | Lendmax Capital MIC | O4: Yes
A5: mortgage investment Canada | B5: Medium-tail | C5: 01 Core mortgage investing | D5: Educational | E5: Unaware | F5: Canada (national) | G5: 5 | H5: 3 | I5: =IF(AND(ISNUMBER(G5),ISNUMBER(H5)),G5*2-H5,"") -> 7 | J5: 2 - build early | K5: High | L5: Pillar: What is mortgage investing | M5: /learn/what-is-mortgage-investing/ | N5: =IF(M5="","Not built (workbook: do not build)",IFERROR(INDEX(Pages!$F$2:$F$98,MATCH(M5,Pages!$B$2:$B$98,0)),"Not found")) -> What Is Mortgage Investing in Canada? | Lendmax Capital MIC | O5: Yes
A6: mortgage investments | B6: Short-tail | C6: 01 Core mortgage investing | D6: Informational | E6: Unaware | F6: Canada (national) | G6: 4 | H6: 4 | I6: =IF(AND(ISNUMBER(G6),ISNUMBER(H6)),G6*2-H6,"") -> 4 | J6: 3 - slower climb | K6: Medium | L6: Pillar: What is mortgage investing | M6: /learn/what-is-mortgage-investing/ | N6: =IF(M6="","Not built (workbook: do not build)",IFERROR(INDEX(Pages!$F$2:$F$98,MATCH(M6,Pages!$B$2:$B$98,0)),"Not found")) -> What Is Mortgage Investing in Canada? | Lendmax Capital MIC | O6: Yes
A7: how to invest in mortgages | B7: Long-tail | C7: 01 Core mortgage investing | D7: Educational | E7: Problem-aware | F7: Canada (national) | G7: 5 | H7: 3 | I7: =IF(AND(ISNUMBER(G7),ISNUMBER(H7)),G7*2-H7,"") -> 7 | J7: 2 - build early | K7: High | L7: Guide: How to invest in mortgages | M7: /how-to-invest/ | N7: =IF(M7="","Not built (workbook: do not build)",IFERROR(INDEX(Pages!$F$2:$F$98,MATCH(M7,Pages!$B$2:$B$98,0)),"Not found")) -> How to Start Investing in Mortgages: Step by Step | O7: Yes
A8: mortgage investing for beginners | B8: Long-tail | C8: 01 Core mortgage investing | D8: Educational | E8: Unaware | F8: Canada (national) | G8: 4 | H8: 2 | I8: =IF(AND(ISNUMBER(G8),ISNUMBER(H8)),G8*2-H8,"") -> 6 | J8: 2 - build early | K8: High | L8: Guide: Beginner's guide | M8: /learn/mortgage-investing-for-beginners/ | N8: =IF(M8="","Not built (workbook: do not build)",IFERROR(INDEX(Pages!$F$2:$F$98,MATCH(M8,Pages!$B$2:$B$98,0)),"Not found")) -> Mortgage Investing for Beginners in Canada | Lendmax Capital MIC | O8: Yes
A9: mortgage investing explained | B9: Long-tail | C9: 01 Core mortgage investing | D9: Educational | E9: Unaware | F9: Canada (national) | G9: 4 | H9: 2 | I9: =IF(AND(ISNUMBER(G9),ISNUMBER(H9)),G9*2-H9,"") -> 6 | J9: 2 - build early | K9: High | L9: Pillar: What is mortgage investing | M9: /learn/mortgage-investing-for-beginners/ | N9: =IF(M9="","Not built (workbook: do not build)",IFERROR(INDEX(Pages!$F$2:$F$98,MATCH(M9,Pages!$B$2:$B$98,0)),"Not found")) -> Mortgage Investing for Beginners in Canada | Lendmax Capital MIC | O9: Yes
A10: mortgage investment opportunities | B10: Medium-tail | C10: 01 Core mortgage investing | D10: Comparison | E10: Solution-aware | F10: Canada (national) | G10: 5 | H10: 3 | I10: =IF(AND(ISNUMBER(G10),ISNUMBER(H10)),G10*2-H10,"") -> 7 | J10: 2 - build early | K10: Medium | L10: Opportunities / contact page | M10: /contact/ | N10: =IF(M10="","Not built (workbook: do not build)",IFERROR(INDEX(Pages!$F$2:$F$98,MATCH(M10,Pages!$B$2:$B$98,0)),"Not found")) -> Mortgage Investment Opportunities Canada | Lendmax Capital MIC | O10: Yes
A11: mortgage investment opportunities Canada | B11: Long-tail | C11: 01 Core mortgage investing | D11: Comparison | E11: Solution-aware | F11: Canada (national) | G11: 5 | H11: 3 | I11: =IF(AND(ISNUMBER(G11),ISNUMBER(H11)),G11*2-H11,"") -> 7 | J11: 2 - build early | K11: Medium | L11: Opportunities / contact page | M11: /contact/ | N11: =IF(M11="","Not built (workbook: do not build)",IFERROR(INDEX(Pages!$F$2:$F$98,MATCH(M11,Pages!$B$2:$B$98,0)),"Not found")) -> Mortgage Investment Opportunities Canada | Lendmax Capital MIC | O11: Yes
A12: mortgage lending as an investment | B12: Long-tail | C12: 01 Core mortgage investing | D12: Educational | E12: Unaware | F12: Canada (national) | G12: 3 | H12: 2 | I12: =IF(AND(ISNUMBER(G12),ISNUMBER(H12)),G12*2-H12,"") -> 4 | J12: 3 - slower climb | K12: Medium | L12: Pillar: What is mortgage investing | M12: /learn/what-is-mortgage-investing/ | N12: =IF(M12="","Not built (workbook: do not build)",IFERROR(INDEX(Pages!$F$2:$F$98,MATCH(M12,Pages!$B$2:$B$98,0)),"Not found")) -> What Is Mortgage Investing in Canada? | Lendmax Capital MIC | O12: Yes
A13: investing in real estate debt | B13: Medium-tail | C13: 01 Core mortgage investing | D13: Educational | E13: Problem-aware | F13: Canada (national) | G13: 4 | H13: 2 | I13: =IF(AND(ISNUMBER(G13),ISNUMBER(H13)),G13*2-H13,"") -> 6 | J13: 2 - build early | K13: High | L13: Pillar: Real estate debt investing | M13: /learn/what-is-mortgage-investing/ | N13: =IF(M13="","Not built (workbook: do not build)",IFERROR(INDEX(Pages!$F$2:$F$98,MATCH(M13,Pages!$B$2:$B$98,0)),"Not found")) -> What Is Mortgage Investing in Canada? | Lendmax Capital MIC | O13: Yes
... A71: what is a syndicated mortgage | B71: Conversational / AI | C71: 04 Mortgage funds and structures | D71: Informational | E71: Problem-aware | F71: Canada (national) | G71: 4 | H71: 2 | I71: =IF(AND(ISNUMBER(G71),ISNUMBER(H71)),G71*2-H71,"") -> 6 | J71: 2 - build early | K71: High | L71: Guide: Syndicated mortgages | M71: /learn/fractional-and-syndicated-mortgage-investing/ | N71: =IF(M71="","Not built (workbook: do not build)",IFERROR(INDEX(Pages!$F$2:$F$98,MATCH(M71,Pages!$B$2:$B$98,0)),"Not found")) -> Fractional Mortgage Investing and Syndicated Mortgages | O71: Yes
A72: qualified syndicated mortgage | B72: Long-tail | C72: 04 Mortgage funds and structures | D72: Risk / due diligence | E72: Evaluating | F72: Ontario | G72: 3 | H72: 1 | I72: =IF(AND(ISNUMBER(G72),ISNUMBER(H72)),G72*2-H72,"") -> 5 | J72: 3 - slower climb | K72: High | L72: Guide: Syndicated mortgages | M72: /learn/syndicated-mortgage-rules/ | N72: =IF(M72="","Not built (workbook: do not build)",IFERROR(INDEX(Pages!$F$2:$F$98,MATCH(M72,Pages!$B$2:$B$98,0)),"Not found")) -> Syndicated Mortgage Investment Rules in Canada | O72: Yes | T72: Ontario-specific regulatory term
A73: non-qualified syndicated mortgage | B73: Long-tail | C73: 04 Mortgage funds and structures | D73: Risk / due diligence | E73: Evaluating | F73: Ontario | G73: 3 | H73: 1 | I73: =IF(AND(ISNUMBER(G73),ISNUMBER(H73)),G73*2-H73,"") -> 5 | J73: 3 - slower climb | K73: High | L73: Guide: Syndicated mortgages | M73: /learn/syndicated-mortgage-rules/ | N73: =IF(M73="","Not built (workbook: do not build)",IFERROR(INDEX(Pages!$F$2:$F$98,MATCH(M73,Pages!$B$2:$B$98,0)),"Not found")) -> Syndicated Mortgage Investment Rules in Canada | O73: Yes | T73: Ontario-specific regulatory term
A74: syndicated mortgage risks | B74: Long-tail | C74: 04 Mortgage funds and structures | D74: Risk / due diligence | E74: Evaluating | F74: Canada (national) | G74: 4 | H74: 2 | I74: =IF(AND(ISNUMBER(G74),ISNUMBER(H74)),G74*2-H74,"") -> 6 | J74: 2 - build early | K74: High | L74: Guide: Syndicated mortgages | M74: /learn/syndicated-mortgage-rules/ | N74: =IF(M74="","Not built (workbook: do not build)",IFERROR(INDEX(Pages!$F$2:$F$98,MATCH(M74,Pages!$B$2:$B$98,0)),"Not found")) -> Syndicated Mortgage Investment Rules in Canada | O74: Yes
A75: MIC vs syndicated mortgage | B75: Long-tail | C75: 04 Mortgage funds and structures | D75: Comparison | E75: Evaluating | F75: Canada (national) | G75: 4 | H75: 1 | I75: =IF(AND(ISNUMBER(G75),ISNUMBER(H75)),G75*2-H75,"") -> 7 | J75: 2 - build early | K75: High | L75: Comparison: structures | M75: /learn/mortgage-investment-structures-compared/ | N75: =IF(M75="","Not built (workbook: do not build)",IFERROR(INDEX(Pages!$F$2:$F$98,MATCH(M75,Pages!$B$2:$B$98,0)),"Not found")) -> Mortgage Investment Structures in Canada Compared | O75: Yes
A76: mortgage limited partnership Canada | B76: Long-tail | C76: 04 Mortgage funds and structures | D76: Educational | E76: Evaluating | F76: Canada (national) | G76: 2 | H76: 1 | I76: =IF(AND(ISNUMBER(G76),ISNUMBER(H76)),G76*2-H76,"") -> 3 | J76: 4 - monitor only | K76: Medium | L76: Comparison: structures | M76: /learn/mortgage-investment-structures-compared/ | N76: =IF(M76="","Not built (workbook: do not build)",IFERROR(INDEX(Pages!$F$2:$F$98,MATCH(M76,Pages!$B$2:$B$98,0)),"Not found")) -> Mortgage Investment Structures in Canada Compared | O76: Yes
A77: mortgage trust investment Canada | B77: Long-tail | C77: 04 Mortgage funds and structures | D77: Educational | E77: Evaluating | F77: Canada (national) | G77: 2 | H77: 1 | I77: =IF(AND(ISNUMBER(G77),ISNUMBER(H77)),G77*2-H77,"") -> 3 | J77: 4 - monitor only | K77: Medium | L77: Comparison: structures | M77: /learn/mortgage-investment-structures-compared/ | N77: =IF(M77="","Not built (workbook: do not build)",IFERROR(INDEX(Pages!$F$2:$F$98,MATCH(M77,Pages!$B$2:$B$98,0)),"Not found")) -> Mortgage Investment Structures in Canada Compared | O77: Yes
A78: pooled mortgage investment | B78: Long-tail | C78: 04 Mortgage funds and structures | D78: Educational | E78: Solution-aware | F78: Canada (national) | G78: 3 | H78: 1 | I78: =IF(AND(ISNUMBER(G78),ISNUMBER(H78)),G78*2-H78,"") -> 5 | J78: 3 - slower climb | K78: Medium | L78: Pillar: Mortgage funds | M78: /learn/mortgage-funds-canada/ | N78: =IF(M78="","Not built (workbook: do not build)",IFERROR(INDEX(Pages!$F$2:$F$98,MATCH(M78,Pages!$B$2:$B$98,0)),"Not found")) -> Mortgage Funds in Canada: How They Differ From a MIC | O78: Yes
A79: senior fund vs junior fund mortgage | B79: Long-tail | C79: 04 Mortgage funds and structures | D79: Comparison | E79: Evaluating | F79: Canada (national) | G79: 2 | H79: 1 | I79: =IF(AND(ISNUMBER(G79),ISNUMBER(H79)),G79*2-H79,"") -> 3 | J79: 4 - monitor only | K79: Medium | L79: Comparison: structures | M79: /learn/mortgage-investment-structures-compared/ | N79: =IF(M79="","Not built (workbook: do not build)",IFERROR(INDEX(Pages!$F$2:$F$98,MATCH(M79,Pages!$B$2:$B$98,0)),"Not found")) -> Mortgage Investment Structures in Canada Compared | O79: Yes
A80: exempt market mortgage investment | B80: Long-tail | C80: 04 Mortgage funds and structures | D80: Risk / due diligence | E80: Evaluating | F80: Canada (national) | G80: 3 | H80: 1 | I80: =IF(AND(ISNUMBER(G80),ISNUMBER(H80)),G80*2-H80,"") -> 5 | J80: 3 - slower climb | K80: High | L80: Guide: Exempt market basics | M80: /learn/exempt-market-and-offering-memorandums/ | N80: =IF(M80="","Not built (workbook: do not build)",IFERROR(INDEX(Pages!$F$2:$F$98,MATCH(M80,Pages!$B$2:$B$98,0)),"Not found")) -> Exempt Market Mortgage Investments and OMs | Lendmax Capital MIC | O80: Yes
A81: exempt market dealer mortgage | B81: Long-tail | C81: 04 Mortgage funds and structures | D81: Risk / due diligence | E81: Evaluating | F81: Canada (national) | G81: 3 | H81: 1 | I81: =IF(AND(ISNUMBER(G81),ISNUMBER(H81)),G81*2-H81,"") -> 5 | J81: 3 - slower climb | K81: High | L81: Guide: Exempt market basics | M81: /learn/exempt-market-and-offering-memorandums/ | N81: =IF(M81="","Not built (workbook: do not build)",IFERROR(INDEX(Pages!$F$2:$F$98,MATCH(M81,Pages!$B$2:$B$98,0)),"Not found")) -> Exempt Market Mortgage Investments and OMs | Lendmax Capital MIC | O81: Yes
A82: first mortgage investments | B82: Medium-tail | C82: 05 Position, priority and security | D82: Educational | E82: Evaluating | F82: Canada (national) | G82: 5 | H82: 2 | I82: =IF(AND(ISNUMBER(G82),ISNUMBER(H82)),G82*2-H82,"") -> 8 | J82: 1 - quick win | K82: High | L82: Guide: First vs second position | M82: /learn/first-mortgage-investments/ | N82: =IF(M82="","Not built (workbook: do not build)",IFERROR(INDEX(Pages!$F$2:$F$98,MATCH(M82,Pages!$B$2:$B$98,0)),"Not found")) -> First Mortgage Investments Explained | Lendmax Capital MIC | O82: Yes
A83: second mortgage investments | B83: Medium-tail | C83: 05 Position, priority and security | D83: Educational | E83: Evaluating | F83: Canada (national) | G83: 5 | H83: 2 | I83: =IF(AND(ISNUMBER(G83),ISNUMBER(H83)),G83*2-H83,"") -> 8 | J83: 1 - quick win | K83: High | L83: Guide: First vs second position | M83: /learn/second-mortgage-investments/ | N83: =IF(M83="","Not built (workbook: do not build)",IFERROR(INDEX(Pages!$F$2:$F$98,MATCH(M83,Pages!$B$2:$B$98,0)),"Not found")) -> Second Mortgage Investments: Yield and Risk | Lendmax Capital MIC | O83: Yes
A84: first mortgage vs second mortgage investing | B84: Long-tail | C84: 05 Position, priority and security | D84: Comparison | E84: Evaluating | F84: Canada (national) | G84: 5 | H84: 1 | I84: =IF(AND(ISNUMBER(G84),ISNUMBER(H84)),G84*2-H84,"") -> 9 | J84: 1 - quick win | K84: High | L84: Comparison: first vs second | M84: /learn/first-vs-second-mortgage-investments/ | N84: =IF(M84="","Not built (workbook: do not build)",IFERROR(INDEX(Pages!$F$2:$F$98,MATCH(M84,Pages!$B$2:$B$98,0)),"Not found")) -> First vs Second Mortgage Investing: What Position Costs | O84: Yes
A85: first position mortgage investment | B85: Long-tail | C85: 05 Position, priority and security | D85: Educational | E85: Evaluating | F85: Canada (national) | G85: 4 | H85: 1 | I85: =IF(AND(ISNUMBER(G85),ISNUMBER(H85)),G85*2-H85,"") -> 7 | J85: 2 - build early | K85: High | L85: Guide: First vs second position | M85: /learn/first-mortgage-investments/ | N85: =IF(M85="","Not built (workbook: do not build)",IFERROR(INDEX(Pages!$F$2:$F$98,MATCH(M85,Pages!$B$2:$B$98,0)),"Not found")) -> First Mortgage Investments Explained | Lendmax Capital MIC | O85: Yes
... A104: home equity loan investment opportunity | B104: Long-tail | C104: 06 Asset and loan types | D104: Educational | E104: Evaluating | F104: Canada (national) | G104: 3 | H104: 2 | I104: =IF(AND(ISNUMBER(G104),ISNUMBER(H104)),G104*2-H104,"") -> 4 | J104: 3 - slower climb | K104: Medium | L104: Guide: Second mortgage investing | M104: /learn/second-mortgage-investments/ | N104: =IF(M104="","Not built (workbook: do not build)",IFERROR(INDEX(Pages!$F$2:$F$98,MATCH(M104,Pages!$B$2:$B$98,0)),"Not found")) -> Second Mortgage Investments: Yield and Risk | Lendmax Capital MIC | O104: Yes
A105: HELOC investment for investors | B105: Long-tail | C105: 06 Asset and loan types | D105: Educational | E105: Evaluating | F105: Canada (national) | G105: 2 | H105: 3 | I105: =IF(AND(ISNUMBER(G105),ISNUMBER(H105)),G105*2-H105,"") -> 1 | J105: 4 - monitor only | K105: Low | L105: — | N105: =IF(M105="","Not built (workbook: do not build)",IFERROR(INDEX(Pages!$F$2:$F$98,MATCH(M105,Pages!$B$2:$B$98,0)),"Not found")) -> Not built (workbook: do not build) | O105: —
A106: interest only mortgage investment | B106: Long-tail | C106: 06 Asset and loan types | D106: Educational | E106: Evaluating | F106: Canada (national) | G106: 3 | H106: 1 | I106: =IF(AND(ISNUMBER(G106),ISNUMBER(H106)),G106*2-H106,"") -> 5 | J106: 3 - slower climb | K106: Medium | L106: Guide: Returns and cash flow | M106: /learn/how-interest-is-paid-to-mortgage-investors/ | N106: =IF(M106="","Not built (workbook: do not build)",IFERROR(INDEX(Pages!$F$2:$F$98,MATCH(M106,Pages!$B$2:$B$98,0)),"Not found")) -> How Is Interest Paid to a Mortgage Investor? | O106: Yes
A107: multi-residential mortgage investing | B107: Long-tail | C107: 06 Asset and loan types | D107: Educational | E107: Evaluating | F107: Canada (national) | G107: 3 | H107: 1 | I107: =IF(AND(ISNUMBER(G107),ISNUMBER(H107)),G107*2-H107,"") -> 5 | J107: 3 - slower climb | K107: Medium | L107: Guide: Commercial mortgage investing | M107: /learn/commercial-mortgage-investing/ | N107: =IF(M107="","Not built (workbook: do not build)",IFERROR(INDEX(Pages!$F$2:$F$98,MATCH(M107,Pages!$B$2:$B$98,0)),"Not found")) -> Commercial Mortgage Investing in Canada | Lendmax Capital MIC | O107: Yes
A108: mixed use property mortgage investment | B108: Long-tail | C108: 06 Asset and loan types | D108: Educational | E108: Evaluating | F108: Canada (national) | G108: 2 | H108: 1 | I108: =IF(AND(ISNUMBER(G108),ISNUMBER(H108)),G108*2-H108,"") -> 3 | J108: 4 - monitor only | K108: Low | L108: Guide: Commercial mortgage investing | M108: /learn/commercial-mortgage-investing/ | N108: =IF(M108="","Not built (workbook: do not build)",IFERROR(INDEX(Pages!$F$2:$F$98,MATCH(M108,Pages!$B$2:$B$98,0)),"Not found")) -> Commercial Mortgage Investing in Canada | Lendmax Capital MIC | O108: Yes
A109: rural property mortgage investment risk | B109: Long-tail | C109: 06 Asset and loan types | D109: Risk / due diligence | E109: Evaluating | F109: Canada (national) | G109: 3 | H109: 1 | I109: =IF(AND(ISNUMBER(G109),ISNUMBER(H109)),G109*2-H109,"") -> 5 | J109: 3 - slower climb | K109: Medium | L109: Guide: Property and marketability risk | M109: /learn/property-marketability-risk/ | N109: =IF(M109="","Not built (workbook: do not build)",IFERROR(INDEX(Pages!$F$2:$F$98,MATCH(M109,Pages!$B$2:$B$98,0)),"Not found")) -> Property Marketability Risk in a Mortgage Investment | O109: Yes
A110: mortgage investment returns | B110: Medium-tail | C110: 07 Returns, income and cash flow | D110: Income / cash-flow intent | E110: Evaluating | F110: Canada (national) | G110: 5 | H110: 3 | I110: =IF(AND(ISNUMBER(G110),ISNUMBER(H110)),G110*2-H110,"") -> 7 | J110: 2 - build early | K110: High | L110: Guide: Returns and cash flow | M110: /learn/mortgage-investment-returns/ | N110: =IF(M110="","Not built (workbook: do not build)",IFERROR(INDEX(Pages!$F$2:$F$98,MATCH(M110,Pages!$B$2:$B$98,0)),"Not found")) -> Where Mortgage Investment Returns Come From | Lendmax Capital MIC | O110: Yes
A111: mortgage investment income | B111: Medium-tail | C111: 07 Returns, income and cash flow | D111: Income / cash-flow intent | E111: Evaluating | F111: Canada (national) | G111: 5 | H111: 3 | I111: =IF(AND(ISNUMBER(G111),ISNUMBER(H111)),G111*2-H111,"") -> 7 | J111: 2 - build early | K111: High | L111: Guide: Returns and cash flow | M111: /learn/how-mortgage-investors-make-money/ | N111: =IF(M111="","Not built (workbook: do not build)",IFERROR(INDEX(Pages!$F$2:$F$98,MATCH(M111,Pages!$B$2:$B$98,0)),"Not found")) -> How Do Mortgage Investors Make Money? | Lendmax Capital MIC | O111: Yes
A112: mortgage passive income | B112: Medium-tail | C112: 07 Returns, income and cash flow | D112: Income / cash-flow intent | E112: Problem-aware | F112: Canada (national) | G112: 5 | H112: 3 | I112: =IF(AND(ISNUMBER(G112),ISNUMBER(H112)),G112*2-H112,"") -> 7 | J112: 2 - build early | K112: High | L112: Pillar: Passive income | M112: /learn/monthly-income-from-mortgage-investments/ | N112: =IF(M112="","Not built (workbook: do not build)",IFERROR(INDEX(Pages!$F$2:$F$98,MATCH(M112,Pages!$B$2:$B$98,0)),"Not found")) -> Monthly Income Investments in Canada: Mortgage Cash Flow | O112: Yes
A113: passive income Canada mortgage | B113: Long-tail | C113: 07 Returns, income and cash flow | D113: Income / cash-flow intent | E113: Problem-aware | F113: Canada (national) | G113: 4 | H113: 3 | I113: =IF(AND(ISNUMBER(G113),ISNUMBER(H113)),G113*2-H113,"") -> 5 | J113: 3 - slower climb | K113: High | L113: Pillar: Passive income | M113: /learn/mortgage-investing-passive-income/ | N113: =IF(M113="","Not built (workbook: do not build)",IFERROR(INDEX(Pages!$F$2:$F$98,MATCH(M113,Pages!$B$2:$B$98,0)),"Not found")) -> Mortgage Passive Income in Canada: How It Works | O113: Yes
A114: mortgage cash flow investments | B114: Medium-tail | C114: 07 Returns, income and cash flow | D114: Income / cash-flow intent | E114: Evaluating | F114: Canada (national) | G114: 4 | H114: 2 | I114: =IF(AND(ISNUMBER(G114),ISNUMBER(H114)),G114*2-H114,"") -> 6 | J114: 2 - build early | K114: High | L114: Guide: Returns and cash flow | M114: /learn/monthly-income-from-mortgage-investments/ | N114: =IF(M114="","Not built (workbook: do not build)",IFERROR(INDEX(Pages!$F$2:$F$98,MATCH(M114,Pages!$B$2:$B$98,0)),"Not found")) -> Monthly Income Investments in Canada: Mortgage Cash Flow | O114: Yes
A115: monthly income investments Canada | B115: Medium-tail | C115: 07 Returns, income and cash flow | D115: Income / cash-flow intent | E115: Problem-aware | F115: Canada (national) | G115: 5 | H115: 3 | I115: =IF(AND(ISNUMBER(G115),ISNUMBER(H115)),G115*2-H115,"") -> 7 | J115: 2 - build early | K115: High | L115: Pillar: Monthly income investing | M115: /learn/monthly-income-from-mortgage-investments/ | N115: =IF(M115="","Not built (workbook: do not build)",IFERROR(INDEX(Pages!$F$2:$F$98,MATCH(M115,Pages!$B$2:$B$98,0)),"Not found")) -> Monthly Income Investments in Canada: Mortgage Cash Flow | O115: Yes
A116: monthly distribution investment Canada | B116: Long-tail | C116: 07 Returns, income and cash flow | D116: Income / cash-flow intent | E116: Evaluating | F116: Canada (national) | G116: 4 | H116: 2 | I116: =IF(AND(ISNUMBER(G116),ISNUMBER(H116)),G116*2-H116,"") -> 6 | J116: 2 - build early | K116: High | L116: Guide: Returns and cash flow | M116: /learn/how-interest-is-paid-to-mortgage-investors/ | N116: =IF(M116="","Not built (workbook: do not build)",IFERROR(INDEX(Pages!$F$2:$F$98,MATCH(M116,Pages!$B$2:$B$98,0)),"Not found")) -> How Is Interest Paid to a Mortgage Investor? | O116: Yes
A117: how do mortgage investors make money | B117: Conversational / AI | C117: 07 Returns, income and cash flow | D117: Educational | E117: Unaware | F117: Canada (national) | G117: 5 | H117: 2 | I117: =IF(AND(ISNUMBER(G117),ISNUMBER(H117)),G117*2-H117,"") -> 8 | J117: 1 - quick win | K117: High | L117: Guide: Where returns come from | M117: /learn/how-mortgage-investors-make-money/ | N117: =IF(M117="","Not built (workbook: do not build)",IFERROR(INDEX(Pages!$F$2:$F$98,MATCH(M117,Pages!$B$2:$B$98,0)),"Not found")) -> How Do Mortgage Investors Make Money? | Lendmax Capital MIC | O117: Yes
... A189: independent legal advice mortgage investment | B189: Long-tail | C189: 09 Risk | D189: Risk / due diligence | E189: Ready to invest | F189: Canada (national) | G189: 3 | H189: 1 | I189: =IF(AND(ISNUMBER(G189),ISNUMBER(H189)),G189*2-H189,"") -> 5 | J189: 3 - slower climb | K189: Medium | L189: Guide: How to invest step by step | M189: /learn/title-insurance-and-legal-file/ | N189: =IF(M189="","Not built (workbook: do not build)",IFERROR(INDEX(Pages!$F$2:$F$98,MATCH(M189,Pages!$B$2:$B$98,0)),"Not found")) -> Title Search for a Mortgage Investment: What to Check | O189: Yes
A190: power of sale Canada investor | B190: Medium-tail | C190: 10 Default, enforcement and recovery | D190: Risk / due diligence | E190: Evaluating | F190: Ontario | G190: 5 | H190: 2 | I190: =IF(AND(ISNUMBER(G190),ISNUMBER(H190)),G190*2-H190,"") -> 8 | J190: 1 - quick win | K190: High | L190: Guide: Power of sale | M190: /learn/power-of-sale-for-mortgage-investors/ | N190: =IF(M190="","Not built (workbook: do not build)",IFERROR(INDEX(Pages!$F$2:$F$98,MATCH(M190,Pages!$B$2:$B$98,0)),"Not found")) -> Power of Sale in Canada: What It Means for Investors | O190: Yes | T190: ON, NB, NL, PEI
A191: what is power of sale | B191: Conversational / AI | C191: 10 Default, enforcement and recovery | D191: Informational | E191: Problem-aware | F191: Ontario | G191: 5 | H191: 3 | I191: =IF(AND(ISNUMBER(G191),ISNUMBER(H191)),G191*2-H191,"") -> 7 | J191: 2 - build early | K191: High | L191: Guide: Power of sale | M191: /learn/power-of-sale-for-mortgage-investors/ | N191: =IF(M191="","Not built (workbook: do not build)",IFERROR(INDEX(Pages!$F$2:$F$98,MATCH(M191,Pages!$B$2:$B$98,0)),"Not found")) -> Power of Sale in Canada: What It Means for Investors | O191: Yes | T191: ON, NB, NL, PEI
A192: foreclosure process for mortgage investors | B192: Long-tail | C192: 10 Default, enforcement and recovery | D192: Risk / due diligence | E192: Evaluating | F192: Canada (national) | G192: 5 | H192: 1 | I192: =IF(AND(ISNUMBER(G192),ISNUMBER(H192)),G192*2-H192,"") -> 9 | J192: 1 - quick win | K192: High | L192: Pillar: Enforcement by province | M192: /learn/mortgage-enforcement-across-canada/ | N192: =IF(M192="","Not built (workbook: do not build)",IFERROR(INDEX(Pages!$F$2:$F$98,MATCH(M192,Pages!$B$2:$B$98,0)),"Not found")) -> Foreclosure Process for Mortgage Investors in Canada | O192: Yes
A193: power of sale vs foreclosure Canada | B193: Long-tail | C193: 10 Default, enforcement and recovery | D193: Comparison | E193: Evaluating | F193: Canada (national) | G193: 5 | H193: 2 | I193: =IF(AND(ISNUMBER(G193),ISNUMBER(H193)),G193*2-H193,"") -> 8 | J193: 1 - quick win | K193: High | L193: Pillar: Enforcement by province | M193: /learn/mortgage-enforcement-across-canada/ | N193: =IF(M193="","Not built (workbook: do not build)",IFERROR(INDEX(Pages!$F$2:$F$98,MATCH(M193,Pages!$B$2:$B$98,0)),"Not found")) -> Foreclosure Process for Mortgage Investors in Canada | O193: Yes
A194: judicial sale mortgage BC | B194: Long-tail | C194: 10 Default, enforcement and recovery | D194: Risk / due diligence | E194: Evaluating | F194: British Columbia | G194: 4 | H194: 1 | I194: =IF(AND(ISNUMBER(G194),ISNUMBER(H194)),G194*2-H194,"") -> 7 | J194: 2 - build early | K194: High | L194: Guide: Enforcement in BC | M194: /learn/mortgage-investment-regulation-british-columbia/ | N194: =IF(M194="","Not built (workbook: do not build)",IFERROR(INDEX(Pages!$F$2:$F$98,MATCH(M194,Pages!$B$2:$B$98,0)),"Not found")) -> BC Mortgage Services Act: What Investors Need to Know | O194: Yes | T194: BC-specific
A195: judicial sale Alberta mortgage investor | B195: Long-tail | C195: 10 Default, enforcement and recovery | D195: Risk / due diligence | E195: Evaluating | F195: Alberta | G195: 4 | H195: 1 | I195: =IF(AND(ISNUMBER(G195),ISNUMBER(H195)),G195*2-H195,"") -> 7 | J195: 2 - build early | K195: High | L195: Guide: Enforcement in Alberta | M195: /learn/mortgage-investment-regulation-alberta/ | N195: =IF(M195="","Not built (workbook: do not build)",IFERROR(INDEX(Pages!$F$2:$F$98,MATCH(M195,Pages!$B$2:$B$98,0)),"Not found")) -> Mortgage Investing in Alberta: Regulation and Enforcement | O195: Yes | T195: AB-specific
A196: mortgage enforcement Quebec hypothecary recourse | B196: Long-tail | C196: 10 Default, enforcement and recovery | D196: Risk / due diligence | E196: Evaluating | F196: Quebec | G196: 3 | H196: 1 | I196: =IF(AND(ISNUMBER(G196),ISNUMBER(H196)),G196*2-H196,"") -> 5 | J196: 3 - slower climb | K196: High | L196: Guide: Enforcement in Quebec | M196: /learn/mortgage-investing-quebec/ | N196: =IF(M196="","Not built (workbook: do not build)",IFERROR(INDEX(Pages!$F$2:$F$98,MATCH(M196,Pages!$B$2:$B$98,0)),"Not found")) -> Mortgage Investing in Quebec: Hypothecs and Recourses | O196: Yes | T196: QC-specific
A197: deficiency judgment mortgage Canada | B197: Long-tail | C197: 10 Default, enforcement and recovery | D197: Risk / due diligence | E197: Evaluating | F197: Canada (national) | G197: 4 | H197: 1 | I197: =IF(AND(ISNUMBER(G197),ISNUMBER(H197)),G197*2-H197,"") -> 7 | J197: 2 - build early | K197: High | L197: Pillar: Enforcement by province | M197: /learn/mortgage-enforcement-across-canada/ | N197: =IF(M197="","Not built (workbook: do not build)",IFERROR(INDEX(Pages!$F$2:$F$98,MATCH(M197,Pages!$B$2:$B$98,0)),"Not found")) -> Foreclosure Process for Mortgage Investors in Canada | O197: Yes
A198: how long does power of sale take | B198: Conversational / AI | C198: 10 Default, enforcement and recovery | D198: Risk / due diligence | E198: Evaluating | F198: Ontario | G198: 4 | H198: 2 | I198: =IF(AND(ISNUMBER(G198),ISNUMBER(H198)),G198*2-H198,"") -> 6 | J198: 2 - build early | K198: High | L198: Guide: Power of sale | M198: /learn/power-of-sale-for-mortgage-investors/ | N198: =IF(M198="","Not built (workbook: do not build)",IFERROR(INDEX(Pages!$F$2:$F$98,MATCH(M198,Pages!$B$2:$B$98,0)),"Not found")) -> Power of Sale in Canada: What It Means for Investors | O198: Yes | T198: ON-specific
A199: cost of enforcing a mortgage investment | B199: Long-tail | C199: 10 Default, enforcement and recovery | D199: Risk / due diligence | E199: Evaluating | F199: Canada (national) | G199: 5 | H199: 1 | I199: =IF(AND(ISNUMBER(G199),ISNUMBER(H199)),G199*2-H199,"") -> 9 | J199: 1 - quick win | K199: High | L199: Guide: Default and recovery | M199: /learn/cost-of-mortgage-enforcement/ | N199: =IF(M199="","Not built (workbook: do not build)",IFERROR(INDEX(Pages!$F$2:$F$98,MATCH(M199,Pages!$B$2:$B$98,0)),"Not found")) -> The Cost of Enforcing a Mortgage Investment | Lendmax Capital MIC | O199: Yes
A200: what happens if a borrower stops paying | B200: Conversational / AI | C200: 10 Default, enforcement and recovery | D200: Risk / due diligence | E200: Evaluating | F200: Canada (national) | G200: 5 | H200: 2 | I200: =IF(AND(ISNUMBER(G200),ISNUMBER(H200)),G200*2-H200,"") -> 8 | J200: 1 - quick win | K200: High | L200: Guide: Default and recovery | M200: /learn/borrower-default-mortgage-investment/ | N200: =IF(M200="","Not built (workbook: do not build)",IFERROR(INDEX(Pages!$F$2:$F$98,MATCH(M200,Pages!$B$2:$B$98,0)),"Not found")) -> Borrower Default on a Mortgage Investment | Lendmax Capital MIC | O200: Yes
A201: mortgage arrears investor meaning | B201: Long-tail | C201: 10 Default, enforcement and recovery | D201: Educational | E201: Evaluating | F201: Canada (national) | G201: 3 | H201: 1 | I201: =IF(AND(ISNUMBER(G201),ISNUMBER(H201)),G201*2-H201,"") -> 5 | J201: 3 - slower climb | K201: Medium | L201: Glossary | M201: /glossary/ | N201: =IF(M201="","Not built (workbook: do not build)",IFERROR(INDEX(Pages!$F$2:$F$98,MATCH(M201,Pages!$B$2:$B$98,0)),"Not found")) -> Mortgage Investment Glossary for Canadian Investors | O201: Yes
A202: do foreclosures affect MIC returns | B202: Conversational / AI | C202: 10 Default, enforcement and recovery | D202: Risk / due diligence | E202: Existing investor | F202: Canada (national) | G202: 4 | H202: 1 | I202: =IF(AND(ISNUMBER(G202),ISNUMBER(H202)),G202*2-H202,"") -> 7 | J202: 2 - build early | K202: High | L202: Guide: Default and recovery | M202: /learn/borrower-default-mortgage-investment/ | N202: =IF(M202="","Not built (workbook: do not build)",IFERROR(INDEX(Pages!$F$2:$F$98,MATCH(M202,Pages!$B$2:$B$98,0)),"Not found")) -> Borrower Default on a Mortgage Investment | Lendmax Capital MIC | O202: Yes
A203: property insurance mortgage investor | B203: Long-tail | C203: 10 Default, enforcement and recovery | D203: Risk / due diligence | E203: Evaluating | F203: Canada (national) | G203: 4 | H203: 1 | I203: =IF(AND(ISNUMBER(G203),ISNUMBER(H203)),G203*2-H203,"") -> 7 | J203: 2 - build early | K203: High | L203: Tool: Due-diligence checklist | M203: /learn/title-insurance-and-legal-file/ | N203: =IF(M203="","Not built (workbook: do not build)",IFERROR(INDEX(Pages!$F$2:$F$98,MATCH(M203,Pages!$B$2:$B$98,0)),"Not found")) -> Title Search for a Mortgage Investment: What to Check | O203: Yes
A204: exit strategy mortgage investment | B204: Medium-tail | C204: 10 Default, enforcement and recovery | D204: Risk / due diligence | E204: Evaluating | F204: Canada (national) | G204: 5 | H204: 1 | I204: =IF(AND(ISNUMBER(G204),ISNUMBER(H204)),G204*2-H204,"") -> 9 | J204: 1 - quick win | K204: High | L204: Guide: Terms, renewals and exits | M204: /learn/mortgage-investment-terms-renewals-and-exits/ | N204: =IF(M204="","Not built (workbook: do not build)",IFERROR(INDEX(Pages!$F$2:$F$98,MATCH(M204,Pages!$B$2:$B$98,0)),"Not found")) -> Mortgage Investment Term Length, Renewals and Exits | O204: Yes
A205: mortgage investment regulations Canada | B205: Medium-tail | C205: 11 Regulation and licensing | D205: Risk / due diligence | E205: Evaluating | F205: Canada (national) | G205: 4 | H205: 1 | I205: =IF(AND(ISNUMBER(G205),ISNUMBER(H205)),G205*2-H205,"") -> 7 | J205: 2 - build early | K205: High | L205: Pillar: Regulation by province | M205: /learn/mortgage-investment-regulation-canada/ | N205: =IF(M205="","Not built (workbook: do not build)",IFERROR(INDEX(Pages!$F$2:$F$98,MATCH(M205,Pages!$B$2:$B$98,0)),"Not found")) -> Mortgage Investment Regulations in Canada | Lendmax Capital MIC | O205: Yes
A206: how is the MIC market regulated | B206: Conversational / AI | C206: 11 Regulation and licensing | D206: Risk / due diligence | E206: Evaluating | F206: Canada (national) | G206: 4 | H206: 1 | I206: =IF(AND(ISNUMBER(G206),ISNUMBER(H206)),G206*2-H206,"") -> 7 | J206: 2 - build early | K206: High | L206: Pillar: Regulation by province | M206: /learn/mortgage-investment-regulation-canada/ | N206: =IF(M206="","Not built (workbook: do not build)",IFERROR(INDEX(Pages!$F$2:$F$98,MATCH(M206,Pages!$B$2:$B$98,0)),"Not found")) -> Mortgage Investment Regulations in Canada | Lendmax Capital MIC | O206: Yes
A207: mortgage administrator licence Canada | B207: Long-tail | C207: 11 Regulation and licensing | D207: Risk / due diligence | E207: Evaluating | F207: Canada (national) | G207: 3 | H207: 1 | I207: =IF(AND(ISNUMBER(G207),ISNUMBER(H207)),G207*2-H207,"") -> 5 | J207: 3 - slower climb | K207: High | L207: Guide: Mortgage administrators | M207: /learn/mortgage-investment-rules-by-province/ | N207: =IF(M207="","Not built (workbook: do not build)",IFERROR(INDEX(Pages!$F$2:$F$98,MATCH(M207,Pages!$B$2:$B$98,0)),"Not found")) -> Mortgage Broker Licensing by Province, Compared | O207: Yes
A208: what is a mortgage administrator | B208: Conversational / AI | C208: 11 Regulation and licensing | D208: Informational | E208: Problem-aware | F208: Canada (national) | G208: 3 | H208: 1 | I208: =IF(AND(ISNUMBER(G208),ISNUMBER(H208)),G208*2-H208,"") -> 5 | J208: 3 - slower climb | K208: High | L208: Guide: Mortgage administrators | M208: /learn/mortgage-administrators/ | N208: =IF(M208="","Not built (workbook: do not build)",IFERROR(INDEX(Pages!$F$2:$F$98,MATCH(M208,Pages!$B$2:$B$98,0)),"Not found")) -> What Is a Mortgage Administrator? | Lendmax Capital MIC | O208: Yes
A209: accredited investor Canada | B209: Medium-tail | C209: 11 Regulation and licensing | D209: Risk / due diligence | E209: Evaluating | F209: Canada (national) | G209: 4 | H209: 3 | I209: =IF(AND(ISNUMBER(G209),ISNUMBER(H209)),G209*2-H209,"") -> 5 | J209: 3 - slower climb | K209: High | L209: Guide: Investor eligibility | M209: /learn/accredited-investor-canada/ | N209: =IF(M209="","Not built (workbook: do not build)",IFERROR(INDEX(Pages!$F$2:$F$98,MATCH(M209,Pages!$B$2:$B$98,0)),"Not found")) -> Accredited Investor in Canada: Who Qualifies | O209: Yes
A210: am I an accredited investor Canada | B210: Conversational / AI | C210: 11 Regulation and licensing | D210: Risk / due diligence | E210: Evaluating | F210: Canada (national) | G210: 4 | H210: 2 | I210: =IF(AND(ISNUMBER(G210),ISNUMBER(H210)),G210*2-H210,"") -> 6 | J210: 2 - build early | K210: High | L210: Guide: Investor eligibility | M210: /learn/accredited-investor-canada/ | N210: =IF(M210="","Not built (workbook: do not build)",IFERROR(INDEX(Pages!$F$2:$F$98,MATCH(M210,Pages!$B$2:$B$98,0)),"Not found")) -> Accredited Investor in Canada: Who Qualifies | O210: Yes
... A214: do I need to be accredited to invest in a MIC | B214: Conversational / AI | C214: 11 Regulation and licensing | D214: Risk / due diligence | E214: Evaluating | F214: Canada (national) | G214: 5 | H214: 1 | I214: =IF(AND(ISNUMBER(G214),ISNUMBER(H214)),G214*2-H214,"") -> 9 | J214: 1 - quick win | K214: High | L214: Guide: Investor eligibility | M214: /learn/accredited-investor-canada/ | N214: =IF(M214="","Not built (workbook: do not build)",IFERROR(INDEX(Pages!$F$2:$F$98,MATCH(M214,Pages!$B$2:$B$98,0)),"Not found")) -> Accredited Investor in Canada: Who Qualifies | O214: Yes
A215: FSRA private mortgage investor | B215: Long-tail | C215: 11 Regulation and licensing | D215: Risk / due diligence | E215: Evaluating | F215: Ontario | G215: 3 | H215: 1 | I215: =IF(AND(ISNUMBER(G215),ISNUMBER(H215)),G215*2-H215,"") -> 5 | J215: 3 - slower climb | K215: High | L215: Guide: Regulation in Ontario | M215: /learn/mortgage-investment-regulation-ontario/ | N215: =IF(M215="","Not built (workbook: do not build)",IFERROR(INDEX(Pages!$F$2:$F$98,MATCH(M215,Pages!$B$2:$B$98,0)),"Not found")) -> FSRA and the Private Mortgage Investor in Ontario | O215: Yes | T215: ON-specific
A216: mortgage investor disclosure form Ontario | B216: Long-tail | C216: 11 Regulation and licensing | D216: Risk / due diligence | E216: Evaluating | F216: Ontario | G216: 3 | H216: 1 | I216: =IF(AND(ISNUMBER(G216),ISNUMBER(H216)),G216*2-H216,"") -> 5 | J216: 3 - slower climb | K216: High | L216: Guide: Regulation in Ontario | M216: /learn/mortgage-investment-regulation-ontario/ | N216: =IF(M216="","Not built (workbook: do not build)",IFERROR(INDEX(Pages!$F$2:$F$98,MATCH(M216,Pages!$B$2:$B$98,0)),"Not found")) -> FSRA and the Private Mortgage Investor in Ontario | O216: Yes | T216: ON-specific
A217: BC Mortgage Services Act investors | B217: Long-tail | C217: 11 Regulation and licensing | D217: Risk / due diligence | E217: Evaluating | F217: British Columbia | G217: 4 | H217: 1 | I217: =IF(AND(ISNUMBER(G217),ISNUMBER(H217)),G217*2-H217,"") -> 7 | J217: 2 - build early | K217: High | L217: Guide: Regulation in BC | M217: /learn/mortgage-investment-regulation-british-columbia/ | N217: =IF(M217="","Not built (workbook: do not build)",IFERROR(INDEX(Pages!$F$2:$F$98,MATCH(M217,Pages!$B$2:$B$98,0)),"Not found")) -> BC Mortgage Services Act: What Investors Need to Know | O217: Yes | T217: BC-specific; time-critical
A218: mortgage broker licensing by province | B218: Long-tail | C218: 11 Regulation and licensing | D218: Comparison | E218: Evaluating | F218: Canada (national) | G218: 4 | H218: 1 | I218: =IF(AND(ISNUMBER(G218),ISNUMBER(H218)),G218*2-H218,"") -> 7 | J218: 2 - build early | K218: High | L218: Pillar: Regulation by province | M218: /learn/mortgage-investment-regulation-canada/ | N218: =IF(M218="","Not built (workbook: do not build)",IFERROR(INDEX(Pages!$F$2:$F$98,MATCH(M218,Pages!$B$2:$B$98,0)),"Not found")) -> Mortgage Investment Regulations in Canada | Lendmax Capital MIC | O218: Yes
A219: single regulator provinces mortgage securities | B219: Long-tail | C219: 11 Regulation and licensing | D219: Informational | E219: Evaluating | F219: Canada (national) | G219: 2 | H219: 1 | I219: =IF(AND(ISNUMBER(G219),ISNUMBER(H219)),G219*2-H219,"") -> 3 | J219: 4 - monitor only | K219: Medium | L219: Pillar: Regulation by province | M219: /learn/mortgage-investment-rules-by-province/ | N219: =IF(M219="","Not built (workbook: do not build)",IFERROR(INDEX(Pages!$F$2:$F$98,MATCH(M219,Pages!$B$2:$B$98,0)),"Not found")) -> Mortgage Broker Licensing by Province, Compared | O219: Yes
A220: suitability determination mortgage investment | B220: Long-tail | C220: 11 Regulation and licensing | D220: Risk / due diligence | E220: Evaluating | F220: Canada (national) | G220: 3 | H220: 1 | I220: =IF(AND(ISNUMBER(G220),ISNUMBER(H220)),G220*2-H220,"") -> 5 | J220: 3 - slower climb | K220: High | L220: Guide: Investor eligibility | M220: /learn/accredited-investor-canada/ | N220: =IF(M220="","Not built (workbook: do not build)",IFERROR(INDEX(Pages!$F$2:$F$98,MATCH(M220,Pages!$B$2:$B$98,0)),"Not found")) -> Accredited Investor in Canada: Who Qualifies | O220: Yes
A221: MIC vs REIT | B221: Medium-tail | C221: 12 Comparisons | D221: Comparison | E221: Evaluating | F221: Canada (national) | G221: 5 | H221: 5 | I221: =IF(AND(ISNUMBER(G221),ISNUMBER(H221)),G221*2-H221,"") -> 5 | J221: 3 - slower climb | K221: High | L221: Comparison: MIC vs REIT | M221: /learn/mic-vs-reit/ | N221: =IF(M221="","Not built (workbook: do not build)",IFERROR(INDEX(Pages!$F$2:$F$98,MATCH(M221,Pages!$B$2:$B$98,0)),"Not found")) -> MIC vs REIT in Canada: Debt Income or Equity | O221: Yes
A222: MIC vs REIT Canada | B222: Long-tail | C222: 12 Comparisons | D222: Comparison | E222: Evaluating | F222: Canada (national) | G222: 5 | H222: 5 | I222: =IF(AND(ISNUMBER(G222),ISNUMBER(H222)),G222*2-H222,"") -> 5 | J222: 3 - slower climb | K222: High | L222: Comparison: MIC vs REIT | M222: /learn/mic-vs-reit/ | N222: =IF(M222="","Not built (workbook: do not build)",IFERROR(INDEX(Pages!$F$2:$F$98,MATCH(M222,Pages!$B$2:$B$98,0)),"Not found")) -> MIC vs REIT in Canada: Debt Income or Equity | O222: Yes
A223: mortgage investing vs GIC | B223: Medium-tail | C223: 12 Comparisons | D223: Comparison | E223: Evaluating | F223: Canada (national) | G223: 5 | H223: 4 | I223: =IF(AND(ISNUMBER(G223),ISNUMBER(H223)),G223*2-H223,"") -> 6 | J223: 2 - build early | K223: High | L223: Comparison: vs GICs | M223: /learn/mortgage-investing-vs-gics/ | N223: =IF(M223="","Not built (workbook: do not build)",IFERROR(INDEX(Pages!$F$2:$F$98,MATCH(M223,Pages!$B$2:$B$98,0)),"Not found")) -> Mortgage Investing vs GICs: Yield and Insurance | O223: Yes
A224: MIC vs GIC Canada | B224: Long-tail | C224: 12 Comparisons | D224: Comparison | E224: Evaluating | F224: Canada (national) | G224: 5 | H224: 4 | I224: =IF(AND(ISNUMBER(G224),ISNUMBER(H224)),G224*2-H224,"") -> 6 | J224: 2 - build early | K224: High | L224: Comparison: vs GICs | M224: /learn/mortgage-investing-vs-gics/ | N224: =IF(M224="","Not built (workbook: do not build)",IFERROR(INDEX(Pages!$F$2:$F$98,MATCH(M224,Pages!$B$2:$B$98,0)),"Not found")) -> Mortgage Investing vs GICs: Yield and Insurance | O224: Yes
A225: mortgage investing vs bonds | B225: Medium-tail | C225: 12 Comparisons | D225: Comparison | E225: Evaluating | F225: Canada (national) | G225: 5 | H225: 1 | I225: =IF(AND(ISNUMBER(G225),ISNUMBER(H225)),G225*2-H225,"") -> 9 | J225: 1 - quick win | K225: High | L225: Comparison: vs bonds | M225: /learn/mortgage-investing-vs-bonds/ | N225: =IF(M225="","Not built (workbook: do not build)",IFERROR(INDEX(Pages!$F$2:$F$98,MATCH(M225,Pages!$B$2:$B$98,0)),"Not found")) -> Mortgage Investing vs Bonds: Two Kinds of Fixed Income | O225: Yes
A226: mortgage investing vs dividend stocks | B226: Medium-tail | C226: 12 Comparisons | D226: Comparison | E226: Evaluating | F226: Canada (national) | G226: 5 | H226: 1 | I226: =IF(AND(ISNUMBER(G226),ISNUMBER(H226)),G226*2-H226,"") -> 9 | J226: 1 - quick win | K226: High | L226: Comparison: vs dividend stocks | M226: /learn/mic-vs-reit/ | N226: =IF(M226="","Not built (workbook: do not build)",IFERROR(INDEX(Pages!$F$2:$F$98,MATCH(M226,Pages!$B$2:$B$98,0)),"Not found")) -> MIC vs REIT in Canada: Debt Income or Equity | O226: Yes
A227: MIC vs private lender | B227: Long-tail | C227: 12 Comparisons | D227: Comparison | E227: Evaluating | F227: Canada (national) | G227: 4 | H227: 2 | I227: =IF(AND(ISNUMBER(G227),ISNUMBER(H227)),G227*2-H227,"") -> 6 | J227: 2 - build early | K227: High | L227: Comparison: MIC vs direct | M227: /learn/mic-vs-direct-mortgage-investing/ | N227: =IF(M227="","Not built (workbook: do not build)",IFERROR(INDEX(Pages!$F$2:$F$98,MATCH(M227,Pages!$B$2:$B$98,0)),"Not found")) -> MIC vs Direct Mortgage Investing: Pooled or Your Own | O227: Yes
A228: MIC vs direct mortgage investing | B228: Long-tail | C228: 12 Comparisons | D228: Comparison | E228: Evaluating | F228: Canada (national) | G228: 5 | H228: 2 | I228: =IF(AND(ISNUMBER(G228),ISNUMBER(H228)),G228*2-H228,"") -> 8 | J228: 1 - quick win | K228: High | L228: Comparison: MIC vs direct | M228: /learn/mic-vs-direct-mortgage-investing/ | N228: =IF(M228="","Not built (workbook: do not build)",IFERROR(INDEX(Pages!$F$2:$F$98,MATCH(M228,Pages!$B$2:$B$98,0)),"Not found")) -> MIC vs Direct Mortgage Investing: Pooled or Your Own | O228: Yes
A229: mortgage investing vs rental property | B229: Medium-tail | C229: 12 Comparisons | D229: Comparison | E229: Problem-aware | F229: Canada (national) | G229: 5 | H229: 2 | I229: =IF(AND(ISNUMBER(G229),ISNUMBER(H229)),G229*2-H229,"") -> 8 | J229: 1 - quick win | K229: High | L229: Comparison: vs rental property | M229: /learn/mortgage-investing-vs-rental-property/ | N229: =IF(M229="","Not built (workbook: do not build)",IFERROR(INDEX(Pages!$F$2:$F$98,MATCH(M229,Pages!$B$2:$B$98,0)),"Not found")) -> Mortgage Investing vs Owning a Rental Property | O229: Yes
... A259: sophisticated investor mortgage Canada | B259: Long-tail | C259: 14 Investor profiles | D259: Risk / due diligence | E259: Evaluating | F259: Canada (national) | G259: 2 | H259: 1 | I259: =IF(AND(ISNUMBER(G259),ISNUMBER(H259)),G259*2-H259,"") -> 3 | J259: 4 - monitor only | K259: Medium | L259: Guide: Investor eligibility | M259: /learn/accredited-investor-canada/ | N259: =IF(M259="","Not built (workbook: do not build)",IFERROR(INDEX(Pages!$F$2:$F$98,MATCH(M259,Pages!$B$2:$B$98,0)),"Not found")) -> Accredited Investor in Canada: Who Qualifies | O259: Yes
A260: mortgage investing Ontario | B260: Medium-tail | C260: 15 Geographic — province | D260: Comparison | E260: Evaluating | F260: Ontario | G260: 5 | H260: 3 | I260: =IF(AND(ISNUMBER(G260),ISNUMBER(H260)),G260*2-H260,"") -> 7 | J260: 2 - build early | K260: High | L260: Province hub: Ontario | M260: /learn/mortgage-investment-regulation-ontario/ | N260: =IF(M260="","Not built (workbook: do not build)",IFERROR(INDEX(Pages!$F$2:$F$98,MATCH(M260,Pages!$B$2:$B$98,0)),"Not found")) -> FSRA and the Private Mortgage Investor in Ontario | O260: Yes | T260: Build — priority province page
A261: private mortgage investing Ontario | B261: Long-tail | C261: 15 Geographic — province | D261: Comparison | E261: Evaluating | F261: Ontario | G261: 5 | H261: 2 | I261: =IF(AND(ISNUMBER(G261),ISNUMBER(H261)),G261*2-H261,"") -> 8 | J261: 1 - quick win | K261: High | L261: Province hub: Ontario | M261: /learn/mortgage-investing-ontario/ | N261: =IF(M261="","Not built (workbook: do not build)",IFERROR(INDEX(Pages!$F$2:$F$98,MATCH(M261,Pages!$B$2:$B$98,0)),"Not found")) -> Mortgage Investing in Ontario: Rules and How to Invest | O261: Yes | T261: Build — priority province page
A262: mortgage investment corporation Ontario | B262: Long-tail | C262: 15 Geographic — province | D262: Comparison | E262: Evaluating | F262: Ontario | G262: 5 | H262: 3 | I262: =IF(AND(ISNUMBER(G262),ISNUMBER(H262)),G262*2-H262,"") -> 7 | J262: 2 - build early | K262: High | L262: Province hub: Ontario | M262: /learn/mortgage-investing-ontario/ | N262: =IF(M262="","Not built (workbook: do not build)",IFERROR(INDEX(Pages!$F$2:$F$98,MATCH(M262,Pages!$B$2:$B$98,0)),"Not found")) -> Mortgage Investing in Ontario: Rules and How to Invest | O262: Yes | T262: Build — priority province page
A263: mortgage investment opportunities Ontario | B263: Long-tail | C263: 15 Geographic — province | D263: Comparison | E263: Solution-aware | F263: Ontario | G263: 5 | H263: 2 | I263: =IF(AND(ISNUMBER(G263),ISNUMBER(H263)),G263*2-H263,"") -> 8 | J263: 1 - quick win | K263: Medium | L263: Province hub: Ontario | M263: /learn/mortgage-investing-ontario/ | N263: =IF(M263="","Not built (workbook: do not build)",IFERROR(INDEX(Pages!$F$2:$F$98,MATCH(M263,Pages!$B$2:$B$98,0)),"Not found")) -> Mortgage Investing in Ontario: Rules and How to Invest | O263: Yes | T263: Build — priority province page
A264: invest in mortgages Ontario | B264: Long-tail | C264: 15 Geographic — province | D264: Transactional / investment intent | E264: Solution-aware | F264: Ontario | G264: 5 | H264: 2 | I264: =IF(AND(ISNUMBER(G264),ISNUMBER(H264)),G264*2-H264,"") -> 8 | J264: 1 - quick win | K264: High | L264: Province hub: Ontario | M264: /learn/mortgage-investing-ontario/ | N264: =IF(M264="","Not built (workbook: do not build)",IFERROR(INDEX(Pages!$F$2:$F$98,MATCH(M264,Pages!$B$2:$B$98,0)),"Not found")) -> Mortgage Investing in Ontario: Rules and How to Invest | O264: Yes | T264: Build — priority province page
A265: mortgage investing British Columbia | B265: Medium-tail | C265: 15 Geographic — province | D265: Comparison | E265: Evaluating | F265: British Columbia | G265: 5 | H265: 2 | I265: =IF(AND(ISNUMBER(G265),ISNUMBER(H265)),G265*2-H265,"") -> 8 | J265: 1 - quick win | K265: High | L265: Province hub: BC | M265: /learn/mortgage-investment-regulation-british-columbia/ | N265: =IF(M265="","Not built (workbook: do not build)",IFERROR(INDEX(Pages!$F$2:$F$98,MATCH(M265,Pages!$B$2:$B$98,0)),"Not found")) -> BC Mortgage Services Act: What Investors Need to Know | O265: Yes | T265: Build — priority province page
A266: private lending BC | B266: Medium-tail | C266: 15 Geographic — province | D266: Comparison | E266: Evaluating | F266: British Columbia | G266: 4 | H266: 3 | I266: =IF(AND(ISNUMBER(G266),ISNUMBER(H266)),G266*2-H266,"") -> 5 | J266: 3 - slower climb | K266: Medium | L266: Province hub: BC | M266: /learn/mortgage-investment-regulation-british-columbia/ | N266: =IF(M266="","Not built (workbook: do not build)",IFERROR(INDEX(Pages!$F$2:$F$98,MATCH(M266,Pages!$B$2:$B$98,0)),"Not found")) -> BC Mortgage Services Act: What Investors Need to Know | O266: Yes | T266: Build — priority province page
A267: mortgage investment corporation BC | B267: Long-tail | C267: 15 Geographic — province | D267: Comparison | E267: Evaluating | F267: British Columbia | G267: 5 | H267: 2 | I267: =IF(AND(ISNUMBER(G267),ISNUMBER(H267)),G267*2-H267,"") -> 8 | J267: 1 - quick win | K267: High | L267: Province hub: BC | M267: /learn/mortgage-investing-british-columbia/ | N267: =IF(M267="","Not built (workbook: do not build)",IFERROR(INDEX(Pages!$F$2:$F$98,MATCH(M267,Pages!$B$2:$B$98,0)),"Not found")) -> Mortgage Investing in British Columbia: 2026 Guide | O267: Yes | T267: Build — priority province page
A268: invest in mortgages BC | B268: Long-tail | C268: 15 Geographic — province | D268: Transactional / investment intent | E268: Solution-aware | F268: British Columbia | G268: 4 | H268: 2 | I268: =IF(AND(ISNUMBER(G268),ISNUMBER(H268)),G268*2-H268,"") -> 6 | J268: 2 - build early | K268: High | L268: Province hub: BC | M268: /learn/mortgage-investing-british-columbia/ | N268: =IF(M268="","Not built (workbook: do not build)",IFERROR(INDEX(Pages!$F$2:$F$98,MATCH(M268,Pages!$B$2:$B$98,0)),"Not found")) -> Mortgage Investing in British Columbia: 2026 Guide | O268: Yes | T268: Build — priority province page
A269: mortgage investing Alberta | B269: Medium-tail | C269: 15 Geographic — province | D269: Comparison | E269: Evaluating | F269: Alberta | G269: 4 | H269: 2 | I269: =IF(AND(ISNUMBER(G269),ISNUMBER(H269)),G269*2-H269,"") -> 6 | J269: 2 - build early | K269: High | L269: Province hub: Alberta | M269: /learn/mortgage-investment-regulation-alberta/ | N269: =IF(M269="","Not built (workbook: do not build)",IFERROR(INDEX(Pages!$F$2:$F$98,MATCH(M269,Pages!$B$2:$B$98,0)),"Not found")) -> Mortgage Investing in Alberta: Regulation and Enforcement | O269: Yes | T269: Build — secondary province page
A270: invest in mortgages Alberta | B270: Long-tail | C270: 15 Geographic — province | D270: Transactional / investment intent | E270: Solution-aware | F270: Alberta | G270: 4 | H270: 2 | I270: =IF(AND(ISNUMBER(G270),ISNUMBER(H270)),G270*2-H270,"") -> 6 | J270: 2 - build early | K270: High | L270: Province hub: Alberta | M270: /learn/mortgage-investment-regulation-alberta/ | N270: =IF(M270="","Not built (workbook: do not build)",IFERROR(INDEX(Pages!$F$2:$F$98,MATCH(M270,Pages!$B$2:$B$98,0)),"Not found")) -> Mortgage Investing in Alberta: Regulation and Enforcement | O270: Yes | T270: Build — secondary province page
A271: mortgage investment corporation Alberta | B271: Long-tail | C271: 15 Geographic — province | D271: Comparison | E271: Evaluating | F271: Alberta | G271: 4 | H271: 2 | I271: =IF(AND(ISNUMBER(G271),ISNUMBER(H271)),G271*2-H271,"") -> 6 | J271: 2 - build early | K271: High | L271: Province hub: Alberta | M271: /learn/mortgage-investing-alberta/ | N271: =IF(M271="","Not built (workbook: do not build)",IFERROR(INDEX(Pages!$F$2:$F$98,MATCH(M271,Pages!$B$2:$B$98,0)),"Not found")) -> Mortgage Investing in Alberta: Rules and Enforcement | O271: Yes | T271: Build — secondary province page
... A288: mortgage investing Montreal | B288: Medium-tail | C288: 16 Geographic — region and city | D288: Comparison | E288: Evaluating | F288: Montreal | G288: 2 | H288: 1 | I288: =IF(AND(ISNUMBER(G288),ISNUMBER(H288)),G288*2-H288,"") -> 3 | J288: 4 - monitor only | K288: Low | L288: Fold into Quebec page | M288: /learn/mortgage-investing-quebec-prairies-atlantic/ | N288: =IF(M288="","Not built (workbook: do not build)",IFERROR(INDEX(Pages!$F$2:$F$98,MATCH(M288,Pages!$B$2:$B$98,0)),"Not found")) -> Mortgage Investing in Quebec, Prairies and Atlantic Canada | O288: Yes | T288: Fold into Quebec
A289: mortgage investing Halifax | B289: Medium-tail | C289: 16 Geographic — region and city | D289: Comparison | E289: Evaluating | F289: Halifax | G289: 1 | H289: 1 | I289: =IF(AND(ISNUMBER(G289),ISNUMBER(H289)),G289*2-H289,"") -> 1 | J289: 4 - monitor only | K289: Low | L289: — | N289: =IF(M289="","Not built (workbook: do not build)",IFERROR(INDEX(Pages!$F$2:$F$98,MATCH(M289,Pages!$B$2:$B$98,0)),"Not found")) -> Not built (workbook: do not build) | O289: — | T289: Do NOT build a dedicated page
A290: private mortgage lender Toronto | B290: Medium-tail | C290: 16 Geographic — region and city | D290: Comparison | E290: Solution-aware | F290: GTA | G290: 2 | H290: 5 | I290: =IF(AND(ISNUMBER(G290),ISNUMBER(H290)),G290*2-H290,"") -> -1 | J290: 4 - monitor only | K290: Low | L290: — | N290: =IF(M290="","Not built (workbook: do not build)",IFERROR(INDEX(Pages!$F$2:$F$98,MATCH(M290,Pages!$B$2:$B$98,0)),"Not found")) -> Not built (workbook: do not build) | O290: — | T290: Do NOT target for investors
A291: private mortgage lender Hamilton | B291: Medium-tail | C291: 16 Geographic — region and city | D291: Comparison | E291: Solution-aware | F291: Hamilton | G291: 1 | H291: 4 | I291: =IF(AND(ISNUMBER(G291),ISNUMBER(H291)),G291*2-H291,"") -> -2 | J291: 4 - monitor only | K291: Low | L291: — | N291: =IF(M291="","Not built (workbook: do not build)",IFERROR(INDEX(Pages!$F$2:$F$98,MATCH(M291,Pages!$B$2:$B$98,0)),"Not found")) -> Not built (workbook: do not build) | O291: — | T291: Do NOT build a dedicated page
A292: private mortgage lender London Ontario | B292: Medium-tail | C292: 16 Geographic — region and city | D292: Comparison | E292: Solution-aware | F292: London ON | G292: 1 | H292: 4 | I292: =IF(AND(ISNUMBER(G292),ISNUMBER(H292)),G292*2-H292,"") -> -2 | J292: 4 - monitor only | K292: Low | L292: — | N292: =IF(M292="","Not built (workbook: do not build)",IFERROR(INDEX(Pages!$F$2:$F$98,MATCH(M292,Pages!$B$2:$B$98,0)),"Not found")) -> Not built (workbook: do not build) | O292: — | T292: Do NOT build a dedicated page
A293: private mortgage lender Kitchener Waterloo | B293: Medium-tail | C293: 16 Geographic — region and city | D293: Comparison | E293: Solution-aware | F293: KW | G293: 1 | H293: 4 | I293: =IF(AND(ISNUMBER(G293),ISNUMBER(H293)),G293*2-H293,"") -> -2 | J293: 4 - monitor only | K293: Low | L293: — | N293: =IF(M293="","Not built (workbook: do not build)",IFERROR(INDEX(Pages!$F$2:$F$98,MATCH(M293,Pages!$B$2:$B$98,0)),"Not found")) -> Not built (workbook: do not build) | O293: — | T293: Do NOT build a dedicated page
A294: mortgage investing Prairies Canada | B294: Long-tail | C294: 16 Geographic — region and city | D294: Comparison | E294: Evaluating | F294: Prairies | G294: 2 | H294: 1 | I294: =IF(AND(ISNUMBER(G294),ISNUMBER(H294)),G294*2-H294,"") -> 3 | J294: 4 - monitor only | K294: Low | L294: Other-provinces page | M294: /learn/mortgage-investing-quebec-prairies-atlantic/ | N294: =IF(M294="","Not built (workbook: do not build)",IFERROR(INDEX(Pages!$F$2:$F$98,MATCH(M294,Pages!$B$2:$B$98,0)),"Not found")) -> Mortgage Investing in Quebec, Prairies and Atlantic Canada | O294: Yes | T294: One thin page at most
...

Sheet Content QA
A1: # | B1: Article | C1: URL | D1: Priority | E1: Primary keyword | F1: Words (article) | G1: Target words | H1: Overall | I1: Front matter | J1: Title length | K1: Description length | L1: K1 Answer in first 120 words | M1: K2 One H1, no heading jumps | N1: K7 Prohibited-language scan | O1: K8 Disclosures in body | P1: K11 Internal links | Q1: Allowed sources only | R1: J2 Seven axes in summary | S1: E7 FAQ | T1: E9 Key takeaways | U1: Length vs target | V1: Checks passed
A2: 1 | B2: What Is Mortgage Investing in Canada? | C2: /learn/what-is-mortgage-investing/ | D2: P1 | E2: mortgage investing | F2: 2821 | G2: 2200 | H2: =IF(COUNTIF(I2:U2,"Fail")=0,"PASS","FAIL") -> PASS | I2: Pass | J2: Pass | K2: Pass | L2: Pass | M2: Pass | N2: Pass | O2: Pass | P2: Pass | Q2: Pass | R2: Pass | S2: Pass | T2: Pass | U2: Pass | V2: =COUNTIF(I2:U2,"Pass") -> 13
A3: 2 | B3: How Does Private Mortgage Investing Work? | C3: /learn/how-private-mortgage-investing-works/ | D3: P1 | E3: private mortgage investing | F3: 2516 | G3: 2400 | H3: =IF(COUNTIF(I3:U3,"Fail")=0,"PASS","FAIL") -> PASS | I3: Pass | J3: Pass | K3: Pass | L3: Pass | M3: Pass | N3: Pass | O3: Pass | P3: Pass | Q3: Pass | R3: Pass | S3: Pass | T3: Pass | U3: Pass | V3: =COUNTIF(I3:U3,"Pass") -> 13
A4: 3 | B4: How Do Mortgage Investors Actually Make Money? | C4: /learn/how-mortgage-investors-make-money/ | D4: P1 | E4: how do mortgage investors make money | F4: 1971 | G4: 1800 | H4: =IF(COUNTIF(I4:U4,"Fail")=0,"PASS","FAIL") -> PASS | I4: Pass | J4: Pass | K4: Pass | L4: Pass | M4: Pass | N4: Pass | O4: Pass | P4: Pass | Q4: Pass | R4: Pass | S4: Pass | T4: Pass | U4: Pass | V4: =COUNTIF(I4:U4,"Pass") -> 13
A5: 4 | B5: How Is Interest Paid to a Private Mortgage Investor? | C5: /learn/how-interest-is-paid-to-mortgage-investors/ | D5: P2 | E5: how is interest paid to a mortgage investor | F5: 1676 | G5: 1400 | H5: =IF(COUNTIF(I5:U5,"Fail")=0,"PASS","FAIL") -> PASS | I5: Pass | J5: Pass | K5: Pass | L5: Pass | M5: Pass | N5: Pass | O5: Pass | P5: Pass | Q5: Pass | R5: Pass | S5: Pass | T5: Pass | U5: Pass | V5: =COUNTIF(I5:U5,"Pass") -> 13
A6: 5 | B6: How Is a Mortgage Investment Secured Against Canadian Real Estate? | C6: /learn/how-mortgage-investments-are-secured/ | D6: P1 | E6: how is a mortgage investment secured | F6: 2246 | G6: 2000 | H6: =IF(COUNTIF(I6:U6,"Fail")=0,"PASS","FAIL") -> PASS | I6: Pass | J6: Pass | K6: Pass | L6: Pass | M6: Pass | N6: Pass | O6: Pass | P6: Pass | Q6: Pass | R6: Pass | S6: Pass | T6: Pass | U6: Pass | V6: =COUNTIF(I6:U6,"Pass") -> 13
A7: 6 | B7: Mortgage Investing for Beginners: A Canadian Guide | C7: /learn/mortgage-investing-for-beginners/ | D7: P1 | E7: mortgage investing for beginners | F7: 2474 | G7: 2600 | H7: =IF(COUNTIF(I7:U7,"Fail")=0,"PASS","FAIL") -> PASS | I7: Pass | J7: Pass | K7: Pass | L7: Pass | M7: Pass | N7: Pass | O7: Pass | P7: Pass | Q7: Pass | R7: Pass | S7: Pass | T7: Pass | U7: Pass | V7: =COUNTIF(I7:U7,"Pass") -> 13
A8: 7 | B8: Canadian Mortgage Investment Glossary: 121 Terms Defined | C8: /glossary/ | D8: P1 | E8: mortgage investment glossary Canada | F8: 4669 | G8: 4000 | H8: =IF(COUNTIF(I8:U8,"Fail")=0,"PASS","FAIL") -> PASS | I8: Pass | J8: Pass | K8: Pass | L8: Pass | M8: Pass | N8: Pass | O8: Pass | P8: Pass | Q8: Pass | R8: Pass | S8: Pass | T8: Pass | U8: Pass | V8: =COUNTIF(I8:U8,"Pass") -> 13
A9: 8 | B9: First Mortgage Investments Explained | C9: /learn/first-mortgage-investments/ | D9: P1 | E9: first mortgage investments | F9: 1802 | G9: 1800 | H9: =IF(COUNTIF(I9:U9,"Fail")=0,"PASS","FAIL") -> PASS | I9: Pass | J9: Pass | K9: Pass | L9: Pass | M9: Pass | N9: Pass | O9: Pass | P9: Pass | Q9: Pass | R9: Pass | S9: Pass | T9: Pass | U9: Pass | V9: =COUNTIF(I9:U9,"Pass") -> 13
A10: 9 | B10: Second Mortgage Investments: The Yield and the Trade-Off | C10: /learn/second-mortgage-investments/ | D10: P1 | E10: second mortgage investments | F10: 2254 | G10: 2000 | H10: =IF(COUNTIF(I10:U10,"Fail")=0,"PASS","FAIL") -> PASS | I10: Pass | J10: Pass | K10: Pass | L10: Pass | M10: Pass | N10: Pass | O10: Pass | P10: Pass | Q10: Pass | R10: Pass | S10: Pass | T10: Pass | U10: Pass | V10: =COUNTIF(I10:U10,"Pass") -> 13
A11: 10 | B11: Residential Mortgage Investing in Canada | C11: /learn/residential-mortgage-investing/ | D11: P2 | E11: residential mortgage investing | F11: 2000 | G11: 1800 | H11: =IF(COUNTIF(I11:U11,"Fail")=0,"PASS","FAIL") -> PASS | I11: Pass | J11: Pass | K11: Pass | L11: Pass | M11: Pass | N11: Pass | O11: Pass | P11: Pass | Q11: Pass | R11: Pass | S11: Pass | T11: Pass | U11: Pass | V11: =COUNTIF(I11:U11,"Pass") -> 13
A12: 11 | B12: Commercial Mortgage Investing in Canada | C12: /learn/commercial-mortgage-investing/ | D12: P2 | E12: commercial mortgage investing Canada | F12: 1977 | G12: 2000 | H12: =IF(COUNTIF(I12:U12,"Fail")=0,"PASS","FAIL") -> PASS | I12: Pass | J12: Pass | K12: Pass | L12: Pass | M12: Pass | N12: Pass | O12: Pass | P12: Pass | Q12: Pass | R12: Pass | S12: Pass | T12: Pass | U12: Pass | V12: =COUNTIF(I12:U12,"Pass") -> 13
A13: 12 | B13: Construction Mortgage Investments: Draws, Holdbacks and Cost to Complete | C13: /learn/construction-mortgage-investments/ | D13: P1 | E13: construction mortgage investments | F13: 2760 | G13: 2800 | H13: =IF(COUNTIF(I13:U13,"Fail")=0,"PASS","FAIL") -> PASS | I13: Pass | J13: Pass | K13: Pass | L13: Pass | M13: Pass | N13: Pass | O13: Pass | P13: Pass | Q13: Pass | R13: Pass | S13: Pass | T13: Pass | U13: Pass | V13: =COUNTIF(I13:U13,"Pass") -> 13
... A91: 90 | B91: Mortgage Investing FAQ: 60 Questions Canadian Investors Ask | C91: /faq/ | D91: P1 | E91: mortgage investment FAQ Canada | F91: 4639 | G91: 4000 | H91: =IF(COUNTIF(I91:U91,"Fail")=0,"PASS","FAIL") -> PASS | I91: Pass | J91: Pass | K91: Pass | L91: Pass | M91: Pass | N91: Pass | O91: Pass | P91: Pass | Q91: Pass | R91: Pass | S91: Pass | T91: Pass | U91: Pass | V91: =COUNTIF(I91:U91,"Pass") -> 13
A94: Manual checks (Tab 3, section K)
A95: Ref | B95: Check | C95: Status | D95: Detail
A96: K4 | B96: Regulatory claims verified at source | C96: Signed off | D96: Signed off — legal review completed 3 October 2026 (confirmed by Lendmax Capital)
A97: K17 | B97: Tax / regulatory sign-off by qualified reviewer | C97: Signed off | D97: Signed off — legal review completed 3 October 2026 (confirmed by Lendmax Capital)
A98: K10 | B98: Calculations recomputed by a second person | C98: Pending | D98: Every worked example was recomputed by its writer with a script; a second person's check is still to be recorded.
A99: K12 | B99: External links resolve (live check) | C99: Mostly passed | D99: Checked 3 October 2026, from the lmcmic.ca server, after launch — 21 of 25 external links resolve; not confirmed from the server: lautorite.qc.ca, www.canada.ca, www.fsrao.ca
A100: K13 | B100: Featured image to Tab 2 spec | C100: Partly met | D100: lendmaxcapital.ca publishes one photograph and four partner logos; they are used on the core pages. Articles use generated title cards until more photography is supplied.

Sheet Internal Links
A1: From page | B1: To page | C1: Anchor text | D1: Target exists
A2: / | B2: /why-invest-in-a-mic/ | C2: How a MIC works | D2: =IF(ISNUMBER(MATCH(B2,Pages!$B$2:$B$98,0)),"Yes","Check") -> Yes
A3: / | B3: /tools/drip-compounding-calculator/ | C3: Model compounding with the DRIP calculator | D3: =IF(ISNUMBER(MATCH(B3,Pages!$B$2:$B$98,0)),"Yes","Check") -> Yes
A4: / | B4: /learn/mic-vs-direct-mortgage-investing/ | C4: lending directly | D4: =IF(ISNUMBER(MATCH(B4,Pages!$B$2:$B$98,0)),"Yes","Check") -> Yes
A5: / | B5: /learn/rrsp-tfsa-rrif-mortgage-investments/ | C5: RRSP, RRIF or TFSA | D5: =IF(ISNUMBER(MATCH(B5,Pages!$B$2:$B$98,0)),"Yes","Check") -> Yes
A6: / | B6: /privacy/ | C6: privacy notice | D6: =IF(ISNUMBER(MATCH(B6,Pages!$B$2:$B$98,0)),"Yes","Check") -> Yes
A7: / | B7: /learn/ | C7: Explore all guides | D7: =IF(ISNUMBER(MATCH(B7,Pages!$B$2:$B$98,0)),"Yes","Check") -> Yes
A8: / | B8: /learn/what-is-a-mortgage-investment-corporation/ | C8: Types of mortgage investmentWhat Is a Mortgage Investment Corporation (MIC)?How section 130.1 of the Income Tax Act makes a MIC a flow-through for mortgage income. | D8: =IF(ISNUMBER(MATCH(B8,Pages!$B$2:$B$98,0)),"Yes","Check") -> Yes
A9: / | B9: /learn/rrsp-tfsa-rrif-mortgage-investments/ | C9: Regulation, tax and eligibilityHolding Mortgage Investments in an RRSP, TFSA or RRIFPlan eligibility, the self-directed trustee, and the 10% prohibited-investment trap. | D9: =IF(ISNUMBER(MATCH(B9,Pages!$B$2:$B$98,0)),"Yes","Check") -> Yes
A10: / | B10: /learn/mortgage-investment-risks/ | C10: Risk, security and due diligenceThe Risks of Mortgage Investing in CanadaDefault, value declines, illiquidity, interest rates and structural risk, stated plainly. | D10: =IF(ISNUMBER(MATCH(B10,Pages!$B$2:$B$98,0)),"Yes","Check") -> Yes
A11: / | B11: /learn/how-mortgage-investors-make-money/ | C11: Understanding mortgage investingHow Do Mortgage Investors Actually Make Money?Interest, lender fees and renewals — and what each is reduced by before it reaches you. | D11: =IF(ISNUMBER(MATCH(B11,Pages!$B$2:$B$98,0)),"Yes","Check") -> Yes
A12: / | B12: /learn/mic-vs-reit/ | C12: Comparisons with other investmentsMIC vs REIT in Canada: Debt Income or Equity OwnershipDebt income or equity ownership, compared fairly in both directions. | D12: =IF(ISNUMBER(MATCH(B12,Pages!$B$2:$B$98,0)),"Yes","Check") -> Yes
A13: / | B13: /learn/mortgage-investor-due-diligence-checklist/ | C13: Risk, security and due diligenceThe Mortgage Investor's Due Diligence ChecklistThe documents and figures to check before you commit capital. | D13: =IF(ISNUMBER(MATCH(B13,Pages!$B$2:$B$98,0)),"Yes","Check") -> Yes
... A1310: /why-invest-in-a-mic/ | B1310: /contact/ | C1310: Request the offering memorandum | D1310: =IF(ISNUMBER(MATCH(B1310,Pages!$B$2:$B$98,0)),"Yes","Check") -> Yes

Sheet Redirects
A1: Requested | B1: Goes to | C1: Status | D1: Why
A2: http://lmcmic.ca/<any path> | B2: https://lmcmic.ca/<same path> | C2: 301 | D2: One canonical origin: HTTPS
A3: http(s)://www.lmcmic.ca/<any path> | B3: https://lmcmic.ca/<same path> | C3: 301 | D3: One canonical host: no www
A4: /<path> (no trailing slash) | B4: /<path>/ | C4: 301 | D4: Directory URLs end in a slash; only one version is indexable
A5: /<path>/index.html | B5: /<path>/ | C5: 301 | D5: Strip index.html (tested on the original request, so no loop)
A6: /home | B6: / | C6: 301 | D6: Legacy WordPress / funnel URL from the previous lmcmic.ca
A7: /homepage | B7: / | C7: 301 | D7: Legacy WordPress / funnel URL from the previous lmcmic.ca
A8: /index.php | B8: / | C8: 301 | D8: Legacy WordPress / funnel URL from the previous lmcmic.ca
A9: /about | B9: /why-invest-in-a-mic/ | C9: 301 | D9: Legacy WordPress / funnel URL from the previous lmcmic.ca
A10: /about-us | B10: /why-invest-in-a-mic/ | C10: 301 | D10: Legacy WordPress / funnel URL from the previous lmcmic.ca
A11: /our-team | B11: /why-invest-in-a-mic/ | C11: 301 | D11: Legacy WordPress / funnel URL from the previous lmcmic.ca
A12: /team | B12: /why-invest-in-a-mic/ | C12: 301 | D12: Legacy WordPress / funnel URL from the previous lmcmic.ca
A13: /who-we-are | B13: /why-invest-in-a-mic/ | C13: 301 | D13: Legacy WordPress / funnel URL from the previous lmcmic.ca
... A47: /wp-json | B47: (gone) | C47: 410 | D47: Old WordPress admin/system path: 410 Gone tells crawlers to drop it

Sheet Images
A1: Image | B1: Source URL (lendmaxcapital.ca) | C1: Source size (KB) | D1: Alt text | E1: Used on | F1: Served file | G1: Format | H1: Width (px) | I1: Size (KB) | J1: Saving vs source
A2: driving-results | B2: https://lendmaxcapital.ca/img/driving-results.jpg | C2: 89 | D2: Mid-rise residential condominium building in Ontario with the caption: Driving Results. In every market condition. | E2: /, /performance-and-risk/, /contact/ | F2: /assets/img/driving-results-400.avif | G2: AVIF | H2: 400 | I2: 14.3 | J2: =IF(ISNUMBER(C2),1-I2/C2,"") -> 0.83932584
A3: driving-results | B3: https://lendmaxcapital.ca/img/driving-results.jpg | C3: 89 | D3: Mid-rise residential condominium building in Ontario with the caption: Driving Results. In every market condition. | E3: /, /performance-and-risk/, /contact/ | F3: /assets/img/driving-results-400.jpg | G3: JPG | H3: 400 | I3: 30.4 | J3: =IF(ISNUMBER(C3),1-I3/C3,"") -> 0.65842697
A4: driving-results | B4: https://lendmaxcapital.ca/img/driving-results.jpg | C4: 89 | D4: Mid-rise residential condominium building in Ontario with the caption: Driving Results. In every market condition. | E4: /, /performance-and-risk/, /contact/ | F4: /assets/img/driving-results-400.webp | G4: WEBP | H4: 400 | I4: 22.3 | J4: =IF(ISNUMBER(C4),1-I4/C4,"") -> 0.7494382
A5: driving-results | B5: https://lendmaxcapital.ca/img/driving-results.jpg | C5: 89 | D5: Mid-rise residential condominium building in Ontario with the caption: Driving Results. In every market condition. | E5: /, /performance-and-risk/, /contact/ | F5: /assets/img/driving-results-690.avif | G5: AVIF | H5: 690 | I5: 32.6 | J5: =IF(ISNUMBER(C5),1-I5/C5,"") -> 0.63370787
A6: driving-results | B6: https://lendmaxcapital.ca/img/driving-results.jpg | C6: 89 | D6: Mid-rise residential condominium building in Ontario with the caption: Driving Results. In every market condition. | E6: /, /performance-and-risk/, /contact/ | F6: /assets/img/driving-results-690.jpg | G6: JPG | H6: 690 | I6: 79.1 | J6: =IF(ISNUMBER(C6),1-I6/C6,"") -> 0.11123596
A7: driving-results | B7: https://lendmaxcapital.ca/img/driving-results.jpg | C7: 89 | D7: Mid-rise residential condominium building in Ontario with the caption: Driving Results. In every market condition. | E7: /, /performance-and-risk/, /contact/ | F7: /assets/img/driving-results-690.webp | G7: WEBP | H7: 690 | I7: 49.3 | J7: =IF(ISNUMBER(C7),1-I7/C7,"") -> 0.44606742
A8: partner-yalepgc | B8: https://lendmaxcapital.ca/img/partner-yalepgc@2x.png | D8: Yale PGC LLP, Chartered Professional Accountants | E8: /, /performance-and-risk/, /how-to-invest/ | F8: /assets/img/partner-yalepgc-40.png | G8: PNG | H8: 140 | I8: 6.3 | J8: =IF(ISNUMBER(C8),1-I8/C8,"")
A9: partner-yalepgc | B9: https://lendmaxcapital.ca/img/partner-yalepgc@2x.png | D9: Yale PGC LLP, Chartered Professional Accountants | E9: /, /performance-and-risk/, /how-to-invest/ | F9: /assets/img/partner-yalepgc-40.webp | G9: WEBP | H9: 140 | I9: 3.9 | J9: =IF(ISNUMBER(C9),1-I9/C9,"")
A10: partner-yalepgc | B10: https://lendmaxcapital.ca/img/partner-yalepgc@2x.png | D10: Yale PGC LLP, Chartered Professional Accountants | E10: /, /performance-and-risk/, /how-to-invest/ | F10: /assets/img/partner-yalepgc-80.png | G10: PNG | H10: 279 | I10: 17.2 | J10: =IF(ISNUMBER(C10),1-I10/C10,"")
A11: partner-yalepgc | B11: https://lendmaxcapital.ca/img/partner-yalepgc@2x.png | D11: Yale PGC LLP, Chartered Professional Accountants | E11: /, /performance-and-risk/, /how-to-invest/ | F11: /assets/img/partner-yalepgc-80.webp | G11: WEBP | H11: 279 | I11: 9.9 | J11: =IF(ISNUMBER(C11),1-I11/C11,"")
A12: partner-drake | B12: https://lendmaxcapital.ca/img/partner-drake@2x.png | D12: Drake Financial Ltd., exempt market dealer | E12: /, /performance-and-risk/, /how-to-invest/ | F12: /assets/img/partner-drake-40.png | G12: PNG | H12: 102 | I12: 5.3 | J12: =IF(ISNUMBER(C12),1-I12/C12,"")
A13: partner-drake | B13: https://lendmaxcapital.ca/img/partner-drake@2x.png | D13: Drake Financial Ltd., exempt market dealer | E13: /, /performance-and-risk/, /how-to-invest/ | F13: /assets/img/partner-drake-40.webp | G13: WEBP | H13: 102 | I13: 1.7 | J13: =IF(ISNUMBER(C13),1-I13/C13,"")
A14: partner-drake | B14: https://lendmaxcapital.ca/img/partner-drake@2x.png | D14: Drake Financial Ltd., exempt market dealer | E14: /, /performance-and-risk/, /how-to-invest/ | F14: /assets/img/partner-drake-80.png | G14: PNG | H14: 205 | I14: 15 | J14: =IF(ISNUMBER(C14),1-I14/C14,"")
A15: partner-drake | B15: https://lendmaxcapital.ca/img/partner-drake@2x.png | D15: Drake Financial Ltd., exempt market dealer | E15: /, /performance-and-risk/, /how-to-invest/ | F15: /assets/img/partner-drake-80.webp | G15: WEBP | H15: 205 | I15: 3.8 | J15: =IF(ISNUMBER(C15),1-I15/C15,"")
A16: partner-olympia | B16: https://lendmaxcapital.ca/img/partner-olympia@2x.png | D16: Olympia Trust Company | E16: /, /performance-and-risk/, /how-to-invest/ | F16: /assets/img/partner-olympia-40.png | G16: PNG | H16: 83 | I16: 5 | J16: =IF(ISNUMBER(C16),1-I16/C16,"")
A17: partner-olympia | B17: https://lendmaxcapital.ca/img/partner-olympia@2x.png | D17: Olympia Trust Company | E17: /, /performance-and-risk/, /how-to-invest/ | F17: /assets/img/partner-olympia-40.webp | G17: WEBP | H17: 83 | I17: 1.9 | J17: =IF(ISNUMBER(C17),1-I17/C17,"")
A18: partner-olympia | B18: https://lendmaxcapital.ca/img/partner-olympia@2x.png | D18: Olympia Trust Company | E18: /, /performance-and-risk/, /how-to-invest/ | F18: /assets/img/partner-olympia-80.png | G18: PNG | H18: 166 | I18: 12.5 | J18: =IF(ISNUMBER(C18),1-I18/C18,"")
A19: partner-olympia | B19: https://lendmaxcapital.ca/img/partner-olympia@2x.png | D19: Olympia Trust Company | E19: /, /performance-and-risk/, /how-to-invest/ | F19: /assets/img/partner-olympia-80.webp | G19: WEBP | H19: 166 | I19: 4.1 | J19: =IF(ISNUMBER(C19),1-I19/C19,"")
... A23: partner-westernpacific | B23: https://lendmaxcapital.ca/img/partner-westernpacific@2x.png | D23: Western Pacific Trust Company | E23: /, /performance-and-risk/, /how-to-invest/ | F23: /assets/img/partner-westernpacific-80.webp | G23: WEBP | H23: 153 | I23: 2.2 | J23: =IF(ISNUMBER(C23),1-I23/C23,"")
A24: Share cards (og:image) | B24: Generated at build | D24: Page title on a navy card with the Lendmax logo | E24: Every page (97) | F24: /assets/og/<page>.png | G24: PNG | H24: 1200

Sheet External Links
A1: URL | B1: Status | C1: Resolves | D1: Note
A2: https://lautorite.qc.ca/en/general-public | B2: 403 | C2: Check by hand | D2: site blocks automated requests from the server's data-centre address (403) or is unreachable from it; opens normally in a browser — check by hand
A3: https://laws-lois.justice.gc.ca/eng/acts/I-3.3/section-130.1.html | B3: 200 | C3: Yes
A4: https://laws-lois.justice.gc.ca/eng/acts/I-3.3/section-207.01.html | B4: 200 | C4: Yes
A5: https://laws-lois.justice.gc.ca/eng/regulations/C.R.C.,_c._945/section-4900.html | B5: 200 | C5: Yes
A6: https://lendmaxcapital.ca/investor-portal | B6: 200 | C6: Yes
A7: https://lendmaxcapital.ca/investors/past-performance | B7: 200 | C7: Yes
A8: https://lendmaxcapital.ca/investors/published-papers | B8: 200 | C8: Yes
A9: https://mbsweblist.fsco.gov.on.ca/ShowLicence.aspx?13398~ | B9: 200 | C9: Yes
A10: https://www.albertasecurities.com/ | B10: 200 | C10: Yes
A11: https://www.bcfsa.ca/industry-resources/mortgage-broker-resources/mortgage-services-act | B11: 200 | C11: Yes
A12: https://www.bcsc.bc.ca/ | B12: 200 | C12: Yes
A13: https://www.canada.ca/en/revenue-agency.html | B13: timeout | C13: Check by hand | D13: site blocks automated requests from the server's data-centre address (403) or is unreachable from it; opens normally in a browser — check by hand
A14: https://www.canada.ca/en/revenue-agency/services/tax/technical-information/income-tax/income-tax-folios-index/series-3-property-investments-savings-plans/folio-10-registered-plans-similar-arrangements/income-tax-folio-s3-f10-c2-prohibited-investments-rrsps-rrifs-rdsps-resps-tfsas-fhsas.html | B14: timeout | C14: Check by hand | D14: site blocks automated requests from the server's data-centre address (403) or is unreachable from it; opens normally in a browser — check by hand
A15: https://www.cdic.ca/ | B15: 200 | C15: Yes
A16: https://www.cmhc-schl.gc.ca/professionals/housing-markets-data-and-research/housing-research/research-reports/housing-finance/residential-mortgage-industry-report | B16: 200 | C16: Yes
A17: https://www.fsrao.ca/ | B17: 403 | C17: Check by hand | D17: site blocks automated requests from the server's data-centre address (403) or is unreachable from it; opens normally in a browser — check by hand
A18: https://www.getsmarteraboutmoney.ca/ | B18: 200 | C18: Yes
A19: https://www.mbrcc.ca/ | B19: 200 | C19: Yes
A20: https://www.ontario.ca/laws/statute/06m29 | B20: 200 | C20: Yes
A21: https://www.ontario.ca/laws/statute/90m40 | B21: 200 | C21: Yes
A22: https://www.osc.ca/en/investors | B22: 200 | C22: Yes
A23: https://www.osc.ca/en/securities-law/instruments-rules-policies/4/45-106 | B23: 200 | C23: Yes
A24: https://www.reca.ca/ | B24: 200 | C24: Yes
A25: https://www.securities-administrators.ca/ | B25: 200 | C25: Yes
A26: https://www.securities-administrators.ca/investor-tools/check-registration-disciplinary-history/ | B26: 200 | C26: Yes
A28: Checked 3 October 2026, from the lmcmic.ca server, after launch.

Sheet Technical SEO
A1: Area | B1: Item | C1: Setting on lmcmic.ca | D1: Status | E1: Notes
A2: Domain | B2: Canonical origin | C2: https://lmcmic.ca (no www, HTTPS, trailing-slash URLs) | D2: Live | E2: Every other form 301s to it in one hop — see Redirects.
A3: Domain | B3: DNS | C3: A lmcmic.ca → 159.203.33.160; www → CNAME lmcmic.ca (Cloudflare, DNS only) | D3: Live | E3: Checked 2026-10-12.
A4: Domain | B4: TLS certificate | C4: Let's Encrypt for lmcmic.ca, www.lmcmic.ca, expires 2027-01-01 | D4: Live | E4: Renews automatically (certbot timer (automatic)). HSTS max-age one year.
A5: Hosting | B5: Server | C5: Lendmax server 159.203.33.160, nginx; static site + lead service | D5: Live | E5: Release 20261003-162939. Registered as site 'lmcmic' in the server's site tools.
A6: Crawling | B6: XML sitemap | C6: https://lmcmic.ca/sitemap.xml | D6: Live | E6: 97 URLs, lastmod on each, video entry on the home page, image entries for the photo pages.
A7: Crawling | B7: robots.txt | C7: Allow all; Disallow /api/; Sitemap line | D7: Live
A8: Crawling | B8: llms.txt | C8: https://lmcmic.ca/llms.txt | D8: Live | E8: Plain map of the site for AI answer engines.
A9: Crawling | B9: 404 page | C9: Custom 404 with links to key pages; noindex | D9: Live | E9: 404s in the access log are automated vulnerability scanners requesting files such as /.env and /.aws/credentials, many with a forged Googlebot user agent. No legitimate page URL is returning 404.
A10: Crawling | B10: Googlebot | C10: 22 successful fetches in today's log | D10: Live | E10: Verified crawls return 200.
A11: Indexing | B11: Canonical tags | C11: Self-referencing rel=canonical on every page | D11: Live | E11: See Pages, column Q.
A12: Indexing | B12: hreflang | C12: en-ca + x-default (self) | D12: Live
A13: Indexing | B13: Robots meta | C13: index, follow, max-image-preview:large, max-snippet:-1 | D13: Live | E13: 404 is noindex.
A14: Search Console | B14: Verification | C14: Meta tag on every page + DNS TXT google-site-verification | D14: Live | E14: TXT records present: 8OZ3VA1aZR…, 9yPV68WVfj….
A15: Search Console | B15: Sitemap submitted | C15: Submit https://lmcmic.ca/sitemap.xml under Sitemaps | D15: To confirm | E15: Confirm in Search Console that it shows 'Success' and 97 discovered URLs.
A16: Analytics | B16: Google Analytics 4 | C16: Measurement ID G-LH6HY77BEY (property 255904887) | D16: Live | E16: Loaded from site.js so the security policy still blocks inline script. Form submits send generate_lead.
A17: Structured data | B17: Types in use | C17: Article, BreadcrumbList, CollectionPage, ContactPage, DefinedTermSet, FAQPage, FinancialService, HowTo, Organization, VideoObject, WebApplication, WebSite | D17: Live | E17: Only marks up what the page shows.
A18: Performance | B18: CSS / JS | C18: Tailwind compiled at build (~40 KB), one deferred script, no CDN script | D18: Live
A19: Performance | B19: Icons | C19: Material Symbols subset to the glyphs used; fixed 1em box (no layout shift) | D19: Live
A20: Performance | B20: Images | C20: AVIF / WebP / JPEG with srcset, width/height, lazy loading | D20: Live | E20: See Images.
A21: Performance | B21: Video | C21: YouTube loads only on click (facade); VideoObject uploadDate 2021-12-31 | D21: Live
A22: Security | B22: Headers | C22: HSTS, CSP (no inline script), X-Frame-Options DENY, nosniff, Referrer-Policy, Permissions-Policy | D22: Live
A23: Leads | B23: Contact form | C23: POST /api/lead → stored → email deals@lendmaxcapital.ca → redirect https://app.lendmaxcapital.ca/investor-start | D23: Live | E23: Email via FormSubmit (activated). For sending from your own domain, add a Resend/Postmark/SendGrid key.
A24: Email DNS | B24: SPF | C24: v=spf1 a mx ~all | D24: Live | E24: Single SPF record (duplicate removed).
A25: Content | B25: Legal review | C25: Legal and regulatory review completed by Lendmax Capital and confirmed to the site build on 3 October 2026. | D25: Done | E25: Shown in every article byline.
A26: Content | B26: Next scheduled review | C26: January 2027 | D26: Scheduled | E26: Returns figures and regulatory pages: review quarterly (Tab 3 L14).

Sheet SEO Checklist
A1: Section | B1: Ref | C1: Requirement | D1: What good looks like | E1: Owner | F1: Status on lmcmic.ca | G1: How lmcmic.ca applies it
A2: A. Research first — before a word is written | B2: 1 | C2: Identify the primary search intent. | D2: One sentence naming what the searcher wants: to understand, to compare, to assess risk, or to act. Written at the top of the brief, not inferred later. | E2: Writer | F2: Applied | G2: Keywords, intent and verification notes come from the workbook per article (plan.json); primary statutes and regulator pages were fetched and checked on 3 Oct 2026; legal review completed 3 Oct 2026.
A3: A. Research first — before a word is written | B3: 2 | C3: Select one primary keyword and appropriate secondary / semantic keywords from Tab 1. | D3: Exactly one primary. Three to six secondaries drawn from the same Tab 1 cluster. One long-tail question phrased the way investors actually phrase it. | E3: SEO lead | F3: Applied | G3: Keywords, intent and verification notes come from the workbook per article (plan.json); primary statutes and regulator pages were fetched and checked on 3 Oct 2026; legal review completed 3 Oct 2026.
A4: A. Research first — before a word is written | B4: 3 | C4: Research current Canadian information from authoritative sources. | D4: Regulator sites, statutes, CMHC and provincial regulator reports, CRA. Not competitor blog posts, and not the model's own recall. | E4: Writer | F4: Applied | G4: Keywords, intent and verification notes come from the workbook per article (plan.json); primary statutes and regulator pages were fetched and checked on 3 Oct 2026; legal review completed 3 Oct 2026.
A5: A. Research first — before a word is written | B5: 4 | C5: Verify rates, regulations, taxation and other time-sensitive information before publication. | D5: Every such claim traced to its own primary source on the day of writing. Regulator names and statute titles checked against the regulator's own page. | E5: Writer | F5: Applied | G5: Keywords, intent and verification notes come from the workbook per article (plan.json); primary statutes and regulator pages were fetched and checked on 3 Oct 2026; legal review completed 3 Oct 2026.
A6: A. Research first — before a word is written | B6: 5 | C6: Cite authoritative sources. | D6: Inline attribution a reader can follow, plus a source list. Statute sections cited by number. | E6: Writer | F6: Applied | G6: Keywords, intent and verification notes come from the workbook per article (plan.json); primary statutes and regulator pages were fetched and checked on 3 Oct 2026; legal review completed 3 Oct 2026.
A7: A. Research first — before a word is written | B7: 6 | C7: State the date or period applicable to time-sensitive statistics. | D7: "As at Q3 2025" or "for the 2024 calendar year", beside the figure — not only in a footer. | E7: Editor | F7: Applied | G7: Keywords, intent and verification notes come from the workbook per article (plan.json); primary statutes and regulator pages were fetched and checked on 3 Oct 2026; legal review completed 3 Oct 2026.
A8: B. Structure and on-page | B8: 7 | C8: Answer the primary search question early. | D8: A direct answer inside the first 120 words, before any context or background. If the honest answer is 'it depends', say what it depends on immediately. | E8: Writer | F8: Applied | G8: Short-answer box first (QA K1); one H1 with the primary keyword (97/97 pages); question-led H2s, no heading jumps (QA K2); terms defined at first use and linked to the 121-term glossary.
A9: B. Structure and on-page | B9: 8 | C9: Use a clear H1. | D9: One H1 per page, containing the primary keyword, readable as a human sentence rather than a keyword string. | E9: Writer | F9: Applied | G9: Short-answer box first (QA K1); one H1 with the primary keyword (97/97 pages); question-led H2s, no heading jumps (QA K2); terms defined at first use and linked to the 121-term glossary.
A10: B. Structure and on-page | B10: 9 | C10: Create logically structured H2 and H3 sections. | D10: H2s that each answer a distinct question and make sense read in isolation. No heading-level jumps. | E10: Editor | F10: Applied | G10: Short-answer box first (QA K1); one H1 with the primary keyword (97/97 pages); question-led H2s, no heading jumps (QA K2); terms defined at first use and linked to the 121-term glossary.
A11: B. Structure and on-page | B11: 10 | C11: Use the primary keyword naturally in the title, introduction and relevant headings. | D11: Present where it belongs and absent where it would read oddly. Natural variants count. | E11: Writer | F11: Applied | G11: Short-answer box first (QA K1); one H1 with the primary keyword (97/97 pages); question-led H2s, no heading jumps (QA K2); terms defined at first use and linked to the 121-term glossary.
A12: B. Structure and on-page | B12: 11 | C12: Avoid keyword stuffing. | D12: No repetition that a careful human writer would not have produced. | E12: Editor | F12: Applied | G12: Short-answer box first (QA K1); one H1 with the primary keyword (97/97 pages); question-led H2s, no heading jumps (QA K2); terms defined at first use and linked to the 121-term glossary.
... A126: L. Time-sensitive review register — scheduled re-checks | B126: L14 | C126: Any published return, yield or rate figure | D126: Ages fastest of anything on the site and carries the most compliance risk. | E126: Legal / licensed reviewer | F126: Monitor | G126: Time-sensitive items: re-check on the dates given. L1 (BC Mortgage Services Act, in force 13 Oct 2026): update the BC pages from 'scheduled to come into force' to 'in force' and confirm licence categories with BCFSA.
