Workbook

Sheet Instasure Topic Plan
A1: Product | B1: Mortgage Protection | C1: Term Life Insurance | D1: Life Insurance Basics & Buying | E1: Life Insurance Basics & Buying | F1: Life Insurance Basics & Buying | G1: Permanent & Whole Life | H1: No Medical & Instant Life | I1: Health Insurance | J1: No Medical & Instant Life | K1: Critical Illness | L1: Family Life Insurance | M1: Life Insurance with Medical Conditions | N1: Life Insurance with Medical Conditions | O1: Permanent & Whole Life | P1: Term Life Insurance | Q1: Final Expense | R1: Family Life Insurance | S1: Seniors (50+) | T1: Seniors (50+) | U1: Term Life Insurance | V1: Universal Life | W1: Life Insurance Basics & Buying | X1: Life Insurance Basics & Buying | Y1: Life Insurance Basics & Buying | Z1: Life Insurance with Medical Conditions | AA1: Permanent & Whole Life | AB1: Life Insurance Basics & Buying | AC1: Life Insurance with Medical Conditions | AD1: Permanent & Whole Life | AE1: Seniors (50+) | AF1: Term Life Insurance | AG1: Universal Life | AH1: Final Expense | AI1: Family Life Insurance | AJ1: Joint Life | AK1: Life Insurance with Medical Conditions | AL1: Life Insurance with Medical Conditions | AM1: Life Insurance Basics & Buying | AN1: Life Insurance Basics & Buying | AO1: Life Insurance Basics & Buying | AP1: Critical Illness | AQ1: Family Life Insurance | AR1: Family Life Insurance | AS1: Health Insurance | AT1: Health Insurance | AU1: Joint Life | AV1: Life Insurance with Medical Conditions | AW1: Term Life Insurance | AX1: Life Insurance Basics & Buying | AY1: Final Expense | AZ1: Family Life Insurance | BA1: Joint Life | BB1: Mortgage Protection | BC1: No Medical & Instant Life
A2: Topic (H1) | B2: Mortgage Insurance in Canada: Default Insurance vs Mortgage Life Insurance Explained | C2: What Is Term Life Insurance and How Does It Work in Canada? | D2: How Does Life Insurance Work in Canada? Premiums, Payouts and Policies Explained | E2: Types of Life Insurance in Canada: Term, Whole, Universal and No-Medical Explained | F2: Is Life Insurance Worth It in Canada? When You Need It and When You Don't | G2: How Much Does Whole Life Insurance Cost in Canada? | H2: Instant Life Insurance in Canada: How Online Approval Works and How Products Compare | I2: Health Insurance After Losing Your Job: Conversion Plans and Your Options | J2: Declined for Life Insurance? Why It Happens and What to Do Next in Canada | K2: Is Critical Illness Insurance Worth It in Canada? A Decision Guide | L2: Family Life Insurance in Canada: How to Protect Everyone You Love | M2: Life Insurance With Pre-Existing Conditions in Canada: Your Options | N2: Life Insurance Medical Exams and Applications: What Insurers Ask and How to Prepare | O2: Term 100 Life Insurance in Canada: Lifetime Cover Without the Cash Value | P2: 10, 20 or 30-Year Term Life Insurance: How to Choose the Right Length | Q2: Funeral Insurance for Seniors: What You Can Buy at 60, 70 and 80 | R2: How to Choose a Life Insurance Beneficiary in Canada: Spouses, Children, Estates and Trusts | S2: Life Insurance Over 70 in Canada: Options, Age Limits and Costs | T2: Life Insurance Over 50 in Canada: Costs, Types and How Much You Need | U2: What Happens When Term Life Insurance Expires? Renewal, Conversion and Your Options | V2: Whole Life vs Universal Life Insurance: How They Differ in Canada | W2: How to Make a Life Insurance Claim in Canada: Steps, Documents and Timelines | X2: Life Insurance Riders in Canada: Which Add-Ons Are Worth Paying For? | Y2: What Does Life Insurance Not Cover? Exclusions Every Canadian Should Know | Z2: Life Insurance With Diabetes in Canada: Type 1, Type 2 and What Underwriters Look For | AA2: Participating Whole Life Insurance: Dividends, Cash Value and Surrender Value Explained | AB2: What Affects Life Insurance Rates in Canada? How Quotes Are Calculated | AC2: Life Insurance After Cancer in Canada: Waiting Periods, Remission and Your Options | AD2: Buy Term and Invest the Difference: Does It Work in Canada? | AE2: Using Life Insurance for Estate Planning in Canada: Capital Gains at Death, Cottages and Inheritances | AF2: Decreasing Term vs Level Term Life Insurance for Your Mortgage | AG2: How Does Universal Life Insurance Work in Canada? | AH2: Funeral Insurance With No Medical Exam: How to Qualify and What It Costs | AI2: Life Insurance for New Parents in Canada: How Much, What Type and When to Buy | AJ2: Funding a Buy-Sell Agreement With Life Insurance: A Guide for Canadian Business Owners | AK2: Life Insurance After a Heart Attack or With Heart Disease in Canada | AL2: How Life Insurance Companies Check Your Medical History in Canada | AM2: Life Insurance Broker vs Agent vs Bank vs Online: Where Should You Buy? | AN2: How to Choose a Life Insurance Company in Canada: What Actually Matters | AO2: Is Group Life Insurance Enough? Work Coverage, Top-Ups and What Happens When You Leave | AP2: How Much Critical Illness Insurance Do I Need? | AQ2: Is Children's Life Insurance Worth It? Pros, Cons and Alternatives in Canada | AR2: Life Insurance for Stay-at-Home Parents: What Their Work Is Worth | AS2: Health Insurance for Early Retirees: Bridging the Gap Before 65 | AT2: Guaranteed-Issue vs Underwritten Health Insurance: Pre-Existing Conditions Explained | AU2: Joint vs Individual Life Insurance: What Couples Should Choose | AV2: Life Insurance With Depression or Anxiety in Canada: How Mental Health Is Underwritten | AW2: How to Convert Term Life Insurance to Permanent in Canada | AX2: 12 Life Insurance Myths Canadians Still Believe (and the Facts) | AY2: Funeral Insurance Waiting Periods: How the Two-Year Rule Works | AZ2: Life Insurance for Young Adults: Should You Buy in Your 20s? | BA2: Joint Last-to-Die Life Insurance: How Couples Cover Estate Taxes | BB2: Joint Mortgage Life Insurance: What Couples Need to Know Before They Sign | BC2: Life Insurance Rating Classes Explained: Preferred, Standard and Rated
A3: Priority (1 = do first) | B3: ='Topic Index'!I5 -> 1 | C3: ='Topic Index'!I6 -> 1 | D3: ='Topic Index'!I7 -> 1 | E3: ='Topic Index'!I8 -> 1 | F3: ='Topic Index'!I9 -> 1 | G3: ='Topic Index'!I10 -> 1 | H3: ='Topic Index'!I11 -> 1 | I3: ='Topic Index'!I12 -> 1 | J3: ='Topic Index'!I13 -> 1 | K3: ='Topic Index'!I14 -> 2 | L3: ='Topic Index'!I15 -> 2 | M3: ='Topic Index'!I16 -> 2 | N3: ='Topic Index'!I17 -> 2 | O3: ='Topic Index'!I18 -> 2 | P3: ='Topic Index'!I19 -> 2 | Q3: ='Topic Index'!I20 -> 2 | R3: ='Topic Index'!I21 -> 2 | S3: ='Topic Index'!I22 -> 2 | T3: ='Topic Index'!I23 -> 2 | U3: ='Topic Index'!I24 -> 2 | V3: ='Topic Index'!I25 -> 2 | W3: ='Topic Index'!I26 -> 2 | X3: ='Topic Index'!I27 -> 2 | Y3: ='Topic Index'!I28 -> 2 | Z3: ='Topic Index'!I29 -> 2 | AA3: ='Topic Index'!I30 -> 2 | AB3: ='Topic Index'!I31 -> 2 | AC3: ='Topic Index'!I32 -> 2 | AD3: ='Topic Index'!I33 -> 2 | AE3: ='Topic Index'!I34 -> 2 | AF3: ='Topic Index'!I35 -> 2 | AG3: ='Topic Index'!I36 -> 2 | AH3: ='Topic Index'!I37 -> 3 | AI3: ='Topic Index'!I38 -> 3 | AJ3: ='Topic Index'!I39 -> 3 | AK3: ='Topic Index'!I40 -> 3 | AL3: ='Topic Index'!I41 -> 3 | AM3: ='Topic Index'!I42 -> 3 | AN3: ='Topic Index'!I43 -> 3 | AO3: ='Topic Index'!I44 -> 3 | AP3: ='Topic Index'!I45 -> 3 | AQ3: ='Topic Index'!I46 -> 3 | AR3: ='Topic Index'!I47 -> 3 | AS3: ='Topic Index'!I48 -> 3 | AT3: ='Topic Index'!I49 -> 3 | AU3: ='Topic Index'!I50 -> 3 | AV3: ='Topic Index'!I51 -> 3 | AW3: ='Topic Index'!I52 -> 3 | AX3: ='Topic Index'!I53 -> 3 | AY3: ='Topic Index'!I54 -> 3 | AZ3: ='Topic Index'!I55 -> 3 | BA3: ='Topic Index'!I56 -> 3 | BB3: ='Topic Index'!I57 -> 3 | BC3: ='Topic Index'!I58 -> 3
A4: Traffic rank (of 54) | B4: ='Topic Index'!J5 -> 1 | C4: ='Topic Index'!J6 -> 2 | D4: ='Topic Index'!J7 -> 3 | E4: ='Topic Index'!J8 -> 3 | F4: ='Topic Index'!J9 -> 5 | G4: ='Topic Index'!J10 -> 5 | H4: ='Topic Index'!J11 -> 7 | I4: ='Topic Index'!J12 -> 20 | J4: ='Topic Index'!J13 -> 32 | K4: ='Topic Index'!J14 -> 8 | L4: ='Topic Index'!J15 -> 8 | M4: ='Topic Index'!J16 -> 8 | N4: ='Topic Index'!J17 -> 8 | O4: ='Topic Index'!J18 -> 8 | P4: ='Topic Index'!J19 -> 8 | Q4: ='Topic Index'!J20 -> 14 | R4: ='Topic Index'!J21 -> 14 | S4: ='Topic Index'!J22 -> 14 | T4: ='Topic Index'!J23 -> 14 | U4: ='Topic Index'!J24 -> 14 | V4: ='Topic Index'!J25 -> 14 | W4: ='Topic Index'!J26 -> 20 | X4: ='Topic Index'!J27 -> 20 | Y4: ='Topic Index'!J28 -> 20 | Z4: ='Topic Index'!J29 -> 20 | AA4: ='Topic Index'!J30 -> 20 | AB4: ='Topic Index'!J31 -> 26 | AC4: ='Topic Index'!J32 -> 26 | AD4: ='Topic Index'!J33 -> 26 | AE4: ='Topic Index'!J34 -> 26 | AF4: ='Topic Index'!J35 -> 26 | AG4: ='Topic Index'!J36 -> 26 | AH4: ='Topic Index'!J37 -> 32 | AI4: ='Topic Index'!J38 -> 32 | AJ4: ='Topic Index'!J39 -> 32 | AK4: ='Topic Index'!J40 -> 32 | AL4: ='Topic Index'!J41 -> 32 | AM4: ='Topic Index'!J42 -> 38 | AN4: ='Topic Index'!J43 -> 38 | AO4: ='Topic Index'!J44 -> 38 | AP4: ='Topic Index'!J45 -> 38 | AQ4: ='Topic Index'!J46 -> 38 | AR4: ='Topic Index'!J47 -> 38 | AS4: ='Topic Index'!J48 -> 38 | AT4: ='Topic Index'!J49 -> 38 | AU4: ='Topic Index'!J50 -> 38 | AV4: ='Topic Index'!J51 -> 38 | AW4: ='Topic Index'!J52 -> 38 | AX4: ='Topic Index'!J53 -> 49 | AY4: ='Topic Index'!J54 -> 49 | AZ4: ='Topic Index'!J55 -> 49 | BA4: ='Topic Index'!J56 -> 49 | BB4: ='Topic Index'!J57 -> 53 | BC4: ='Topic Index'!J58 -> 53
A5: Monthly searches (modelled) | B5: ='Topic Index'!E5 -> 1900 | C5: ='Topic Index'!E6 -> 1000 | D5: ='Topic Index'!E7 -> 880 | E5: ='Topic Index'!E8 -> 880 | F5: ='Topic Index'!E9 -> 720 | G5: ='Topic Index'!E10 -> 720 | H5: ='Topic Index'!E11 -> 590 | I5: ='Topic Index'!E12 -> 320 | J5: ='Topic Index'!E13 -> 210 | K5: ='Topic Index'!E14 -> 480 | L5: ='Topic Index'!E15 -> 480 | M5: ='Topic Index'!E16 -> 480 | N5: ='Topic Index'!E17 -> 480 | O5: ='Topic Index'!E18 -> 480 | P5: ='Topic Index'!E19 -> 480 | Q5: ='Topic Index'!E20 -> 390 | R5: ='Topic Index'!E21 -> 390 | S5: ='Topic Index'!E22 -> 390 | T5: ='Topic Index'!E23 -> 390 | U5: ='Topic Index'!E24 -> 390 | V5: ='Topic Index'!E25 -> 390 | W5: ='Topic Index'!E26 -> 320 | X5: ='Topic Index'!E27 -> 320 | Y5: ='Topic Index'!E28 -> 320 | Z5: ='Topic Index'!E29 -> 320 | AA5: ='Topic Index'!E30 -> 320 | AB5: ='Topic Index'!E31 -> 260 | AC5: ='Topic Index'!E32 -> 260 | AD5: ='Topic Index'!E33 -> 260 | AE5: ='Topic Index'!E34 -> 260 | AF5: ='Topic Index'!E35 -> 260 | AG5: ='Topic Index'!E36 -> 260 | AH5: ='Topic Index'!E37 -> 210 | AI5: ='Topic Index'!E38 -> 210 | AJ5: ='Topic Index'!E39 -> 210 | AK5: ='Topic Index'!E40 -> 210 | AL5: ='Topic Index'!E41 -> 210 | AM5: ='Topic Index'!E42 -> 170 | AN5: ='Topic Index'!E43 -> 170 | AO5: ='Topic Index'!E44 -> 170 | AP5: ='Topic Index'!E45 -> 170 | AQ5: ='Topic Index'!E46 -> 170 | AR5: ='Topic Index'!E47 -> 170 | AS5: ='Topic Index'!E48 -> 170 | AT5: ='Topic Index'!E49 -> 170 | AU5: ='Topic Index'!E50 -> 170 | AV5: ='Topic Index'!E51 -> 170 | AW5: ='Topic Index'!E52 -> 170 | AX5: ='Topic Index'!E53 -> 140 | AY5: ='Topic Index'!E54 -> 140 | AZ5: ='Topic Index'!E55 -> 140 | BA5: ='Topic Index'!E56 -> 140 | BB5: ='Topic Index'!E57 -> 110 | BC5: ='Topic Index'!E58 -> 110
A6: Primary keyword | B6: mortgage insurance canada | C6: what is term life insurance | D6: how does life insurance work | E6: types of life insurance canada | F6: is life insurance worth it | G6: whole life insurance cost | H6: instant life insurance canada | I6: health insurance after losing job canada | J6: declined for life insurance | K6: is critical illness insurance worth it | L6: family life insurance | M6: life insurance with pre existing conditions | N6: life insurance medical exam | O6: term 100 life insurance | P6: 20 year term life insurance | Q6: funeral insurance for seniors | R6: life insurance beneficiary canada | S6: life insurance over 70 | T6: life insurance over 50 | U6: what happens when term life insurance expires | V6: whole life vs universal life insurance | W6: how to claim life insurance canada | X6: life insurance riders | Y6: what does life insurance not cover | Z6: life insurance for diabetics | AA6: participating whole life insurance | AB6: what affects life insurance rates | AC6: life insurance after cancer | AD6: buy term and invest the difference | AE6: life insurance for estate planning canada | AF6: decreasing term life insurance | AG6: how does universal life insurance work | AH6: funeral insurance no medical | AI6: life insurance for new parents | AJ6: buy sell agreement life insurance | AK6: life insurance after heart attack | AL6: how do life insurance companies check medical history | AM6: life insurance broker vs agent | AN6: how to choose a life insurance company | AO6: is group life insurance enough | AP6: how much critical illness insurance do i need | AQ6: is children's life insurance worth it | AR6: life insurance for stay at home parent | AS6: health insurance for early retirees canada | AT6: guaranteed issue health insurance | AU6: joint vs individual life insurance | AV6: life insurance with depression | AW6: convert term life insurance to permanent | AX6: life insurance myths | AY6: funeral insurance waiting period | AZ6: life insurance for young adults | BA6: joint last to die life insurance | BB6: joint mortgage life insurance | BC6: life insurance rating classes
A7: SEO title tag | B7: Mortgage Insurance in Canada: CMHC vs Mortgage Life Cover | C7: What Is Term Life Insurance? How It Works in Canada | D7: How Does Life Insurance Work in Canada? A Simple Guide | E7: Types of Life Insurance in Canada: Every Option Explained | F7: Is Life Insurance Worth It in Canada? A Plain Answer | G7: Whole Life Insurance Cost in Canada: Example Premiums | H7: Instant Life Insurance in Canada: Online Options Compared | I7: Health Insurance After Losing Your Job in Canada | J7: Declined for Life Insurance? What to Do Next (Canada) | K7: Is Critical Illness Insurance Worth It? Canada Guide | L7: Family Life Insurance in Canada: How to Cover Everyone | M7: Life Insurance With Pre-Existing Conditions in Canada | N7: Life Insurance Medical Exam: What to Expect in Canada | O7: Term 100 Life Insurance in Canada: How It Works | P7: 20 Year Term Life Insurance vs 10 and 30-Year Terms | Q7: Funeral Insurance for Seniors in Canada: Options by Age | R7: Choosing a Life Insurance Beneficiary in Canada | S7: Life Insurance Over 70 in Canada: Options and Age Limits | T7: Life Insurance Over 50 in Canada: Costs and Options | U7: What Happens When Term Life Insurance Expires? | V7: Whole Life vs Universal Life Insurance in Canada | W7: How to Claim Life Insurance in Canada: Step by Step | X7: Life Insurance Riders in Canada: What Each Add-On Does | Y7: What Does Life Insurance Not Cover? Canadian Exclusions | Z7: Life Insurance for Diabetics in Canada: Type 1 and 2 | AA7: Participating Whole Life Insurance and Cash Value | AB7: What Affects Life Insurance Rates in Canada? Key Factors | AC7: Life Insurance After Cancer in Canada: Options by Stage | AD7: Buy Term and Invest the Difference in Canada: Does It Work? | AE7: Life Insurance for Estate Planning in Canada: A Guide | AF7: Decreasing Term Life Insurance vs Level Term (Canada) | AG7: How Does Universal Life Insurance Work in Canada? | AH7: Funeral Insurance With No Medical Exam: How to Qualify | AI7: Life Insurance for New Parents in Canada: A Clear Plan | AJ7: Buy-Sell Agreement Life Insurance: Owner's Guide (Canada) | AK7: Life Insurance After a Heart Attack in Canada: Options | AL7: How Life Insurance Companies Check Your Medical History | AM7: Life Insurance Broker vs Agent vs Bank: Where to Buy | AN7: How to Choose a Life Insurance Company in Canada | AO7: Is Group Life Insurance Enough? Work Cover vs Your Own | AP7: How Much Critical Illness Insurance Do I Need? | AQ7: Is Children's Life Insurance Worth It? Pros and Cons | AR7: Life Insurance for Stay-at-Home Parents in Canada | AS7: Health Insurance for Early Retirees in Canada (Under 65) | AT7: Guaranteed Issue Health Insurance vs Underwritten | AU7: Joint vs Individual Life Insurance for Couples (Canada) | AV7: Life Insurance With Depression or Anxiety in Canada | AW7: Convert Term Life Insurance to Permanent: How It Works | AX7: 12 Life Insurance Myths Canadians Still Believe | AY7: Funeral Insurance Waiting Periods: The Two-Year Rule | AZ7: Life Insurance for Young Adults: Should You Buy in Your 20s? | BA7: Joint Last-to-Die Life Insurance: Estate Tax Guide | BB7: Joint Mortgage Life Insurance: A Guide for Couples | BC7: Life Insurance Rating Classes: Preferred to Rated
A8: Title length (target 45–60) | B8: =LEN(B7) -> 57 | C8: =LEN(C7) -> 51 | D8: =LEN(D7) -> 54 | E8: =LEN(E7) -> 57 | F8: =LEN(F7) -> 52 | G8: =LEN(G7) -> 53 | H8: =LEN(H7) -> 57 | I8: =LEN(I7) -> 48 | ... BC8: =LEN(BC7) -> 49
A9: Meta description | B9: Mortgage insurance in Canada explained: CMHC default insurance vs mortgage life insurance, who each protects, what is mandatory and when term life fits. | C9: What is term life insurance? How 10, 20 and 30-year terms work in Canada, what drives the price, renewal and conversion, pros and cons, and who it suits. | D9: How does life insurance work in Canada? Premiums, death benefits, beneficiaries, term vs permanent, how insurers price risk, taxes and how a claim gets paid. | E9: Types of life insurance in Canada: term, term to 100, whole, universal, no-medical, joint, group and creditor cover, with a comparison table and tips. | F9: Is life insurance worth it in Canada? Who usually needs it, who may not, what to check before cancelling, cheaper ways to stay covered and a self-test. | G9: Whole life insurance cost in Canada: example premiums by age and amount, lifetime vs 20-pay, par vs non-par, and ways to make permanent cover affordable. | H9: Instant life insurance in Canada: how online approval works, issue ages and maximums, the health questions, when instant costs more and how to apply safely. | I9: Health insurance after losing your job in Canada: how long group benefits last, no-medical conversion plans, new plan costs, a spouse's plan and a checklist. | J9: Declined for life insurance in Canada? What declined, postponed and rated mean, how to get the reason, the MIB, reapplying and no-medical options. | K9: Is critical illness insurance worth it in Canada? Costs health plans don't pay, who benefits most, when to skip it and a five-question decision test. | L9: Family life insurance in Canada: why one policy rarely covers everyone, options for parents, couples and children, a comparison table and how to buy. | M9: Life insurance with pre-existing conditions in Canada: how underwriters assess health issues, why disclosure matters, no-medical options and better odds. | N9: Life insurance medical exam in Canada: what the paramedical exam involves, blood and urine tests, doctor reports, underwriting time and how to prepare. | O9: Term 100 life insurance in Canada: lifetime cover, level premiums and no cash value. How it compares with whole and universal life, what it costs, who it suits. | P9: 20 year term life insurance vs 10 and 30-year terms in Canada: price differences, matching your mortgage and kids, laddering and a term length decision table. | Q9: Funeral insurance for seniors in Canada: options at 60, 70 and 80, simplified vs guaranteed issue, labelled cost estimates by age and replacing group life. | R9: Choosing a life insurance beneficiary in Canada: revocable vs irrevocable, minor children, contingent and multiple beneficiaries, your estate and Quebec rules. | S9: Life insurance over 70 in Canada: policies you can still buy, age limits at 75, 80 and 85, no-medical and guaranteed issue options, costs and if it's worth it. | T9: Life insurance over 50 in Canada: example rates by age and amount, term vs permanent, no-medical options, health factors after 50 and how much cover you need. | U9: What happens when term life insurance expires in Canada: renewal rates, converting to permanent without a medical, buying a new policy or letting it lapse. | V9: Whole life vs universal life insurance in Canada: guarantees, cash value, investment options, level vs YRT cost of insurance, tax rules and who each one suits. | W9: How to claim life insurance in Canada: find the policy, gather documents, submit forms, typical payout times, the two-year rule and denied claims. | X9: Life insurance riders in Canada: waiver of premium, child term, guaranteed insurability, critical illness and accidental death, with costs and who each suits. | Y9: What life insurance does not cover in Canada: the suicide clause, the two-year contestability rule, misrepresentation, lapses, accidental death limits. | Z9: Life insurance for diabetics in Canada: how type 1 or 2, A1C, age at diagnosis and complications affect rates, no-medical options and an application checklist. | AA9: Participating whole life insurance in Canada: how dividends and cash value grow, surrender value, policy loans, paid-up additions and when a par policy fits. | AB9: What affects life insurance rates in Canada: age, sex, health, smoking, family history, job, hobbies, driving record, amount and term, and how quotes work. | AC9: Life insurance after cancer in Canada: how type, stage and time since treatment affect approval, typical waiting periods, no-medical options and records. | AD9: Buy term and invest the difference, or whole life? A worked Canadian TFSA example, the discipline risk, taxes and the cases where permanent cover wins. | AE9: Life insurance for estate planning in Canada: covering tax on capital gains at death, keeping the cottage, equalising inheritances, charity and probate. | AF9: Decreasing term life insurance vs level term in Canada: how each works, the cost over a 25-year mortgage, where lender insurance fits and which to choose. | AG9: How universal life insurance works in Canada: cost of insurance, the investment account, flexible deposits, tax-exempt growth, the risks and how to buy. | AH9: Funeral insurance with no medical exam in Canada: the health questions simplified plans ask, when guaranteed acceptance fits and how health changes cost. | AI9: Life insurance for new parents in Canada: how much cover a family with a baby needs, insuring a stay-at-home parent, parental leave and a checklist. | AJ9: Buy-sell agreement life insurance in Canada: funding a partner buyout, cross-purchase vs corporate-owned policies, the capital dividend account and sizing. | AK9: Life insurance after a heart attack in Canada: waiting times, stents and bypass, the tests underwriters ask for and no-medical options while you recover. | AL9: How life insurance companies check your medical history in Canada: health questions, the MIB, doctor reports, prescriptions, exams and the two-year rule. | AM9: Life insurance broker vs agent vs bank vs online in Canada: insurer choice, advice, underwriting help, how each is paid and the questions to ask before you buy. | AN9: How to choose a life insurance company in Canada: financial strength, claims practices, Assuris protection, complaint records, products and service. | AO9: Is group life insurance enough in Canada? What work plans pay, optional top-ups, what happens when you leave or are laid off, conversion and sizing. | AP9: How much critical illness insurance do you need in Canada? A three-step worksheet for income, uncovered costs and debts, plus term choices and group cover. | AQ9: Is children's life insurance worth it in Canada? What it covers, the case for and against, child riders and RESPs as alternatives, and grandparent policies. | AR9: Life insurance for stay-at-home parents in Canada: what unpaid work costs to replace, how much cover to buy, term vs permanent and what it costs. | AS9: Health insurance for early retirees in Canada: retiree benefits, converting a group plan, plan costs from 55 to 64, drug coverage before 65 and travel cover. | AT9: Guaranteed issue health insurance vs underwritten plans in Canada: pre-existing conditions, drug coverage limits, conversion plans and how to choose. | AU9: Joint vs individual life insurance for Canadian couples: first-to-die vs last-to-die, cost, the single payout, separation and a couple's decision guide. | AV9: Life insurance with depression or anxiety in Canada: what underwriters ask, how severity, medication and time off work count, and how to apply with confidence. | AW9: How to convert term life insurance to permanent in Canada: conversion deadlines, no-medical eligibility, which plans qualify and what the new premium costs. | AX9: Twelve life insurance myths debunked for Canadians: cost, medical exams, group cover, stay-at-home parents, age, health, investing and salary rules. | AY9: Funeral insurance waiting periods in Canada: how the two-year rule and graded benefits work, accidental death cover and how to avoid a waiting period. | AZ9: Life insurance for young adults in Canada: when buying in your 20s makes sense, locking in rates and insurability, what it costs, and when you can safely wait. | BA9: Joint last-to-die life insurance in Canada: how it pays at the second death, covering the tax on a cottage or RRIF, cost vs two policies and who it suits. | BB9: Joint mortgage life insurance in Canada pays once: what that means for the surviving partner, separation and refinancing, and how two term policies compare. | BC9: Life insurance rating classes in Canada: preferred plus, preferred, standard and table ratings, how BMI, blood pressure and family history count, and cost.
A10: Meta length (target 140–160) | B10: =LEN(B9) -> 152 | C10: =LEN(C9) -> 153 | D10: =LEN(D9) -> 157 | E10: =LEN(E9) -> 150 | F10: =LEN(F9) -> 151 | G10: =LEN(G9) -> 153 | H10: =LEN(H9) -> 156 | I10: =LEN(I9) -> 157 | ... BC10: =LEN(BC9) -> 155
A11: URL | B11: https://instasure.ca/guides/mortgage-insurance-canada-explained/ | C11: https://instasure.ca/guides/what-is-term-life-insurance-canada/ | D11: https://instasure.ca/guides/how-does-life-insurance-work-canada/ | E11: https://instasure.ca/guides/types-of-life-insurance-canada/ | F11: https://instasure.ca/guides/is-life-insurance-worth-it-canada/ | G11: https://instasure.ca/guides/whole-life-insurance-cost-canada/ | H11: https://instasure.ca/guides/instant-life-insurance-canada/ | I11: https://instasure.ca/guides/health-insurance-after-losing-job/ | J11: https://instasure.ca/guides/declined-for-life-insurance-what-next/ | K11: https://instasure.ca/guides/is-critical-illness-insurance-worth-it/ | L11: https://instasure.ca/guides/family-life-insurance-canada/ | M11: https://instasure.ca/guides/life-insurance-pre-existing-conditions-canada/ | N11: https://instasure.ca/guides/life-insurance-medical-exam-application/ | O11: https://instasure.ca/guides/term-100-life-insurance-canada/ | P11: https://instasure.ca/guides/10-20-30-year-term-life-insurance/ | Q11: https://instasure.ca/guides/funeral-insurance-for-seniors-canada/ | R11: https://instasure.ca/guides/life-insurance-beneficiary-canada/ | S11: https://instasure.ca/guides/life-insurance-over-70-canada/ | T11: https://instasure.ca/guides/life-insurance-over-50-canada/ | U11: https://instasure.ca/guides/what-happens-when-term-life-insurance-expires/ | V11: https://instasure.ca/guides/whole-life-vs-universal-life-insurance/ | W11: https://instasure.ca/guides/how-to-make-a-life-insurance-claim-canada/ | X11: https://instasure.ca/guides/life-insurance-riders-canada/ | Y11: https://instasure.ca/guides/what-does-life-insurance-not-cover/ | Z11: https://instasure.ca/guides/life-insurance-with-diabetes-canada/ | AA11: https://instasure.ca/guides/participating-whole-life-insurance-cash-value/ | AB11: https://instasure.ca/guides/what-affects-life-insurance-rates/ | AC11: https://instasure.ca/guides/life-insurance-after-cancer-canada/ | AD11: https://instasure.ca/guides/buy-term-and-invest-the-difference-canada/ | AE11: https://instasure.ca/guides/life-insurance-estate-planning-canada/ | AF11: https://instasure.ca/guides/decreasing-term-vs-level-term-life-insurance/ | AG11: https://instasure.ca/guides/how-universal-life-insurance-works/ | AH11: https://instasure.ca/guides/funeral-insurance-no-medical-exam/ | AI11: https://instasure.ca/guides/life-insurance-for-new-parents-canada/ | AJ11: https://instasure.ca/guides/buy-sell-agreement-life-insurance-canada/ | AK11: https://instasure.ca/guides/life-insurance-after-heart-attack-canada/ | AL11: https://instasure.ca/guides/how-life-insurance-companies-check-medical-history/ | AM11: https://instasure.ca/guides/life-insurance-broker-vs-agent-vs-bank/ | AN11: https://instasure.ca/guides/how-to-choose-a-life-insurance-company/ | AO11: https://instasure.ca/guides/is-group-life-insurance-enough/ | AP11: https://instasure.ca/guides/how-much-critical-illness-insurance-do-i-need/ | AQ11: https://instasure.ca/guides/is-childrens-life-insurance-worth-it/ | AR11: https://instasure.ca/guides/life-insurance-for-stay-at-home-parents/ | AS11: https://instasure.ca/guides/health-insurance-for-early-retirees/ | AT11: https://instasure.ca/guides/guaranteed-issue-vs-underwritten-health-insurance/ | AU11: https://instasure.ca/guides/joint-life-insurance-vs-two-policies/ | AV11: https://instasure.ca/guides/life-insurance-depression-anxiety-canada/ | AW11: https://instasure.ca/guides/convert-term-life-insurance-to-permanent/ | AX11: https://instasure.ca/guides/life-insurance-myths-canada/ | AY11: https://instasure.ca/guides/funeral-insurance-waiting-period/ | AZ11: https://instasure.ca/guides/life-insurance-for-young-adults-canada/ | BA11: https://instasure.ca/guides/joint-last-to-die-life-insurance/ | BB11: https://instasure.ca/guides/joint-mortgage-life-insurance/ | BC11: https://instasure.ca/guides/life-insurance-rating-classes-canada/
A12: Secondary keywords (H2s, FAQ, body) | B12: cmhc insurance vs mortgage life insurance, is mortgage life insurance mandatory, mortgage protection insurance, mortgage default insurance, mortgage loan insurance | C12: how does term life insurance work, term life insurance canada, types of term life insurance, term life insurance pros and cons, yearly renewable term | D12: how does life insurance work in canada, life insurance explained, what is life insurance, how do life insurance payouts work, life insurance basics | E12: different types of life insurance, term vs permanent life insurance, term to 100 life insurance, what is permanent life insurance, variable life insurance canada | F12: do i need life insurance, who needs life insurance, life insurance for single people, do i need life insurance if i have no kids, should i cancel life insurance | G12: whole life insurance rates canada, limited pay whole life insurance, 20 pay whole life cost, whole life insurance cost by age, permanent life insurance cost | H12: buy life insurance online, instant approval life insurance, same day life insurance canada, online term life insurance canada, life insurance without meeting an advisor | I12: health insurance between jobs canada, group benefits conversion plan, what happens to benefits when laid off, continue health insurance after leaving job, individual health plan no medical | J12: denied life insurance canada, life insurance postponed, reapply after life insurance decline, high risk life insurance, anonymous pre-underwriting | K12: what is critical illness insurance, should i get critical illness insurance, critical illness insurance pros and cons, do i need critical illness insurance, critical illness insurance with group benefits | L12: family life insurance canada, life insurance for the whole family, life insurance for parents and children, family life insurance plan, life insurance for young families | M12: life insurance with health issues, how to get life insurance with health problems, high risk life insurance canada, life insurance for chronic illness, no medical life insurance pre existing conditions | N12: what is asked on a life insurance application, paramedical exam, life insurance blood test, attending physician statement, how long does life insurance underwriting take | O12: term to 100 life insurance, term 100 vs whole life, term 100 cost, permanent life insurance without cash value, term 100 canada | P12: 10 year term life insurance, 30 year term life insurance, how long should term life insurance be, term length for mortgage, term to 65 | Q12: funeral insurance over 70, funeral insurance over 80, final expense insurance for seniors, burial insurance for seniors, life insurance for seniors over 75 | R12: revocable vs irrevocable beneficiary, minor child beneficiary life insurance, contingent beneficiary, multiple beneficiaries life insurance, naming estate as beneficiary | S12: life insurance age limit canada, life insurance over 75, life insurance for seniors over 80, is life insurance worth it after 70, guaranteed issue life insurance for seniors | T12: life insurance cost for 50 year old, term life insurance over 50, no medical life insurance at 50, life insurance for 55 year old, life insurance at 60 canada | U12: term life insurance renewal, convert term life to whole life, term conversion deadline, renewable term life insurance canada, end of term life insurance | V12: universal life insurance canada, universal life insurance pros and cons, level vs yrt cost of insurance, is universal life insurance worth it, variable life insurance canada | W12: life insurance claim process, how long does a life insurance payout take, life insurance claim documents, why life insurance claims are denied, life insurance contestability period | X12: waiver of premium rider, child term rider, guaranteed insurability rider, critical illness rider vs standalone, accidental death benefit rider | Y12: life insurance exclusions canada, life insurance suicide clause canada, life insurance contestability period, does life insurance cover overdose, life insurance fine print | Z12: life insurance type 2 diabetes canada, life insurance type 1 diabetes, insulin dependent life insurance, a1c life insurance, no medical life insurance diabetes | AA12: cash value life insurance canada, cash surrender value, whole life dividends, paid-up additions, par vs non-par whole life, life insurance as savings | AB12: how are life insurance quotes calculated, life insurance rates canada, factors affecting life insurance premiums, why are life insurance quotes different, how to lower life insurance premiums | AC12: life insurance for cancer survivors canada, life insurance with cancer, life insurance in remission, stage 4 cancer life insurance, guaranteed issue after cancer | AD12: is whole life insurance a good investment, term vs whole life investment, life insurance as an investment canada, whole life vs tfsa, cash value vs investing | AE12: deemed disposition at death canada, capital gains tax on cottage at death, life insurance for inheritance, best way to leave money to family, life insurance probate | AF12: decreasing term life insurance canada, level term life insurance, increasing term life insurance, mortgage term life insurance, reducing term insurance | AG12: universal life insurance explained, universal life insurance tax, universal life cash value, universal life insurance canada, what is universal life insurance | AH12: no medical funeral insurance, final expense insurance no medical exam, guaranteed acceptance funeral insurance, simplified issue funeral insurance, funeral insurance with health conditions | AI12: life insurance for young parents, life insurance after having a baby, how much life insurance with kids, life insurance during parental leave, life insurance for young families | AJ12: shareholder agreement life insurance, business partner life insurance, cross-purchase vs corporate redemption, capital dividend account life insurance, joint first to die business partners | AK12: life insurance heart disease canada, life insurance with a heart condition, life insurance after stent, life insurance after bypass surgery, atrial fibrillation life insurance | AL12: mib life insurance canada, attending physician statement, life insurance medical records, can life insurance see my medical records, life insurance misrepresentation | AM12: independent life insurance broker canada, captive agent vs broker, buying life insurance from your bank, buy life insurance online vs advisor, how are life insurance advisors paid | AN12: most reputable life insurance companies canada, life insurance company ratings, assuris protection, life insurance claim settlement ratio canada, can i trust online insurance reviews | AO12: group life insurance vs individual, group life insurance conversion, life insurance when you leave your job, optional group life top up, employer life insurance canada | AP12: critical illness insurance calculator, critical illness coverage amount, critical illness insurance term length, term 10 vs term 100 critical illness, critical illness insurance canada | AQ12: children's life insurance, life insurance for kids canada, child term rider, whole life for children, grandparent buying life insurance for grandchild | AR12: stay at home mom life insurance, stay at home dad life insurance, life insurance for non working spouse, spousal life insurance canada, how much life insurance for a stay at home mom | AS12: retiree health benefits canada, health insurance after retirement before 65, retiree health and dental plan, post retirement health insurance, health insurance for retirees canada | AT12: health insurance pre existing conditions canada, no medical health insurance canada, guaranteed approval health insurance, underwritten health plan, pre-existing condition exclusion health plan | AU12: joint life insurance, first to die life insurance, joint last to die life insurance, life insurance for couples canada, joint life insurance divorce | AV12: life insurance with anxiety canada, mental health life insurance, antidepressants life insurance, adhd life insurance, does therapy affect life insurance | AW12: term life conversion option, convert term to whole life, term conversion deadline, conversion privilege life insurance, convertible term life insurance | AX12: life insurance misconceptions, is life insurance a waste of money, do i need life insurance, life insurance facts canada, common life insurance mistakes | AY12: final expense insurance waiting period, guaranteed issue waiting period, graded death benefit, funeral insurance two year rule, accidental death funeral insurance | AZ12: life insurance in your 20s, should i get life insurance at 25, life insurance for students canada, cheap life insurance for young adults, too young for life insurance | BA12: last to die life insurance canada, joint second to die, life insurance for estate taxes, cottage capital gains life insurance, joint survivorship life insurance | BB12: mortgage insurance for couples, joint mortgage insurance pays once, mortgage life insurance after divorce, two term policies vs joint mortgage insurance, co-borrower mortgage insurance | BC12: preferred vs standard life insurance, table rating life insurance, life insurance build chart bmi, life insurance underwriting classes, rated life insurance policy
A13: Value asset (why it ranks and gets cited) | B13: A two-column comparison graphic (default insurance vs life cover: who pays, who benefits, when it pays, required or optional) and a signing-day question card. | C13: A worked timeline for one 35-year-old buying 20-year term: premium schedule from the Instasure model, the renewal-rate jump at year 21 and the conversion deadline, shown as a labelled chart and table (estimates, dated). | D13: A one-screen diagram of a policy's life cycle (apply, underwriting, premiums, claim, tax-free payout) with the roles of owner, life insured and beneficiary, plus a plain-language glossary box. | E13: A one-screen comparison table of seven policy types (term 10/20/30, term to 100, participating whole, universal, simplified issue, guaranteed issue, group) with columns for duration, cash value, premium pattern, medical underwriting and typical use, plus a five-question decision tree. | F13: A six-question self-test that scores need (dependants, debts, income reliance, estate goals) with result bands, plus a 'before you cancel' checklist tied to 2026 reports of Canadians cutting insurance. | G13: A dated example-premium table for $100K and $250K whole life at ages 30, 45 and 60 across lifetime, 20-pay and 10-pay options from the Instasure model. | H13: A dated comparison table of direct-to-consumer products (Sun Life Go Term, Go Simplified, Go Guaranteed, Manulife CoverMe and others) with issue ages, maximum coverage, number of health questions, refund period and time to coverage, each cell sourced. | I13: A 30-day action checklist with deadlines and a comparison table of conversion plan vs underwritten plan vs guaranteed-issue plan. | J13: A step-by-step recovery plan (get the reason, request records, fix errors, shop with a desk advisor, fallback options) and a decision tree from decline reason to next step. | K13: A five-question decision tree plus a worked example comparing a lump-sum benefit with six months of lost income and uncovered costs for a stated two-income household. | L13: A comparison table of family coverage options (term per parent, joint, whole or universal, mortgage, children's policy, child rider) by who is covered, payout, cost and best use, plus a worked family example. | M13: A condition-by-condition table (diabetes, cancer history, heart, blood pressure, mental health, other chronic conditions) showing the usual route (fully underwritten, simplified, guaranteed) and what records help, reviewed by the Medical underwriting desk. | N13: An exam-day preparation checklist and an underwriting timeline graphic (application to approval) with typical step durations, plus the question categories found on a standard application. | O13: A side-by-side table (term 100, participating whole life, universal life, 30-year term) by premium, cash value, guarantees and best use, plus labelled example premiums for one profile from the Instasure model. | P13: A decision table matching term length to life-stage triggers (youngest child's age, mortgage years left, planned retirement date) plus a price-by-term comparison for one example profile from the Instasure model. | Q13: A dated table of Instasure example estimates for $10,000 and $15,000 at ages 60, 65, 70, 75 and 80 (female and male non-smokers), labelled with profile and month, plus a pre-purchase checklist. | R13: A beneficiary-designation decision tree and a table comparing options (spouse, minor child with trustee, insurance trust, estate, charity) by payout speed, probate, creditor protection and control. | S13: An issue-age table by product type (term 10/20, term to 100, whole life, simplified issue, guaranteed issue, final expense) with typical maximum issue ages and coverage caps, each verified against insurer guides and dated. | T13: A dated age-50 rate table (sex × amount × term × smoker status) and a side-by-side of fully underwritten vs simplified-issue estimates for the same profile. | U13: A five-year pre-expiry checklist and a three-way comparison (renew, convert, reapply) with a worked example of renewal vs new-policy cost for a 55-year-old from the Instasure model. | V13: A side-by-side table (premium flexibility, guarantees, cash value, investment risk, cost-of-insurance type, typical fit) and a worked example showing how a UL policy can lapse when returns fall short. | W13: A printable claim checklist (documents by situation: death in Canada, death abroad, accidental death) and a timeline graphic from notification to payout, with OLHI escalation steps. | X13: A rider checklist table showing what each rider pays, typical eligibility, who it suits, red flags and a 'skip it if' column. | Y13: An exclusions table (exclusion, how long it applies, what is paid instead, how to avoid the problem) with the source of each rule, plus a "read before you sign" checklist. | Z13: An underwriting factor matrix for diabetes (type, diagnosis age, A1C band, complications) showing likely outcome ranges, reviewed by the medical underwriting desk, plus a document checklist. | AA13: An annotated sample policy illustration (guaranteed vs non-guaranteed columns) with plain-language callouts, plus a glossary box of participating-policy terms. | AB13: A factor table (each rating factor, how insurers check it, how much it can move the price as a labelled model example, what you can change) built from the Instasure model. | AC13: A cancer-type table (skin, breast, prostate, thyroid, colon, blood cancers) with typical postponement periods and post-remission outcomes, reviewed by the medical underwriting desk, plus a bridge-coverage plan. | AD13: A worked 30-year example (term plus TFSA contributions vs participating whole life) with every assumption stated (premiums from the Instasure model, a stated return range, no tax advice), plus a "which approach fits" table. | AE13: A worked example estimating the deemed-disposition tax on a cottage and a RRIF for a couple, then sizing a joint last-to-die policy to cover it (assumptions and CRA sources stated). | AF13: A benefit-over-time chart (decreasing term, level term, lender balance-based cover) for one $500,000 mortgage, with model cost estimates. | AG13: A diagram of one universal life policy over 20 years (deposits in, cost of insurance out, account value) with level vs YRT shown side by side, plus a step-by-step buying checklist. | AH13: A sample of typical simplified-issue question types (described, not copied from an insurer) and a cost comparison of simplified vs guaranteed issue from the quote engine tiers, labelled. | AI13: A worked example for a family with a newborn (income replacement, childcare replacement cost, mortgage) and a one-page new-parent checklist covering will, guardian, beneficiary and coverage. | AJ13: A structure comparison table (cross-purchase, promissory note, corporate redemption, hybrid) with tax notes, plus a worked two-partner example sizing coverage to a stated valuation. | AK13: A cardiac-event timeline (0–6 months, 6–12 months, 1–2 years, 2+ years) with typical options at each stage, plus a list of cardiology reports to request, desk-reviewed. | AL13: A flow diagram from application to decision showing each information source (application, MIB, doctor reports, prescription records, exam results) and when consent is given, plus a "what to have ready" checklist. | AM13: A channel comparison table (insurer choice, advice, underwriting help, cost, payment model, after-sale service) and a seven-question checklist to ask any seller. | AN13: A checklist scorecard (financial strength, Assuris coverage, complaint route, conversion options, underwriting flexibility, service) the reader can apply to any insurer, with the source for each item. No ranking until a review method is published. | AO13: A group-vs-individual comparison table and a worked layoff scenario showing coverage before and after a job loss, with a conversion-window checklist (deadline verified per plan). | AP13: A fill-in sizing worksheet (income gap + uncovered costs + debts − group cover) with a worked family example, and an embedded instant estimate pre-filled with the resulting amount. | AQ13: A 25-year comparison of three approaches for one child (whole life policy, child term rider, investing the same premium in an RESP or TFSA), with assumptions stated and labelled hypothetical. | AR13: A replacement-cost worksheet (childcare, household work, transport, lost income if the working parent cuts hours) with a worked example using cited childcare costs, sized into a term amount and length. | AS13: Year-by-year budget template from retirement to 65 with modelled plan premiums and out-of-pocket estimates, plus a province table of the age when public drug coverage for seniors begins. | AT13: Comparison table of plan routes (guaranteed issue, underwritten, conversion) by health questions, drug limits, maximums and cost, with a worked example for a person on a monthly maintenance drug. | AU13: A cost-and-payout comparison for one example couple (joint first-to-die vs two term policies vs joint last-to-die) from the Instasure model, plus a separation scenario table. | AV13: A severity-and-stability table showing typical outcomes and the questionnaire items insurers use, reviewed by the medical underwriting desk, with a support-resources box (9-8-8 suicide crisis line). | AW13: A conversion timeline for one example policy (purchase, conversion deadline, renewal) and a table comparing full conversion, partial conversion and a new policy by health questions, premium and coverage length. | AX13: A myth-vs-fact table with a source or labelled model example for every fact, plus one example premium table by age from the Instasure model to answer "too expensive". | AY13: A year-by-year table showing what a typical graded or limited-benefit policy pays (refund of premiums, with or without interest, or the full benefit) versus a simplified-issue policy, flagged as typical structures to verify. | AZ13: A "buy now or wait" decision table by situation (no debts, co-signed loans, partner, mortgage, family history) with labelled example premiums at 25, 30 and 35 from the Instasure model. | BA13: A worked example for one couple (cottage gain and RRIF balance at the second death, estimated tax, policy sized to cover it) with every assumption stated, reviewed against CRA rules. | BB13: A scenario table (one partner dies, both die, separation, refinance, switching lenders) showing outcomes under joint lender cover vs two term policies. | BC13: A rating-class price impact table for one profile (preferred plus through table 4) from the Instasure model and an illustrative explanation of build-chart bands (no insurer's proprietary chart reproduced).
A14: Call to action | B14: Mortgage protection calculator (/calculators/mortgage-protection/) | C14: Instant term life estimate (/quote/) | D14: Instant life insurance estimate (/quote/life-insurance/) | E14: Instant life insurance estimate (/quote/) | F14: Life insurance needs calculator (/calculators/life-insurance-needs/) | G14: Instant life insurance estimate (/quote/) | H14: Instant life insurance estimate (/quote/) | I14: Instant health & dental estimate (/health-dental-insurance/) | J14: Request a specialist call: Medical underwriting desk (/life-insurance/medical-conditions/) | K14: Instant critical illness estimate (/critical-illness-insurance/) | L14: Life insurance needs calculator (/calculators/life-insurance-needs/) | M14: Request a specialist call: Medical underwriting desk (/life-insurance/medical-conditions/) | N14: Request a specialist call: Medical underwriting desk (/life-insurance/medical-conditions/) | O14: Instant life insurance estimate (/quote/life-insurance/) | P14: Instant term life estimate (/quote/) | Q14: Funeral expense estimate, from about $1 a day for the example profile (/life-insurance/funeral-expense/); Request a specialist call: Funeral expense desk | R14: Book a policy review with a licensed advisor (/advisors/) | S14: Instant seniors life insurance estimate (/quote/) | T14: Instant life insurance estimate (/quote/) | U14: Book a policy review with a licensed advisor (/advisors/) | V14: Talk to a licensed advisor about permanent cover (/life-insurance/universal-life/) | W14: Book a policy review with a licensed advisor (/advisors/) | X14: Instant life insurance estimate (/quote/) | Y14: Book a policy review with a licensed advisor (/advisors/) | Z14: Request a specialist call: Medical underwriting desk (/life-insurance/medical-conditions/) | AA14: Talk to a licensed advisor about permanent cover (/whole-life-insurance/) | AB14: Instant life insurance estimate (/quote/life-insurance/) | AC14: Request a specialist call: Medical underwriting desk (/life-insurance/medical-conditions/) | AD14: Life insurance needs calculator (/calculators/life-insurance-needs/) | AE14: Talk to a licensed advisor about permanent cover (/whole-life-insurance/) | AF14: Mortgage protection calculator (/calculators/mortgage-protection/) | AG14: Talk to a licensed advisor about permanent cover (/life-insurance/universal-life/) | AH14: Funeral expense estimate, from about $1 a day for the example profile (/life-insurance/funeral-expense/); Request a specialist call: Funeral expense desk | AI14: Life insurance needs calculator (/calculators/life-insurance-needs/) | AJ14: Talk to a licensed advisor about business cover (/business-insurance/key-person/) | AK14: Request a specialist call: Medical underwriting desk (/life-insurance/medical-conditions/) | AL14: Request a specialist call: Medical underwriting desk (/life-insurance/medical-conditions/) | AM14: Instant life insurance estimate (/quote/) | AN14: Instant life insurance estimate (/quote/life-insurance/) | AO14: Life insurance needs calculator (/calculators/life-insurance-needs/) | AP14: Instant critical illness estimate (/critical-illness-insurance/) | AQ14: Talk to a licensed advisor (/life-insurance/children/) | AR14: Life insurance needs calculator (/calculators/life-insurance-needs/) | AS14: Instant health & dental estimate (/health-dental-insurance/) | AT14: Instant health & dental estimate (/health-dental-insurance/) | AU14: Instant life insurance estimate (/quote/) | AV14: Request a specialist call: Medical underwriting desk (/life-insurance/medical-conditions/) | AW14: Book a policy review with a licensed advisor (/advisors/) | AX14: Instant life insurance estimate (/quote/life-insurance/) | AY14: Funeral expense estimate, from about $1 a day for the example profile (/life-insurance/funeral-expense/); Request a specialist call: Funeral expense desk | AZ14: Instant life insurance estimate (/quote/life-insurance/) | BA14: Talk to a licensed advisor about permanent cover (/whole-life-insurance/) | BB14: Mortgage protection calculator (/calculators/mortgage-protection/) | BC14: Request a specialist call: Medical underwriting desk (/life-insurance/medical-conditions/)
A15: Must link to | B15: /mortgage-life-insurance/ /guides/mortgage-life-insurance-vs-term-life-insurance/ /calculators/mortgage-protection/ /glossary/ | C15: /term-life-insurance/ /guides/how-much-does-life-insurance-cost-canada/ /guides/term-vs-whole-life-insurance-canada/ /calculators/life-insurance-needs/ | D15: /life-insurance/ /guides/types-of-life-insurance-canada/ /guides/how-much-life-insurance-do-i-need-canada/ /guides/is-life-insurance-taxable-in-canada/ /calculators/life-insurance-needs/ | E15: /life-insurance/ /term-life-insurance/ /whole-life-insurance/ /no-medical-life-insurance/ /guides/term-vs-whole-life-insurance-canada/ | F15: /life-insurance/ /calculators/life-insurance-needs/ /guides/how-much-life-insurance-do-i-need-canada/ /guides/term-vs-whole-life-insurance-canada/ | G15: /whole-life-insurance/ /guides/term-vs-whole-life-insurance-canada/ /guides/participating-whole-life-insurance-cash-value/ /life-insurance/final-expense/ | H15: /no-medical-life-insurance/ /term-life-insurance/ /guides/simplified-vs-guaranteed-issue-life-insurance/ /how-we-make-money/ | I15: /health-dental-insurance/ /guides/guaranteed-issue-vs-underwritten-health-insurance/ /guides/private-health-insurance-cost-canada/ /guides/group-vs-individual-disability-insurance/ | J15: /life-insurance/medical-conditions/ /no-medical-life-insurance/ /guides/simplified-vs-guaranteed-issue-life-insurance/ /guides/life-insurance-medical-exam-application/ | K15: /critical-illness-insurance/ /guides/critical-illness-vs-disability-insurance/ /guides/cancer-drug-coverage-by-province/ /guides/critical-illness-insurance-cost-canada/ | L15: /calculators/life-insurance-needs/ /life-insurance/children/ /life-insurance/joint/ /guides/how-much-life-insurance-do-i-need-canada/ /guides/life-insurance-for-new-parents-canada/ | M15: /life-insurance/medical-conditions/ /guides/life-insurance-with-diabetes-canada/ /guides/life-insurance-after-cancer-canada/ /guides/life-insurance-after-heart-attack-canada/ /guides/simplified-vs-guaranteed-issue-life-insurance/ | N15: /life-insurance/ /no-medical-life-insurance/ /life-insurance/medical-conditions/ /guides/life-insurance-rating-classes-canada/ | O15: /whole-life-insurance/ /guides/types-of-life-insurance-canada/ /guides/whole-life-vs-universal-life-insurance/ /guides/life-insurance-estate-planning-canada/ | P15: /term-life-insurance/ /guides/how-much-does-life-insurance-cost-canada/ /calculators/life-insurance-needs/ /guides/life-insurance-laddering-canada/ | Q15: /life-insurance/funeral-expense/ /life-insurance/seniors/ /life-insurance/final-expense/ /no-medical-life-insurance/ | R15: /life-insurance/ /guides/does-life-insurance-go-through-probate/ /guides/is-life-insurance-taxable-in-canada/ /life-insurance/children/ /guides/quebec-life-insurance-beneficiary-rules/ | S15: /life-insurance/seniors/ /life-insurance/final-expense/ /no-medical-life-insurance/ /guides/simplified-vs-guaranteed-issue-life-insurance/ | T15: /term-life-insurance/ /no-medical-life-insurance/ /guides/how-much-does-life-insurance-cost-canada/ /guides/simplified-vs-guaranteed-issue-life-insurance/ | U15: /term-life-insurance/ /whole-life-insurance/ /guides/term-vs-whole-life-insurance-canada/ /life-insurance/medical-conditions/ | V15: /life-insurance/universal-life/ /whole-life-insurance/ /guides/term-vs-whole-life-insurance-canada/ /guides/participating-whole-life-insurance-cash-value/ | W15: /life-insurance/ /guides/find-a-lost-life-insurance-policy-canada/ /guides/life-insurance-beneficiary-canada/ /guides/category/claims-rules/ | X15: /life-insurance/ /term-life-insurance/ /critical-illness-insurance/ /life-insurance/children/ /guides/critical-illness-vs-disability-insurance/ | Y15: /guides/how-to-make-a-life-insurance-claim-canada/ /guides/life-insurance-riders-canada/ /guides/how-life-insurance-companies-check-medical-history/ /guides/does-life-insurance-cover-you-abroad/ | Z15: /life-insurance/medical-conditions/ /no-medical-life-insurance/ /guides/simplified-vs-guaranteed-issue-life-insurance/ /critical-illness-insurance/ | AA15: /whole-life-insurance/ /guides/term-vs-whole-life-insurance-canada/ /life-insurance/universal-life/ /glossary/ | AB15: /quote/life-insurance/ /guides/how-much-does-life-insurance-cost-canada/ /guides/life-insurance-rating-classes-canada/ /guides/instant-insurance-estimates-explained/ | AC15: /life-insurance/medical-conditions/ /no-medical-life-insurance/ /guides/simplified-vs-guaranteed-issue-life-insurance/ /guides/declined-for-life-insurance-what-next/ | AD15: /guides/term-vs-whole-life-insurance-canada/ /guides/participating-whole-life-insurance-cash-value/ /term-life-insurance/ /whole-life-insurance/ | AE15: /whole-life-insurance/ /life-insurance/joint/ /life-insurance/universal-life/ /guides/does-life-insurance-go-through-probate/ /guides/is-life-insurance-taxable-in-canada/ | AF15: /term-life-insurance/ /mortgage-life-insurance/ /calculators/mortgage-protection/ /guides/mortgage-life-insurance-vs-term-life-insurance/ | AG15: /life-insurance/universal-life/ /guides/whole-life-vs-universal-life-insurance/ /guides/is-life-insurance-taxable-in-canada/ /whole-life-insurance/ | AH15: /life-insurance/funeral-expense/ /no-medical-life-insurance/ /life-insurance/medical-conditions/ /guides/funeral-insurance-waiting-period/ | AI15: /life-insurance/ /term-life-insurance/ /calculators/life-insurance-needs/ /life-insurance/children/ /guides/life-insurance-beneficiary-canada/ | AJ15: /business-insurance/key-person/ /life-insurance/ /guides/corporate-owned-life-insurance-canada/ /group-benefits/ | AK15: /life-insurance/medical-conditions/ /no-medical-life-insurance/ /critical-illness-insurance/ /guides/simplified-vs-guaranteed-issue-life-insurance/ | AL15: /guides/life-insurance-medical-exam-application/ /guides/life-insurance-rating-classes-canada/ /guides/declined-for-life-insurance-what-next/ /life-insurance/medical-conditions/ | AM15: /how-we-make-money/ /advisors/ /licensing/ /guides/instant-life-insurance-canada/ /life-insurance/ | AN15: /guides/life-insurance-broker-vs-agent-vs-bank/ /guides/how-to-make-a-life-insurance-claim-canada/ /how-we-make-money/ /editorial-guidelines/ | AO15: /life-insurance/ /term-life-insurance/ /group-benefits/ /guides/how-much-life-insurance-do-i-need-canada/ /calculators/life-insurance-needs/ | AP15: /critical-illness-insurance/ /calculators/life-insurance-needs/ /guides/critical-illness-insurance-cost-canada/ /guides/cancer-drug-coverage-by-province/ | AQ15: /life-insurance/children/ /whole-life-insurance/ /guides/life-insurance-riders-canada/ /guides/participating-whole-life-insurance-cash-value/ | AR15: /calculators/life-insurance-needs/ /guides/life-insurance-for-new-parents-canada/ /guides/family-life-insurance-canada/ /term-life-insurance/ | AS15: /health-dental-insurance/ /travel-insurance/snowbirds/ /guides/health-insurance-for-seniors-over-65/ /guides/prescription-drug-coverage-by-province/ | AT15: /health-dental-insurance/ /guides/health-insurance-after-losing-job/ /guides/private-health-insurance-cost-canada/ /life-insurance/medical-conditions/ | AU15: /life-insurance/joint/ /term-life-insurance/ /guides/mortgage-life-insurance-vs-term-life-insurance/ /guides/joint-mortgage-life-insurance/ | AV15: /life-insurance/medical-conditions/ /guides/declined-for-life-insurance-what-next/ /no-medical-life-insurance/ /disability-insurance/ | AW15: /guides/what-happens-when-term-life-insurance-expires/ /whole-life-insurance/ /life-insurance/universal-life/ /guides/term-vs-whole-life-insurance-canada/ | AX15: /guides/is-life-insurance-worth-it-canada/ /guides/is-group-life-insurance-enough/ /guides/life-insurance-for-stay-at-home-parents/ /guides/life-insurance-pre-existing-conditions-canada/ /guides/buy-term-and-invest-the-difference-canada/ | AY15: /life-insurance/funeral-expense/ /no-medical-life-insurance/ /guides/simplified-vs-guaranteed-issue-life-insurance/ /life-insurance/final-expense/ | AZ15: /term-life-insurance/ /guides/how-much-does-life-insurance-cost-canada/ /guides/is-group-life-insurance-enough/ /guides/is-life-insurance-worth-it-canada/ | BA15: /guides/life-insurance-estate-planning-canada/ /life-insurance/joint/ /guides/joint-life-insurance-vs-two-policies/ /guides/term-100-life-insurance-canada/ | BB15: /mortgage-life-insurance/ /life-insurance/joint/ /guides/joint-life-insurance-vs-two-policies/ /calculators/mortgage-protection/ | BC15: /life-insurance/medical-conditions/ /guides/how-much-does-life-insurance-cost-canada/ /guides/life-insurance-medical-exam-application/ /life-insurance/
A16: Blog plan row | B16: B0096 (priority 1 in docs/blog-content-plan.csv) | C16: B0036 (priority 2 in docs/blog-content-plan.csv) | D16: New topic: add to the blog plan | E16: B0035 (priority 2 in docs/blog-content-plan.csv) | F16: B0057 (priority 2 in docs/blog-content-plan.csv) | G16: B0073 (priority 3 in docs/blog-content-plan.csv) | H16: B0023 (priority 1 in docs/blog-content-plan.csv) | I16: B0150 (priority 1 in docs/blog-content-plan.csv) | J16: B0026 (priority 1 in docs/blog-content-plan.csv) | K16: B0118 (priority 2 in docs/blog-content-plan.csv) | L16: New topic: add to the blog plan | M16: New topic: add to the blog plan | N16: B0066 (priority 2 in docs/blog-content-plan.csv) | O16: New topic: add to the blog plan | P16: B0033 (priority 2 in docs/blog-content-plan.csv) | Q16: B0041 (priority 2 in docs/blog-content-plan.csv) | R16: B0064 (priority 2 in docs/blog-content-plan.csv) | S16: B0058 (priority 2 in docs/blog-content-plan.csv) | T16: B0031 (priority 2 in docs/blog-content-plan.csv) | U16: B0061 (priority 2 in docs/blog-content-plan.csv) | V16: B0072 (priority 3 in docs/blog-content-plan.csv) | W16: B0028 (priority 2 in docs/blog-content-plan.csv) | X16: B0075 (priority 3 in docs/blog-content-plan.csv) | Y16: New topic: add to the blog plan | Z16: B0055 (priority 2 in docs/blog-content-plan.csv) | AA16: B0076 (priority 3 in docs/blog-content-plan.csv) | AB16: New topic: add to the blog plan | AC16: B0053 (priority 2 in docs/blog-content-plan.csv) | AD16: New topic: add to the blog plan | AE16: B0065 (priority 2 in docs/blog-content-plan.csv) | AF16: B0106 (priority 3 in docs/blog-content-plan.csv) | AG16: New topic: add to the blog plan | AH16: B0040 (priority 2 in docs/blog-content-plan.csv) | AI16: B0059 (priority 2 in docs/blog-content-plan.csv) | AJ16: B0027 (priority 2 in docs/blog-content-plan.csv) | AK16: B0083 (priority 3 in docs/blog-content-plan.csv) | AL16: New topic: add to the blog plan | AM16: B0029 (priority 2 in docs/blog-content-plan.csv) | AN16: New topic: add to the blog plan | AO16: B0034 (priority 2 in docs/blog-content-plan.csv) | AP16: B0121 (priority 2 in docs/blog-content-plan.csv) | AQ16: B0087 (priority 3 in docs/blog-content-plan.csv) | AR16: New topic: add to the blog plan | AS16: B0160 (priority 2 in docs/blog-content-plan.csv) | AT16: B0155 (priority 2 in docs/blog-content-plan.csv) | AU16: B0071 (priority 3 in docs/blog-content-plan.csv) | AV16: B0054 (priority 2 in docs/blog-content-plan.csv) | AW16: New topic: add to the blog plan | AX16: New topic: add to the blog plan | AY16: B0039 (priority 2 in docs/blog-content-plan.csv) | AZ16: New topic: add to the blog plan | BA16: New topic: add to the blog plan | BB16: B0099 (priority 2 in docs/blog-content-plan.csv) | BC16: B0067 (priority 2 in docs/blog-content-plan.csv)
A17: Covers familialife.ca pages | B17: The Ultimate Guide on Mortgage Insurance (familialife.ca/what-is-mortgage-insurance/); Mortgage Protection Insurance (familialife.ca/mortgage-protection-insurance/) | C17: Term Life Insurance (familialife.ca/term-life-insurance/); Everything about Term Life Insurance (familialife.ca/everything-about-term-life-insurance/) | D17: How Does Life Insurance Work in Canada? (familialife.ca/how-does-life-insurance-work-in-canada/); Life Insurance Quotes in Canada (familialife.ca/life-insurance-quotes-in-canada/) | E17: How Does Life Insurance Work in Canada? (familialife.ca/how-does-life-insurance-work-in-canada/); Everything about Permanent Life Insurance in Canada (familialife.ca/everything-about-permanent-life-insurance/); Family Life Insurance in Canada: Separating Fact from Fiction (familialife.ca/family-life-insurance/) | F17: 12 Life Insurance Myths You Need to Stop Believing (familialife.ca/12-myths-debunked/); Don’t Buy Life Insurance Without Doing These 2 Things (familialife.ca/two-things-before-buying/) | G17: Permanent Life Insurance (familialife.ca/whole-life-insurance/); Everything about Permanent Life Insurance in Canada (familialife.ca/everything-about-permanent-life-insurance/) | H17: Familia Life - Lowest Life Insurance Rates in Canada (familialife.ca/); No Medical Insurance (familialife.ca/no-medical-insurance/); Everything about No Medical Life Insurance (familialife.ca/everything-about-no-medical-life-insurance/) | I17: Health Insurance (familialife.ca/health-insurance/) | J17: How To Get Life Insurance If You Have Health Issues (familialife.ca/how-to-get-life-insurance-if-you-have-health-issues/); Familia Life - Lowest Life Insurance Rates in Canada (familialife.ca/) | K17: Protect Your Health and Wallet: A Complete Guide to Critical Illness Insurance in Canada (familialife.ca/whats-ci/) | L17: Family Life Insurance in Canada: Separating Fact from Fiction (familialife.ca/family-life-insurance/); Familia Life - Lowest Life Insurance Rates in Canada (familialife.ca/) | M17: How To Get Life Insurance If You Have Health Issues (familialife.ca/how-to-get-life-insurance-if-you-have-health-issues/); 12 Life Insurance Myths You Need to Stop Believing (familialife.ca/12-myths-debunked/); Life Insurance Quotes in Canada (familialife.ca/life-insurance-quotes-in-canada/) | N17: How Do Life Insurance Companies Check Medical Background? (familialife.ca/how-do-life-insurance-companies-check-medical-background/); Everything about No Medical Life Insurance (familialife.ca/everything-about-no-medical-life-insurance/) | O17: Everything about Permanent Life Insurance in Canada (familialife.ca/everything-about-permanent-life-insurance/) | P17: Everything about Term Life Insurance (familialife.ca/everything-about-term-life-insurance/) | Q17: Final Expense (familialife.ca/final-expense-insurance/); Life Insurance After 50: A Canadian Senior’s Handbook (familialife.ca/seniors-life-insurance/) | R17: Joint Life Insurance vs Individual Life Insurance: A Comparative Analysis (familialife.ca/what-is-joint-life/); Family Life Insurance in Canada: Separating Fact from Fiction (familialife.ca/family-life-insurance/) | S17: Life Insurance After 50: A Canadian Senior’s Handbook (familialife.ca/seniors-life-insurance/) | T17: Life Insurance After 50: A Canadian Senior’s Handbook (familialife.ca/seniors-life-insurance/) | U17: What Happens at the End of Term Life Insurance? (familialife.ca/what-happens-at-the-end-of-term-life-insurance/); Everything about Term Life Insurance (familialife.ca/everything-about-term-life-insurance/) | V17: Permanent Life Insurance (familialife.ca/whole-life-insurance/); Everything about Permanent Life Insurance in Canada (familialife.ca/everything-about-permanent-life-insurance/); What is Universal Life Insurance and How Does it Work? (familialife.ca/what-is-universal-life-insurance/) | W17: A Step-by-Step Guide to Filing a Life Insurance Claim (familialife.ca/how-to-claim/) | X17: Life Insurance Quotes in Canada (familialife.ca/life-insurance-quotes-in-canada/) | Y17: Life Insurance Quotes in Canada (familialife.ca/life-insurance-quotes-in-canada/); Family Life Insurance in Canada: Separating Fact from Fiction (familialife.ca/family-life-insurance/) | Z17: Life Insurance for Diabetics: How to Get the Best Rates in Canada (familialife.ca/life-insurance-for-diabetics/); Everything about No Medical Life Insurance (familialife.ca/everything-about-no-medical-life-insurance/) | AA17: Permanent Life Insurance (familialife.ca/whole-life-insurance/); Everything about Permanent Life Insurance in Canada (familialife.ca/everything-about-permanent-life-insurance/) | AB17: Life Insurance Quotes in Canada (familialife.ca/life-insurance-quotes-in-canada/) | AC17: Life Insurance with a Cancer Diagnosis in Canada (familialife.ca/life-insurance-with-cancer/) | AD17: 12 Life Insurance Myths You Need to Stop Believing (familialife.ca/12-myths-debunked/); Permanent Life Insurance (familialife.ca/whole-life-insurance/) | AE17: Life Insurance After 50: A Canadian Senior’s Handbook (familialife.ca/seniors-life-insurance/); Joint Life Insurance vs Individual Life Insurance: A Comparative Analysis (familialife.ca/what-is-joint-life/); Family Life Insurance in Canada: Separating Fact from Fiction (familialife.ca/family-life-insurance/) | AF17: Everything about Term Life Insurance (familialife.ca/everything-about-term-life-insurance/); The Ultimate Guide on Mortgage Insurance (familialife.ca/what-is-mortgage-insurance/) | AG17: What is Universal Life Insurance and How Does it Work? (familialife.ca/what-is-universal-life-insurance/) | AH17: Final Expense (familialife.ca/final-expense-insurance/) | AI17: Familia Life - Lowest Life Insurance Rates in Canada (familialife.ca/); Family Life Insurance in Canada: Separating Fact from Fiction (familialife.ca/family-life-insurance/) | AJ17: Joint Life Insurance vs Individual Life Insurance: A Comparative Analysis (familialife.ca/what-is-joint-life/) | AK17: Applying for Life Insurance with a Heart Condition in Canada (familialife.ca/life-insurance-with-heart-condition/) | AL17: How Do Life Insurance Companies Check Medical Background? (familialife.ca/how-do-life-insurance-companies-check-medical-background/) | AM17: Don’t Buy Life Insurance Without Doing These 2 Things (familialife.ca/two-things-before-buying/); Life Insurance for Diabetics: How to Get the Best Rates in Canada (familialife.ca/life-insurance-for-diabetics/) | AN17: Don’t Buy Life Insurance Without Doing These 2 Things (familialife.ca/two-things-before-buying/) | AO17: 12 Life Insurance Myths You Need to Stop Believing (familialife.ca/12-myths-debunked/) | AP17: Protect Your Health and Wallet: A Complete Guide to Critical Illness Insurance in Canada (familialife.ca/whats-ci/) | AQ17: Family Life Insurance in Canada: Separating Fact from Fiction (familialife.ca/family-life-insurance/) | AR17: 12 Life Insurance Myths You Need to Stop Believing (familialife.ca/12-myths-debunked/); Family Life Insurance in Canada: Separating Fact from Fiction (familialife.ca/family-life-insurance/) | AS17: Health Insurance (familialife.ca/health-insurance/) | AT17: Health Insurance (familialife.ca/health-insurance/) | AU17: Joint Life Insurance vs Individual Life Insurance: A Comparative Analysis (familialife.ca/what-is-joint-life/) | AV17: Life Insurance Quotes in Canada (familialife.ca/life-insurance-quotes-in-canada/) | AW17: What Happens at the End of Term Life Insurance? (familialife.ca/what-happens-at-the-end-of-term-life-insurance/); Everything about Permanent Life Insurance in Canada (familialife.ca/everything-about-permanent-life-insurance/) | AX17: 12 Life Insurance Myths You Need to Stop Believing (familialife.ca/12-myths-debunked/) | AY17: Final Expense (familialife.ca/final-expense-insurance/) | AZ17: 12 Life Insurance Myths You Need to Stop Believing (familialife.ca/12-myths-debunked/) | BA17: Joint Life Insurance vs Individual Life Insurance: A Comparative Analysis (familialife.ca/what-is-joint-life/); Life Insurance After 50: A Canadian Senior’s Handbook (familialife.ca/seniors-life-insurance/) | BB17: Joint Life Insurance vs Individual Life Insurance: A Comparative Analysis (familialife.ca/what-is-joint-life/); Mortgage Protection Insurance (familialife.ca/mortgage-protection-insurance/) | BC17: Everything about No Medical Life Insurance (familialife.ca/everything-about-no-medical-life-insurance/); Life Insurance with a Cancer Diagnosis in Canada (familialife.ca/life-insurance-with-cancer/)
A18: Notes / compliance | B18: Enhances blog plan row B0096 with a higher-traffic primary keyword; use this title and URL when the row is written (the plan's URL was /guides/mortgage-default-insurance-vs-mortgage-life-insurance/). | K18: Do not quote Instasure critical illness prices until a licensed advisor reviews the CI model (see docs/drafts/README.md). | M18: Hub page for the medical-condition cluster: link every condition guide from it and back. Never promise approval. | O18: Avoid "cheapest" in the published title (no published methodology); the video title can ask it as a question only if the answer is balanced. | S18: Enhances blog plan row B0058 (focus was "life insurance age limit canada", URL /guides/life-insurance-age-limit-canada/); the age-limit keyword stays as a secondary keyword and H2. | T18: Enhances blog plan row B0031 (focus was "life insurance cost for 50 year old", URL /guides/life-insurance-cost-at-50-canada/). | Y18: Exclusion periods vary by contract and province; cite the provincial Insurance Act rules for contestability and say "check your policy" for the rest. | AD18: An investment comparison: state assumptions and return ranges, show both outcomes, no promises of returns, no individual investment advice. | AL18: Describe information sources insurers may use with consent; verify MIB and privacy statements against MIB's Canadian consumer page and the Office of the Privacy Commissioner. | AN18: Must not rank or name a "best" insurer; Assuris limits must be quoted from assuris.ca with the date. | AO18: Video title must be backed by the article's worked example; soften to a question if the example doesn't support "probably not". | AP18: Do not quote Instasure critical illness prices until the CI model is reviewed. | AR18: Childcare costs must come from a cited source (Statistics Canada or provincial childcare data); insurer limits on non-earning spouses vary, so describe them generally. | AW18: Conversion deadlines and eligible plans vary by insurer and policy: describe them as "check your contract", never as a fixed age. | AX18: Strong video series: one short per myth. Every "fact" needs a source or a labelled estimate. | AZ18: "cheap life insurance for young adults" is a secondary keyword only; never claim "cheapest". | BA18: Tax examples must cite CRA rules (deemed disposition, RRIF income at death) and say they are illustrations, not tax advice.
A19: Video title | B19: CMHC Insurance vs Mortgage Life Insurance: Most Buyers Mix These Up | C19: Term Life Insurance Explained in 5 Minutes (Canada) | D19: How Life Insurance Works in Canada (Explained Simply) | E19: Every Type of Life Insurance in Canada Explained in 8 Minutes | F19: Do You Actually Need Life Insurance? A 2-Minute Test | G19: What Whole Life Insurance Really Costs in Canada (Example Premiums) | H19: Can You Really Get Life Insurance Online in Minutes in Canada? | I19: Lost Your Job? How to Keep Your Health and Dental Coverage | J19: Declined for Life Insurance? Do This Next | K19: Is Critical Illness Insurance Worth It? A 5-Question Test | L19: Family Life Insurance: Is There One Policy That Covers Everyone? | M19: Life Insurance With Health Problems: How to Still Get Covered | N19: The Life Insurance Medical Exam: What Happens and How to Prepare | O19: Term 100 Life Insurance: The Cheapest Way to Get Lifetime Cover? | P19: 10, 20 or 30-Year Term Life Insurance? How to Pick the Right Length | Q19: Funeral Insurance at 60, 70 and 80: What Seniors Can Still Buy | R19: Who Should Be Your Life Insurance Beneficiary? Avoid These Mistakes | S19: Life Insurance After 70: Is It Worth It and What Can You Still Buy? | T19: Buying Life Insurance in Your 50s: Costs, Types and Mistakes to Avoid | U19: Your Term Life Insurance Is Ending: 4 Options Explained | V19: Whole Life vs Universal Life Insurance: Which One Fits You? | W19: How to Claim Life Insurance After a Death: Step by Step | X19: Life Insurance Riders: Which Add-Ons Are Worth It? | Y19: What Life Insurance Won't Pay For: The Fine Print Explained | Z19: Life Insurance With Diabetes: What Insurers Actually Look At | AA19: Can Life Insurance Be a Savings Plan? Whole Life Cash Value Explained | AB19: Why Your Life Insurance Quote Is Higher Than Your Friend's | AC19: Can You Get Life Insurance After Cancer? Timelines Explained | AD19: Buy Term and Invest the Difference: Real Numbers for Canadians | AE19: How Life Insurance Pays the Tax Bill When You Die (Canada) | AF19: Decreasing vs Level Term Life Insurance: Which Protects Your Mortgage? | AG19: Universal Life Insurance Explained: How the Investment Account Works | AH19: Funeral Insurance With No Medical Exam: Who Qualifies? | AI19: New Parents: The Life Insurance Checklist Nobody Gives You | AJ19: Business Partners: How Life Insurance Funds a Buyout | AK19: Life Insurance After a Heart Attack: When and How to Apply | AL19: How Insurers Check Your Medical History (and What They Can See) | AM19: Broker, Agent, Bank or Online: Where Should You Buy Life Insurance? | AN19: How to Pick a Life Insurance Company You Can Trust | AO19: Is Your Work Life Insurance Enough? Probably Not. Here's Why | AP19: How Much Critical Illness Insurance Do You Need? 3 Steps | AQ19: Should You Buy Life Insurance for Your Child? Pros and Cons | AR19: Why Stay-at-Home Parents Need Life Insurance Too | AS19: Retiring Before 65? How to Replace Your Health Benefits | AT19: Health Insurance With a Pre-Existing Condition: Your 3 Routes | AU19: Joint vs Individual Life Insurance: What Couples Get Wrong | AV19: Does Depression or Anxiety Affect Life Insurance in Canada? | AW19: How to Convert Term Life Insurance Without a Medical Exam | AX19: 12 Life Insurance Myths That Cost Canadians Money | AY19: Funeral Insurance Waiting Periods: What Happens in Years 1 and 2 | AZ19: Life Insurance in Your 20s: Smart Move or Waste of Money? | BA19: Joint Last-to-Die Life Insurance: Protect the Cottage From Taxes | BB19: Joint Mortgage Insurance Pays Once: What That Means for Couples | BC19: Preferred, Standard or Rated? How Insurers Grade Your Health
A20: Video opening question | B20: Does CMHC insurance pay off my mortgage if I die? | C20: Does term life insurance pay out if I outlive it? | D20: How does a life insurance payout work in Canada? | E20: What is the most common type of life insurance in Canada? | F20: Do I need life insurance if I'm single with no kids? | G20: Why is whole life insurance so expensive? | H20: Can I get life insurance coverage the same day in Canada? | I20: How long do I have to convert my group health benefits? | J20: Can I get the reason my life insurance was declined? | K20: Is critical illness insurance a waste of money? | L20: What type of life insurance is best for a family? | M20: Can I be denied life insurance for a pre-existing condition? | N20: Who pays for a life insurance medical exam? | O20: Is term 100 the same as whole life insurance? | P20: Is 20-year or 30-year term life insurance better value? | Q20: Can I get funeral insurance at 80? | R20: Can I name my child as a life insurance beneficiary in Canada? | S20: Can I buy term life insurance at 70? | T20: Can I get 20-year term life insurance at 50? | U20: Does term life insurance renew automatically in Canada? | V20: Can a universal life policy lapse? | W20: How long does a life insurance payout take in Canada? | X20: Is a waiver of premium rider worth it? | Y20: Does life insurance pay out for suicide in Canada? | Z20: What A1C do insurers want for life insurance? | AA20: Are whole life dividends guaranteed? | AB20: How are life insurance quotes determined? | AC20: How long after cancer can I get life insurance? | AD20: Is whole life insurance a good investment in Canada? | AE20: Do you pay capital gains tax on a cottage when you die in Canada? | AF20: Is decreasing term life insurance available in Canada? | AG20: Can universal life insurance lose value? | AH20: What health questions do funeral insurance applications ask? | AI20: When should new parents buy life insurance? | AJ20: Who should own buy-sell life insurance, the partners or the company? | AK20: How long after a heart attack can I get life insurance? | AL20: Can life insurance companies see my medical records without consent? | AM20: Is it cheaper to buy life insurance directly from an insurer? | AN20: How do I know if a life insurance company is reputable? | AO20: How much life insurance does an employer usually provide? | AP20: Is $50,000 enough critical illness insurance? | AQ20: How much does life insurance for a child cost in Canada? | AR20: How much life insurance does a stay-at-home mom or dad need? | AS20: What happens to my health benefits when I retire early? | AT20: Can I get health insurance with a pre-existing condition in Canada? | AU20: Is joint life insurance cheaper than two policies? | AV20: Does seeing a therapist affect life insurance? | AW20: Do I need a medical exam to convert term life insurance? | AX20: Is life insurance a waste of money? | AY20: Does all funeral insurance have a waiting period? | AZ20: Is it worth getting life insurance at 25? | BA20: When does last-to-die life insurance make sense? | BB20: Does joint mortgage insurance pay out twice if both partners die? | BC20: What is the top rating class for life insurance?
A21: Subheadings: article outline and video chapters | B21: 10 sections · 5 FAQ | C21: 12 sections · 5 FAQ | D21: 11 sections · 4 FAQ | E21: 12 sections · 4 FAQ | F21: 8 sections · 4 FAQ | G21: 9 sections · 4 FAQ | H21: 9 sections · 4 FAQ | I21: 10 sections · 4 FAQ | J21: 10 sections · 4 FAQ | K21: 11 sections · 4 FAQ | L21: 9 sections · 4 FAQ | M21: 10 sections · 4 FAQ | N21: 11 sections · 4 FAQ | O21: 10 sections · 4 FAQ | P21: 11 sections · 4 FAQ | Q21: 8 sections · 4 FAQ | R21: 9 sections · 4 FAQ | S21: 11 sections · 5 FAQ | T21: 10 sections · 4 FAQ | U21: 10 sections · 5 FAQ | V21: 12 sections · 4 FAQ | W21: 9 sections · 4 FAQ | X21: 9 sections · 4 FAQ | Y21: 11 sections · 4 FAQ | Z21: 12 sections · 5 FAQ | AA21: 12 sections · 4 FAQ | AB21: 14 sections · 5 FAQ | AC21: 10 sections · 5 FAQ | AD21: 9 sections · 4 FAQ | AE21: 11 sections · 4 FAQ | AF21: 9 sections · 4 FAQ | AG21: 11 sections · 4 FAQ | AH21: 8 sections · 4 FAQ | AI21: 8 sections · 4 FAQ | AJ21: 10 sections · 4 FAQ | AK21: 11 sections · 5 FAQ | AL21: 11 sections · 4 FAQ | AM21: 11 sections · 4 FAQ | AN21: 11 sections · 4 FAQ | AO21: 9 sections · 4 FAQ | AP21: 9 sections · 4 FAQ | AQ21: 9 sections · 4 FAQ | AR21: 8 sections · 4 FAQ | AS21: 9 sections · 4 FAQ | AT21: 9 sections · 4 FAQ | AU21: 12 sections · 4 FAQ | AV21: 10 sections · 4 FAQ | AW21: 9 sections · 4 FAQ | AX21: 15 sections · 4 FAQ | AY21: 9 sections · 4 FAQ | AZ21: 10 sections · 4 FAQ | BA21: 10 sections · 4 FAQ | BB21: 8 sections · 4 FAQ | BC21: 9 sections · 4 FAQ
A22: How to read the outline: Bold = H2 section – = H3 under the H2 above Q: = FAQ question (FAQPage schema) The first H2 holds a 40–60 word direct answer. Use the H2s as video chapters. | B22: What is mortgage insurance in Canada? (quick answer) | C22: What is term life insurance? (quick answer) | D22: How does life insurance work? (quick answer) | E22: What are the main types of life insurance in Canada? (quick answer) | F22: Is life insurance worth it? (quick answer) | G22: How much does whole life insurance cost? (quick answer) | H22: Can you buy life insurance instantly in Canada? (quick answer) | I22: What happens to your benefits when you leave a job? (quick answer) | J22: What to do if you are declined for life insurance (quick answer) | K22: Is critical illness insurance worth it? (quick answer) | L22: Is there a family life insurance policy in Canada? (quick answer) | M22: Can you get life insurance with a pre-existing condition? (quick answer) | N22: Do you need a medical exam for life insurance? (quick answer) | O22: What is term 100 life insurance? (quick answer) | P22: Which term length should you choose? (quick answer) | Q22: Can seniors still buy funeral insurance? (quick answer) | R22: Who can be a life insurance beneficiary? (quick answer) | S22: Can you get life insurance over 70? (quick answer) | T22: Do you need life insurance over 50? (quick answer) | U22: What happens when your term life insurance ends? (quick answer) | V22: Whole life vs universal life: the short answer | W22: How to make a life insurance claim (quick answer) | X22: What are life insurance riders? (quick answer) | Y22: What does life insurance not cover? (quick answer) | Z22: Can diabetics get life insurance in Canada? (quick answer) | AA22: What is participating whole life insurance? (quick answer) | AB22: What affects life insurance rates? (quick answer) | AC22: Can cancer survivors get life insurance? (quick answer) | AD22: Buy term and invest the difference: the short answer | AE22: How life insurance helps with estate planning (quick answer) | AF22: Decreasing vs level term: the short answer | AG22: How does universal life insurance work? (quick answer) | AH22: Can you get funeral insurance with no medical exam? (quick answer) | AI22: Do new parents need life insurance? (quick answer) | AJ22: What is buy-sell agreement life insurance? (quick answer) | AK22: Can you get life insurance after a heart attack? (quick answer) | AL22: How do insurers check your medical history? (quick answer) | AM22: Broker, agent, bank or online: the short answer | AN22: How to choose a life insurance company (quick answer) | AO22: Is group life insurance enough on its own? (quick answer) | AP22: How much critical illness coverage you need (quick answer) | AQ22: Is children's life insurance worth it? (quick answer) | AR22: Does a stay-at-home parent need life insurance? (quick answer) | AS22: Your options after leaving work before 65 (quick answer) | AT22: Guaranteed issue vs underwritten (quick answer) | AU22: Joint or individual life insurance: the short answer | AV22: Can you get life insurance with depression or anxiety? (quick answer) | AW22: Can you convert term life insurance to permanent? (quick answer) | AX22: The 12 myths at a glance (quick answer) | AY22: What is a funeral insurance waiting period? (quick answer) | AZ22: Do young adults need life insurance? (quick answer) | BA22: What is joint last-to-die life insurance? (quick answer) | BB22: How joint mortgage life insurance works (quick answer) | BC22: What are life insurance rating classes? (quick answer)
B23: Mortgage default insurance (CMHC, Sagen, Canada Guaranty) | C23: How term life insurance works in Canada | D23: The basics: policy owner, life insured and beneficiary | E23: Term life insurance: 10, 20, 30 years and term to 65 | F23: Who usually needs life insurance | G23: Example whole life premiums by age and coverage (labelled estimates) | H23: How instant decisions work behind the scenes | I23: How long group coverage lasts after termination | J23: Declined, postponed or rated: what each means | K23: How critical illness insurance works: the tax-free lump sum | L23: What insurers mean by "family" coverage | M23: How insurers assess health issues | N23: When an exam is required: age and coverage amount | O23: How term 100 works | P23: 10-year term life insurance | Q23: Options at 60, 70 and 80 | R23: Revocable vs irrevocable beneficiaries | S23: Is there an age limit for life insurance in Canada? | T23: What life insurance costs at 50, 55 and 60 (labelled estimates) | U23: Option 1: Renew automatically | V23: How whole life insurance works | W23: Step 1: Find the policy and contact the insurer | X23: Waiver of premium | Y23: The suicide exclusion | Z23: Type 1 vs type 2 diabetes underwriting | AA23: Can permanent life insurance be used as savings? | AB23: Age: why waiting costs more | AC23: Does life insurance cover death from cancer? | AD23: How the strategy works | AE23: Deemed disposition: the tax bill at death | AF23: How decreasing term life insurance works | AG23: The two parts: insurance cost and investment account | AH23: The health questions simplified-issue plans ask | AI23: How much cover a new family needs | AJ23: Why business partners fund buyouts with insurance | AK23: What counts as a heart condition for life insurance | AL23: The application: health questions you must answer | AM23: Independent brokers and advisors | AN23: Financial strength: ratings and capital | AO23: What a typical group plan pays | AP23: Step 1: Months of income to replace | AQ23: What children's life insurance covers | AR23: The real cost of replacing a stay-at-home parent | AS23: Employer retiree benefits: what's typical | AT23: How guaranteed-issue plans handle pre-existing conditions | AU23: What is individual life insurance? | AV23: What underwriters ask about mental health | AW23: How the conversion privilege works | AX23: Myth 1: Life insurance is too expensive | AY23: How graded and limited benefits work | AZ23: Myth: "I'm too young for life insurance" | BA23: Why it pays at the second death | BB23: It pays once: what that means for the survivor | BC23: Preferred plus, preferred and standard
B24: – When it's required: less than 20% down | C24: – Level premiums and the death benefit | D24: Premiums and the death benefit | E24: Term to 100 | F24: Who may not need it | G24: What drives the price of whole life insurance | H24: – Health questions, the MIB and prescription checks | I24: Conversion plans: the no-medical window | J24: How to find out why | K24: What a serious illness costs that provincial health plans don't pay | L24: Ways to protect a family | M24: – Fully underwritten | N24: What the application asks | O24: – Level premiums for life (or paid up at 100) | P24: – Short needs and bridge coverage | Q24: Simplified vs guaranteed issue for older buyers | R24: Naming minor children: trustees and trusts | S24: Your options at 65, 70, 75 and 80+ | T24: Term vs permanent life insurance after 50 | U24: – How renewal premiums are set | V24: How universal life insurance works | W24: Step 2: Gather the documents | X24: Child term rider | Y24: The two-year contestability period | Z24: Why insurers consider diabetes | AA24: How cash value builds | AB24: Sex and life expectancy | AC24: What insurers weigh | AD24: Worked example: term plus a TFSA vs whole life (assumptions stated) | AE24: RRSP and RRIF balances at death | AF24: How level term life insurance works | AG24: – Level vs YRT cost of insurance | AH24: When guaranteed acceptance is the right fallback | AI24: Insuring a stay-at-home parent | AJ24: Joint first-to-die vs individual policies for partners | AK24: What underwriters look at | AL24: The MIB: what it records and how to see your file | AM24: Captive agents | AN24: Assuris: what happens if an insurer fails | AO24: Optional top-ups: pros and cons | AP24: Step 2: Costs provincial plans don't pay | AQ24: The case for: insurability and cash value | AR24: – Childcare | AS24: Converting your group plan at retirement | AT24: What underwriting asks and what it unlocks | AU24: – One life, its own beneficiaries | AV24: Mild, moderate and severe: how ratings differ | AW24: – No new medical evidence | AX24: Myth 2: It's only for funeral costs | AY24: What is paid if death happens in year one or two | AZ24: When buying in your 20s makes sense | BA24: The tax bill at the second death: deemed disposition and RRIF income | BB24: Joint lender cover vs two individual term policies | BC24: Rated policies: table ratings and flat extras
B25: – How the premium is calculated and added to your mortgage | C25: – Term lengths: 10, 20, 30 years and term to 65 | D25: Types of life insurance | E25: Permanent life insurance: whole and universal | F25: Cutting coverage to save money: what to check first | G25: – Age, sex, health and smoking | H25: – Accelerated underwriting vs simplified issue | I25: Conversion vs a new underwritten plan vs guaranteed issue | J25: Does a decline follow you? The MIB explained | K25: Who benefits most from critical illness coverage | L25: – Term life for each parent | M25: – Simplified issue | N25: What happens at a paramedical exam | O25: – No cash value, no dividends | P25: – What renewal costs after year 10 | Q25: Estimated monthly cost by age (labelled) | R25: Contingent and multiple beneficiaries | S25: Issue-age table by product type | T25: Fully underwritten vs no-medical at 50+ | U25: – Renewal age limits: check your contract | V25: Level vs YRT cost of insurance | W25: Step 3: Submit the claim forms | X25: Guaranteed insurability rider | Y25: Misrepresentation and non-disclosure | Z25: – Life expectancy and complications | AA25: – Guaranteed cash value | AB25: Health, build and family history | AC25: – Type of cancer | AD25: When buy term and invest wins | AE25: Keeping the family cottage | AF25: Increasing term and indexed coverage | AG25: – Investment options inside the policy | AH25: Health conditions and funeral insurance | AI25: Buying while on parental leave | AJ25: Cross-purchase vs corporate-owned structures | AK25: – Age at diagnosis and family history | AL25: Attending physician statements and medical records | AM25: Bank and creditor channels | AN25: Claims practices and how to judge them | AO25: What happens to group life when you leave or are laid off | AP25: Step 3: Debts and childcare during recovery | AQ25: The case against: cost and opportunity cost | AR25: – Household work and transport | AS25: Individual plans for ages 55 to 64: costs and limits | AT25: Drug coverage limits on guaranteed-issue plans | AU25: – When it fits best: single earners and business owners | AV25: Medication and therapy: do they count against you? | AW25: – Conversion deadlines: the age or policy year in your contract | AX25: Myth 3: You always need a medical exam | AY25: Accidental death during the waiting period | AZ25: – Co-signed debts and private student loans | BA25: Covering the family cottage, rental property or business shares | BB25: Separation, divorce and refinancing | BC25: What decides your class
B26: – Who it protects: the lender | C26: – Renewable and convertible features | D26: – Term life insurance | E26: Is variable life insurance sold in Canada? | F26: Lower-cost ways to keep protection | G26: – Coverage amount | H26: Online products compared: issue ages, maximums, questions (dated table) | I26: Coverage between jobs: how soon a new plan starts | J26: Reapplying with another insurer | K26: When critical illness insurance is not worth it | L26: – Joint life insurance | M26: – Guaranteed issue | N26: Blood, urine and other tests | O26: – What happens at age 100 | P26: 20-year term life insurance | Q26: Replacing group life that ended at retirement | R26: Naming your estate: pros and cons | S26: Term vs whole life after 70 | T26: Health factors that matter most after 50 | U26: Option 2: Convert to permanent life insurance | V26: Cash value and investment accounts compared | W26: How long payouts usually take | X26: Critical illness rider vs a standalone policy | Y26: Lapsed policies and grace periods | Z26: – How risk changes with age: under 40, 40 to 60, over 60 | AA26: – Dividends and the dividend scale | AB26: Smoking, vaping and cannabis | AC26: – Stage and grade | AD26: – Temporary needs: mortgage, children, income | AE26: Equalising inheritances between children | AF26: Cost comparison over a 25-year mortgage | AG26: Flexible deposits: minimum, target and maximum | AH26: Cost difference (labelled estimates) | AI26: Term, child riders and children's policies | AJ26: The capital dividend account explained | AK26: – Build, blood pressure and cholesterol | AL26: Prescription and pharmacy records | AM26: Direct online insurers | AN26: – Why "claim settlement ratio" figures need care in Canada | AO26: The conversion privilege and its limits | AP26: Choosing a term: 10, 20, to 65, to 75 or to 100 | AQ26: Child riders and RESPs as alternatives | AR26: – Lost income if the working parent cuts hours | AS26: Drug coverage before provincial senior plans start | AT26: Conversion plans as a third route | AU26: What is joint life insurance? | AV26: Time off work and disability claims | AW26: – Which permanent plans are eligible | AX26: Myth 4: Only people with dependants need it | AY26: Which policies have no waiting period | AZ26: – A partner, a mortgage or plans for children | BA26: Cost vs two individual permanent policies | BB26: Co-borrowers who aren't spouses | BC26: – Height, weight and BMI build charts
B27: Mortgage protection insurance (mortgage life insurance) | C27: Types of term life insurance | D27: – Whole life insurance | E27: No-medical options: simplified and guaranteed issue | F27: A two-minute self-test | G27: – Payment period: lifetime, 20-pay or 10-pay | H27: Buying remotely with a licensed advisor (no face-to-face meeting) | I27: Spouse's plan and provincial programs | J27: Simplified and guaranteed issue as a fallback | K27: Critical illness vs emergency savings: a worked example | L27: – Whole and universal life | M27: Common conditions and what to expect | N27: Doctor reports and the MIB | O27: Term 100 vs whole life insurance | P27: – Raising children and most mortgages | Q27: Questions to ask before you sign | R27: Quebec's different rules | S27: No-medical and guaranteed issue for seniors | T27: How much cover you still need: debts, income, spouse, estate | U27: – No new medical questions | V27: Guarantees and risks compared | W27: Why claims are delayed or denied: the two-year contestability rule | X27: Accidental death benefit | Y27: Exclusions on accidental death benefits and riders | Z27: What affects the price | AA27: Cash value vs cash surrender value | AB27: Occupation, hobbies and travel | AC27: – Time since diagnosis and treatment | AD27: – Disciplined investors with TFSA and RRSP room | AE27: Joint last-to-die policies for couples | AF27: Where your bank's mortgage insurance fits | AG27: Death benefit options: level vs level plus account value | AH27: How the Funeral expense desk helps | AI27: A new-parent checklist: will, guardian, beneficiary | AJ27: Valuing the business and sizing coverage | AK27: – Medications and follow-up tests | AL27: Paramedical exams, blood and urine tests | AM27: How each is paid: commissions and disclosure | AN27: Complaint records: OLHI and provincial regulators | AO27: Group vs individual coverage compared | AP27: A worked example for a two-income family | AQ27: Grandparents buying a policy | AR27: How much cover to buy: worked example | AS27: Travel coverage for early retirees | AT27: Worked example: someone with a chronic prescription | AU27: – Joint first-to-die | AV27: ADHD, PTSD and other diagnoses | AW27: Full vs partial conversion | AX27: Myth 5: Group insurance at work is enough | AY27: Level premiums and lifetime cover: what "rates never go up" really means | AZ27: – A family history of illness | BA27: Underwriting when one spouse has health issues | BB27: Couple decision checklist | BC27: – Blood pressure and cholesterol
B28: – How lender coverage works | C28: – Level term | D28: – Universal life insurance | E28: Joint life insurance: first-to-die and last-to-die | F28: Michael's take | G28: Participating vs non-participating whole life cost | H28: When an instant policy costs more than a fully underwritten one | I28: Life and disability coverage you can convert too | J28: Anonymous pre-underwriting before you apply | K28: Group benefits, disability insurance and critical illness: how they fit together | L28: – Mortgage life insurance | M28: – Diabetes | N28: How long underwriting takes | O28: Term 100 vs universal life insurance | P28: 30-year term life insurance | Q28: Michael's take | R28: How to change a beneficiary | S28: When life insurance is worth it after 70 | T28: Replacing group life before retirement | U28: – Conversion deadlines and eligible plans | V28: Tax-sheltered growth and exempt-policy limits | W28: What to do if a claim is denied | X28: Rider cost and value checklist | Y28: High-risk activities, travel and war exclusions | Z28: – Age at diagnosis | AA28: Using your cash value: policy loans, withdrawals and collateral | AB28: Driving record and criminal record | AC28: – Recurrence and other health issues | AD28: When permanent insurance wins | AE28: Avoiding probate with named beneficiaries | AF28: – A shrinking benefit with a level premium | AG28: Tax implications | AH28: Michael's take | AI28: Michael's take | AJ28: Disability and critical illness buyouts | AK28: – Smoking and lifestyle | AL28: Risk classification: turning your history into a price | AM28: What good advice looks like: experience, underwriting know-how, transparency | AN28: Product range, underwriting and conversion options | AO28: How to size a personal policy around group cover | AP28: Coordinating with disability and group coverage | AQ28: Verdict by family situation | AR28: Term length: until the youngest child is independent | AS28: Budgeting health costs from retirement to 65 | AT28: How to choose | AU28: – Joint last-to-die | AV28: Disclosure: why honesty protects your claim | AW28: What the new premium costs (example estimate) | AX28: Myth 6: Stay-at-home parents don't need cover | AY28: Questions to ask the insurer | AZ28: Locking in insurability and lower rates | BA28: Ownership, beneficiaries and probate | BB28: Michael's take | BC28: – Family history
B29: – A shrinking benefit with a level premium | C29: – Decreasing term (mortgage-style) | D29: – No-medical life insurance | E29: Group and creditor life insurance | F29: FAQ | G29: Whole life vs term life: the price gap | H29: Provinces where online buying is limited | I29: A 30-day action checklist | J29: Improving your insurability over time | K29: A five-question decision tree | L29: – Children's life insurance and child riders | M29: – Cancer history | N29: Exam-day preparation checklist | O29: Term 100 vs a 20 or 30-year term | P29: – Young families and first-time buyers | Q29: FAQ | R29: Michael's take | S29: – Final expenses | T29: Types compared: term, whole, universal, simplified and guaranteed issue | U29: Option 3: Apply for a new term policy | V29: Is variable life insurance sold in Canada? | W29: Michael's take | X29: Michael's take | Y29: Waiting periods on no-medical policies | Z29: – Type of diabetes and treatment (insulin or oral medication) | AA29: Dividend options: paid-up additions, cash or premium reduction | AB29: Coverage amount, term length and policy type | AC29: Typical postponement periods by cancer type | AD29: – Lifelong needs: estate taxes, final expenses, a dependant with a disability | AE29: Charitable gifts with life insurance | AF29: Which to choose: decision guide | AG29: – Tax-exempt growth and the exempt test | AH29: FAQ | AI29: FAQ | AJ29: Setup checklist with your lawyer and accountant | AK29: How long insurers wait after a cardiac event (timeline) | AL29: Leaving something out: misrepresentation and the two-year rule | AM29: How to check a licence in your province | AN29: Service: online tools, advisors and policy changes | AO29: Michael's take | AP29: Michael's take | AQ29: Michael's take | AR29: How insurers set limits for a parent without income | AS29: Michael's take | AT29: Michael's take | AU29: Key differences | AV29: No-medical options if you are declined | AW29: When converting makes sense | AX29: Myth 7: You're too young to need it | AY29: Michael's take | AZ29: What it costs in your 20s (labelled estimates) | BA29: Last-to-die cover for blended families | BB29: FAQ | BC29: – Smoking, vaping and cannabis
B30: – Underwriting at claim time: what to check | C30: – Increasing and indexed term | D30: How life insurance is priced | E30: Side-by-side comparison table | F30: Q: Do I need life insurance if I'm single with no kids? | G30: Is whole life insurance worth the cost? | H30: How to apply online without misstatements | I30: Michael's take | J30: Michael's take | K30: How to buy only the coverage you need | L30: Comparison table: family life insurance options | M30: – Heart conditions | N30: No-exam alternatives and when they cost more | O30: How much does term 100 cost? (example estimates) | P30: Term to 65 and term to 100 | Q30: Q: Can I get funeral insurance at 80? | R30: FAQ | S30: – Estate taxes and leaving an inheritance | T30: Michael's take | U30: Option 4: Let the policy expire | V30: Comparison table | W30: FAQ | X30: FAQ | Y30: How to read the fine print before you sign | Z30: – A1C and blood sugar control | AA30: Par vs non-par whole life | AB30: How quotes are calculated | AC30: Your options by stage of recovery | AD30: – Tax-sheltered growth after registered room is full | AE30: Worked example: a cottage-owning couple | AF30: Michael's take | AG30: – Withdrawals, policy loans and taxable gains | AH30: Q: What health questions do funeral insurance applications ask? | AI30: Q: When should new parents buy life insurance? | AJ30: Michael's take | AK30: Stents, bypass surgery, heart failure and atrial fibrillation | AL30: Your privacy rights and consent | AM30: Questions to ask before you buy | AN30: Can you trust online reviews of insurers? | AO30: FAQ | AP30: FAQ | AQ30: FAQ | AR30: Term vs permanent for a stay-at-home parent | AS30: FAQ | AT30: FAQ | AU30: – Coverage and payouts | AV30: Michael's take | AW30: – Your health has changed | AX30: Myth 8: You're too old to get it | AY30: FAQ | AZ30: When you can safely wait | BA30: Michael's take | BB30: Q: Does joint mortgage insurance pay out twice if both partners die? | BC30: Worked example: one diabetic applicant across rating classes
B31: Mortgage default vs mortgage protection vs mortgage loan insurance: comparison table | C31: – Yearly renewable term (YRT) | D31: How payouts work | E31: How to choose the right type | F31: Q: Is life insurance worth it after the mortgage is paid? | G31: Ways to make permanent cover affordable | H31: Michael's take | I31: FAQ | J31: FAQ | K31: Michael's take | L31: How much cover a family needs | M31: – High blood pressure and cholesterol | N31: Michael's take | O31: Who term 100 suits | P31: How price changes with term length (example estimates) | Q31: Q: Is there an age limit for funeral insurance? | R31: Q: Can I name my child as a life insurance beneficiary in Canada? | S31: – Debts and a surviving spouse's income | T31: FAQ | U31: What to weigh before you decide | V31: Who each one suits | W31: Q: How long does a life insurance payout take in Canada? | X31: Q: Is a waiver of premium rider worth it? | Y31: Michael's take | Z31: – Complications: kidney, eye, nerve and heart | AA31: How cash value growth is taxed (exempt policies) | AB31: – Mortality tables and actuarial pricing | AC31: – During treatment: guaranteed issue | AD31: – Guarantees vs market risk | AE31: Michael's take | AF31: FAQ | AG31: – The tax-free death benefit | AH31: Q: Can I get funeral insurance with diabetes or heart disease? | AI31: Q: Can I get life insurance while on maternity or parental leave? | AJ31: FAQ | AK31: Your options: traditional, simplified and guaranteed issue | AL31: Michael's take | AM31: Michael's take | AN31: Red flags: signs of an unreliable seller | AO31: Q: How much life insurance does an employer usually provide? | AP31: Q: Is $50,000 enough critical illness insurance? | AQ31: Q: How much does life insurance for a child cost in Canada? | AR31: Michael's take | AS31: Q: What happens to my health benefits when I retire early? | AT31: Q: Can I get health insurance with a pre-existing condition in Canada? | AU31: – Cost | AV31: FAQ | AW31: – You need cover for life: estate, final expenses, a dependant with a disability | AX31: Myth 9: Pre-existing conditions disqualify you | AY31: Q: Does all funeral insurance have a waiting period? | AZ31: Group coverage through work: is it enough? | BA31: FAQ | BB31: Q: What happens to joint mortgage insurance if we separate? | BC31: Rating class price impact table
B32: Is mortgage life insurance mandatory? | C32: How much does term life insurance cost? | D32: – Is the death benefit taxable? | E32: Michael's take | F32: Q: Is it smarter to invest instead of buying life insurance? | G32: – Term to 100 | H32: FAQ | I32: Q: How long do I have to convert my group health benefits? | J32: Q: Can I get the reason my life insurance was declined? | K32: FAQ | L32: Insuring a stay-at-home parent | M32: – Mental health | N32: FAQ | O32: – Estate taxes and final expenses | P32: Matching your term to your mortgage and your kids | Q32: Q: Do seniors need a medical exam for funeral insurance? | R32: Q: What happens if my beneficiary dies before me? | S32: – A dependant with special needs | T32: Q: Can I get 20-year term life insurance at 50? | U32: – Your health today | V32: Michael's take | W32: Q: What documents do I need to claim life insurance? | X32: Q: Can I add a rider after my policy starts? | Y32: FAQ | Z32: – Other conditions: blood pressure, cholesterol, weight | AA32: Reading a policy illustration line by line | AB32: – Risk classes | AC32: – After treatment: simplified issue | AD32: The behaviour risk: actually investing the difference | AE32: FAQ | AF32: Q: Is decreasing term life insurance available in Canada? | AG32: Risks: lapse, market returns and rising YRT costs | AH32: Q: Is guaranteed acceptance funeral insurance more expensive? | AI32: Q: How much life insurance does a stay-at-home parent need? | AJ32: Q: Who should own buy-sell life insurance, the partners or the company? | AK32: Will existing life insurance pay after a heart attack? | AL32: FAQ | AM32: FAQ | AN32: Michael's take | AO32: Q: Can I keep my group life insurance if I quit? | AP32: Q: Should critical illness coverage equal my annual salary? | AQ32: Q: Can grandparents buy life insurance on a grandchild? | AR32: FAQ | AS32: Q: Can I get health insurance at 60 without a medical? | AT32: Q: What does guaranteed issue mean? | AU32: – Flexibility after life changes | AV32: Q: Does seeing a therapist affect life insurance? | AW32: When it doesn't: lower-cost alternatives | AX32: Myth 10: Investing beats insurance every time | AY32: Q: What happens if I die during the waiting period? | AZ32: Term, permanent or a convertible term policy? | BA32: Q: When does last-to-die life insurance make sense? | BB32: Q: Can unmarried co-owners get joint mortgage insurance? | BC32: How to ask for a reconsideration
B33: Why term life insurance can be a better fit | C33: – What drives your premium: age, health, smoking, amount and term | D33: – Paying final expenses | E33: FAQ | F33: Q: Should retirees keep life insurance? | G33: – Blending term and permanent | H33: Q: Can I get life insurance coverage the same day in Canada? | I33: Q: Do my benefits continue during the notice period? | J33: Q: Will one decline stop other insurers from approving me? | K33: Q: Is critical illness insurance a waste of money? | L33: How to buy family life insurance | M33: – Other chronic conditions | N33: Q: Who pays for a life insurance medical exam? | O33: – Leaving an inheritance | P33: Laddering two policies instead of one | Q33: Q: Should I buy funeral insurance or save the money? | R33: Q: Should I name my estate as beneficiary? | S33: – Charitable giving | T33: Q: Is no-medical life insurance worth it at 50? | U33: – Debts and dependants still relying on you | V33: FAQ | W33: Q: Can a life insurance claim be denied after two years? | X33: Q: Does a child term rider cover all my children? | Y33: Q: Does life insurance pay out for suicide in Canada? | Z33: Prediabetes and gestational diabetes | AA33: When participating whole life fits, and when it doesn't | AB33: – Medical exams and records | AC33: – In remission: fully underwritten (standard or rated) | AD33: Is life insurance an investment? Myth vs reality | AE33: Q: Do you pay capital gains tax on a cottage when you die in Canada? | AF33: Q: Is decreasing term cheaper than level term? | AG33: Universal life vs whole life vs term | AH33: Q: What if I answer a health question wrong? | AI33: Q: Should I name my baby as a beneficiary? | AJ33: Q: How much buy-sell coverage do we need? | AK33: How lifestyle changes help your rating | AL33: Q: Can life insurance companies see my medical records without consent? | AM33: Q: Is it cheaper to buy life insurance directly from an insurer? | AN33: FAQ | AO33: Q: Is optional group life cheaper than individual term? | AP33: Q: How long should my critical illness term be? | AQ33: Q: Is a child term rider enough? | AR33: Q: How much life insurance does a stay-at-home mom or dad need? | AS33: Q: When do provincial drug plans start covering seniors? | AT33: Q: Do guaranteed-issue plans cover existing prescriptions? | AU33: Joint vs individual term life | AV33: Q: Can I get life insurance if I take antidepressants? | AW33: How to convert, step by step | AX33: Myth 11: Permanent insurance is only for the wealthy | AY33: Q: Is accidental death covered from day one? | AZ33: Michael's take | BA33: Q: Is joint last-to-die cheaper than two policies? | BB33: Q: Is joint mortgage insurance cheaper than two policies? | BC33: Michael's take
B34: – A fixed benefit | C34: – Example estimates by age (labelled, dated) | D34: – Paying off the mortgage | E34: Q: What is the most common type of life insurance in Canada? | G34: – Converting term later | H34: Q: Is buying life insurance online cheaper? | I34: Q: Is a conversion plan more expensive than a new plan? | J34: Q: How long should I wait before reapplying? | K34: Q: Do I need critical illness insurance if I have group benefits? | L34: – Work out your family's needs | M34: Disclose your full medical history: why it protects your claim | N34: Q: Can I eat before a life insurance blood test? | O34: – Business owners funding buy-sell agreements | P34: Term length decision table | R34: Q: Can I change my beneficiary without telling them? | S34: What it costs: labelled estimates by age | T34: Q: How much does $250,000 of life insurance cost at 50? | U34: – Affordability on a fixed income | V34: Q: Can a universal life policy lapse? | W34: Q: Who do I complain to if my claim is denied? | X34: Q: Is a critical illness rider the same as critical illness insurance? | Y34: Q: Does life insurance cover death from a drug overdose? | Z34: Fully underwritten vs no-medical options | AA34: Michael's take | AB34: Temporary health issues vs chronic conditions | AC34: Cancer-type table: skin, breast, prostate, thyroid, colon and blood cancers | AD34: Michael's take | AE34: Q: How much life insurance do I need to cover estate taxes? | AF34: Q: Does lender mortgage insurance work like decreasing term? | AG34: Is universal life insurance right for you? | AJ34: Q: Is the payout tax-free to the corporation? | AK34: Cardiology reports to request before you apply | AL34: Q: Do insurers check pharmacy records in Canada? | AM34: Q: How are life insurance brokers paid in Canada? | AN34: Q: How do I know if a life insurance company is reputable? | AO34: Q: Does group life insurance cover me after retirement? | AP34: Q: Does group critical illness coverage count toward what I need? | AQ34: Q: Who owns a child's life insurance policy? | AR34: Q: Can you get life insurance without an income? | AS34: Q: Should early retirees keep travel insurance? | AT34: Q: Is underwritten health insurance cheaper? | AU34: Joint vs individual permanent life | AV34: Q: Will a past suicide attempt mean a decline? | AW34: Michael's take | AX34: Myth 12: Ten times your salary is always enough | AY34: Q: Can I switch to a policy without a waiting period? | AZ34: FAQ | BA34: Q: Can one spouse be uninsurable and still get joint last-to-die? | BC34: FAQ
B35: – Cost | C35: Pros and cons of term life insurance | D35: Life insurance with health issues | E35: Q: Is term to 100 the same as whole life? | G35: Michael's take | H35: Q: What happens if an online application is referred to underwriting? | I35: Q: Can I get health insurance with a pre-existing condition after leaving work? | J35: Q: What is anonymous pre-underwriting? | K35: Q: What are the downsides of critical illness insurance? | L35: – Compare insurers and policy types | M35: Temporary health issues vs chronic conditions | N35: Q: What is the MIB and can I see my file? | O35: Drawbacks to know | P35: Michael's take | S35: The medical questions to expect | T35: Q: Should I buy permanent life insurance at 50? | U35: – Estate planning and final expenses | V35: Q: Which is cheaper, whole life or universal life? | Y35: Q: Will life insurance pay if I die abroad? | Z35: Term vs permanent cover for diabetics | AA35: FAQ | AB35: Why quotes from different insurers vary | AC35: Records to gather before you apply | AD35: FAQ | AE35: Q: Is joint last-to-die cheaper than two policies? | AF35: Q: Can I reduce a level term policy later? | AG35: Buying universal life insurance, step by step | AJ35: Q: What happens to the policy if a partner leaves? | AK35: Michael's take | AL35: Q: What is the MIB and can I correct my file? | AM35: Q: Can a bank advisor sell me any insurer's policy? | AN35: Q: What happens to my policy if my insurer goes bankrupt? | AR35: Q: Is spousal coverage through work enough? | AU35: Scenarios: married couples, business partners, parents and adult children | AV35: Q: Does ADHD affect life insurance in Canada? | AW35: FAQ | AX35: Michael's take | AZ35: Q: Is it worth getting life insurance at 25? | BA35: Q: What happens to the policy after a divorce? | BC35: Q: What is the top rating class for life insurance?
B36: – You choose the beneficiary | C36: – Pros: affordability, simplicity, flexibility | D36: How much life insurance you need | E36: Q: Which types of life insurance build cash value? | G36: FAQ | H36: Q: Can I buy life insurance online in Quebec? | K36: Q: Is critical illness insurance worth it for a 30-year-old? | L36: – Work with a licensed advisor | M36: How a licensed advisor helps: shopping underwriting, not just price | N36: Q: How long does life insurance underwriting take in Canada? | O36: – The policy lapses if you stop paying | P36: FAQ | S36: Michael's take | U36: Renew vs convert vs new policy: comparison table | V36: Q: Can I switch from universal life to whole life? | Y36: Q: Can an insurer refuse to pay after two years? | Z36: The underwriting process: tests, records and timing | AA36: Q: Are whole life dividends guaranteed? | AB36: How to lower your life insurance rate | AC36: Critical illness insurance after cancer | AD36: Q: Is whole life insurance a good investment in Canada? | AE36: Q: What is the best way to leave money to family? | AG36: – Work out your insurance need | AK36: FAQ | AL36: Q: Can an insurer deny a claim for something I didn't disclose? | AM36: Q: Do I pay more if I use a broker? | AN36: Q: Can I switch insurance companies later? | AR36: Q: What does it cost to insure a stay-at-home parent? | AU36: Underwriting for joint life: how two health histories combine | AW36: Q: Do I need a medical exam to convert term life insurance? | AX36: FAQ | AZ36: Q: Are student loans forgiven if you die in Canada? | BC36: Q: Can my rating class improve later?
B37: – It moves with you when you switch lenders | C37: – Cons: temporary cover, no cash value, renewal increases | D37: How to buy: online, through an advisor or at work | E37: Q: Can I combine term and permanent life insurance? | G37: Q: Why is whole life insurance so expensive? | L37: – Know your policy before you sign | M37: Improving your insurability | O37: – Availability varies by insurer | P37: Q: Is 20-year or 30-year term life insurance better value? | S37: FAQ | U37: A five-year checklist before your term ends | V37: Q: Does universal life insurance build cash value? | Z37: What helps your case and what hurts it | AA37: Q: Can I borrow against the cash value of my policy? | AB37: Michael's take | AC37: Michael's take | AD37: Q: What if I can't keep investing every month? | AG37: – Choose a licensed advisor | AK37: Q: How long after a heart attack can I get life insurance? | AN37: Q: Can I trust online reviews about insurance companies? | AU37: What happens if you separate or divorce | AW37: Q: Can I convert only part of my coverage? | AX37: Q: Is life insurance a waste of money? | AZ37: Q: How much life insurance should a 25-year-old get? | BC37: Q: Does BMI affect life insurance rates in Canada?
B38: When lender coverage can make sense | C38: Is term insurance a waste if you outlive it? | D38: Michael's take | G38: Q: Is limited-pay whole life worth it? | L38: Michael's take | M38: Choosing the right amount when cover is rated | O38: Michael's take | P38: Q: Can I renew a 10-year term policy? | S38: Q: Can I buy term life insurance at 70? | U38: Michael's take | Z38: Diabetes underwriting factor matrix | AA38: Q: Is the cash surrender value taxable? | AB38: FAQ | AC38: FAQ | AD38: Q: Does buy term and invest work for business owners? | AG38: – Medical underwriting | AK38: Q: Can you get life insurance with a stent? | AU38: Pros and cons table | AW38: Q: Does my premium go up when I convert? | AX38: Q: Can I get life insurance without a medical exam? | AZ38: Q: Can I increase my coverage later? | BC38: Q: What does a table 2 rating mean?
B39: Questions to ask at signing | C39: Who term life insurance suits | D39: FAQ | G39: Q: How much is a $100,000 whole life policy? | L39: FAQ | M39: Michael's take | O39: FAQ | P39: Q: Should my term match my mortgage amortization? | S39: Q: What is the oldest age to get life insurance in Canada? | U39: FAQ | Z39: Michael's take | AA39: Q: What happens if the insurer cuts its dividend scale? | AB39: Q: How are life insurance quotes determined? | AC39: Q: How long after cancer can I get life insurance? | AD39: Q: Can I do both: term now and permanent later? | AG39: – Policy issue and annual statements | AK39: Q: Can you get life insurance after heart bypass surgery? | AU39: Michael's take | AW39: Q: What happens if I miss the conversion deadline? | AX39: Q: Does life insurance cover suicide in Canada?
B40: Michael's take | C40: – Young families | D40: Q: How does a life insurance payout work in Canada? | G40: Q: Can I lower my whole life premium later? | L40: Q: What type of life insurance is best for a family? | M40: FAQ | O40: Q: Is term 100 the same as whole life insurance? | P40: Q: Can I shorten or reduce my term later? | S40: Q: Is life insurance worth it after 70? | U40: Q: Does term life insurance renew automatically in Canada? | Z40: FAQ | AB40: Q: Is life insurance more expensive as you age? | AC40: Q: Can a stage 4 cancer patient get life insurance? | AG40: Michael's take | AK40: Q: Does atrial fibrillation affect life insurance? | AU40: FAQ | AX40: Q: Is life insurance through work enough?
B41: FAQ | C41: – Homeowners with a mortgage | D41: Q: What happens if I stop paying premiums? | L41: Q: Is there life insurance that covers the whole family? | M41: Q: Can I be denied life insurance for a pre-existing condition? | O41: Q: Does term 100 have a cash value? | S41: Q: Is guaranteed issue the only option after 80? | U41: Q: How much do premiums rise at renewal? | Z41: Q: What A1C do insurers want for life insurance? | AB41: Q: Do all life insurance policies require a medical exam? | AC41: Q: Can I get life insurance if I had cancer 10 years ago? | AG41: FAQ | AK41: Q: Is a heart attack covered by my life insurance? | AU41: Q: Is joint life insurance cheaper than two policies?
B42: Q: Does CMHC insurance pay off my mortgage if I die? | C42: – Business owners and partners | D42: Q: Do you get money back from life insurance? | L42: Q: What is one benefit of life insurance to your family? | M42: Q: Is no-medical life insurance better if I have health issues? | O42: Q: What happens to term 100 if I live past 100? | S42: Q: Do seniors need a medical exam for life insurance? | U42: Q: What is the deadline to convert term life insurance? | Z42: Q: Can insulin-dependent diabetics get life insurance? | AB42: Q: Can I get life insurance with a pre-existing condition? | AC42: Q: Will my existing policy pay if I die of cancer? | AG42: Q: Can universal life insurance lose value? | AU42: Q: What happens to joint life insurance after a divorce?
B43: Q: Can my bank require me to buy mortgage life insurance? | C43: Term vs permanent life insurance at a glance | D43: Q: Who gets the money if there is no beneficiary? | L43: Q: What is the best way to leave money to family? | M43: Q: Will my premiums go down if my health improves? | O43: Q: Can I convert my term policy to term 100? | U43: Q: Can I get a new policy if my health has changed? | Z43: Q: How does type 2 diabetes affect life insurance rates? | AB43: Q: Do women pay less for life insurance? | AC43: Q: Does skin cancer affect life insurance? | AG43: Q: Can I skip premium payments on universal life? | AU43: Q: Can I split a joint policy into two individual policies?
B44: Q: Is mortgage protection insurance the same as mortgage insurance? | C44: A worked example: a 35-year-old with a mortgage | M44: Q: What happens if I don't disclose a condition? | U44: Q: Do I get money back when term life insurance expires? | Z44: Q: Does prediabetes raise life insurance rates? | AG44: Q: Is the universal life death benefit tax-free? | AU44: Q: Does joint first-to-die pay out twice?
B45: Q: Do I need mortgage insurance with 20% down? | C45: How to buy term life insurance in Canada | Z45: Q: Is no-medical life insurance a good option for diabetics? | AG45: Q: Who should consider universal life insurance?
B46: Q: Can I cancel mortgage life insurance after signing? | C46: Michael's take
C47: FAQ
C48: Q: Does term life insurance pay out if I outlive it?
C49: Q: Can I cancel term life insurance at any time?
C50: Q: Is a term life insurance payout taxable in Canada?
C51: Q: Can I get term life insurance without a medical exam?
C52: Q: Can I convert term life insurance to permanent?

Sheet Knowledge Content
A1: familialife.ca: knowledge-based content that creates value
A2: Every page that teaches the reader something (guides, articles, product explainers). Outlines from Internet Archive snapshots (see 'Method & Notes'); three pages known from search results only.
A4: # | B4: Content type | C4: Product / topic | D4: Title (as published) | E4: URL | F4: What the reader learns (value created) | G4: Value devices | H4: Main sections | I4: Subheadings (count) | J4: Page words (incl. site template) | K4: Approx. article words | L4: Published | M4: Last updated | N4: Schema types | O4: Instasure equivalent | P4: Outline source
A5: 1 | B5: Home page | C5: Brand & home page | D5: Familia Life - Lowest Life Insurance Rates in Canada | E5: https://familialife.ca/ | F5: Brand pitch: national brokers comparing Canadian insurers, with highlights for young families, final expense, high-risk and hard-to-insure clients, mortgage protection and fully remote (no face-to-face) service; client testimonials; latest articles. | G5: Cost and pricing factors | H5: Life Insurance is a sturdy umbrella - Often overlooked in fair weather, but priceless protection when life's storms hit. | Best Life Insurance Rates in Canada | Buying life insurance can seem like a perplexing puzzle | Read our latest | I5: 10 | J5: 2537 | K5: =IF(J5="","",MAX(0,J5-'Method & Notes'!$B$6)) -> 1363 | L5: 2020-06-09 | M5: 2025-03-30 | N5: Article, InsuranceAgency, Organization, Person, SearchAction, WebPage, WebSite | O5: Home page (instant estimates, desks, insurer scroller) | P5: Internet Archive snapshot 2025-04-18
A6: 2 | B6: Product explainer page | C6: Term Life Insurance | D6: Term Life Insurance | E6: https://familialife.ca/term-life-insurance/ | F6: What term life is in Canada, whether coverage that expires is a drawback, benefits and cost; quote call to action. | G6: Benefits / pros and cons, Cost and pricing factors | H6: Term Life Insurance | I6: 5 | J6: 2706 | K6: =IF(J6="","",MAX(0,J6-'Method & Notes'!$B$6)) -> 1532 | L6: 2022-03-04 | M6: 2023-06-07 | N6: Article, BreadcrumbList, InsuranceAgency, Organization, Person, WebPage, WebSite | O6: /term-life-insurance/ product page | P6: Internet Archive snapshot 2024-01-16
A7: 3 | B7: Guide | C7: Term Life Insurance | D7: Everything about Term Life Insurance | E7: https://familialife.ca/everything-about-term-life-insurance/ | F7: Types of term (decreasing, increasing, yearly renewable), who it suits (young families, homeowners, business owners), pros (affordability, simplicity, flexibility) and cons (temporary cover, no cash value, rising renewal premiums). | G7: Benefits / pros and cons, Cost and pricing factors | H7: Term Life Insurance 101. | What Is Term Life Insurance? | I7: 19 | J7: 3326 | K7: =IF(J7="","",MAX(0,J7-'Method & Notes'!$B$6)) -> 2152 | L7: 2023-06-01 | M7: 2023-06-07 | N7: BlogPosting, BreadcrumbList, InsuranceAgency, Organization, Person, WebPage, WebSite | O7: Partly: Term vs Whole Life Insurance in Canada (published); Types of Life Insurance in Canada (planned) | P7: Internet Archive snapshot 2024-01-16
A8: 4 | B8: Article | C8: Term Life Insurance | D8: What Happens at the End of Term Life Insurance? | E8: https://familialife.ca/what-happens-at-the-end-of-term-life-insurance/ | F8: What happens when a term ends (policy ends, renewal, conversion), what to weigh (health, finances, affordability, estate), new term policy vs conversion vs letting it expire. | H8: The Term Ends – Now What? | Factors To Consider at the End of Your Term Life Insurance | Is A New Term Policy An Option? | Conversion to Permanent Life Insurance | Letting Your Term Life Insurance Expire | I8: 13 | J8: 2296 | K8: =IF(J8="","",MAX(0,J8-'Method & Notes'!$B$6)) -> 1122 | L8: 2023-06-23 | M8: 2023-09-06 | N8: BlogPosting, BreadcrumbList, InsuranceAgency, Organization, Person, WebPage, WebSite | O8: Planned: What Happens When Term Life Insurance Expires? | P8: Internet Archive snapshot 2024-01-16
A9: 5 | B9: Product explainer page | C9: Permanent & Whole Life | D9: Permanent Life Insurance | E9: https://familialife.ca/whole-life-insurance/ | F9: What permanent life is, its types (whole, universal, variable), permanent vs term, and using permanent insurance as savings. | G9: Comparisons | H9: Permanent Life Insurance | Why Familia Life? | I9: 9 | J9: 2321 | K9: =IF(J9="","",MAX(0,J9-'Method & Notes'!$B$6)) -> 1147 | L9: 2022-03-04 | M9: 2023-06-09 | N9: Article, BreadcrumbList, InsuranceAgency, Organization, Person, WebPage, WebSite | O9: /whole-life-insurance/ product page | P9: Internet Archive snapshot 2024-01-16
A10: 6 | B10: Guide | C10: Permanent & Whole Life | D10: Everything about Permanent Life Insurance in Canada | E10: https://familialife.ca/everything-about-permanent-life-insurance/ | F10: Definition and key features, types (whole, universal, Term 100) with benefits, advantages, permanent vs term comparison, no-medical permanent options, how much to buy, converting term to permanent. | G10: 2 tables, Comparisons, Scenarios / examples, Benefits / pros and cons, Cost and pricing factors | H10: What is Permanent Life Insurance? | I10: 47 | J10: 3042 | K10: =IF(J10="","",MAX(0,J10-'Method & Notes'!$B$6)) -> 1868 | L10: 2023-08-17 | M10: 2023-09-19 | N10: BlogPosting, BreadcrumbList, InsuranceAgency, Organization, Person, WebPage, WebSite | O10: Partly: Term vs Whole Life (published); Whole Life vs Universal Life (planned) | P10: Internet Archive snapshot 2024-01-16
A11: 7 | B11: Article | C11: Universal Life | D11: What is Universal Life Insurance and How Does it Work? | E11: https://familialife.ca/what-is-universal-life-insurance/ | F11: How universal life works, the cash-value component, how it differs from other types, who it suits, tax implications and a step-by-step buying process. | G11: Steps / checklist, Underwriting explained | H11: The Basics of Universal Life Insurance | Understanding the Cash Value Component | Differentiating Universal Life Insurance from Other Types | Is Universal Life Insurance Right for You? | Tax Implications and the Purchase Process | Buying Universal Life Insurance: Step-by-Step | I11: 11 | J11: 2468 | K11: =IF(J11="","",MAX(0,J11-'Method & Notes'!$B$6)) -> 1294 | L11: 2023-06-22 | M11: 2023-08-31 | N11: BlogPosting, BreadcrumbList, InsuranceAgency, Organization, Person, WebPage, WebSite | O11: Planned: Whole Life vs Universal Life; /life-insurance/universal-life/ service page | P11: Internet Archive snapshot 2024-01-16
A12: 8 | B12: Guide | C12: Joint Life | D12: Joint Life Insurance vs Individual Life Insurance: A Comparative Analysis | E12: https://familialife.ca/what-is-joint-life/ | F12: Individual vs joint life: features, first-to-die vs last-to-die, scenarios (couples, business partners, estate planning), term and permanent versions, case studies, pros and cons, joint underwriting (average age band), coverage and pricing, FAQ. | G12: FAQ, 1 table, Comparisons, Scenarios / examples, Benefits / pros and cons, Cost and pricing factors, Underwriting explained | H12: What is Individual Life Insurance? | What is Joint Life Insurance? | Key Differences | Comparative Analysis | Pros and Cons of Individual Life Insurance | Pros and Cons of Joint Life Insurance | Underwriting for Joint Life Insurance: A Deeper Dive | How Much Insurance Do You Need? | Quotes and Pricing | I12: 67 | J12: 2928 | K12: =IF(J12="","",MAX(0,J12-'Method & Notes'!$B$6)) -> 1754 | L12: 2023-09-08 | M12: 2023-09-08 | N12: BlogPosting, BreadcrumbList, InsuranceAgency, Organization, Person, WebPage, WebSite | O12: Planned: Joint Life Insurance vs Two Separate Policies; /life-insurance/joint/ service page | P12: Internet Archive snapshot 2024-01-09
A13: 9 | B13: Product explainer page | C13: No Medical Life Insurance | D13: No Medical Insurance | E13: https://familialife.ca/no-medical-insurance/ | F13: What no-medical insurance is, how it works, its benefits and cost. | G13: Benefits / pros and cons, Cost and pricing factors | H13: No Medical Insurance | I13: 5 | J13: 2356 | K13: =IF(J13="","",MAX(0,J13-'Method & Notes'!$B$6)) -> 1182 | L13: 2022-03-04 | M13: 2023-06-09 | N13: Article, BreadcrumbList, InsuranceAgency, Organization, Person, WebPage, WebSite | O13: /no-medical-life-insurance/ product page | P13: Internet Archive snapshot 2024-01-19
A14: 10 | B14: Guide | C14: No Medical Life Insurance | D14: Everything about No Medical Life Insurance | E14: https://familialife.ca/everything-about-no-medical-life-insurance/ | F14: What no-medical life insurance is, benefits, who it suits (health conditions, seniors, speed, needle phobia, busy schedules), rate classes (standard, preferred, ratings) with a diabetic worked example, and simplified issue. | G14: Benefits / pros and cons, Cost and pricing factors, Underwriting explained | H14: No Medical Life Insurance 101. | What Is No Medical Life Insurance? | I14: 21 | J14: 3169 | K14: =IF(J14="","",MAX(0,J14-'Method & Notes'!$B$6)) -> 1995 | L14: 2023-06-02 | M14: 2023-06-07 | N14: BlogPosting, BreadcrumbList, InsuranceAgency, Organization, Person, WebPage, WebSite | O14: Published: No-Medical Life Insurance: Simplified Issue vs Guaranteed Issue | P14: Internet Archive snapshot 2024-01-19
A15: 11 | B15: Article | C15: No Medical Life Insurance | D15: How To Get Life Insurance If You Have Health Issues | E15: https://familialife.ca/how-to-get-life-insurance-if-you-have-health-issues/ | F15: Options for applicants with health issues: full disclosure, no-medical policies, working with an advisor, improving insurability and sizing coverage. | G15: Underwriting explained | H15: Understanding Life Insurance Options | Navigating Health Issues and Life Insurance | Leverage the Expertise of an Insurance Advisor | Role of No Medical Life Insurance | Enhancing Your Insurability and Determining Coverage Amount | Conclusion | I15: 16 | J15: 2165 | K15: =IF(J15="","",MAX(0,J15-'Method & Notes'!$B$6)) -> 991 | L15: 2020-04-22 | M15: 2023-09-06 | N15: BlogPosting, BreadcrumbList, InsuranceAgency, Organization, Person, WebPage, WebSite | O15: /life-insurance/medical-conditions/ (Medical underwriting desk) | P15: Internet Archive snapshot 2024-01-19
A16: 12 | B16: Guide | C16: Life Insurance with Medical Conditions | D16: Life Insurance for Diabetics: How to Get the Best Rates in Canada | E16: https://familialife.ca/life-insurance-for-diabetics/ | F16: How insurers view type 1 and type 2 diabetes, risks by age group, pricing factors (age at diagnosis, type, complications, blood-sugar control), underwriting requirements, broker vs captive agent, non-medical vs traditional, permanent options, FAQ. | G16: FAQ, 4 tables, Comparisons, Cost and pricing factors, Underwriting explained | H16: Why Life Insurance Companies Consider Diabetes | Pricing Life Insurance for Diabetics | The Underwriting Process | Recommendations for Diabetics Seeking Life Insurance | Best Life Insurance Options for Diabetics | FAQ: Life Insurance for Diabetics | I16: 51 | J16: 2840 | K16: =IF(J16="","",MAX(0,J16-'Method & Notes'!$B$6)) -> 1666 | L16: 2023-09-22 | M16: 2023-09-22 | N16: BlogPosting, BreadcrumbList, InsuranceAgency, Organization, Person, WebPage, WebSite | O16: Planned: Life Insurance With Diabetes in Canada | P16: Internet Archive snapshot 2024-01-19
A17: 13 | B17: Guide | C17: Life Insurance with Medical Conditions | D17: Life Insurance with a Cancer Diagnosis in Canada | E17: https://familialife.ca/life-insurance-with-cancer/ | F17: Whether cancer is covered, guaranteed, simplified and traditional options, what insurers weigh (type, stage and grade, time since diagnosis), offer types by health, FAQ (stage 4, cancer 10 years ago). | G17: FAQ, 2 tables, Key takeaways, Cost and pricing factors | H17: Does Life Insurance Cover Cancer? | Factors Insurers Consider for Cancer Patients | Types of Insurance Offers Based on Health | Your Beacon: Familia Life Brokers | Where to Anchor: Life Insurance Options | Frequently Asked Questions | Conclusion | I17: 34 | J17: 2855 | K17: =IF(J17="","",MAX(0,J17-'Method & Notes'!$B$6)) -> 1681 | L17: 2023-10-04 | M17: 2023-10-04 | N17: BlogPosting, BreadcrumbList, InsuranceAgency, Organization, Person, WebPage, WebSite | O17: Planned: Life Insurance After Cancer in Canada | P17: Internet Archive snapshot 2024-01-19
A18: 14 | B18: Guide | C18: Life Insurance with Medical Conditions | D18: Applying for Life Insurance with a Heart Condition in Canada | E18: https://familialife.ca/life-insurance-with-heart-condition/ | F18: How heart conditions are assessed (age, family history, build, history, habits, medication), options after a heart attack (traditional, simplified, guaranteed), 10-question FAQ (stents, bypass, timing), working with a broker. | G18: FAQ, 2 tables, Key takeaways, Comparisons, Underwriting explained | H18: Understanding Heart Conditions for Life Insurance | Details on Heart Disease and Life Insurance | Life Insurance Options after a Heart Attack | Getting the Right Coverage for Your Situation | Frequently Asked Questions (FAQs) | Working with a Broker | Conclusion | I18: 32 | J18: 3125 | K18: =IF(J18="","",MAX(0,J18-'Method & Notes'!$B$6)) -> 1951 | L18: 2023-10-03 | M18: 2023-10-04 | N18: BlogPosting, BreadcrumbList, InsuranceAgency, Organization, Person, WebPage, WebSite | O18: Planned: Life Insurance After a Heart Attack or With Heart Disease | P18: Internet Archive snapshot 2024-01-19
A19: 15 | B19: Product explainer page | C19: Mortgage Protection | D19: Mortgage Protection Insurance | E19: https://familialife.ca/mortgage-protection-insurance/ | F19: What mortgage insurance is, its main drawbacks, term life as the alternative and the cost difference. | G19: Benefits / pros and cons, Cost and pricing factors | H19: Mortgage Protection Insurance | I19: 5 | J19: 2136 | K19: =IF(J19="","",MAX(0,J19-'Method & Notes'!$B$6)) -> 962 | L19: 2022-03-04 | M19: 2023-06-07 | N19: Article, BreadcrumbList, InsuranceAgency, Organization, Person, WebPage, WebSite | O19: /mortgage-life-insurance/ product page (Mortgage renewal protection desk) | P19: Internet Archive snapshot 2024-01-19
A20: 16 | B20: Guide | C20: Mortgage Protection | D20: The Ultimate Guide on Mortgage Insurance | E20: https://familialife.ca/what-is-mortgage-insurance/ | F20: Mortgage insurance vs mortgage protection vs mortgage loan (default) insurance, why term life can beat bank protection (fixed benefit, cost, flexibility), its pitfalls, when term isn't ideal, choosing an advisor. | G20: Benefits / pros and cons, Cost and pricing factors | H20: Mortgage Insurance, Explained | Unraveling Mortgage Protection Insurance | Mortgage Loan Insurance: A Closer Look | Why Term Life Insurance Can Be A Better Choice | Deep Dive into the Pitfalls of Mortgage Protection Insurance | Advantages of Term Life Insurance Over MPI | Choose Wisely, Live Confidently | When Term Life Insurance Isn’t the Perfect Solution | Choose the Right Life Insurance Advisor | I20: 19 | J20: 2376 | K20: =IF(J20="","",MAX(0,J20-'Method & Notes'!$B$6)) -> 1202 | L20: 2023-06-22 | M20: 2023-08-31 | N20: BlogPosting, BreadcrumbList, InsuranceAgency, Organization, Person, WebPage, WebSite | O20: Published: Mortgage Life Insurance vs Term Life; Mortgage Life Insurance Cost | P20: Internet Archive snapshot 2024-01-19
... A23: 19 | B23: Guide | C23: Family Life Insurance | D23: Family Life Insurance in Canada: Separating Fact from Fiction | E23: https://familialife.ca/family-life-insurance/ | F23: Why no single policy covers a whole family, the types (whole, universal, mortgage, joint, children's) with a comparison table, why use a broker, how to buy, FAQ. | G23: FAQ, 2 tables, Myth vs reality, Comparisons, Steps / checklist | H23: The Reality of Family Life Insurance in Canada | Types of Family Life Insurance in Canada | Finding the Ideal Family Life Insurance | How to Buy Family Life Insurance | Conclusion | Frequently Asked Questions (FAQ) | I23: 38 | J23: 2705 | K23: =IF(J23="","",MAX(0,J23-'Method & Notes'!$B$6)) -> 1531 | L23: 2023-09-19 | M23: 2023-09-29 | N23: BlogPosting, BreadcrumbList, InsuranceAgency, Organization, Person, WebPage, WebSite | O23: Gap: no family life guide (/life-insurance/children/ service page exists; children's life insurance guide planned) | P23: Internet Archive snapshot 2024-01-19
A24: 20 | B24: Guide (search only) | C24: Critical Illness | D24: Protect Your Health and Wallet: A Complete Guide to Critical Illness Insurance in Canada | E24: https://familialife.ca/whats-ci/ | F24: Listed on the blog (posted September 7, 2023). Search results show only its opening line: critical illness insurance as a financial safety net when diagnosed with a major illness. | O24: Published: What Does Critical Illness Insurance Cover?; Critical Illness vs Disability | P24: Search results only (page blocks automated access; no archived copy)
A25: 21 | B25: Product (sales) page | C25: Health Insurance | D25: Health Insurance | E25: https://familialife.ca/health-insurance/ | F25: Health insurance for people leaving an employer, between jobs or retired: low-premium claim, guaranteed approval plans, immediate coverage. | G25: Cost and pricing factors | H25: Leaving work? In between jobs? Retired? We got you covered! | Buying Health Insurance made Easy Quick Hassle FREE | I25: 6 | J25: 2089 | K25: =IF(J25="","",MAX(0,J25-'Method & Notes'!$B$6)) -> 915 | L25: 2022-03-04 | M25: 2023-09-06 | N25: Article, BreadcrumbList, InsuranceAgency, Organization, Person, WebPage, WebSite | O25: /health-dental-insurance/; Published: Private Health Insurance Cost | P25: Internet Archive snapshot 2024-01-16
A26: 22 | B26: Guide | C26: Life Insurance Basics & Buying | D26: How Does Life Insurance Work in Canada? | E26: https://familialife.ca/how-does-life-insurance-work-in-canada/ | F26: The basics, types of life insurance, how pricing works, how payouts work (final expenses, mortgage, health issues), how much you need, choosing an advisor. | G26: Cost and pricing factors | H26: The Basics: What is Life Insurance? | Different Types of Life Insurance | How is Life Insurance Priced? | How Life Insurance Payouts Work | How Much Life Insurance Do You Need? | I26: 12 | J26: 2316 | K26: =IF(J26="","",MAX(0,J26-'Method & Notes'!$B$6)) -> 1142 | L26: 2023-06-23 | M26: 2023-08-31 | N26: BlogPosting, BreadcrumbList, InsuranceAgency, Organization, Person, WebPage, WebSite | O26: Planned: Types of Life Insurance in Canada | P26: Internet Archive snapshot 2024-01-16
A27: 23 | B27: Article | C27: Life Insurance Basics & Buying | D27: Finding the Right Amount of Life Insurance: Budget, Debts, and Dependents | E27: https://familialife.ca/how-much-life-insurance-should-i-get/ | F27: Five steps to the right amount: affordability, needs analysis, debts, dependants' needs, balancing all three. | G27: Steps / checklist | H27: 1. Prioritize Affordability. | 2. Understanding Needs Analysis. | 3. Assessing Debts. | 4. Comprehensive Assessment of Dependents’ Needs. | 5. Balancing Budget, Debts, and Dependents. | I27: 6 | J27: 1801 | K27: =IF(J27="","",MAX(0,J27-'Method & Notes'!$B$6)) -> 627 | L27: 2021-01-22 | M27: 2023-06-02 | N27: BlogPosting, BreadcrumbList, InsuranceAgency, Organization, Person, WebPage, WebSite | O27: Published: How Much Life Insurance Do I Need in Canada? | P27: Internet Archive snapshot 2024-01-16
A28: 24 | B28: Guide | C28: Life Insurance Basics & Buying | D28: Life Insurance Quotes in Canada | E28: https://familialife.ca/life-insurance-quotes-in-canada/ | F28: Why quotes vary (age, health, occupation, term and amount, gender), how quotes are calculated (actuarial science, risk classes, medicals, credit checks), how health affects a quote, life vs mortgage insurance, fine print (exclusions, riders), 5-question FAQ. | G28: FAQ, Comparisons, Cost and pricing factors, Underwriting explained | H28: Introduction: Navigating the Maze of Life Insurance Quotes in Canada | Why Life Insurance Quotes Vary: Factors that Influence Your Premium | Decoding the Different Types of Life Insurance Policies | Understanding Quote Calculations | The Financial Implications of Life Insurance | How Health Concerns Impact Your Quote | Life Insurance vs. Mortgage Insurance: A Quick Comparison | The Importance of Reading the Fine Print | Working With a Competent Advisor is Crucial | Frequently Asked Questions: | I28: 31 | J28: 3064 | K28: =IF(J28="","",MAX(0,J28-'Method & Notes'!$B$6)) -> 1890 | L28: 2023-08-31 | M28: 2023-09-05 | N28: BlogPosting, BreadcrumbList, InsuranceAgency, Organization, Person, WebPage, WebSite | O28: Published: How Much Does Life Insurance Cost in Canada?; Instant Estimates Explained | P28: Internet Archive snapshot 2024-01-16
A29: 25 | B29: Article | C29: Life Insurance Basics & Buying | D29: How Do Life Insurance Companies Check Medical Background? | E29: https://familialife.ca/how-do-life-insurance-companies-check-medical-background/ | F29: How insurers review medical history, medical exams, risk classification, medical records, risk vs premium, tailoring cover to your health. | G29: Comparisons, Cost and pricing factors, Underwriting explained | H29: A Deep Dive Into Medical History | Medical Examinations: The Next Step | Risk Classification | Unfolding The Medical Record Enigma | Risk vs Premium: The Balancing Act | Tailoring Insurance To Your Health | Choosing The Right Path | I29: 7 | J29: 2211 | K29: =IF(J29="","",MAX(0,J29-'Method & Notes'!$B$6)) -> 1037 | L29: 2023-06-14 | M29: 2023-09-14 | N29: BlogPosting, BreadcrumbList, InsuranceAgency, Organization, Person, WebPage, WebSite | O29: Planned: Life Insurance Medical Exams and Applications | P29: Internet Archive snapshot 2024-01-19
A30: 26 | B30: Guide | C30: Life Insurance Basics & Buying | D30: 12 Life Insurance Myths You Need to Stop Believing | E30: https://familialife.ca/12-myths-debunked/ | F30: Twelve myths (cost, funeral-only, mandatory medicals, dependants, group cover, stay-at-home parents, too young, too old, preexisting conditions, investments, permanent for the wealthy, 2x salary), each with 'the reality', breakdowns, a premiums-by-age table and tips. | G30: 7 tables, Key takeaways, Myth vs reality, Comparisons, Scenarios / examples, Benefits / pros and cons, Cost and pricing factors, Underwriting explained | H30: Myth 1: Life Insurance Is Expensive | Myth 2: Life Insurance Is Just for Funeral Costs | Myth 3: Medical Exams Are Mandatory | Myth 4: Only for Those with Dependents | Myth 5: Group Insurance Is Sufficient | Myth 6: Stay-at-Home Parents Don’t Need Insurance | Myth 7: Too Young for Life Insurance | Myth 8: Too Old for Life Insurance | Myth 9: Preexisting Conditions Disqualify You | Myth 10: Other Investments Are Better | Myth 11: Permanent Insurance Is for the Wealthy | Myth 12: Coverage Should Be Twice the Annual Salary | Conclusion | I30: 64 | J30: 2273 | K30: =IF(J30="","",MAX(0,J30-'Method & Notes'!$B$6)) -> 1099 | L30: 2023-09-19 | M30: 2023-09-20 | N30: BlogPosting, BreadcrumbList, InsuranceAgency, Organization, Person, WebPage, WebSite | O30: Gap: not in the Instasure plan | P30: Internet Archive snapshot 2024-01-19
A31: 27 | B31: Article | C31: Life Insurance Basics & Buying | D31: Don’t Buy Life Insurance Without Doing These 2 Things | E31: https://familialife.ca/two-things-before-buying/ | F31: Two must-dos: use an experienced broker (access to insurers, underwriting expertise, trust) and choose a reputable insurer (longevity, claim settlement ratio); to-do list; FAQ. | G31: FAQ, Comparisons, Steps / checklist, Underwriting explained | H31: The Pitfalls of Hasty Decisions | Thing #1: The Indispensable Role of a Broker | Thing #2: Choosing Reputable Insurance Companies | I31: 27 | J31: 2279 | K31: =IF(J31="","",MAX(0,J31-'Method & Notes'!$B$6)) -> 1105 | L31: 2023-09-07 | M31: 2023-09-07 | N31: BlogPosting, BreadcrumbList, InsuranceAgency, Organization, Person, WebPage, WebSite | O31: Planned: Life Insurance Broker vs Agent vs Bank vs Online | P31: Internet Archive snapshot 2024-01-19
A32: 28 | B32: Article (search only) | C32: Life Insurance Basics & Buying | D32: Are Life Insurance Premiums Tax Deductible in Canada? | E32: https://familialife.ca/are-life-insurance-premiums-tax-deductible-in-canada/ | F32: Newer article found only in search results. Search snippets indicate: premiums generally not deductible for individuals; exceptions mentioned for business owners using a policy as loan collateral and some employer-paid group term plans. | O32: Published: Is Life Insurance Taxable in Canada? | P32: Search results only (page blocks automated access; no archived copy)
A33: 29 | B33: Guide (search only) | C33: Life Insurance Basics & Buying | D33: A Step-by-Step Guide to Filing a Life Insurance Claim | E33: https://familialife.ca/how-to-claim/ | F33: Listed on the blog as a featured article. No outline available. | O33: Planned: How to Make a Life Insurance Claim in Canada | P33: Search results only (page blocks automated access; no archived copy)

Sheet Topics by Product
A1: Brand & home page | B1: Term Life Insurance | E1: Permanent & Whole Life | G1: Universal Life | H1: Joint Life | I1: No Medical Life Insurance | L1: Life Insurance with Medical Conditions | O1: Mortgage Protection | Q1: Final Expense | R1: Seniors (50+) | S1: Family Life Insurance | T1: Critical Illness | U1: Health Insurance | V1: Life Insurance Basics & Buying
A2: Familia Life - Lowest Life Insurance Rates in Canada | B2: Term Life Insurance | C2: Everything about Term Life Insurance | D2: What Happens at the End of Term Life Insurance? | E2: Permanent Life Insurance | F2: Everything about Permanent Life Insurance in Canada | G2: What is Universal Life Insurance and How Does it Work? | H2: Joint Life Insurance vs Individual Life Insurance: A Comparative Analysis | I2: No Medical Insurance | J2: Everything about No Medical Life Insurance | K2: How To Get Life Insurance If You Have Health Issues | L2: Life Insurance for Diabetics: How to Get the Best Rates in Canada | M2: Life Insurance with a Cancer Diagnosis in Canada | N2: Applying for Life Insurance with a Heart Condition in Canada | O2: Mortgage Protection Insurance | P2: The Ultimate Guide on Mortgage Insurance | Q2: Final Expense | R2: Life Insurance After 50: A Canadian Senior’s Handbook | S2: Family Life Insurance in Canada: Separating Fact from Fiction | T2: Protect Your Health and Wallet: A Complete Guide to Critical Illness Insurance in Canada | U2: Health Insurance | V2: How Does Life Insurance Work in Canada? | W2: Finding the Right Amount of Life Insurance: Budget, Debts, and Dependents | X2: Life Insurance Quotes in Canada | Y2: How Do Life Insurance Companies Check Medical Background? | Z2: 12 Life Insurance Myths You Need to Stop Believing | AA2: Don’t Buy Life Insurance Without Doing These 2 Things | AB2: Are Life Insurance Premiums Tax Deductible in Canada? | AC2: A Step-by-Step Guide to Filing a Life Insurance Claim
A3: Home page | B3: Product explainer page | C3: Guide | D3: Article | E3: Product explainer page | F3: Guide | G3: Article | H3: Guide | I3: Product explainer page | J3: Guide | K3: Article | L3: Guide | M3: Guide | N3: Guide | O3: Product explainer page | P3: Guide | Q3: Product (sales) page | R3: Guide | S3: Guide | T3: Guide (search only) | U3: Product (sales) page | V3: Guide | W3: Article | X3: Guide | Y3: Article | Z3: Guide | AA3: Article | AB3: Article (search only) | AC3: Guide (search only)
A4: https://familialife.ca/ | B4: https://familialife.ca/term-life-insurance/ | C4: https://familialife.ca/everything-about-term-life-insurance/ | D4: https://familialife.ca/what-happens-at-the-end-of-term-life-insurance/ | E4: https://familialife.ca/whole-life-insurance/ | F4: https://familialife.ca/everything-about-permanent-life-insurance/ | G4: https://familialife.ca/what-is-universal-life-insurance/ | H4: https://familialife.ca/what-is-joint-life/ | I4: https://familialife.ca/no-medical-insurance/ | J4: https://familialife.ca/everything-about-no-medical-life-insurance/ | K4: https://familialife.ca/how-to-get-life-insurance-if-you-have-health-issues/ | L4: https://familialife.ca/life-insurance-for-diabetics/ | M4: https://familialife.ca/life-insurance-with-cancer/ | N4: https://familialife.ca/life-insurance-with-heart-condition/ | O4: https://familialife.ca/mortgage-protection-insurance/ | P4: https://familialife.ca/what-is-mortgage-insurance/ | Q4: https://familialife.ca/final-expense-insurance/ | R4: https://familialife.ca/seniors-life-insurance/ | S4: https://familialife.ca/family-life-insurance/ | T4: https://familialife.ca/whats-ci/ | U4: https://familialife.ca/health-insurance/ | V4: https://familialife.ca/how-does-life-insurance-work-in-canada/ | W4: https://familialife.ca/how-much-life-insurance-should-i-get/ | X4: https://familialife.ca/life-insurance-quotes-in-canada/ | Y4: https://familialife.ca/how-do-life-insurance-companies-check-medical-background/ | Z4: https://familialife.ca/12-myths-debunked/ | AA4: https://familialife.ca/two-things-before-buying/ | AB4: https://familialife.ca/are-life-insurance-premiums-tax-deductible-in-canada/ | AC4: https://familialife.ca/how-to-claim/
A5: Archive 2025-04-18 · 10 subheadings | B5: Archive 2024-01-16 · 5 subheadings | C5: Archive 2024-01-16 · 19 subheadings | D5: Archive 2024-01-16 · 13 subheadings | E5: Archive 2024-01-16 · 9 subheadings | F5: Archive 2024-01-16 · 47 subheadings | G5: Archive 2024-01-16 · 11 subheadings | H5: Archive 2024-01-09 · 67 subheadings | I5: Archive 2024-01-19 · 5 subheadings | J5: Archive 2024-01-19 · 21 subheadings | K5: Archive 2024-01-19 · 16 subheadings | L5: Archive 2024-01-19 · 51 subheadings | M5: Archive 2024-01-19 · 34 subheadings | N5: Archive 2024-01-19 · 32 subheadings | O5: Archive 2024-01-19 · 5 subheadings | P5: Archive 2024-01-19 · 19 subheadings | Q5: Archive 2024-01-16 · 8 subheadings | R5: Archive 2024-01-19 · 23 subheadings | S5: Archive 2024-01-19 · 38 subheadings | T5: Search results only: outline not available | U5: Archive 2024-01-16 · 6 subheadings | V5: Archive 2024-01-16 · 12 subheadings | W5: Archive 2024-01-16 · 6 subheadings | X5: Archive 2024-01-16 · 31 subheadings | Y5: Archive 2024-01-19 · 7 subheadings | Z5: Archive 2024-01-19 · 64 subheadings | AA5: Archive 2024-01-19 · 27 subheadings | AB5: Search results only: outline not available | AC5: Search results only: outline not available
A6: Subheadings | B6: Subheadings | C6: Subheadings | D6: Subheadings | E6: Subheadings | F6: Subheadings | G6: Subheadings | H6: Subheadings | I6: Subheadings | J6: Subheadings | K6: Subheadings | L6: Subheadings | M6: Subheadings | N6: Subheadings | O6: Subheadings | P6: Subheadings | Q6: Subheadings | R6: Subheadings | S6: Subheadings | T6: Subheadings | U6: Subheadings | V6: Subheadings | W6: Subheadings | X6: Subheadings | Y6: Subheadings | Z6: Subheadings | AA6: Subheadings | AB6: Subheadings | AC6: Subheadings
A7: Life Insurance is a sturdy umbrella - Often overlooked in fair weather, but priceless protection when life's storms hit. | B7: Term Life Insurance | C7: Term Life Insurance 101. | D7: The Term Ends – Now What? | E7: Permanent Life Insurance | F7: Everything about Permanent Life Insurance in Canada | G7: What is Universal Life Insurance and How Does it Work? | H7: What is Individual Life Insurance? | I7: No Medical Insurance | J7: No Medical Life Insurance 101. | K7: Understanding Life Insurance Options | L7: Type I and Type II Diabetics: You’re Covered! | M7: Key Takeaways | N7: • Key Takeaways | O7: Mortgage Protection Insurance | P7: Mortgage Insurance, Explained | Q7: Let's face it, nobody wants to ponder about their own funeral. | R7: What is Senior Life Insurance? | S7: Family Life Insurance in Canada: Separating Fact from Fiction | T7: Listed on the blog (posted September 7, 2023). Search results show only its opening line: critical illness insurance as a financial safety net when diagnosed with a major illness. | U7: Leaving work? In between jobs? Retired? We got you covered! | V7: The Basics: What is Life Insurance? | W7: Finding the Right Amount of Life Insurance: Budget, Debts, and Dependents | X7: Introduction: Navigating the Maze of Life Insurance Quotes in Canada | Y7: A Deep Dive Into Medical History | Z7: Key Takeaways | AA7: The Pitfalls of Hasty Decisions | AB7: Newer article found only in search results. Search snippets indicate: premiums generally not deductible for individuals; exceptions mentioned for business owners using a policy as loan collateral and some employer-paid group term plans. | AC7: Listed on the blog as a featured article. No outline available.
A8: Best Life Insurance Rates in Canada | B8: Understanding Term Life Insurance in Canada | C8: What Is Term Life Insurance? | D8: • Policy Ends | E8: Understanding Permanent Life Insurance | F8: What is Permanent Life Insurance? | G8: The Basics of Universal Life Insurance | H8: Features | I8: Understanding No Medical Insurance | J8: What Is No Medical Life Insurance? | K8: • Whole Life Insurance | L8: Medical or Non-Medical: You Choose! | M8: • Navigating Coverage | N8: Understanding Heart Conditions for Life Insurance | O8: Understanding Mortgage Insurance | P8: Unraveling Mortgage Protection Insurance | Q8: • We only work with reputable Canadian companies | R8: What type of life insurance is best for seniors? | S8: The Reality of Family Life Insurance in Canada | U8: LOWEST PREMIUM - GUARANTEED! | V8: Different Types of Life Insurance | W8: 1. Prioritize Affordability. | X8: Why Life Insurance Quotes Vary: Factors that Influence Your Premium | Y8: Medical Examinations: The Next Step | Z8: • Tip | AA8: Understanding the Basics: No Deep Dives, Just Snorkeling
A9: Your family, our priority. We're here to protect and secure what matters most to you. | B9: Is Term Insurance No Good Because It Expires? | C9: Different Types of Term Life Insurance | D9: • Renewal | E9: Different Types of Permanent Life Insurance | F9: • Definition | G9: Understanding the Cash Value Component | H9: • Single Coverage | I9: How It Works | J9: The Benefits of No Medical Life Insurance: | K9: Navigating Health Issues and Life Insurance | L9: • Table: Traditional vs. Non-Medical Plans | M9: • Policy Varieties | N9: • Age | O9: Main Drawbacks of Mortgage Insurance | P9: Mortgage Loan Insurance: A Closer Look | Q9: Best Rates for Final Expense Insurance | R9: Types of Life Insurance Plans for Seniors | S9: Myth-Busting Time! | U9: LEAVING YOUR EMPLOYER? | V9: • Whole life insurance | W9: 2. Understanding Needs Analysis. | X9: Age and its Influence | Y9: Risk Classification | Z9: Myth 1: Life Insurance Is Expensive | AA9: Thing #1: The Indispensable Role of a Broker
A10: Life Insurance For Young Families | B10: Benefits | C10: Decreasing Term Insurance | D10: • Conversion to Permanent Life Insurance | E10: • Whole Life Insurance | F10: Key Features: | G10: Differentiating Universal Life Insurance from Other Types | H10: • Flexible | I10: Benefits of getting no medical life insurance | J10: Quick and Convenient Application Process | K10: • Disclose Your Medical History Fully | L10: Why Life Insurance Companies Consider Diabetes | M10: • Insurer’s Lens | N10: • Family History | O10: The Alternative Option: Term Life Insurance | P10: Why Term Life Insurance Can Be A Better Choice | Q10: RATES WILL NEVER GO UP | R10: Which is Better: Whole Life or Term Life Insurance? | S10: What Insurance Companies Really Mean | U10: GUARANTEED APPROVAL PLANS AVAILABLE | V10: • Universal life insurance | W10: 3. Assessing Debts. | X10: Health Factors | Y10: Unfolding The Medical Record Enigma | Z10: The Reality | AA10: What’s a Broker and Why Should You Care?
A11: Final Expense Insurance | B11: Cost | C11: Increasing Term Insurance | D11: Factors To Consider at the End of Your Term Life Insurance | E11: • Universal Life Insurance | F11: • Lifelong Coverage | G11: Is Universal Life Insurance Right for You? | H11: • Independent | I11: Cost | J11: Flexibility in Coverage Amounts | K11: • Consider No Medical Life Insurance | L11: The Risk Equation: Why Diabetes Matters to Insurers | M11: • Tailored Solutions | N11: • Body Build | O11: Cost Differences Between Mortgage Insurance and Term Life Insurance | P11: • Fixed Benefits | Q11: THERE IS NO EXPIRY | R11: • Whole Life Insurance | S11: Types of Family Life Insurance in Canada | U11: IMMEDIATE COVERAGE | V11: How is Life Insurance Priced? | W11: 4. Comprehensive Assessment of Dependents’ Needs. | X11: Occupation and Lifestyle | Y11: Risk vs Premium: The Balancing Act | Z11: Cost Breakdown | AA11: The Gold Standard: Why Experienced Brokers Shine
A12: High-Risk & Hard to Insure clients | C12: Yearly Renewable Term Insurance | D12: • Health Condition | E12: • Variable Life Insurance | F12: • Cash Value Accumulation | G12: Tax Implications and the Purchase Process | H12: Scenarios Where It’s Beneficial | J12: Simplified Underwriting Process | K12: • Work with an Insurance Advisor | L12: The Impact on Life Expectancy | M12: • Securing the Future | N12: Details on Heart Disease and Life Insurance | P12: • Cost-Effectiveness | Q12: NO MEDICAL EXAMS OR NEEDLES NECESSARY | R12: When is Life Insurance Necessary for Seniors? | S12: The Insurance Buffet | U12: Buying Health Insurance made Easy Quick Hassle FREE | V12: • No medical life insurance | W12: 5. Balancing Budget, Debts, and Dependents. | X12: Policy Duration and Amount | Y12: Tailoring Insurance To Your Health | Z12: • Did You Know? | AA12: • Access to All Canadian Insurers
A13: Mortgage Protection | C13: Who is Term Life Insurance for? | D13: • Current Financial Responsibilities | E13: Which Option is Better: Permanent or Term Life Insurance? | F13: • Fixed Premiums | G13: Buying Universal Life Insurance: Step-by-Step | H13: • Single Breadwinners | J13: Guaranteed Acceptance Options | K13: Leverage the Expertise of an Insurance Advisor | L13: • Note | M13: Does Life Insurance Cover Cancer? | N13: • Detailed Medical History | P13: • Flexibility | Q13: IS THERE ANY WAITING PERIOD? | R13: • Final Expenses | S13: Whole Life Insurance | V13: How Life Insurance Payouts Work | X13: Gender’s Role | Y13: Choosing The Right Path | Z13: Myth 2: Life Insurance Is Just for Funeral Costs | AA13: • Years of Experience
A14: 100% None Face-to-Face | C14: Young Families | D14: • Affordability | E14: Can Permanent Life Insurance be used as a Saving? | F14: • Death Benefit | G14: • Determine Your Insurance Needs | H14: • Business Owners | J14: Who is no medical life insurance for? | K14: • Personalized Advice | L14: The Silver Lining: Manage Well, Live Well | M14: Guaranteed Issue Life Insurance | N14: • Lifestyle Habits | P14: Deep Dive into the Pitfalls of Mortgage Protection Insurance | Q14: Buying Final Expense Coverage made Easy Quick Hassle FREE | R14: • Income Replacement | S14: Universal Life Insurance | V14: Dealing with Final Expenses | X14: Decoding the Different Types of Life Insurance Policies | Z14: The Reality | AA14: • Underwriting Expertise
A15: Buying life insurance can seem like a perplexing puzzle | C15: Homeowners with Mortgage | D15: • Estate Planning | E15: Why Familia Life? | F15: Types of Permanent Life Insurance in Canada | G15: • Choose a Reliable Insurance Advisor | H15: What is Joint Life Insurance? | J15: Individuals with Pre-existing Health Conditions | K15: • Understanding of Underwriting Policies | L15: Statistical Risks | M15: Simplified Issue Life Insurance | N15: • Medications | P15: • Decreasing Value | R15: • Estate Planning | S15: Mortgage Life Insurance | V15: Insurance and Mortgage Protection | X15: No Medical Life Insurance | Z15: Where the Money Goes | AA15: Trust: The Bedrock of a Healthy Broker-Client Relationship
A16: Read our latest | C16: Business Owners | D16: Is A New Term Policy An Option? | F16: • Whole Life Insurance | G16: • Medical Background Check | H16: Features | J16: Older Individuals & Seniors | K16: • Navigating Through Different Options | L16: • List of Diabetes-Related Risks by Age Group | M16: Traditional Life Insurance | N16: Life Insurance Options after a Heart Attack | P16: • Limited Coverage | R16: • Special Needs | S16: Joint Life Insurance | V16: Life Insurance with Health Issues | X16: Understanding Quote Calculations | Z16: • Mortgage Payments | AA16: • Transparency
C17: Pros and Cons of Term Life Insurance | D17: Conversion to Permanent Life Insurance | F17: • Description | G17: • Policy Issuance | H17: • Dual Coverage | J17: Those Seeking Convenience and Speed | K17: Role of No Medical Life Insurance | L17: • Under 40 | M17: Factors Insurers Consider for Cancer Patients | N17: • Traditional Life Insurance | P17: • Lack of Control | R17: • Debts | S17: Life Insurance for Children | V17: How Much Life Insurance Do You Need? | X17: The Actuarial Science | Z17: • Children’s Education | AA17: • Client’s Best Interest
C18: Advantages of Term Life Insurance | D18: Letting Your Term Life Insurance Expire | F18: • Benefits | H18: • Unified Policy | J18: Individuals with Needle Phobia or Medical Procedure Anxiety | K18: Enhancing Your Insurability and Determining Coverage Amount | L18: • 40-60 | M18: • Type of Cancer | N18: • Simplified Life Insurance | P18: Advantages of Term Life Insurance Over MPI | R18: • Charitable Donation | S18: Table: Comparing Different Types of Family Life Insurance | V18: Choosing the Right Life Insurance Advisor | X18: Risk Categories | Z18: • Day-to-Day Expenses | AA18: Thing #2: Choosing Reputable Insurance Companies
C19: Affordability | D19: Wrapping Up | F19: • Universal Life Insurance | H19: • Types | J19: Individuals with Busy Schedules | K19: • Income Replacement | L19: • Over 60 | M19: • Stage and Grade | N19: • Guaranteed Life Insurance | P19: • Greater Coverage | R19: Is Life Insurance Worth It After 70? | S19: Finding the Ideal Family Life Insurance | X19: The Role of Medical Examinations | Z19: • Pro Tip | AA19: Why the Name Matters: The Importance of Company Reputation
C20: Simplicity | F20: • Description | H20: Joint-First-to-Die vs Joint-Last-to-Die | J20: Understanding Different Insurance Rate Classifications | K20: • Debt and Final Expenses | L20: Pricing Life Insurance for Diabetics | M20: • Time Since Diagnosis | N20: Getting the Right Coverage for Your Situation | P20: • Cost Advantage | R20: The Medical Background Scoop | S20: Why Making the Right Choice Matters | X20: Credit and Background Checks | Z20: Myth 3: Medical Exams Are Mandatory | AA20: The Dynamic Duo: Longevity and Claim Settlement Ratio
C21: Flexibility | F21: • Benefits | H21: • Joint-First-to-Die | J21: What is a Standard Rate? | K21: • Future Financial Goals | L21: A Closer Look at the Price Tag | M21: • Complicating Issues | N21: Frequently Asked Questions (FAQs) | P21: • Flexibility and Control | R21: What is the best insurance for those over 65? | S21: Why Familia Life Recommends Using a Skilled Broker | X21: The Financial Implications of Life Insurance | Z21: The Reality | AA21: • Longevity
C22: Disadvantages of Term Life Insurance | F22: • Term 100 | H22: • Joint-Last-to-Die | J22: What is a Preferred Rate? | K22: Conclusion | L22: Key Factors in Pricing | M22: • Table 1: Factors Insurers Consider | N22: Is a heart attack covered in life insurance? | P22: Choose Wisely, Live Confidently | R22: Life Insurance Type Comparison | S22: Affordability Meets Value at Familia Life | X22: How Health Concerns Impact Your Quote | Z22: Pros and Cons | AA22: • Claim Settlement Ratio
C23: Temporary coverage | F23: • Description | H23: Scenarios and Examples | J23: What are “ratings”? | L23: • Age at Diagnosis | M23: Types of Insurance Offers Based on Health | N23: Will the insurance payout after a heart attack? | P23: When Term Life Insurance Isn’t the Perfect Solution | R23: Is Term Life Insurance Worth It for Seniors? | S23: Comprehensive Protection: A Familia Life Specialty | X23: Common Health Conditions | Z23: • Note | AA23: Comparison: Reputable vs. Sketchy
C24: No cash value | F24: • Benefits | H24: Married Couples with Shared Financial Responsibilities | J24: Mild Diabetes (Controlled Without Medication) | L24: • Type of Diabetes | M24: • Traditional Life Insurance (Standard Rates) | N24: Can I get insured after heart failure, disease, or attack? | P24: Choose the Right Life Insurance Advisor | R24: Is Whole Life Insurance Worth It for Seniors? | S24: Exceptional Customer Service: A Familia Life Hallmark | X24: Mental Health Considerations | Z24: Myth 4: Only for Those with Dependents | AA24: Your To-Do List
C25: Increasing Premiums | F25: Advantages of Permanent Life Insurance | H25: Business Partners | J25: Moderate to Severe Diabetes (Requires Medication) | L25: • Complications | M25: • Traditional Rated Life Insurance (Increased Rates) | N25: What’s the best life insurance for heart conditions? | P25: Final Thoughts | R25: No Medical Life Insurance for Seniors | S25: Flexibility: Because Life Happens | X25: No-medical Life Insurance Options | Z25: The Reality | AA25: • Consult a Broker
F26: • Lifelong Coverage | H26: Parents and Children for Estate Planning | J26: Multiple Health Conditions | L26: • Blood Sugar Control | M26: • No Medical Life Insurance (Simplified Issue) | N26: How to get a quote? | R26: Where is the best place to get life insurance for Seniors? | S26: List: Why Familia Life Stands Out | X26: Temporary Health Issues vs. Chronic Conditions | Z26: Single Life Insurance Use-Cases | AA26: • Research Companies
F27: • Cash Value Accumulation | H27: Key Differences | J27: What is a Simplified Issue Life Insurance? | L27: • Additional Medical Conditions | M27: • Table 2: Insurance Offers Based on Health | N27: Can you get life insurance after you’ve had a heart attack? | R27: Guaranteed Approval Life Insurance: The Last Resort | S27: How to Buy Family Life Insurance | X27: Life Insurance vs. Mortgage Insurance: A Quick Comparison | Z27: • Debt Payoff | AA27: The Road Ahead
F28: • Fixed Premiums | H28: • Coverage Scope | L28: • What Helps and Hurts Your Case | M28: Your Beacon: Familia Life Brokers | N28: Can you get life insurance if you have a stent? | R28: What type of life insurance is best for 70 year old? | S28: Get Your Ducks in a Row | X28: The Importance of Reading the Fine Print | Z28: • Charitable Contributions | AA28: Frequently Asked Questions (FAQs)
F29: • Death Benefits and Beneficiaries | H29: • Cost Efficiency | L29: Improve Your Case: What Can Help | M29: Where to Anchor: Life Insurance Options | N29: What is considered heart trouble for life insurance? | R29: What is the cheapest life insurance for seniors over 70? | S29: Identify Your Family’s Needs | X29: Policy Exclusions and Limitations | Z29: • Estate Planning | AA29: 1. Why is a Broker So Important in the Life Insurance Process?
F30: Comparison: Permanent vs. Term Life Insurance | H30: • Policy Flexibility | L30: Watch Out: What Could Hurt | M30: Frequently Asked Questions | N30: Can you get life insurance after heart bypass surgery? | S30: Research and Choose a Reputable Insurance Company | X30: Potential Riders | Z30: • Think About This | AA30: 2. How Do I Know if a Company is Reputable?
F31: • Duration of Coverage | H31: Individual vs Joint Term Life | L31: The Underwriting Process | M31: Can I get life insurance if I have cancer in Canada? | N31: How long after a heart attack can I get life insurance? | S31: The Role of Insurance Agents | X31: Working With a Competent Advisor is Crucial | Z31: Myth 5: Group Insurance Is Sufficient | AA31: 3. Can I Trust Online Reviews About Insurance Companies?
F32: • Cost Implications | H32: • Individual Term Life | L32: The Waiting Game | M32: Can a Stage 4 cancer patient get life insurance? | N32: Working with a Broker | S32: Two Things Before Buying | X32: Frequently Asked Questions: | Z32: The Reality | AA32: 4. What if I Have Health Issues? Can I Still Get Life Insurance?
F33: • Purpose and Benefits | H33: • Joint Term Life | L33: Additional Medical Requirements | M33: What is the best insurance for cancer patients? | N33: • Wide Access to Insurers | S33: • Know Your Policy Inside and Out | X33: Q1: How are life insurance quotes determined? | Z33: Group vs Individual Policies | AA33: 5. Can I Change My Insurance Company Later On?
F34: • Suitability check-up | H34: Individual vs. Joint Permanent Life | L34: • List: Typical Underwriting Requirements | M34: Can I get life insurance if I had cancer 10 years ago? | N34: • Personalized Guidance | S34: • Consult Multiple Sources | X34: Q2: Is life insurance more expensive as you age? | Z34: • Pro Tip
F35: Understanding No Medical Life Insurance within the Permanent Category | H35: • Individual Permanent Life | L35: Recommendations for Diabetics Seeking Life Insurance | M35: How does a cancer diagnosis affect life insurance? | N35: • Understanding Underwriting Nuances | S35: Conclusion | X35: Q3: Do all life insurance policies require a medical exam? | Z35: Myth 6: Stay-at-Home Parents Don’t Need Insurance
F36: • Brief about No Medical Life Insurance | H36: • Joint Permanent Life | L36: Work with a Broker: Your Best Ally | M36: • Premiums | N36: • Simplified Process | S36: The Final Word | X36: Q4: Can I get life insurance if I have a pre-existing condition? | Z36: The Reality
F37: • Benefits | H37: The Interplay of Types and Choices | L37: Why Brokers Are Better | M37: • Eligibility | N37: • Comparative Analysis | S37: Importance of the Right Choice | X37: Q5: How do Canadian life insurance policies differ from those in other countries? | Z37: The Real Cost of a Stay-At-Home Parent
F38: • Downsides | H38: Comparative Analysis | L38: • Diverse Options | M38: • Coverage Amount | N38: Conclusion | S38: The Need for Proper Research and Consultation | Z38: • Note
F39: • Who Should Consider It? | H39: Table: Feature-by-Feature Comparison | L39: • Personalized Guidance | M39: • Waiting Periods | S39: Frequently Asked Questions (FAQ) | Z39: Myth 7: Too Young for Life Insurance
F40: Determining How Much Permanent Life Insurance You Need | H40: Case Studies: Real-life Scenarios | L40: • Saves Time and Money | M40: Conclusion | S40: What type of life insurance is best for a family? | Z40: The Reality
F41: • Factors to Consider | H41: Financial Implications | L41: • Broker vs. Captive Agent vs. Call Center Agent | S41: What is family life insurance Canada? | Z41: Premiums by Age
F42: • Financial Obligations | H42: Long-term vs Short-term Benefits | L42: Non-Medical vs. Traditional | S42: Is there life insurance that covers the whole family? | Z42: • Smart Move
F43: • Dependents | H43: Pros and Cons of Individual Life Insurance | L43: Avoid Short-Term Contracts | S43: What is one benefit of life insurance to your family? | Z43: Myth 8: Too Old for Life Insurance
F44: • Final Expenses | H44: Advantages | L44: The Power of Permanent | S44: What is the best way to leave money to family? | Z44: The Reality
F45: • Future Financial Needs | H45: • Flexibility | L45: Diabetics with Additional Health Issues | Z45: Tips for Older Applicants
F46: • Existing Savings and Investments | H46: • Multiple Beneficiaries | L46: Best Life Insurance Options for Diabetics | Z46: • Shop Around
F47: • Tax implications of your assets | H47: • Independence | L47: Non-Medical Policies: Often Your Best Bet | Z47: • Consult Advisors
F48: End-of-Term Scenarios and Their Impact on Permanent Policies | H48: Disadvantages | L48: Why Permanent Policies Shine | Z48: • Pro Tip
F49: • What Happens When a Term Policy Ends? | H49: • Cost | L49: • Non-Medical vs. Fully-Underwritten Life Insurance | Z49: Myth 9: Preexisting Conditions Disqualify You
F50: • Expiration Without Claim | H50: • Simplicity | L50: Individual Needs Vary: Consult a Broker | Z50: The Reality
F51: • Renewal Option | H51: Pros and Cons of Joint Life Insurance | L51: The Final Word | Z51: Considerations for Preexisting Conditions
F52: • Converting Term Policies to Permanent | H52: Advantages | L52: FAQ: Life Insurance for Diabetics | Z52: • Note
F53: • Conclusion | H53: • Cost-Effective | L53: Do diabetics qualify for life insurance? | Z53: Myth 10: Other Investments Are Better
H54: • Unified Management | L54: Does Canada life cover diabetes? | Z54: The Reality
H55: • Simplicity | L55: Can insulin-dependent diabetics get life insurance? | Z55: Investment Comparison
H56: Disadvantages | L56: How does Type 2 diabetes affect life insurance? | Z56: • Smart Move
H57: • Limited Flexibility | L57: Is Type 2 diabetes considered a permanent disability? | Z57: Myth 11: Permanent Insurance Is for the Wealthy
H58: • Single Payout | Z58: The Reality
H59: Underwriting for Joint Life Insurance: A Deeper Dive | Z59: Scenarios for Permanent Insurance
H60: Individual vs Joint Underwriting | Z60: • Wealth Transfer
H61: The Average Age Band Factor | Z61: • Business Planning
H62: The Domino Effect on Risk | Z62: • Think About This
H63: What to Expect in Medical Checks | Z63: Myth 12: Coverage Should Be Twice the Annual Salary
H64: How Much Insurance Do You Need? | Z64: The Reality
H65: Quotes and Pricing | Z65: How Much Coverage Do You Really Need?
H66: Frequently Asked Questions (FAQs) | Z66: • Debts
H67: 1. What’s the Main Difference Between Joint and Individual Life Insurance? | Z67: • Expenses
H68: 2. Can I Convert a Joint Life Insurance Policy into Two Individual Policies? | Z68: • Future Goals
H69: 3. How Do Medical Background Checks Work for Joint Life Insurance? | Z69: • Pro Tip
H70: 4. What Happens If One Person Dies in a Joint Life Insurance Policy? | Z70: Conclusion
H71: • Joint-First-to-Die
H72: • Joint-Last-to-Die
H73: 5. How Do I Decide How Much Coverage I Need?

Sheet Site Review
A1: familialife.ca: full site review (Familia Life)
A2: Reviewed October 14, 2026. Live site blocks automated access (HTTP 403), so page content comes from Internet Archive snapshots (mostly January 2024; home page April 2025) plus current search results. See 'Method & Notes'.
A4: AT A GLANCE (formulas over the other tabs)
A5: Knowledge pages listed | B5: =COUNTA('Knowledge Content'!D5:D33) -> 29
A6: Guides | B6: =COUNTIF('Knowledge Content'!B5:B33,"Guide*") -> 15
A7: Articles | B7: =COUNTIF('Knowledge Content'!B5:B33,"Article*") -> 7
A8: Product explainer and sales pages | B8: =COUNTIF('Knowledge Content'!B5:B33,"Product*") -> 6
A9: Known from search results only | B9: =COUNTIF('Knowledge Content'!P5:P33,"Search results only*") -> 3
A10: Pages with an FAQ section | B10: =COUNTIF('Knowledge Content'!G5:G33,"*FAQ*") -> 7
A11: Subheadings catalogued (Topics by Product) | B11: =SUM('Knowledge Content'!I5:I33) -> 586
A12: Average approx. article words (archived pages) | B12: =ROUND(AVERAGE('Knowledge Content'!K5:K33),0) -> 1375
A13: Topics with no Instasure equivalent yet | B13: =COUNTIF('Knowledge Content'!O5:O33,"Gap*") -> 2
A14: All URLs found (URL Inventory) | B14: =COUNTA('URL Inventory'!A5:A100) -> 40
A15: Instasure topics to add (Tab 1) | B15: =COUNTA('Topic Index'!A5:A58) -> 54
A16: Priority 1 topics | B16: =COUNTIF('Topic Index'!I5:I58,1) -> 9
A17: New topics not yet in the blog plan | B17: =COUNTIF('Topic Index'!G5:G58,"New*") -> 15
A18: Modelled monthly searches across all topics | B18: =SUM('Topic Index'!E5:E58) -> 19300
A20: WHO THEY ARE
A21: Business | B21: Familia Life, a Toronto-based life insurance brokerage. It presents itself as a team of national brokers with access to 20+ Canadian insurers (self-reported; not verified). Toll-free 1-844-625-0992, info@familialife.ca. Author named on the blog: Richard Kim.
A22: Products sold | B22: Term life, permanent/whole life (incl. universal), no-medical life, mortgage protection (positioned as term life instead of bank coverage), final expense, and health insurance for people leaving group plans. Critical illness appears only as a blog guide and a rider mention.
A23: Platform | B23: WordPress with Elementor and the Pixfort theme, hosted on SiteGround (CDN with bot protection). Lead capture: per-product quote forms plus a multi-step quote quiz (coverage, age, smoking, conditions, postal code, then contact details).
A25: HOW THE CONTENT CREATES VALUE
A26: Long-form explainers | B26: Each core product has a long 'Everything about…' guide (term, permanent, no medical) that defines the product, lists types, who it suits, pros and cons, and cost logic.
A27: Underwriting and health niche | B27: Their strongest content: diabetes, cancer and heart-condition guides, plus 'how insurers check medical background', 'health issues' and rate-class explanations (standard, preferred, ratings) with a worked example (45-year-old diabetic). Each ends with FAQs targeting long-tail questions (stage 4 cancer, stents, bypass, insulin-dependent).
A28: Decision help | B28: Comparisons (joint vs individual, permanent vs term, term vs bank mortgage protection), myth-busting (12 myths with 'the reality'), 'two things before buying', end-of-term options, how much to buy.
A29: Broker positioning | B29: Almost every guide steers to 'work with a broker' (broker vs captive agent vs call centre, access to all insurers, underwriting expertise). Content is the trust engine for the quote forms.
A30: Formats used | B30: Key takeaways boxes, FAQ blocks, comparison tables (up to 7 per page), scenario examples, numbered steps, bold lead-in labels for sub-points. No calculators, no rate tables by age (apart from one table in the myths article), no province or city pages.
A32: WEAKNESSES AND SEO ISSUES
A33: H1 misuse | B33: The mega-menu codes every menu item as an H1: 36–37 H1 tags on every page. The real page title is often an H2 or missing as H1, which muddies the heading outline for search engines and screen readers.
A34: Thin product pages | B34: Product pages carry only 4–5 short sections (Understanding / How it works / Benefits / Cost) and rely on testimonials (8 client names coded as H5 headings) and quote buttons.
A35: Headings misused for paragraphs | B35: Full paragraphs are marked up as headings on: /everything-about-no-medical-life-insurance, /everything-about-term-life-insurance.
A36: Missing meta descriptions | B36: No meta description on 7 pages: /how-much-life-insurance-should-i-get, /mortgage-protection-insurance, /mortgage-protection-insurance-quote-form, /no-medical-insurance, /no-medical-life-insurance-quote-form, /permanent-life-insurance-quote-form, /term-life-insurance-quote-form.
A37: No FAQ markup | B37: FAQ sections exist on several guides, but no FAQPage structured data was found (schema is BlogPosting/Article, BreadcrumbList, InsuranceAgency, Person).
A38: Stale content | B38: Article publish dates run 2020-04-22 to 2023-10-04; last edits found 2022-12-06 to 2025-03-30. Apart from the newer tax-deductibility article (found only in search), no new guides appear after October 2023, and figures carry no 'as of' dates.
A39: Compliance-risk claims | B39: Superlatives and guarantees in titles and headings: 'Lowest Life Insurance Rates in Canada', 'Best Life Insurance Rates in Canada', 'LOWEST PREMIUM - GUARANTEED!', 'RATES WILL NEVER GO UP'. These are claims Canadian advertising rules (Competition Act, FSRA/RIBO) expect to be substantiated.
A40: Crawlability | B40: The site answers HTTP 403 to non-browser and data-centre requests (SiteGround bot protection). Pages like the critical illness and claims guides were captured by the archive only as challenge pages, which suggests some crawlers may also be blocked.
A41: Coverage gaps | B41: No pages for critical illness (product), disability, travel/super visa, business or group benefits, no provincial pages, no tools or calculators, no licensed-reviewer lines on articles.
A43: WHAT INSTASURE CAN TAKE FROM THIS
A44: Topics to publish first | B44: Their medical-condition trio (diabetes, cancer, heart) is already in the Instasure plan as planned guides: moving them up, with Instasure's Medical underwriting desk as the call to action, targets their strongest content directly.
A45: Clear gaps | B45: Life insurance myths and family life insurance have no Instasure equivalent; joint life, universal life, end-of-term options, medical exams and how to claim are planned but unpublished (see Tab 1, column O).
A46: Topic plan (Tab 1) | B46: The first tab turns this review into 54 Instasure pages, ordered by modelled search traffic: SEO title, meta description, URL, primary and secondary keywords, value asset, call to action, links and a full H2/H3/FAQ outline for each, plus a video title. 39 reuse a blog plan row; 15 are new.
A47: Ways to beat them | B47: Fresh 'as of' dates, a licensed reviewer line, FAQPage markup, one H1 per page, instant estimates and rate tables (they have none), and province coverage.

Sheet URL Inventory
A1: familialife.ca: every URL found
A2: From the Internet Archive index, the archived blog listing and search results (October 14, 2026).
A4: URL | B4: Page type | C4: Title | D4: Meta description | E4: Source | F4: Page words | G4: H1 tags (raw) | H4: Published | I4: Last updated
A5: https://familialife.ca/ | B5: Home page | C5: Familia Life - Lowest Life Insurance Rates in Canada | D5: At Familia Life, we deliver the best life insurance rates in Canada and unbiased advice, always putting your family first. | E5: Archive 2025-04-18 | F5: 2537 | G5: 36 | H5: 2020-06-09 | I5: 2025-03-30
A6: https://familialife.ca/term-life-insurance/ | B6: Product explainer page | C6: Term Life Insurance | D6: Term life insurance in Canada is a form of life insurance coverage that is active for a predetermined period, often known as a "term". This could span 10, 20, | E6: Archive 2024-01-16 | F6: 2706 | G6: 36 | H6: 2022-03-04 | I6: 2023-06-07
A7: https://familialife.ca/everything-about-term-life-insurance/ | B7: Guide | C7: Everything about Term Life Insurance | D7: Everything you need to know about Term Life Insurance in Canada | E7: Archive 2024-01-16 | F7: 3326 | G7: 36 | H7: 2023-06-01 | I7: 2023-06-07
A8: https://familialife.ca/what-happens-at-the-end-of-term-life-insurance/ | B8: Article | C8: What Happens at the End of Term Life Insurance? | D8: In this informative article, we explore what happens at the end of term life insurance in Canada. It covers the different options available, including renewal, conversion to permanent insurance, or letting the policy simply expire. We emphasize the importance of considering your individual circumstances and future financial needs, encouraging readers to stay informed and consult with a trusted life insurance advisor when making crucial decisions. | E8: Archive 2024-01-16 | F8: 2296 | G8: 37 | H8: 2023-06-23 | I8: 2023-09-06
A9: https://familialife.ca/whole-life-insurance/ | B9: Product explainer page | C9: Permanent Life Insurance | D9: Lowest whole life insurance rates in Canada. Qualify within minutes. Get your free quote today. | E9: Archive 2024-01-16 | F9: 2321 | G9: 36 | H9: 2022-03-04 | I9: 2023-06-09
A10: https://familialife.ca/everything-about-permanent-life-insurance/ | B10: Guide | C10: Everything about Permanent Life Insurance in Canada | D10: Navigating the world of life insurance can be daunting, especially with the myriad of options available. This article delves deep into the realm of Permanent Life Insurance, contrasting it with its counterpart - Term Life Insurance. Readers will gain insights into the types, advantages, cost implications, and key considerations of Permanent Life Insurance. Whether you're contemplating which policy is right for you or simply seeking to understand the intricacies of life insurance, this guide offers clarity and direction. | E10: Archive 2024-01-16 | F10: 3042 | G10: 37 | H10: 2023-08-17 | I10: 2023-09-19
A11: https://familialife.ca/what-is-universal-life-insurance/ | B11: Article | C11: What is Universal Life Insurance and How Does it Work? | D11: Understanding the complexities of universal life insurance can be a challenging task. This comprehensive guide breaks down the basics of universal life insurance, differentiates it from other insurance types, and explores its tax implications. Uncover whether this flexible, investment-linked insurance option could be the right fit for your financial planning. Navigate your path in the insurance landscape with the help of Familialife.ca, your trusted Canadian Insurance brokerage firm. | E11: Archive 2024-01-16 | F11: 2468 | G11: 37 | H11: 2023-06-22 | I11: 2023-08-31
A12: https://familialife.ca/what-is-joint-life/ | B12: Guide | C12: Joint Life Insurance vs Individual Life Insurance: A Comparative Analysis | D12: Choosing between Joint and Individual Life Insurance can feel like a high-stakes game of "Would You Rather?" But it doesn't have to be. Our comprehensive guide dives deep into the nuances of both options, offering real-life scenarios, pros and cons, and even a feature-by-feature comparison. Whether you're a couple looking to share financial responsibilities or an individual seeking tailored coverage, this article is your roadmap to making an informed decision. Get the answers to all your burning questions and more. Ready to secure your family's financial future? Read on. | E12: Archive 2024-01-09 | F12: 2928 | G12: 37 | H12: 2023-09-08 | I12: 2023-09-08
A13: https://familialife.ca/no-medical-insurance/ | B13: Product explainer page | C13: No Medical Insurance | D13: (missing) | E13: Archive 2024-01-19 | F13: 2356 | G13: 36 | H13: 2022-03-04 | I13: 2023-06-09
A14: https://familialife.ca/everything-about-no-medical-life-insurance/ | B14: Guide | C14: Everything about No Medical Life Insurance | D14: Everything you need to know about No Medical Life Insurance in Canada | E14: Archive 2024-01-19 | F14: 3169 | G14: 36 | H14: 2023-06-02 | I14: 2023-06-07
A15: https://familialife.ca/how-to-get-life-insurance-if-you-have-health-issues/ | B15: Article | C15: How To Get Life Insurance If You Have Health Issues | D15: How do you get or qualify for a life insurance if you have health issues? In this article, we'll answer all of your questions on how you can get life insurance even if you have health concerns. | E15: Archive 2024-01-19 | F15: 2165 | G15: 37 | H15: 2020-04-22 | I15: 2023-09-06
A16: https://familialife.ca/life-insurance-for-diabetics/ | B16: Guide | C16: Life Insurance for Diabetics: How to Get the Best Rates in Canada | D16: Think diabetes puts life insurance out of reach? Think again! This comprehensive guide dispels the myths and lays out the facts about securing life insurance as a diabetic in Canada. From understanding how your diagnosis impacts rates to tips for navigating the underwriting process, we've got you covered. Read on to learn why working with a broker could be your best bet and how to get the most out of your policy. | E16: Archive 2024-01-19 | F16: 2840 | G16: 37 | H16: 2023-09-22 | I16: 2023-09-22
... A23: https://familialife.ca/family-life-insurance/ | B23: Guide | C23: Family Life Insurance in Canada: Separating Fact from Fiction | D23: Confused about family life insurance in Canada? You're not alone. Dive into this comprehensive guide to discover what really counts when choosing the perfect plan for your loved ones. From the importance of a skilled broker to the balance between affordability and value, we've got you covered. Familia Life is here to help you navigate the complex world of family insurance, so you can make an informed decision that genuinely meets your family's needs. Ready to secure your family's financial future? Let's get started! | E23: Archive 2024-01-19 | F23: 2705 | G23: 37 | H23: 2023-09-19 | I23: 2023-09-29
A24: https://familialife.ca/whats-ci/ | B24: Guide (search only) | C24: Protect Your Health and Wallet: A Complete Guide to Critical Illness Insurance in Canada | E24: Search results only
A25: https://familialife.ca/health-insurance/ | B25: Product (sales) page | C25: Health Insurance | D25: Lost employer health coverage? Facing big medical bills? Don't stress! We've got tailored plans for you and your family. We've got your back. | E25: Archive 2024-01-16 | F25: 2089 | G25: 36 | H25: 2022-03-04 | I25: 2023-09-06
A26: https://familialife.ca/how-does-life-insurance-work-in-canada/ | B26: Guide | C26: How Does Life Insurance Work in Canada? | D26: Life insurance in Canada: a quick guide that walks you through the basic concepts, different types of policies, how premiums are determined, tax implications, and how to choose the right coverage for your needs. Stay informed to make the best decisions for your family's future. | E26: Archive 2024-01-16 | F26: 2316 | G26: 37 | H26: 2023-06-23 | I26: 2023-08-31
A27: https://familialife.ca/how-much-life-insurance-should-i-get/ | B27: Article | C27: Finding the Right Amount of Life Insurance: Budget, Debts, and Dependents | D27: (missing) | E27: Archive 2024-01-16 | F27: 1801 | G27: 37 | H27: 2021-01-22 | I27: 2023-06-02
A28: https://familialife.ca/life-insurance-quotes-in-canada/ | B28: Guide | C28: Life Insurance Quotes in Canada | D28: "Life insurance can often feel like a maze of terms, rates, and policies. Delve into the intricacies of how life insurance quotes are determined in Canada, and arm yourself with the knowledge to navigate this essential financial safeguard. From understanding the factors that influence your premium to demystifying the Canadian life insurance landscape, this comprehensive guide answers your most pressing questions." | E28: Archive 2024-01-16 | F28: 3064 | G28: 36 | H28: 2023-08-31 | I28: 2023-09-05
A29: https://familialife.ca/how-do-life-insurance-companies-check-medical-background/ | B29: Article | C29: How Do Life Insurance Companies Check Medical Background? | D29: How does life insurance companies check medical backgrounds? We answer this question in-depth in this article. | E29: Archive 2024-01-19 | F29: 2211 | G29: 37 | H29: 2023-06-14 | I29: 2023-09-14
A30: https://familialife.ca/12-myths-debunked/ | B30: Guide | C30: 12 Life Insurance Myths You Need to Stop Believing | D30: Unravel the tangled web of life insurance myths that could be holding you back from vital financial planning. From misconceptions about costs to the role of preexisting conditions, this comprehensive guide busts 12 common myths, setting the facts straight. Whether you're young, old, or somewhere in between, find out how life insurance can fit into your financial roadmap. Brought to you by Familia Life, your trusted Canadian life and health insurance brokerage. 🍁 | E30: Archive 2024-01-19 | F30: 2273 | G30: 37 | H30: 2023-09-19 | I30: 2023-09-20
A31: https://familialife.ca/two-things-before-buying/ | B31: Article | C31: Don’t Buy Life Insurance Without Doing These 2 Things | D31: Ready to dive into the world of life insurance? Hold up! Our latest article zeroes in on two must-dos: picking a seasoned broker and opting for a reputable insurance company. Discover why these are your keys to unlocking a secure future. 🌟🔒 | E31: Archive 2024-01-19 | F31: 2279 | G31: 37 | H31: 2023-09-07 | I31: 2023-09-07
A32: https://familialife.ca/are-life-insurance-premiums-tax-deductible-in-canada/ | B32: Article (search only) | C32: Are Life Insurance Premiums Tax Deductible in Canada? | E32: Search results only
A33: https://familialife.ca/how-to-claim/ | B33: Guide (search only) | C33: A Step-by-Step Guide to Filing a Life Insurance Claim | E33: Search results only
A34: https://familialife.ca/about/ | B34: Company page | C34: About Us | D34: There were over 45,000 life insurance agents in Canada as of 2017 and counting, according to FSRA (Financial Services Regulatory Authority of Ontario). | E34: Archive 2024-01-16 | F34: 1533 | G34: 36 | H34: 2019-07-12 | I34: 2023-09-14
A35: https://familialife.ca/contact-us/ | B35: Contact page | C35: Contact Us | D35: info@familialife.ca | E35: Archive 2024-01-16 | F35: 1234 | G35: 37 | H35: 2022-03-03 | I35: 2023-12-27
